Workbook

Sheet Dashboard

Sheet Summary
A1: =TODAY() -> 46218
M2: Monitoring Surat 2026
A3: Keterangan | M3: Keterangan | N3: Compliance | O3: Corcom | P3: Finance | Q3: HC | R3: HSE | V3: Maintenance | W3: Permit | X3: Planning | Y3: PMO | Z3: Produksi | AA3: SCM | AB3: QMS | AC3: WQA
A4: Level 1 | B4: Perlu dibalas dengan tenggat waktu (max 7 hari) | M4: Incoming Open | N4: =COUNTIFS('Incoming 2026'!L:L,$B$19,'Incoming 2026'!N:N,N3) -> 3 | O4: =COUNTIFS('Incoming 2026'!L:L,$B$19,'Incoming 2026'!N:N,"$O$3") -> 0 | P4: =COUNTIFS('Incoming 2026'!L:L,$B$19,'Incoming 2026'!N:N,"HC") -> 0 | Q4: =COUNTIFS('Incoming 2026'!L:L,$B$19,'Incoming 2026'!N:N,"HC") -> 0 | R4: =COUNTIFS('Incoming 2026'!L:L,$B$19,'Incoming 2026'!N:N,"HSE") -> 29 | V4: =COUNTIFS('Incoming 2026'!L:L,$B$19,'Incoming 2026'!N:N,"maintenance") -> 0 | W4: =COUNTIFS('Incoming 2026'!L:L,$B$19,'Incoming 2026'!N:N,"permit") -> 2 | X4: =COUNTIFS('Incoming 2026'!L:L,$B$19,'Incoming 2026'!N:N,"Planning") -> 16 | Y4: =COUNTIFS('Incoming 2026'!L:L,$B$19,'Incoming 2026'!N:N,"PMO") -> 1 | Z4: =COUNTIFS('Incoming 2026'!L:L,$B$19,'Incoming 2026'!N:N,"Produksi") -> 2 | AA4: =COUNTIFS('Incoming 2024'!L:L,$B$19,'Incoming 2024'!N:N,"SCM") -> 0 | AB4: =COUNTIFS('Incoming 2024'!L:L,$B$19,'Incoming 2024'!N:N,"QMS") -> 0 | AC4: =COUNTIFS('Incoming 2024'!L:L,$B$19,'Incoming 2024'!N:N,"WQA") -> 0
A5: Level 2 | B5: Perlu dibalas dengan tenggat waktu (Max 14 hari) | M5: Incoming Closed | N5: =COUNTIFS('Incoming 2026'!L:L,Summary!$B$20,'Incoming 2026'!N:N,Summary!N3) -> 11 | O5: =COUNTIFS('Incoming 2026'!L:L,Summary!$B$20,'Incoming 2026'!N:N,Summary!O3) -> 0 | P5: =COUNTIFS('Incoming 2026'!L:L,Summary!$B$20,'Incoming 2026'!N:N,Summary!P3) -> 4 | Q5: =COUNTIFS('Incoming 2026'!L:L,Summary!$B$20,'Incoming 2026'!N:N,Summary!Q3) -> 0 | R5: =COUNTIFS('Incoming 2026'!L:L,Summary!$B$20,'Incoming 2026'!N:N,Summary!R3) -> 23 | V5: =COUNTIFS('Incoming 2026'!L:L,Summary!$B$20,'Incoming 2026'!N:N,Summary!V3) -> 0 | W5: =COUNTIFS('Incoming 2026'!L:L,Summary!$B$20,'Incoming 2026'!N:N,Summary!W3) -> 2 | X5: =COUNTIFS('Incoming 2026'!L:L,Summary!$B$20,'Incoming 2026'!N:N,Summary!X3) -> 2 | Y5: =COUNTIFS('Incoming 2026'!L:L,Summary!$B$20,'Incoming 2026'!N:N,Summary!Y3) -> 0 | Z5: =COUNTIFS('Incoming 2026'!L:L,Summary!$B$20,'Incoming 2026'!N:N,Summary!Z3) -> 7 | AA5: =COUNTIFS('Incoming 2024'!L:L,Summary!$B$20,'Incoming 2024'!N:N,Summary!AA3) -> 0 | AB5: =COUNTIFS('Incoming 2024'!L:L,Summary!$B$20,'Incoming 2024'!N:N,Summary!AB3) -> 1 | AC5: =COUNTIFS('Incoming 2024'!L:L,Summary!$B$20,'Incoming 2024'!N:N,Summary!AC3) -> 2
A6: Level 3 | B6: Perlu dibalas dengan tenggat waktu (Max 30 hari) | M6: Outgoing Open | N6: =COUNTIFS('Outgoing 2026'!K:K,$B$19,'Outgoing 2026'!L:L,"compliance") -> 11 | O6: =COUNTIFS('Outgoing 2026'!K:K,$B$19,'Outgoing 2026'!L:L,"corcom") -> 0 | P6: =COUNTIFS('Outgoing 2026'!K:K,$B$19,'Outgoing 2026'!L:L,"Finance") -> 0 | Q6: =COUNTIFS('Outgoing 2026'!K:K,$B$19,'Outgoing 2026'!L:L,"HC") -> 0 | R6: =COUNTIFS('Outgoing 2026'!K:K,$B$19,'Outgoing 2026'!L:L,"HSE") -> 0 | V6: =COUNTIFS('Outgoing 2026'!K:K,$B$19,'Outgoing 2026'!L:L,"Maintenance") -> 0 | W6: =COUNTIFS('Outgoing 2026'!K:K,$B$19,'Outgoing 2026'!L:L,"Permit") -> 2 | X6: =COUNTIFS('Outgoing 2026'!K:K,$B$19,'Outgoing 2026'!L:L,"Planning") -> 0 | Y6: =COUNTIFS('Outgoing 2026'!K:K,$B$19,'Outgoing 2026'!L:L,$Y$3) -> 0 | Z6: =COUNTIFS('Outgoing 2026'!K:K,$B$19,'Outgoing 2026'!L:L,$Z$3) -> 2 | AA6: =COUNTIFS('Outgoing 2024'!K:K,$B$19,'Outgoing 2024'!L:L,$AA$3) -> 0 | AB6: =COUNTIFS('Outgoing 2024'!K:K,$B$19,'Outgoing 2024'!L:L,$AB$3) -> 0 | AC6: =COUNTIFS('Outgoing 2024'!K:K,$B$19,'Outgoing 2024'!L:L,$AC$3) -> 0
M7: Outgoing Closed | N7: =COUNTIFS('Outgoing 2026'!K:K,$B$20,'Outgoing 2026'!L:L,"compliance") -> 21 | O7: =COUNTIFS('Outgoing 2026'!K:K,$B$20,'Outgoing 2026'!L:L,"corcom") -> 0 | P7: =COUNTIFS('Outgoing 2026'!K:K,$B$20,'Outgoing 2026'!L:L,"Finance") -> 0 | Q7: =COUNTIFS('Outgoing 2026'!K:K,$B$20,'Outgoing 2026'!L:L,"HC") -> 0 | R7: =COUNTIFS('Outgoing 2026'!K:K,$B$20,'Outgoing 2026'!L:L,"HSE") -> 0 | V7: =COUNTIFS('Outgoing 2026'!K:K,$B$20,'Outgoing 2026'!L:L,"Maintenance") -> 0 | W7: =COUNTIFS('Outgoing 2026'!K:K,$B$20,'Outgoing 2026'!L:L,"Permit") -> 0 | X7: =COUNTIFS('Outgoing 2026'!K:K,$B$20,'Outgoing 2026'!L:L,"Planning") -> 0 | Y7: =COUNTIFS('Outgoing 2026'!K:K,$B$20,'Outgoing 2026'!L:L,$Y$3) -> 0 | Z7: =COUNTIFS('Outgoing 2026'!K:K,$B$20,'Outgoing 2026'!L:L,$Z$3) -> 0 | AA7: =COUNTIFS('Outgoing 2024'!K:K,$B$20,'Outgoing 2024'!L:L,$AA$3) -> 0 | AB7: =COUNTIFS('Outgoing 2024'!K:K,$B$20,'Outgoing 2024'!L:L,$AB$3) -> 0 | AC7: =COUNTIFS('Outgoing 2024'!K:K,$B$20,'Outgoing 2024'!L:L,$AC$3) -> 1
A8: 1) Total Surat | B8: 2023 | C8: Incoming | D8: =SUBTOTAL(3,'Incoming 2023'!D:D) -> 439
C9: Outgoing | D9: =SUBTOTAL(3,'Outgoing 2023'!B:B) -> 531
B10: 2024 | C10: Incoming | D10: =SUBTOTAL(3,'Incoming 2024'!B:B) -> 835
C11: Outgoing | D11: =SUBTOTAL(3,'Outgoing 2024'!A:A) -> 975
B12: 2025 | C12: Incoming | D12: =SUBTOTAL(3,'Incoming 2025'!B2:B2001) -> 502
C13: Outgoing | D13: =SUBTOTAL(3,'Outgoing 2025'!B2:B1898) -> 1158
B14: 2026 | C14: Incoming | D14: =SUBTOTAL(3,'Incoming 2026'!B2:B1990) -> 304
C15: Outgoing | D15: =SUBTOTAL(3,'Outgoing 2026'!B2:B961) -> 820
B18: Surat Masuk | C18: 2026 | D18: 2025 | E18: 2024 | F18: 2023 | I18: Surat Keluar | J18: 2026 | K18: 2025 | L18: 2024
B19: Open | C19: =COUNTIF('Incoming 2026'!L2:L1988,Summary!B19) -> 98 | D19: =COUNTIF('Incoming 2025'!L2:L2001,Summary!B19) -> 44 | E19: =COUNTIF('Incoming 2024'!L:L,"open") -> 37 | F19: =COUNTIF('Incoming 2023'!I:I,"open") -> 9 | I19: Open | J19: =COUNTIF('Outgoing 2026'!$K$2:$K$961,Summary!I19) -> 24 | K19: =COUNTIF('Outgoing 2025'!K2:K963,Summary!I19) -> 11 | L19: =COUNTIF('Outgoing 2024'!K:K,"Open") -> 2
B20: Closed | C20: =COUNTIF('Incoming 2026'!L2:L1988,Summary!B20) -> 70 | D20: =COUNTIF('Incoming 2025'!L3:L2001,Summary!B20) -> 111 | E20: =COUNTIF('Incoming 2024'!L:L,"closed") -> 244 | F20: =COUNTIF('Incoming 2023'!I:I,"closed") -> 252 | I20: Closed | J20: =COUNTIF('Outgoing 2026'!$K$2:$K$961,Summary!I20) -> 25 | K20: =COUNTIF('Outgoing 2025'!K3:K963,Summary!I20) -> 7 | L20: =COUNTIF('Outgoing 2024'!K:K,"Closed") -> 177
B21: Info | C21: =COUNTIF('Incoming 2026'!L2:L1989,Summary!B21) -> 136 | D21: =COUNTIF('Incoming 2025'!L4:L1001,Summary!B21) -> 338 | E21: =COUNTIF('Incoming 2024'!L:L,"info") -> 553 | F21: =COUNTIF('Incoming 2023'!I:I,"info") -> 177 | I21: Info | J21: =COUNTIF('Outgoing 2026'!$K$2:$K$961,Summary!I21) -> 643 | K21: =COUNTIF('Outgoing 2025'!K4:K963,Summary!I21) -> 639 | L21: =COUNTIF('Outgoing 2024'!K:K,"Info") -> 777
M34: Jumlah surat masuk berdasarkan Durasi Keterlambatan
N35: 7 | O35: 14 | P35: 21 | Q35: 30
M36: Level 1 | N36: =COUNTIF('Incoming 2026'!M2:M192,Summary!M36) -> 23 | O36: =COUNTIFS('Incoming 2026'!M:M,Summary!M36,'Incoming 2026'!S:S,Summary!O35) -> 2 | P36: =COUNTIFS('Incoming 2026'!M:M,Summary!M36,'Incoming 2026'!S:S,Summary!P35) -> 3 | Q36: =COUNTIFS('Incoming 2026'!M:M,Summary!N36,'Incoming 2026'!S:S,Summary!Q35) -> 0
M37: Level 2 | N37: =COUNTIF('Incoming 2026'!M3:M193,Summary!M37) -> 33 | O37: =COUNTIFS('Incoming 2026'!M:M,Summary!M37,'Incoming 2026'!S:S,Summary!O35) -> 0 | P37: =COUNTIFS('Incoming 2026'!M:M,Summary!M37,'Incoming 2026'!S:S,Summary!P35) -> 0 | Q37: =COUNTIFS('Incoming 2026'!M:M,Summary!M37,'Incoming 2026'!S:S,Summary!Q35) -> 0
M38: Level 3 | N38: =COUNTIF('Incoming 2026'!M4:M194,Summary!M38) -> 3 | O38: =COUNTIFS('Incoming 2026'!M:M,Summary!M38,'Incoming 2026'!S:S,Summary!O35) -> 0 | P38: =COUNTIFS('Incoming 2026'!M:M,Summary!M38,'Incoming 2026'!S:S,Summary!P35) -> 0 | Q38: =COUNTIFS('Incoming 2026'!M:M,Summary!M38,'Incoming 2026'!S:S,Summary!Q35) -> 4
A40: Kategori Surat
A41: TOK | B41: =COUNTIF('Incoming 2026'!#REF!,A41) -> #REF!
A42: DED/RAB | B42: =COUNTIF('Incoming 2026'!#REF!,A42) -> #REF!
A43: PKS | B43: =COUNTIF('Incoming 2026'!#REF!,A43) -> #REF!
A44: Dokumentasi | B44: =COUNTIF('Incoming 2026'!#REF!,A44) -> #REF!
A45: Denda | B45: =COUNTIF('Incoming 2026'!#REF!,A45) -> #REF!
A46: Perizinan | B46: =COUNTIF('Incoming 2026'!#REF!,A46) -> #REF!
A47: Sambungan Rumah/Sambungan Baru | B47: =COUNTIF('Incoming 2026'!#REF!,A47) -> #REF!
A48: Teguran | B48: =COUNTIF('Incoming 2026'!#REF!,A48) -> #REF!
A49: Komisioning/Pengoperasian | B49: =COUNTIF('Incoming 2026'!#REF!,A49) -> #REF!
A50: Spesifikasi Teknis/Metode Kerja | B50: =COUNTIF('Incoming 2026'!#REF!,A50) -> #REF!
A51: Inspeksi | B51: =COUNTIF('Incoming 2026'!#REF!,A51) -> #REF!
A53: Pengadaan | B53: =COUNTIF('Incoming 2026'!#REF!,A53) -> #REF!
... A56: Rencana Pekerjaan | B56: =COUNTIF('Incoming 2026'!#REF!,A56) -> #REF!
A59: Kategori Surat Masuk "Open"
A60: Shop Drawing | B60: =COUNTIFS('Incoming 2025'!L:L,Summary!$B$19,'Incoming 2025'!J:J,Summary!A60) -> 0
A61: DED/RAB | B61: =COUNTIFS('Incoming 2025'!L:L,Summary!$B$19,'Incoming 2025'!J:J,Summary!A61) -> 14
A62: PKS | B62: =COUNTIFS('Incoming 2025'!L:L,Summary!$B$19,'Incoming 2025'!J:J,Summary!A62) -> 2
A63: Laporan Bulanan | B63: =COUNTIFS('Incoming 2025'!L:L,Summary!$B$19,'Incoming 2025'!J:J,Summary!A63) -> 0
A64: Denda | B64: =COUNTIFS('Incoming 2025'!L:L,Summary!$B$19,'Incoming 2025'!J:J,Summary!A64) -> 0
A65: Perizinan | B65: =COUNTIFS('Incoming 2025'!L:L,Summary!$B$19,'Incoming 2025'!J:J,Summary!A65) -> 5
A66: MoM | B66: =COUNTIFS('Incoming 2025'!L:L,Summary!$B$19,'Incoming 2025'!J:J,Summary!A66) -> 0
A67: Tagihan | B67: =COUNTIFS('Incoming 2025'!L:L,Summary!$B$19,'Incoming 2025'!J:J,Summary!A67) -> 0
A68: Gangguan | B68: =COUNTIFS('Incoming 2025'!L:L,Summary!$B$19,'Incoming 2025'!J:J,Summary!A68) -> 0
A69: Spesifikasi Teknis/Metode Kerja | B69: =COUNTIFS('Incoming 2025'!L:L,Summary!$B$19,'Incoming 2025'!J:J,Summary!A69) -> 1
A70: Inspeksi | B70: =COUNTIFS('Incoming 2025'!L:L,Summary!$B$19,'Incoming 2025'!J:J,Summary!A70) -> 1
A71: Komisioning/Pengoperasian | B71: =COUNTIFS('Incoming 2025'!L:L,Summary!$B$19,'Incoming 2025'!J:J,Summary!A71) -> 0
... A75: Rencana Pekerjaan | B75: =COUNTIFS('Incoming 2025'!L:L,Summary!$B$19,'Incoming 2025'!J:J,Summary!A75) -> 0
A77: 2026
N78: PIC Surat Keluar 2026
A79: Surat kategori | B79: Incoming | C79: Outgoing | O79: Incoming | P79: Outgoing
A80: Brownfield | N80: {=_xlfn.UNIQUE('Incoming 2026'!N2:N17)} -> PMO Infill | O80: =COUNTIF('Incoming 2026'!$N$2:$N$990,Summary!N80) -> 78 | P80: =COUNTIF('Outgoing 2026'!$L$2:$L$961,Summary!N80) -> 158
A81: Operation & Maintenance | B81: =COUNTIF('Incoming 2026'!$J$2:$J$990,Summary!A81) -> 15 | C81: =COUNTIF('Outgoing 2026'!$I$2:$I$961,Summary!A81) -> 40 | N81: Compliance | O81: =COUNTIF('Incoming 2026'!$N$2:$N$990,Summary!N81) -> 39 | P81: =COUNTIF('Outgoing 2026'!$L$2:$L$961,Summary!N81) -> 68
A82: Denda & Kegagalan | B82: =COUNTIF('Incoming 2026'!$J$2:$J$990,Summary!A82) -> 3 | C82: =COUNTIF('Outgoing 2026'!$I$2:$I$961,Summary!A82) -> 2 | N82: Finance | O82: =COUNTIF('Incoming 2026'!$N$2:$N$990,Summary!N82) -> 5 | P82: =COUNTIF('Outgoing 2026'!$L$2:$L$961,Summary!N82) -> 30
A83: Perencanaan Program Rehabilitasi | B83: =COUNTIF('Incoming 2026'!$J$2:$J$990,Summary!A83) -> 6 | C83: =COUNTIF('Outgoing 2026'!$I$2:$I$961,Summary!A83) -> 24 | N83: PMO NC | O83: =COUNTIF('Incoming 2026'!$N$2:$N$990,Summary!N83) -> 14 | P83: =COUNTIF('Outgoing 2026'!$L$2:$L$961,Summary!N83) -> 186
A84: Konstruksi Program Brownfield | B84: =COUNTIF('Incoming 2026'!$J$2:$J$990,Summary!A84) -> 0 | C84: =COUNTIF('Outgoing 2026'!$I$2:$I$961,Summary!A84) -> 0 | N84: PMO Cyclical | O84: =COUNTIF('Incoming 2026'!$N$2:$N$990,Summary!N84) -> 8 | P84: =COUNTIF('Outgoing 2026'!$L$2:$L$961,Summary!N84) -> 44
A85: Administrasi & Dokumentasi | B85: =COUNTIF('Incoming 2026'!$J$2:$J$990,Summary!A85) -> 3 | C85: =COUNTIF('Outgoing 2026'!$I$2:$I$961,Summary!A85) -> 4 | N85: PMO; Permit | O85: =COUNTIF('Incoming 2026'!$N$2:$N$990,Summary!N85) -> 1 | P85: =COUNTIF('Outgoing 2026'!$L$2:$L$961,Summary!N85) -> 0
A86: Greenfield | O86: =COUNTIF('Incoming 2026'!$N$2:$N$990,Summary!N86) -> 0 | P86: =COUNTIF('Outgoing 2026'!$L$2:$L$961,Summary!N86) -> 0
A87: Perencanaan Program Greenfield | B87: =COUNTIF('Incoming 2026'!$J$2:$J$990,Summary!A87) -> 41 | C87: =COUNTIF('Outgoing 2026'!$I$2:$I$961,Summary!A87) -> 43 | N87: PGO | O87: =COUNTIF('Incoming 2026'!$N$2:$N$990,Summary!N87) -> 9 | P87: =COUNTIF('Outgoing 2026'!$L$2:$L$961,Summary!N87) -> 18
A88: Konstruksi Program Greenfield | B88: =COUNTIF('Incoming 2026'!$J$2:$J$990,Summary!A88) -> 87 | C88: =COUNTIF('Outgoing 2026'!$I$2:$I$961,Summary!A88) -> 238 | N88: WQA | O88: =COUNTIF('Incoming 2026'!$N$2:$N$990,Summary!N88) -> 2 | P88: =COUNTIF('Outgoing 2026'!$L$2:$L$961,Summary!N88) -> 10
A89: Administrasi & Dokumentasi | B89: =COUNTIF('Incoming 2026'!$J$2:$J$990,Summary!A89) -> 3 | C89: =COUNTIF('Outgoing 2026'!$I$2:$I$961,Summary!A89) -> 4 | N89: Legal | O89: =COUNTIF('Incoming 2026'!$N$2:$N$990,Summary!N89) -> 1 | P89: =COUNTIF('Outgoing 2026'!$L$2:$L$961,Summary!N89) -> 19
A90: Sambungan Langsung | B90: =COUNTIF('Incoming 2026'!$J$2:$J$990,Summary!A90) -> 14 | C90: =COUNTIF('Outgoing 2026'!$I$2:$I$961,Summary!A90) -> 182 | N90: Permit | O90: =COUNTIF('Incoming 2026'!$N$2:$N$990,Summary!N90) -> 19 | P90: =COUNTIF('Outgoing 2026'!$L$2:$L$961,Summary!N90) -> 29
A91: Support
A92: Kontrak & Legal | B92: =COUNTIF('Incoming 2026'!$J$2:$J$990,Summary!A92) -> 14 | C92: =COUNTIF('Outgoing 2026'!$I$2:$I$961,Summary!A92) -> 29 | N92: GF
A93: Keuangan & Pembayaran | B93: =COUNTIF('Incoming 2026'!$J$2:$J$990,Summary!A93) -> 0 | C93: =COUNTIF('Outgoing 2026'!$I$2:$I$961,Summary!A93) -> 0
A94: Perizinan | B94: =COUNTIF('Incoming 2026'!$J$2:$J$990,Summary!A94) -> 5 | C94: =COUNTIF('Outgoing 2026'!$I$2:$I$961,Summary!A94) -> 29
A95: Monitoring & Pelaporan | B95: =COUNTIF('Incoming 2026'!$J$2:$J$990,Summary!A95) -> 19 | C95: =COUNTIF('Outgoing 2026'!$I$2:$I$961,Summary!A95) -> 23
A96: HSE | B96: =COUNTIF('Incoming 2026'!$J$2:$J$990,Summary!A96) -> 52 | C96: =COUNTIF('Outgoing 2026'!$I$2:$I$961,Summary!A96) -> 21
A97: Koordinasi & Sosialisasi | B97: =COUNTIF('Incoming 2026'!$J$2:$J$990,Summary!A97) -> 15 | C97: =COUNTIF('Outgoing 2026'!$I$2:$I$961,Summary!A97) -> 59
A98: Manajemen risiko | B98: =COUNTIF('Incoming 2026'!$J$2:$J$990,Summary!A98) -> 0 | C98: =COUNTIF('Outgoing 2026'!$I$2:$I$961,Summary!A98) -> 2
A104: PIC Surat Keluar 2026
A105: Dept | B105: Incoming | C105: Open | D105: Level 1 | E105: Level 2 | F105: lewat 30d | G105: lewat 14d | H105: lewat 7d | I105: > 30 | J105: > 14 | K105: > 7 | L105: < 7
A106: PMO Infill | B106: =COUNTIF('Incoming 2026'!$N$2:$N$990,Summary!A106) -> 78 | C106: =COUNTIFS('Incoming 2026'!$N$2:$N$990,Summary!A106,'Incoming 2026'!$L$2:$L$990,$C$105) -> 25 | D106: =COUNTIFS('Incoming 2026'!$N$2:$N$990,Summary!A106,'Incoming 2026'!$M$2:$M$990,$D$105) -> 6 | E106: =COUNTIFS('Incoming 2026'!$N$2:$N$990,Summary!A106,'Incoming 2026'!$M$2:$M$990,$E$105) -> 19 | F106: =COUNTIFS('Incoming 2026'!$N$2:$N$990,Summary!A106,'Incoming 2026'!$R$2:$R$990,$F$105) -> 16 | G106: =COUNTIFS('Incoming 2026'!$N$2:$N$990,Summary!A106,'Incoming 2026'!$R$2:$R$990,$G$105) -> 0 | H106: =COUNTIFS('Incoming 2026'!$N$2:$N$990,Summary!A106,'Incoming 2026'!$R$2:$R$990,$H$105) -> 0 | I106: 16 | J106: 15 | K106: 1
A107: Compliance | B107: =COUNTIF('Incoming 2026'!$N$2:$N$990,Summary!A107) -> 39 | C107: =COUNTIFS('Incoming 2026'!$N$2:$N$990,Summary!A107,'Incoming 2026'!$L$2:$L$990,$C$105) -> 3 | D107: =COUNTIFS('Incoming 2026'!$N$2:$N$990,Summary!A107,'Incoming 2026'!$M$2:$M$990,$D$105) -> 1 | E107: =COUNTIFS('Incoming 2026'!$N$2:$N$990,Summary!A107,'Incoming 2026'!$M$2:$M$990,$E$105) -> 2 | F107: =COUNTIFS('Incoming 2026'!$N$2:$N$990,Summary!A107,'Incoming 2026'!$R$2:$R$990,$F$105) -> 0 | G107: =COUNTIFS('Incoming 2026'!$N$2:$N$990,Summary!A107,'Incoming 2026'!$R$2:$R$990,$G$105) -> 0 | H107: =COUNTIFS('Incoming 2026'!$N$2:$N$990,Summary!A107,'Incoming 2026'!$R$2:$R$990,$H$105) -> 0 | I107: 0 | J107: 0 | K107: 0
A108: Finance | B108: =COUNTIF('Incoming 2026'!$N$2:$N$990,Summary!A108) -> 5 | C108: =COUNTIFS('Incoming 2026'!$N$2:$N$990,Summary!A108,'Incoming 2026'!$L$2:$L$990,$C$105) -> 1 | D108: =COUNTIFS('Incoming 2026'!$N$2:$N$990,Summary!A108,'Incoming 2026'!$M$2:$M$990,$D$105) -> 0 | E108: =COUNTIFS('Incoming 2026'!$N$2:$N$990,Summary!A108,'Incoming 2026'!$M$2:$M$990,$E$105) -> 1 | F108: =COUNTIFS('Incoming 2026'!$N$2:$N$990,Summary!A108,'Incoming 2026'!$R$2:$R$990,$F$105) -> 1 | G108: =COUNTIFS('Incoming 2026'!$N$2:$N$990,Summary!A108,'Incoming 2026'!$R$2:$R$990,$G$105) -> 0 | H108: =COUNTIFS('Incoming 2026'!$N$2:$N$990,Summary!A108,'Incoming 2026'!$R$2:$R$990,$H$105) -> 0 | I108: 1 | J108: 1 | K108: 0
A109: PMO NC | B109: =COUNTIF('Incoming 2026'!$N$2:$N$990,Summary!A109) -> 14 | C109: =COUNTIFS('Incoming 2026'!$N$2:$N$990,Summary!A109,'Incoming 2026'!$L$2:$L$990,$C$105) -> 2 | D109: =COUNTIFS('Incoming 2026'!$N$2:$N$990,Summary!A109,'Incoming 2026'!$M$2:$M$990,$D$105) -> 2 | E109: =COUNTIFS('Incoming 2026'!$N$2:$N$990,Summary!A109,'Incoming 2026'!$M$2:$M$990,$E$105) -> 0 | F109: =COUNTIFS('Incoming 2026'!$N$2:$N$990,Summary!A109,'Incoming 2026'!$R$2:$R$990,$F$105) -> 2 | G109: =COUNTIFS('Incoming 2026'!$N$2:$N$990,Summary!A109,'Incoming 2026'!$R$2:$R$990,$G$105) -> 0 | H109: =COUNTIFS('Incoming 2026'!$N$2:$N$990,Summary!A109,'Incoming 2026'!$R$2:$R$990,$H$105) -> 1 | I109: 2 | J109: 0 | K109: 2
A110: PMO Cyclical | B110: =COUNTIF('Incoming 2026'!$N$2:$N$990,Summary!A110) -> 8 | C110: =COUNTIFS('Incoming 2026'!$N$2:$N$990,Summary!A110,'Incoming 2026'!$L$2:$L$990,$C$105) -> 0 | D110: =COUNTIFS('Incoming 2026'!$N$2:$N$990,Summary!A110,'Incoming 2026'!$M$2:$M$990,$D$105) -> 0 | E110: =COUNTIFS('Incoming 2026'!$N$2:$N$990,Summary!A110,'Incoming 2026'!$M$2:$M$990,$E$105) -> 0 | F110: =COUNTIFS('Incoming 2026'!$N$2:$N$990,Summary!A110,'Incoming 2026'!$R$2:$R$990,$F$105) -> 0 | G110: =COUNTIFS('Incoming 2026'!$N$2:$N$990,Summary!A110,'Incoming 2026'!$R$2:$R$990,$G$105) -> 0 | H110: =COUNTIFS('Incoming 2026'!$N$2:$N$990,Summary!A110,'Incoming 2026'!$R$2:$R$990,$H$105) -> 0 | I110: 0 | J110: 0 | K110: 0
A111: PMO; Permit | B111: =COUNTIF('Incoming 2026'!$N$2:$N$990,Summary!A111) -> 1 | C111: =COUNTIFS('Incoming 2026'!$N$2:$N$990,Summary!A111,'Incoming 2026'!$L$2:$L$990,$C$105) -> 0 | D111: =COUNTIFS('Incoming 2026'!$N$2:$N$990,Summary!A111,'Incoming 2026'!$M$2:$M$990,$D$105) -> 0 | E111: =COUNTIFS('Incoming 2026'!$N$2:$N$990,Summary!A111,'Incoming 2026'!$M$2:$M$990,$E$105) -> 0 | F111: =COUNTIFS('Incoming 2026'!$N$2:$N$990,Summary!A111,'Incoming 2026'!$R$2:$R$990,$F$105) -> 0 | G111: =COUNTIFS('Incoming 2026'!$N$2:$N$990,Summary!A111,'Incoming 2026'!$R$2:$R$990,$G$105) -> 0 | H111: =COUNTIFS('Incoming 2026'!$N$2:$N$990,Summary!A111,'Incoming 2026'!$R$2:$R$990,$H$105) -> 0 | I111: 0 | J111: 0 | K111: 0
A112: Planning | B112: =COUNTIF('Incoming 2026'!$N$2:$N$990,Summary!A112) -> 27 | C112: =COUNTIFS('Incoming 2026'!$N$2:$N$990,Summary!A112,'Incoming 2026'!$L$2:$L$990,$C$105) -> 16 | D112: =COUNTIFS('Incoming 2026'!$N$2:$N$990,Summary!A112,'Incoming 2026'!$M$2:$M$990,$D$105) -> 1 | E112: =COUNTIFS('Incoming 2026'!$N$2:$N$990,Summary!A112,'Incoming 2026'!$M$2:$M$990,$E$105) -> 11 | F112: =COUNTIFS('Incoming 2026'!$N$2:$N$990,Summary!A112,'Incoming 2026'!$R$2:$R$990,$F$105) -> 2 | G112: =COUNTIFS('Incoming 2026'!$N$2:$N$990,Summary!A112,'Incoming 2026'!$R$2:$R$990,$G$105) -> 0 | H112: =COUNTIFS('Incoming 2026'!$N$2:$N$990,Summary!A112,'Incoming 2026'!$R$2:$R$990,$H$105) -> 3 | I112: 2 | J112: 8 | K112: 0
A113: PGO | B113: =COUNTIF('Incoming 2026'!$N$2:$N$990,Summary!A113) -> 9 | C113: =COUNTIFS('Incoming 2026'!$N$2:$N$990,Summary!A113,'Incoming 2026'!$L$2:$L$990,$C$105) -> 1 | D113: =COUNTIFS('Incoming 2026'!$N$2:$N$990,Summary!A113,'Incoming 2026'!$M$2:$M$990,$D$105) -> 1 | E113: =COUNTIFS('Incoming 2026'!$N$2:$N$990,Summary!A113,'Incoming 2026'!$M$2:$M$990,$E$105) -> 0 | F113: =COUNTIFS('Incoming 2026'!$N$2:$N$990,Summary!A113,'Incoming 2026'!$R$2:$R$990,$F$105) -> 0 | G113: =COUNTIFS('Incoming 2026'!$N$2:$N$990,Summary!A113,'Incoming 2026'!$R$2:$R$990,$G$105) -> 0 | H113: =COUNTIFS('Incoming 2026'!$N$2:$N$990,Summary!A113,'Incoming 2026'!$R$2:$R$990,$H$105) -> 0 | I113: 0 | J113: 0 | K113: 0
A114: WQA | B114: =COUNTIF('Incoming 2026'!$N$2:$N$990,Summary!A114) -> 2 | C114: =COUNTIFS('Incoming 2026'!$N$2:$N$990,Summary!A114,'Incoming 2026'!$L$2:$L$990,$C$105) -> 0 | D114: =COUNTIFS('Incoming 2026'!$N$2:$N$990,Summary!A114,'Incoming 2026'!$M$2:$M$990,$D$105) -> 0 | E114: =COUNTIFS('Incoming 2026'!$N$2:$N$990,Summary!A114,'Incoming 2026'!$M$2:$M$990,$E$105) -> 0 | F114: =COUNTIFS('Incoming 2026'!$N$2:$N$990,Summary!A114,'Incoming 2026'!$R$2:$R$990,$F$105) -> 0 | G114: =COUNTIFS('Incoming 2026'!$N$2:$N$990,Summary!A114,'Incoming 2026'!$R$2:$R$990,$G$105) -> 0 | H114: =COUNTIFS('Incoming 2026'!$N$2:$N$990,Summary!A114,'Incoming 2026'!$R$2:$R$990,$H$105) -> 0 | I114: 0 | J114: 0 | K114: 0
A115: Legal | B115: =COUNTIF('Incoming 2026'!$N$2:$N$990,Summary!A115) -> 1 | C115: =COUNTIFS('Incoming 2026'!$N$2:$N$990,Summary!A115,'Incoming 2026'!$L$2:$L$990,$C$105) -> 0 | D115: =COUNTIFS('Incoming 2026'!$N$2:$N$990,Summary!A115,'Incoming 2026'!$M$2:$M$990,$D$105) -> 0 | E115: =COUNTIFS('Incoming 2026'!$N$2:$N$990,Summary!A115,'Incoming 2026'!$M$2:$M$990,$E$105) -> 0 | F115: =COUNTIFS('Incoming 2026'!$N$2:$N$990,Summary!A115,'Incoming 2026'!$R$2:$R$990,$F$105) -> 0 | G115: =COUNTIFS('Incoming 2026'!$N$2:$N$990,Summary!A115,'Incoming 2026'!$R$2:$R$990,$G$105) -> 0 | H115: =COUNTIFS('Incoming 2026'!$N$2:$N$990,Summary!A115,'Incoming 2026'!$R$2:$R$990,$H$105) -> 0 | I115: 0 | J115: 0 | K115: 0
A116: Permit | B116: =COUNTIF('Incoming 2026'!$N$2:$N$990,Summary!A116) -> 19 | C116: =COUNTIFS('Incoming 2026'!$N$2:$N$990,Summary!A116,'Incoming 2026'!$L$2:$L$990,$C$105) -> 2 | D116: =COUNTIFS('Incoming 2026'!$N$2:$N$990,Summary!A116,'Incoming 2026'!$M$2:$M$990,$D$105) -> 1 | E116: =COUNTIFS('Incoming 2026'!$N$2:$N$990,Summary!A116,'Incoming 2026'!$M$2:$M$990,$E$105) -> 1 | F116: =COUNTIFS('Incoming 2026'!$N$2:$N$990,Summary!A116,'Incoming 2026'!$R$2:$R$990,$F$105) -> 0 | G116: =COUNTIFS('Incoming 2026'!$N$2:$N$990,Summary!A116,'Incoming 2026'!$R$2:$R$990,$G$105) -> 0 | H116: =COUNTIFS('Incoming 2026'!$N$2:$N$990,Summary!A116,'Incoming 2026'!$R$2:$R$990,$H$105) -> 0 | I116: 0 | J116: 0 | K116: 0
A117: PMO Infill / PMO TM | B117: =COUNTIF('Incoming 2026'!$N$2:$N$990,Summary!A117) -> 3 | C117: =COUNTIFS('Incoming 2026'!$N$2:$N$990,Summary!A117,'Incoming 2026'!$L$2:$L$990,$C$105) -> 0 | D117: =COUNTIFS('Incoming 2026'!$N$2:$N$990,Summary!A117,'Incoming 2026'!$M$2:$M$990,$D$105) -> 0 | E117: =COUNTIFS('Incoming 2026'!$N$2:$N$990,Summary!A117,'Incoming 2026'!$M$2:$M$990,$E$105) -> 0 | F117: =COUNTIFS('Incoming 2026'!$N$2:$N$990,Summary!A117,'Incoming 2026'!$R$2:$R$990,$F$105) -> 0 | G117: =COUNTIFS('Incoming 2026'!$N$2:$N$990,Summary!A117,'Incoming 2026'!$R$2:$R$990,$G$105) -> 0 | H117: =COUNTIFS('Incoming 2026'!$N$2:$N$990,Summary!A117,'Incoming 2026'!$R$2:$R$990,$H$105) -> 1 | I117: 2 | J117: 0 | K117: 2
... A119: HSE | B119: =COUNTIF('Incoming 2026'!$N$2:$N$990,Summary!A119) -> 52 | C119: =COUNTIFS('Incoming 2026'!$N$2:$N$990,Summary!A119,'Incoming 2026'!$L$2:$L$990,$C$105) -> 29 | D119: =COUNTIFS('Incoming 2026'!$N$2:$N$990,Summary!A119,'Incoming 2026'!$M$2:$M$990,$D$105) -> 29 | E119: =COUNTIFS('Incoming 2026'!$N$2:$N$990,Summary!A119,'Incoming 2026'!$M$2:$M$990,$E$105) -> 0 | F119: =COUNTIFS('Incoming 2026'!$N$2:$N$990,Summary!A119,'Incoming 2026'!$R$2:$R$990,$F$105) -> 0 | G119: =COUNTIFS('Incoming 2026'!$N$2:$N$990,Summary!A119,'Incoming 2026'!$R$2:$R$990,$G$105) -> 0 | H119: =COUNTIFS('Incoming 2026'!$N$2:$N$990,Summary!A119,'Incoming 2026'!$R$2:$R$990,$H$105) -> 0 | I119: 0 | J119: 1 | K119: 3

Sheet Reminder
A1: Reminder Surat Masuk
A2: No | B2: Nomor Surat | C2: Perihal | D2: Keterangan | E2: PIC | F2: Due Date | G2: Status
A3: 1 | B3: e-72456/PS.04.00 | C3: Permintaan Pemenuhan Realisasi Investasi Amandemen dan Pernyataan Kembali Perjanjian Greenfield Periode Tahun 2026 | D3: PAM JAYA mengingatkan ABJ untuk memenuhi kewajiban investasi sebagaimana PKS A&R Greenfield | E3: Compliance; PGO; Legal A. Levi; Lusian F; Bahtera | F3: 46224
A4: 2 | B4: e-76222/PP.01.02 | C4: Teguran Permintaan Pemenuhan Kewajiban Penyelesaian Paket Pekerjaan Ketiga atau Tanggal Operasi Komersial 5 April 2026 | D4: PAM JAYA menyampaikan progres TOK 5 April 2026, di mana dari 108 program terdapat 18 program batal, 30 selesai, dan 60 masih berjalan, serta meminta PT ABJ memastikan penyelesaian pekerjaan, kelengkapan dokumen, perizinan, dan pembaruan progres sesuai ketentuan. | E4: PMO/PGO-Suci/Lusian F | F4: 46224
A5: 3 | B5: e-76340/PS.04.06 | C5: Permintaan Program Kepastian Kualitas terkait Kualitas Pekerjaan pada Proyek Bundling | D5: ABJ diminta menyampaikan dan menjalankan program kepastian kualitas (SOP, ITP, checklist) untuk seluruh tahap proyek, serta memastikan pekerjaan sesuai standar dan mematuhi perjanjian dengan PAM JAYA. | E5: Compliance; PGO; QMS-A. Levi; Lusian F; Sri H | F5: 46224
A6: 4 | B6: e-76450/PP.00.02 | C6: Permintaan Penyampaian Konfirmasi Progress Infill Percepatan | D6: PT ABJ belum menyampaikan pemutakhiran Desain Akhir Proyek Greenfield. ABJ diminta unggah data ke BIM, pembaruan database dan status pekerjaan, serta kepatuhan terhadap perjanjian kerja sama. | E6: Planning-Aji S | F6: 46224
A7: 5 | B7: E-77961/PP.01.02 | C7: Surat Teguran atas Tidak Sesuainya Penerapan Aspek Keselamatan dan Kesehatan Kerja (K3) dan Ketidaksesuaian Pelaksanaan Pengurugan dan Perbaikan Bekas Galian yang Berdampak pada Kecelakaan Lalu Lintas dan Citra Buruk PAM JAYA pada Masyarakat | D7: PAM JAYA meminta ABJ untuk menindaklanjuti seluruh temuan dalam 1x24 jam; Melaksanakan pengawasan dan monitoring; Memastikan tidak adanya pelanggaran K3 | E7: HSE-Irsan/Suhendro | F7: 46224
A8: 6 | B8: e-78854/PP.01.02 | C8: Teguran Penerapan Aspek K3 pada proyek Buaran Hilir | D8: Teguran berulang atas atas pelanggaran K3 berulang pada proyek Buaran Hilir dan meminta perbaikan segera, pengawasan lebih ketat, penerapan K3 yang konsisten, serta kepatuhan penuh terhadap ketentuan perjanjian. | E8: HSE-Irsan/Suhendro | F8: 46224
A9: 7 | B9: e-78852/PS.04.06 | C9: Pemuktahiran Hak Akses PAM JAYA | D9: PAM JAYA meminta PT ABJ memberikan akses kepada karyawan dan perwakilan sah PAM JAYA untuk memasuki lokasi proyek sesuai ketentuan perjanjian. (152 user) | E9: Compliance-A. Levi | F9: 46224
A10: 8 | B10: 271/SCI-KPI/V/2026 | C10: Tanggapan atas Surat PT Air Bersih Jakarta No. ABJ/DIR/EKS/05.26/0511 Tentang Penyampaian Informasi Proyek SPAM Buaran 3 Hilir – PC 161 JDU | D10: ABJ diminta untuk membuat justifikasi teknis dan justifikasi finansial dalam perubahan metode pemasangan pipa crossing | E10: PMO Infill-Topan | F10: 46224
A11: 9 | B11: 1960/PS.04.05/EKST/V/2026 | C11: Permintaan Pemenuhan Perizinan Pekerjaan TOK 5 Oktober 2026 | D11: (i) ABJ wajib menyelesaikan seluruh perizinan proyek. (ii) PAM JAYA meminta percepatan izin untuk target TOK 5 Oktober 2026. (iii) ABJ wajib lapor progres perizinan rutin setiap Kamis pukul 15.00 WIB. (iv) Semua izin harus valid agar proyek tidak terlambat. | E11: Permit-Rudy | F11: 46224
A12: 10 | B12: 1969/PS.04.04/EKST/V/2026 | C12: Surat Teguran atas Tidak Sesuainya Penerapan Aspek Keselamatan dan Kesehatan Kerja(K3) yang berdampak pada Kecelakaan dan Citra Buruk PAM JAYA pada Masyarakat | D12: teguran berulang kepada ABJ atas pelanggaran K3 yang menyebabkan kecelakaan dan keluhan masyarakat, serta mewajibkan ABJ segera melakukan perbaikan, meningkatkan pengawasan, bertanggung jawab atas insiden, dan mencegah kejadian serupa terulang. | E12: HSE-Irsan/Suhendro | F12: 46224
A13: 11 | B13: 1970/PS.04.04/EKST/V/2026 | C13: Permintaan Komitmen atas Seluruh Fasilitas Baru Siap Dioperasikan Sesuai Ketentuan Dokumen Amandemen dan Pernyataan Kembali Perjanjian Kerja sama Bundling | D13: PAM JAYA menemukan kebocoran pada pipa Trunk Main P5 SPAM Buaran 3 Hilir setelah pekerjaan dinyatakan selesai oleh PT ABJ. Oleh karena itu, PT ABJ diminta memperbaiki kebocoran, memastikan kualitas pekerjaan agar tidak terulang, dan mempercepat operasional fasilitas untuk mendukung target cakupan layanan air minum 100%. | E13: PMO TM-Puji R | F13: 46224
A14: 12 | B14: e-80724/PP.01.02 | C14: Teguran atas Ketidaksesuaian Pelaksanaan Pengurugan dan Perbaikan Bekas Galian yang Berdampak pada Gangguan Lalu Lintas dan Keterlambatan Penyelesaian Proyek pada Program Infill SPAM Buaran III | D14: PAM JAYA menemukan 168 titik bekas galian yang belum diperbaiki sesuai standar, penerapan K3 yang belum memadai, gangguan lalu lintas, serta pekerjaan yang menimbulkan keluhan masyarakat dan pemberitaan negatif pada PAMJAYA (wilayah condet) | ABJ diminta untuk segera perbaikin hal tersebut | E14: HSE-Suhendro | F14: 46224
... A45: 43 | B45: e-83262/PS.04.01 | C45: Penyampaian Hasil Inspeksi Perawatan Peralatan di IPA Buaran | D45: dari hasil Inspeksi terjadwal perawatan alat di IPA Buaran 1, IPA Buaran 2, dan IPA Buaran 3 yang dilakukan tanggal 20 Mei 2026, Pamjaya menemukan 26 temuan, dan ABJ diminta menindaklanjuti dalam 14 hari kalender | E45: Produksi-Wahyudian | F45: 46224

Sheet Outgoing 2026
A1: No | B1: Nomor Surat | C1: Tanggal Surat | D1: Penerima | E1: Perihal | F1: Deskripsi | G1: Produksi/Project | H1: Lokasi | I1: Kategori | J1: Due Date | K1: Status | L1: DIC | M1: PIC | N1: Durasi | O1: Durasi (Hari) | Q1: =TODAY() -> 46218
A2: 1 | B2: ABJ/DIR/EKS/01.26/0001 | C2: 46024 | D2: PAM JAYA | E2: Usulan Diskusi Mengenai Konsultan Independen atas Perhitungan Tagihan KBA | G2: Project | H2: Greenfield | I2: Keuangan, Pembayaran, Investasi | K2: Closed | L2: Compliance | M2: Indradi | N2: =DATEDIF(C2,$Q$1,"Y")&" tahun, "&DATEDIF(C2,$Q$1,"YM")&" bulan, "&DATEDIF(C2,$Q$1,"MD")&" hari" -> 0 tahun, 6 bulan, 13 hari | O2: =TODAY()-C2 -> 194
A3: 2 | B3: ABJ/DIR/EKS/01.26/0002 | C3: 46024 | D3: PAM JAYA | E3: Penyampaian Progres Penyelesaian Pekerjaan Program TOK 5 Oktober 2025 | G3: Project | H3: Greenfield | I3: Konstruksi Program Greenfield | K3: Info | L3: PGO | M3: Angelika | N3: =DATEDIF(C3,$Q$1,"Y")&" tahun, "&DATEDIF(C3,$Q$1,"YM")&" bulan, "&DATEDIF(C3,$Q$1,"MD")&" hari" -> 0 tahun, 6 bulan, 13 hari | O3: =TODAY()-C3 -> 194
A4: 3 | B4: ABJ/DIR/EKS/01.26/0003 | C4: 46024 | D4: PAM JAYA | E4: Pemasangan Pipa Ramset Pada Program Master Meter Binton | G4: Project | H4: Jatiluhur Hilir | I4: Konstruksi Program Greenfield | K4: Info | L4: PMO Infill | M4: Muhrojin | N4: =DATEDIF(C4,$Q$1,"Y")&" tahun, "&DATEDIF(C4,$Q$1,"YM")&" bulan, "&DATEDIF(C4,$Q$1,"MD")&" hari" -> 0 tahun, 6 bulan, 13 hari | O4: =TODAY()-C4 -> 194
A5: 4 | B5: ABJ/DIR/EKS/01.26/0004 | C5: 46024 | D5: KPI | E5: Permintaan Laporan Verifikasi KPI atas Program Rehabilitasi Proyek Greenfield (IPA Buaran III) | G5: Project | H5: Buaran 3 Hulu | I5: Administrasi & Dokumentasi | K5: Open | L5: Compliance | M5: Indradi | N5: =DATEDIF(C5,$Q$1,"Y")&" tahun, "&DATEDIF(C5,$Q$1,"YM")&" bulan, "&DATEDIF(C5,$Q$1,"MD")&" hari" -> 0 tahun, 6 bulan, 13 hari | O5: =TODAY()-C5 -> 194
A6: 5 | B6: ABJ/DIR/EKS/01.26/0009 | C6: 46027 | D6: Lurah Rawamangun | E6: Surat Pemberitahuan | G6: Project | H6: Greenfield | I6: Konstruksi Program Greenfield | K6: Info | L6: PMO TM | M6: Suci | N6: =DATEDIF(C6,$Q$1,"Y")&" tahun, "&DATEDIF(C6,$Q$1,"YM")&" bulan, "&DATEDIF(C6,$Q$1,"MD")&" hari" -> 0 tahun, 6 bulan, 10 hari | O6: =TODAY()-C6 -> 191
A7: 6 | B7: ABJ/DIR/EKS/01.26/0010 | C7: 46027 | D7: PAM JAYA | E7: Tagihan Air Curah Perjanjian Brownfield – Periode Desember 2025 | G7: Corporate | H7: Corporate | I7: Keuangan, Pembayaran, Investasi | K7: Closed | L7: Compliance | M7: Indradi | N7: =DATEDIF(C7,$Q$1,"Y")&" tahun, "&DATEDIF(C7,$Q$1,"YM")&" bulan, "&DATEDIF(C7,$Q$1,"MD")&" hari" -> 0 tahun, 6 bulan, 10 hari | O7: =TODAY()-C7 -> 191
A8: 7 | B8: ABJ/DIR/EKS/01.26/0011 | C8: 46027 | D8: PAM JAYA | E8: Tagihan Air Curah Perjanjian Greenfield - Periode Desember 2025 | G8: Corporate | H8: Corporate | I8: Keuangan, Pembayaran, Investasi | K8: Closed | L8: Compliance | M8: Indradi | N8: =DATEDIF(C8,$Q$1,"Y")&" tahun, "&DATEDIF(C8,$Q$1,"YM")&" bulan, "&DATEDIF(C8,$Q$1,"MD")&" hari" -> 0 tahun, 6 bulan, 10 hari | O8: =TODAY()-C8 -> 191
A9: 8 | B9: ABJ/DIR/EKS/01.26/0012 | C9: 46027 | D9: PAM JAYA | E9: Pembaharuan Informasi Dokumen Persyaratan Penyelesaian Pekerjaan Fasilitas Distribusi Baru Paket Kedua TOK Oktober 2025 | G9: Project | H9: Greenfield | I9: Administrasi & Dokumentasi | K9: Info | L9: PGO | M9: Angelika | N9: =DATEDIF(C9,$Q$1,"Y")&" tahun, "&DATEDIF(C9,$Q$1,"YM")&" bulan, "&DATEDIF(C9,$Q$1,"MD")&" hari" -> 0 tahun, 6 bulan, 10 hari | O9: =TODAY()-C9 -> 191
A10: 9 | B10: ABJ/DIR/EKS/01.26/0013 | C10: 46027 | D10: PAM JAYA | E10: Laporan Bulanan Kualitas Air Baku dan Air Curah Periode Desember 2025 | G10: Produksi | H10: ALL WTP | I10: Monitoring & Pelaporan | K10: Info | L10: WQA | M10: Novi | N10: =DATEDIF(C10,$Q$1,"Y")&" tahun, "&DATEDIF(C10,$Q$1,"YM")&" bulan, "&DATEDIF(C10,$Q$1,"MD")&" hari" -> 0 tahun, 6 bulan, 10 hari | O10: =TODAY()-C10 -> 191
A11: 10 | B11: ABJ/DIR/EKS/01.26/0014 | C11: 46027 | D11: Direktur Jenderal Administrasi Hukum Umum cq. Direktur Badan Usaha Kementerian Hukum | E11: Permohonan Perbaikan Data Email dan Nomor Telepon PT AIR BERSIH JAKARTA | G11: Corporate | H11: Corporate | I11: Kontrak & Legal | K11: Info | L11: Legal - Moya | M11: Angelina | N11: =DATEDIF(C11,$Q$1,"Y")&" tahun, "&DATEDIF(C11,$Q$1,"YM")&" bulan, "&DATEDIF(C11,$Q$1,"MD")&" hari" -> 0 tahun, 6 bulan, 10 hari | O11: =TODAY()-C11 -> 191
A12: 11 | B12: ABJ/DIR/EKS/01.26/0015 | C12: 46028 | D12: Bank OCBC NISP, Tbk - Agency & Trust Services | E12: Penyampaian Salinan Asli Polis Asuransi | G12: Corporate | H12: Corporate | I12: Keuangan, Pembayaran, Investasi | K12: Info | L12: Finance | M12: Nurul S | N12: =DATEDIF(C12,$Q$1,"Y")&" tahun, "&DATEDIF(C12,$Q$1,"YM")&" bulan, "&DATEDIF(C12,$Q$1,"MD")&" hari" -> 0 tahun, 6 bulan, 9 hari | O12: =TODAY()-C12 -> 190
A13: 12 | B13: ABJ/DIR/EKS/01.26/0016 | C13: 46028 | D13: PT Bank Central Asia Tbk | E13: Permohonan Penghapusan Lampiran 6 Step-In dalam Persyaratan Lebih Lanjut | G13: Corporate | H13: Corporate | I13: Kontrak & Legal | K13: Info | L13: Legal | M13: Bahtera N | N13: =DATEDIF(C13,$Q$1,"Y")&" tahun, "&DATEDIF(C13,$Q$1,"YM")&" bulan, "&DATEDIF(C13,$Q$1,"MD")&" hari" -> 0 tahun, 6 bulan, 9 hari | O13: =TODAY()-C13 -> 190
... A144: 144 | B144: ABJ/DIR/EKS/02.26/0150 | C144: 46065 | D144: PAM JAYA | E144: Pembatalan Program Basri | G144: Project | H144: Jatiluhur Hilir | I144: Konstruksi Program Greenfield | K144: Info | L144: PMO Infill | M144: Aan | N144: =DATEDIF(C144,$Q$1,"Y")&" tahun, "&DATEDIF(C144,$Q$1,"YM")&" bulan, "&DATEDIF(C144,$Q$1,"MD")&" hari" -> 0 tahun, 5 bulan, 3 hari | O144: =TODAY()-C144 -> 153
A145: 145 | B145: ABJ/DIR/EKS/02.26/0151 | C145: 46065 | K145: Info | N145: =DATEDIF(C145,$Q$1,"Y")&" tahun, "&DATEDIF(C145,$Q$1,"YM")&" bulan, "&DATEDIF(C145,$Q$1,"MD")&" hari" -> 0 tahun, 5 bulan, 3 hari | O145: =TODAY()-C145 -> 153
A146: 146 | B146: ABJ/DIR/EKS/02.26/0152 | C146: 46066 | D146: PAM JAYA | E146: Tanggapan Atas Surat PAM JAYA No. e-69891.TK.03.04 Perihal Dokumen Risk Register Brownfield 2026 dan Risk Register New Connection 2026 | G146: Project | H146: Greenfield | I146: Manajemen Risiko | K146: Info | L146: QMS | M146: Dio | N146: =DATEDIF(C146,$Q$1,"Y")&" tahun, "&DATEDIF(C146,$Q$1,"YM")&" bulan, "&DATEDIF(C146,$Q$1,"MD")&" hari" -> 0 tahun, 5 bulan, 2 hari | O146: =TODAY()-C146 -> 152
A147: 147 | B147: ABJ/DIR/EKS/02.26/0153 | C147: 46066 | D147: PT. Bestindo Putra Mandiri | E147: Pernyataan Pembayaran Biaya Penggunaan Air | G147: Project | H147: Greenfield | I147: Keuangan, Pembayaran, Investasi | K147: Info | L147: Finance | M147: Nurul S | N147: =DATEDIF(C147,$Q$1,"Y")&" tahun, "&DATEDIF(C147,$Q$1,"YM")&" bulan, "&DATEDIF(C147,$Q$1,"MD")&" hari" -> 0 tahun, 5 bulan, 2 hari | O147: =TODAY()-C147 -> 152
A148: 148 | B148: ABJ/DIR/EKS/02.26/0154 | C148: 46066 | D148: PAM JAYA | E148: Proses Pembahasan Alur untuk Pengakuan Investasi SL dan Cyble | G148: Project | H148: Greenfield | I148: Sambungan Langsung | K148: Info | L148: PMO NC | M148: A. Levi | N148: =DATEDIF(C148,$Q$1,"Y")&" tahun, "&DATEDIF(C148,$Q$1,"YM")&" bulan, "&DATEDIF(C148,$Q$1,"MD")&" hari" -> 0 tahun, 5 bulan, 2 hari | O148: =TODAY()-C148 -> 152
A149: 149 | B149: ABJ/DIR/EKS/02.26/0155 | C149: 46066 | D149: PAM JAYA | E149: Penjelasan Kondisi Eksternal Penyebab Keterlambatan Pemasangan dan Pengembalian Field Activity (“FA”) Sambungan Langsung (“SL”) as per 13 Februari 2026 | G149: Project | H149: Greenfield | I149: Sambungan Langsung | K149: Info | L149: PMO NC | M149: A. Levi | N149: =DATEDIF(C149,$Q$1,"Y")&" tahun, "&DATEDIF(C149,$Q$1,"YM")&" bulan, "&DATEDIF(C149,$Q$1,"MD")&" hari" -> 0 tahun, 5 bulan, 2 hari | O149: =TODAY()-C149 -> 152
A150: 150 | B150: ABJ/DIR/EKS/02.26/0156 | C150: 46066 | D150: PAM JAYA | E150: Penyampaian Informasi Terkait Tagihan Air Curah Perjanjian Brownfield dan Greenfield – Periode Penagihan Januari 2026 | G150: Project | H150: Project | I150: Keuangan, Pembayaran, Investasi | K150: Closed | L150: Compliance | M150: Indradi | N150: =DATEDIF(C150,$Q$1,"Y")&" tahun, "&DATEDIF(C150,$Q$1,"YM")&" bulan, "&DATEDIF(C150,$Q$1,"MD")&" hari" -> 0 tahun, 5 bulan, 2 hari | O150: =TODAY()-C150 -> 152
A151: 151 | B151: ABJ/DIR/EKS/02.26/0157 | C151: 46066 | D151: PAM JAYA | E151: Penyampaian Dokumen Pendukung Program Konstruksi SPAM Karian Hilir | G151: Project | H151: Greenfield | I151: Konstruksi Program Greenfield | K151: Info | L151: PMO TM | M151: Suci | N151: =DATEDIF(C151,$Q$1,"Y")&" tahun, "&DATEDIF(C151,$Q$1,"YM")&" bulan, "&DATEDIF(C151,$Q$1,"MD")&" hari" -> 0 tahun, 5 bulan, 2 hari | O151: =TODAY()-C151 -> 152
A152: 152 | B152: ABJ/DIR/EKS/02.26/0158 | C152: 46071 | D152: PAM JAYA | E152: Alternatif Water Meter ITRON Aquadis 15mm Menggantikan Tipe Water Meter Multimag 15mm | G152: Project | H152: Greenfield | I152: Sambungan Langsung | K152: Info | L152: PMO NC | M152: A. Levi | N152: =DATEDIF(C152,$Q$1,"Y")&" tahun, "&DATEDIF(C152,$Q$1,"YM")&" bulan, "&DATEDIF(C152,$Q$1,"MD")&" hari" -> 0 tahun, 4 bulan, 27 hari | O152: =TODAY()-C152 -> 147
A153: 153 | B153: ABJ/DIR/EKS/02.26/0159 | C153: 46071 | D153: PT. Bestindo Putra Mandiri | E153: Surat Teguran BPM - Updating Stok Material | G153: Project | H153: Greenfield | I153: Konstruksi Program Greenfield | K153: Info | L153: PMO NC | M153: A. Levi | N153: =DATEDIF(C153,$Q$1,"Y")&" tahun, "&DATEDIF(C153,$Q$1,"YM")&" bulan, "&DATEDIF(C153,$Q$1,"MD")&" hari" -> 0 tahun, 4 bulan, 27 hari | O153: =TODAY()-C153 -> 147
A154: 154 | B154: ABJ/DIR/EKS/02.26/0160 | C154: 46071 | D154: PAM JAYA | E154: Tanggapan PJ e 71125 PP 01 02 Teguran Keterlambatan Realisasi SL Desember 2025 | G154: Project | H154: Greenfield | I154: Sambungan Langsung | K154: Info | L154: PMO NC | M154: A. Levi | N154: =DATEDIF(C154,$Q$1,"Y")&" tahun, "&DATEDIF(C154,$Q$1,"YM")&" bulan, "&DATEDIF(C154,$Q$1,"MD")&" hari" -> 0 tahun, 4 bulan, 27 hari | O154: =TODAY()-C154 -> 147
A155: 155 | B155: ABJ/DIR/EKS/02.26/0161 | C155: 46071 | D155: Keluarahan Bambu Apus | E155: Pemberitahuan Kegiatan Pekerjaan Galian Pipa di wilayah Keluarahan Bambu Apus | G155: Project | H155: Greenfield | I155: Koordinasi & Sosialisasi | K155: Info | L155: PMO TM | M155: Suci | N155: =DATEDIF(C155,$Q$1,"Y")&" tahun, "&DATEDIF(C155,$Q$1,"YM")&" bulan, "&DATEDIF(C155,$Q$1,"MD")&" hari" -> 0 tahun, 4 bulan, 27 hari | O155: =TODAY()-C155 -> 147
A156: 156 | B156: ABJ/DIR/EKS/02.26/0162 | C156: 46071 | D156: Keluarahan Setu | E156: Pemberitahuan Kegiatan Pekerjaan Galian Pipa di wilayah Keluarahan Setu | G156: Project | H156: Greenfield | I156: Koordinasi & Sosialisasi | K156: Info | L156: PMO TM | M156: Suci | N156: =DATEDIF(C156,$Q$1,"Y")&" tahun, "&DATEDIF(C156,$Q$1,"YM")&" bulan, "&DATEDIF(C156,$Q$1,"MD")&" hari" -> 0 tahun, 4 bulan, 27 hari | O156: =TODAY()-C156 -> 147
A157: 157 | B157: ABJ/DIR/EKS/02.26/0163 | C157: 46071 | D157: Kecamatan Pademangan | E157: Pemberitahuan Kegiatan Pekerjaan Galian Pipa di wilayah Kecamatan Pademangan | G157: Project | H157: Greenfield | I157: Koordinasi & Sosialisasi | K157: Info | L157: PMO TM | M157: Suci | N157: =DATEDIF(C157,$Q$1,"Y")&" tahun, "&DATEDIF(C157,$Q$1,"YM")&" bulan, "&DATEDIF(C157,$Q$1,"MD")&" hari" -> 0 tahun, 4 bulan, 27 hari | O157: =TODAY()-C157 -> 147
... A294: 294 | B294: ABJ/DIR/EKS/03.26/0302 | C294: 46098 | D294: PAM JAYA | E294: Undangan Uji Komisioning SPAM Buaran III Hilir – Trunkmain (P6 dan P11) | G294: Project | H294: Buaran 3 Hilir | I294: Konstruksi Program Greenfield | K294: Info | L294: PMO TM | M294: Puji R | N294: =DATEDIF(C294,$Q$1,"Y")&" tahun, "&DATEDIF(C294,$Q$1,"YM")&" bulan, "&DATEDIF(C294,$Q$1,"MD")&" hari" -> 0 tahun, 3 bulan, 28 hari | O294: =TODAY()-C294 -> 120
A295: 295 | B295: ABJ/DIR/EKS/03.26/0303 | C295: 46098 | D295: PT. Bina Lestari Lingkungan Sejahtera | E295: Permohonan Bantuan BLSS Dalam Percepatan Verifikasi Dokumen | G295: Corporate | I295: Koordinasi & Sosialisasi | K295: Info | L295: PGO | M295: Lusian F | N295: =DATEDIF(C295,$Q$1,"Y")&" tahun, "&DATEDIF(C295,$Q$1,"YM")&" bulan, "&DATEDIF(C295,$Q$1,"MD")&" hari" -> 0 tahun, 3 bulan, 28 hari | O295: =TODAY()-C295 -> 120
A296: 296 | B296: ABJ/DIR/EKS/03.26/0304 | C296: 46098 | D296: PAM JAYA | E296: Pemberitahuan Pelaksanaan Pekerjaan Masa Libur Lebaran - Proyek Karian Serpong Trunk Main Pesanggrahan TMPSG 04 | G296: Project | H296: Karian Serpong Hilir | I296: Konstruksi Program Greenfield | K296: Info | L296: PMO TM | M296: Suci | N296: =DATEDIF(C296,$Q$1,"Y")&" tahun, "&DATEDIF(C296,$Q$1,"YM")&" bulan, "&DATEDIF(C296,$Q$1,"MD")&" hari" -> 0 tahun, 3 bulan, 28 hari | O296: =TODAY()-C296 -> 120
A297: 297 | B297: ABJ/DIR/EKS/03.26/0305 | C297: 46098 | D297: PAM JAYA | K297: Info | N297: =DATEDIF(C297,$Q$1,"Y")&" tahun, "&DATEDIF(C297,$Q$1,"YM")&" bulan, "&DATEDIF(C297,$Q$1,"MD")&" hari" -> 0 tahun, 3 bulan, 28 hari | O297: =TODAY()-C297 -> 120
A298: 298 | B298: ABJ/DIR/EKS/03.26/0306 | C298: 46098 | D298: Agen Fasilitas PT. BCA | E298: Permohonan Perpanjangan Periode Ketersediaan untuk Fasilitas E1 | G298: Corporate | H298: Corporate | I298: Kontrak & Legal | K298: Info | L298: Legal | M298: Bahtera N | N298: =DATEDIF(C298,$Q$1,"Y")&" tahun, "&DATEDIF(C298,$Q$1,"YM")&" bulan, "&DATEDIF(C298,$Q$1,"MD")&" hari" -> 0 tahun, 3 bulan, 28 hari | O298: =TODAY()-C298 -> 120
A299: 299 | B299: ABJ/DIR/EKS/03.26/0307 | C299: 46098 | D299: PAM JAYA | E299: Penjelasan Kondisi Eksternal Penyebab Keterlambatan Pemasangan dan Pengembalian Field Activity (“FA”) Sambungan Langsung (“SL”) as per 17 Maret 2026 | G299: Project | H299: Greenfield | I299: Sambungan Langsung | K299: Info | L299: PMO NC | M299: Angelika | N299: =DATEDIF(C299,$Q$1,"Y")&" tahun, "&DATEDIF(C299,$Q$1,"YM")&" bulan, "&DATEDIF(C299,$Q$1,"MD")&" hari" -> 0 tahun, 3 bulan, 28 hari | O299: =TODAY()-C299 -> 120
A300: 300 | B300: ABJ/DIR/EKS/03.26/0308 | C300: 46098 | D300: PT Bestindo Putra Mandiri | E300: Teguran Ketidakpatuhan Pekerjaan Harian Pemasangan Cyble | G300: Project | H300: Greenfield | I300: Sambungan Langsung | K300: Info | L300: PMO NC | M300: Angelika | N300: =DATEDIF(C300,$Q$1,"Y")&" tahun, "&DATEDIF(C300,$Q$1,"YM")&" bulan, "&DATEDIF(C300,$Q$1,"MD")&" hari" -> 0 tahun, 3 bulan, 28 hari | O300: =TODAY()-C300 -> 120
A301: 301 | B301: ABJ/DIR/EKS/03.26/0309 | C301: 46098 | D301: PAM JAYA | K301: Info | N301: =DATEDIF(C301,$Q$1,"Y")&" tahun, "&DATEDIF(C301,$Q$1,"YM")&" bulan, "&DATEDIF(C301,$Q$1,"MD")&" hari" -> 0 tahun, 3 bulan, 28 hari | O301: =TODAY()-C301 -> 120
A302: 302 | B302: ABJ/DIR/EKS/03.26/0310 | C302: 46099 | D302: PAM JAYA | E302: Penyampaian Informasi Proyek SPAM Jatiluhur Hilir - Program MCD Jatipadang | G302: Project | H302: Jatiluhur Hilir | I302: Konstruksi Program Greenfield | K302: Info | L302: PMO Infill | M302: Danny L | N302: =DATEDIF(C302,$Q$1,"Y")&" tahun, "&DATEDIF(C302,$Q$1,"YM")&" bulan, "&DATEDIF(C302,$Q$1,"MD")&" hari" -> 0 tahun, 3 bulan, 27 hari | O302: =TODAY()-C302 -> 119
A303: 303 | B303: ABJ/DIR/EKS/03.26/0311 | C303: 46099 | D303: PAM JAYA | E303: Pemberitahuan Perubahan Jadwal Flushing - SPAM Buaran Hilir Paket P6 dan P11 | G303: Project | H303: Buaran 3 Hilir | I303: Konstruksi Program Greenfield | K303: Info | L303: PMO TM | M303: Puji R | N303: =DATEDIF(C303,$Q$1,"Y")&" tahun, "&DATEDIF(C303,$Q$1,"YM")&" bulan, "&DATEDIF(C303,$Q$1,"MD")&" hari" -> 0 tahun, 3 bulan, 27 hari | O303: =TODAY()-C303 -> 119
A304: 304 | B304: ABJ/DIR/EKS/03.26/0313 | C304: 46106 | D304: PAM JAYA | E304: Penyampaian Laporan Penyelesaian Uji Komisioning PC 162 Centex Gg Jengki dan PC 162 Hanjuang | G304: Project | H304: Greenfield | I304: Konstruksi Program Greenfield | K304: Info | L304: PMO Infill | M304: Topan | N304: =DATEDIF(C304,$Q$1,"Y")&" tahun, "&DATEDIF(C304,$Q$1,"YM")&" bulan, "&DATEDIF(C304,$Q$1,"MD")&" hari" -> 0 tahun, 3 bulan, 20 hari | O304: =TODAY()-C304 -> 112
A305: 305 | B305: ABJ/DIR/EKS/03.26/0314 | C305: 46106 | D305: PAM JAYA | E305: Tanggapan Surat PAM JAYA Nomor 1186/PS.04.04/EKST/III/2026 Mengenai Pembayaran atas Realisasi Kontrak Berbasis Angsuran (KBA) Tahun 2025 | G305: Project | H305: Greenfield | I305: Keuangan, Pembayaran, Investasi | K305: Closed | L305: Compliance | M305: A. Levi | N305: =DATEDIF(C305,$Q$1,"Y")&" tahun, "&DATEDIF(C305,$Q$1,"YM")&" bulan, "&DATEDIF(C305,$Q$1,"MD")&" hari" -> 0 tahun, 3 bulan, 20 hari | O305: =TODAY()-C305 -> 112
A306: 306 | B306: ABJ/DIR/EKS/03.26/0315 | C306: 46106 | D306: PAM JAYA | E306: Permintaan Percepatan Persetujuan Program Brownfield Sebagai Pemenuhan ISO 14001:2015 | G306: Project | H306: Cyclical | I306: Perencanaan Program Rehabilitasi | K306: Open | L306: PMO Cyclical | M306: Agus H | N306: =DATEDIF(C306,$Q$1,"Y")&" tahun, "&DATEDIF(C306,$Q$1,"YM")&" bulan, "&DATEDIF(C306,$Q$1,"MD")&" hari" -> 0 tahun, 3 bulan, 20 hari | O306: =TODAY()-C306 -> 112
A307: 307 | B307: ABJ/DIR/EKS/03.26/0316 | C307: 46106 | D307: PAM JAYA | E307: Penyampaian Informasi Proyek SPAM Jatiluhur Hilir - Program MCD Jatipadang | G307: Project | H307: Jatiluhur Hilir | I307: Konstruksi Program Greenfield | K307: Info | L307: PMO Infill | M307: Yodi | N307: =DATEDIF(C307,$Q$1,"Y")&" tahun, "&DATEDIF(C307,$Q$1,"YM")&" bulan, "&DATEDIF(C307,$Q$1,"MD")&" hari" -> 0 tahun, 3 bulan, 20 hari | O307: =TODAY()-C307 -> 112
A308: 308 | B308: ABJ/DIR/EKS/03.26/0317 | C308: 46106 | D308: PAM JAYA | E308: Surat Penyampaian Informasi Proyek SPAM Jatiluhur Hilir - Program PT Honor Decoration Internasional | G308: Project | H308: Jatiluhur Hilir | I308: Konstruksi Program Greenfield | K308: Info | L308: PMO Infill | M308: Yodi | N308: =DATEDIF(C308,$Q$1,"Y")&" tahun, "&DATEDIF(C308,$Q$1,"YM")&" bulan, "&DATEDIF(C308,$Q$1,"MD")&" hari" -> 0 tahun, 3 bulan, 20 hari | O308: =TODAY()-C308 -> 112
A309: 309 | B309: ABJ/DIR/EKS/03.26/0318 | C309: 46106 | D309: PAM JAYA | E309: Permohonan Persetujuan Perubahan Water Meter Itron Tipe Water Meter DN 15 mm Menjadi Tipe Aquadis DN15 mm | G309: Project | H309: Greenfield | I309: Sambungan Langsung | K309: Info | L309: PMO NC | M309: Angelika | N309: =DATEDIF(C309,$Q$1,"Y")&" tahun, "&DATEDIF(C309,$Q$1,"YM")&" bulan, "&DATEDIF(C309,$Q$1,"MD")&" hari" -> 0 tahun, 3 bulan, 20 hari | O309: =TODAY()-C309 -> 112
A310: 310 | B310: ABJ/DIR/EKS/03.26/0319 | C310: 46106 | D310: PAM JAYA | E310: Penjelasan Kondisi Eksternal Penyebab Keterlambatan Pemasangan dan Pengembalian Field Activity (“FA”) Sambungan Langsung (“SL”) as per 25 Maret 2026 | G310: Project | H310: Greenfield | I310: Sambungan Langsung | K310: Info | L310: PMO NC | M310: Angelika | N310: =DATEDIF(C310,$Q$1,"Y")&" tahun, "&DATEDIF(C310,$Q$1,"YM")&" bulan, "&DATEDIF(C310,$Q$1,"MD")&" hari" -> 0 tahun, 3 bulan, 20 hari | O310: =TODAY()-C310 -> 112
A311: 311 | B311: ABJ/DIR/EKS/03.26/0320 | C311: 46107 | D311: PAM JAYA | E311: Pengiriman Revisi Pertama Jadwal Program Rehabilitasi Tahun 2026 | G311: Project | H311: Cyclical | I311: Perencanaan Program Rehabilitasi | K311: Info | L311: PMO Cyclical | M311: Agus H | N311: =DATEDIF(C311,$Q$1,"Y")&" tahun, "&DATEDIF(C311,$Q$1,"YM")&" bulan, "&DATEDIF(C311,$Q$1,"MD")&" hari" -> 0 tahun, 3 bulan, 19 hari | O311: =TODAY()-C311 -> 111
A312: 312 | B312: ABJ/DIR/EKS/03.26/0321 | C312: 46107 | D312: Bestindo | E312: Penyampaian Jadwal Program Rehabilitasi (Cyclical Maintenance) 2026 | G312: Project | H312: Cyclical | I312: Perencanaan Program Rehabilitasi | K312: Info | L312: PMO Cyclical | M312: Agus H | N312: =DATEDIF(C312,$Q$1,"Y")&" tahun, "&DATEDIF(C312,$Q$1,"YM")&" bulan, "&DATEDIF(C312,$Q$1,"MD")&" hari" -> 0 tahun, 3 bulan, 19 hari | O312: =TODAY()-C312 -> 111
A313: 313 | B313: ABJ/DIR/EKS/03.26/0322 | C313: 46107 | D313: PAM JAYA | E313: Penjelasan Kondisi Eksternal Penyebab Keterlambatan Pemasangan dan Pengembalian Field Activity (“FA”) Sambungan Langsung (“SL”) as per 26 Maret 2026 | G313: Project | H313: Greenfield | I313: Sambungan Langsung | K313: Info | L313: PMO NC | M313: Angelika | N313: =DATEDIF(C313,$Q$1,"Y")&" tahun, "&DATEDIF(C313,$Q$1,"YM")&" bulan, "&DATEDIF(C313,$Q$1,"MD")&" hari" -> 0 tahun, 3 bulan, 19 hari | O313: =TODAY()-C313 -> 111
... A349: 349 | B349: ABJ/DIR/EKS/04.26/0362 | C349: 46115 | D349: PAM JAYA | E349: Penyampaian Laporan Penyelesaian Uji Komisioning Project Greenfield – SPAM Buaran Hilir Trunkmain P6 | G349: Project | H349: Buaran 3 Hilir | I349: Konstruksi Program Greenfield | K349: Info | L349: PMO TM | M349: Suci | N349: =DATEDIF(C349,$Q$1,"Y")&" tahun, "&DATEDIF(C349,$Q$1,"YM")&" bulan, "&DATEDIF(C349,$Q$1,"MD")&" hari" -> 0 tahun, 3 bulan, 12 hari | O349: =TODAY()-C349 -> 103
A350: 350 | B350: ABJ/DIR/EKS/04.26/0363 | C350: 46115 | D350: PAM JAYA | K350: Info | N350: =DATEDIF(C350,$Q$1,"Y")&" tahun, "&DATEDIF(C350,$Q$1,"YM")&" bulan, "&DATEDIF(C350,$Q$1,"MD")&" hari" -> 0 tahun, 3 bulan, 12 hari | O350: =TODAY()-C350 -> 103
A351: 351 | B351: ABJ/DIR/EKS/04.26/0364 | C351: 46115 | D351: PAM JAYA | K351: Info | N351: =DATEDIF(C351,$Q$1,"Y")&" tahun, "&DATEDIF(C351,$Q$1,"YM")&" bulan, "&DATEDIF(C351,$Q$1,"MD")&" hari" -> 0 tahun, 3 bulan, 12 hari | O351: =TODAY()-C351 -> 103
A352: 352 | B352: ABJ/DIR/EKS/04.26/0365 | C352: 46117 | D352: PAM JAYA | E352: Pembaruan Informasi Penyampaian Dokumen Persyaratan Penyelesaian Pekerjaan Fasilitas Distribusi Baru Paket Ketiga TOK April 2026 | G352: Project | H352: Greenfield | I352: Administrasi & Dokumentasi Program Greenfield | K352: Info | L352: PGO | M352: Lusian F | N352: =DATEDIF(C352,$Q$1,"Y")&" tahun, "&DATEDIF(C352,$Q$1,"YM")&" bulan, "&DATEDIF(C352,$Q$1,"MD")&" hari" -> 0 tahun, 3 bulan, 10 hari | O352: =TODAY()-C352 -> 101
A353: 353 | B353: ABJ/DIR/EKS/04.26/0369 | C353: 46118 | D353: PAM JAYA | E353: Tagihan Air Curah Perjanjian Brownfield - Periode Maret 2026 | G353: Corporate | H353: ALL WTP | I353: Keuangan, Pembayaran, Investasi | K353: Closed | L353: Compliance | M353: A. Levi | N353: =DATEDIF(C353,$Q$1,"Y")&" tahun, "&DATEDIF(C353,$Q$1,"YM")&" bulan, "&DATEDIF(C353,$Q$1,"MD")&" hari" -> 0 tahun, 3 bulan, 9 hari | O353: =TODAY()-C353 -> 100
A354: 354 | B354: ABJ/DIR/EKS/04.26/0370 | C354: 46118 | D354: PAM JAYA | E354: Tagihan Air Curah Perjanjian Greenfield - Periode Maret 2026 | G354: Corporate | H354: Greenfield | I354: Keuangan, Pembayaran, Investasi | K354: Closed | L354: Compliance | M354: A. Levi | N354: =DATEDIF(C354,$Q$1,"Y")&" tahun, "&DATEDIF(C354,$Q$1,"YM")&" bulan, "&DATEDIF(C354,$Q$1,"MD")&" hari" -> 0 tahun, 3 bulan, 9 hari | O354: =TODAY()-C354 -> 100
A355: 355 | B355: ABJ/DIR/EKS/04.26/0371 | C355: 46118 | D355: Camat Kecamatan Pasar Minggu - Ibu Guguk Trirahayu | E355: Pelaksanaan Pekerjaan Pemasangan Pipa Air Minum di Kecamatan Pasar Minggu, Jakarta Selatan. | G355: Project | H355: Greenfield | I355: Koordinasi & Sosialisasi | K355: Info | L355: Corcomm | M355: Ninuk | N355: =DATEDIF(C355,$Q$1,"Y")&" tahun, "&DATEDIF(C355,$Q$1,"YM")&" bulan, "&DATEDIF(C355,$Q$1,"MD")&" hari" -> 0 tahun, 3 bulan, 9 hari | O355: =TODAY()-C355 -> 100
A356: 356 | B356: ABJ/DIR/EKS/04.26/0372 | C356: 46118 | D356: Camat Kecamatan Tebet | E356: Pelaksanaan Pekerjaan Pemasangan Pipa Air Minum di Kecamatan Tebet, Jakarta Selatan. | G356: Project | H356: Greenfield | I356: Koordinasi & Sosialisasi | K356: Info | L356: Corcomm | M356: Ninuk | N356: =DATEDIF(C356,$Q$1,"Y")&" tahun, "&DATEDIF(C356,$Q$1,"YM")&" bulan, "&DATEDIF(C356,$Q$1,"MD")&" hari" -> 0 tahun, 3 bulan, 9 hari | O356: =TODAY()-C356 -> 100
A357: 357 | B357: ABJ/DIR/EKS/04.26/0373 | C357: 46118 | D357: Kecamatan Cakung | E357: Pelaksanaan Pekerjaan Pemasangan Pipa Air Minum di Kecamatan Cakung | G357: Project | H357: Greenfield | I357: Koordinasi & Sosialisasi | K357: Info | L357: Corcomm | M357: Ninuk | N357: =DATEDIF(C357,$Q$1,"Y")&" tahun, "&DATEDIF(C357,$Q$1,"YM")&" bulan, "&DATEDIF(C357,$Q$1,"MD")&" hari" -> 0 tahun, 3 bulan, 9 hari | O357: =TODAY()-C357 -> 100
A358: 358 | B358: ABJ/DIR/EKS/04.26/0374 | C358: 46118 | D358: Kecamatan Mampang Prapatan | E358: Pelaksanaan Pekerjaan Pemasangan Pipa Air Minum di Kecamatan Mampang Prapatan | G358: Project | H358: Greenfield | I358: Koordinasi & Sosialisasi | K358: Info | L358: Corcomm | M358: Ninuk | N358: =DATEDIF(C358,$Q$1,"Y")&" tahun, "&DATEDIF(C358,$Q$1,"YM")&" bulan, "&DATEDIF(C358,$Q$1,"MD")&" hari" -> 0 tahun, 3 bulan, 9 hari | O358: =TODAY()-C358 -> 100
A359: 359 | B359: ABJ/DIR/EKS/04.26/0375 | C359: 46118 | D359: Kecamatan Duren Sawit | E359: Pelaksanaan Pekerjaan Pemasangan Pipa Air Minum di Kecamatan Duren Sawit | G359: Project | H359: Greenfield | I359: Koordinasi & Sosialisasi | K359: Info | L359: Corcomm | M359: Ninuk | N359: =DATEDIF(C359,$Q$1,"Y")&" tahun, "&DATEDIF(C359,$Q$1,"YM")&" bulan, "&DATEDIF(C359,$Q$1,"MD")&" hari" -> 0 tahun, 3 bulan, 9 hari | O359: =TODAY()-C359 -> 100
A360: 360 | B360: ABJ/DIR/EKS/04.26/0376 | C360: 46118 | D360: Kecamatan Cilincing | E360: Pelaksanaan Pekerjaan Pemasangan Pipa Air Minum di Kecamatan Cilincing | G360: Project | H360: Greenfield | I360: Koordinasi & Sosialisasi | K360: Info | L360: Corcomm | M360: Ninuk | N360: =DATEDIF(C360,$Q$1,"Y")&" tahun, "&DATEDIF(C360,$Q$1,"YM")&" bulan, "&DATEDIF(C360,$Q$1,"MD")&" hari" -> 0 tahun, 3 bulan, 9 hari | O360: =TODAY()-C360 -> 100
A361: 361 | B361: ABJ/DIR/EKS/04.26/0377 | C361: 46118 | D361: PAM JAYA | E361: DED dan RAB Perluasan Jaringan Untuk 2 Lokasi Infill Ad hoc Sambungan Baru Proyek SPAM Karian Serpong Hilir | G361: Project | H361: Karian Serpong Hilir | I361: Perencanaan Program Greenfield | K361: Info | L361: Planning | M361: Aji S | N361: =DATEDIF(C361,$Q$1,"Y")&" tahun, "&DATEDIF(C361,$Q$1,"YM")&" bulan, "&DATEDIF(C361,$Q$1,"MD")&" hari" -> 0 tahun, 3 bulan, 9 hari | O361: =TODAY()-C361 -> 100
A362: 362 | B362: ABJ/DIR/EKS/04.26/0378 | C362: 46118 | D362: PAM JAYA | E362: Informasi Mengenai Pekerjaan Rehabilitasi Sludge Dewatering System | G362: Project | H362: Cyclical | I362: Konstruksi Program Rehabilitasi | K362: Info | L362: PMO Cyclical | M362: Agus H | N362: =DATEDIF(C362,$Q$1,"Y")&" tahun, "&DATEDIF(C362,$Q$1,"YM")&" bulan, "&DATEDIF(C362,$Q$1,"MD")&" hari" -> 0 tahun, 3 bulan, 9 hari | O362: =TODAY()-C362 -> 100
A363: 363 | B363: ABJ/DIR/EKS/04.26/0379 | C363: 46118 | D363: PAM JAYA | E363: Permohonan Dokumen Pendukung Perizinan Proyek Reservoir Pejompongan 2 | G363: Project | H363: Jatiluhur Hilir | I363: Perizinan | K363: Info | L363: PMO TM | M363: Suci | N363: =DATEDIF(C363,$Q$1,"Y")&" tahun, "&DATEDIF(C363,$Q$1,"YM")&" bulan, "&DATEDIF(C363,$Q$1,"MD")&" hari" -> 0 tahun, 3 bulan, 9 hari | O363: =TODAY()-C363 -> 100
... A374: 374 | B374: ABJ/DIR/EKS/04.26/0390 | C374: 46119 | D374: PAM JAYA | E374: Penjelasan Kondisi Eksternal Penyebab Keterlambatan Pemasangan dan Pengembalian Field Activity (“FA”) Sambungan Langsung (“SL”) as per 07 April 2026 | G374: Project | H374: Greenfield | I374: Sambungan Langsung | K374: Info | L374: PMO NC | M374: Angelika | N374: =DATEDIF(C374,$Q$1,"Y")&" tahun, "&DATEDIF(C374,$Q$1,"YM")&" bulan, "&DATEDIF(C374,$Q$1,"MD")&" hari" -> 0 tahun, 3 bulan, 8 hari | O374: =TODAY()-C374 -> 99
A375: 375 | B375: ABJ/DIR/EKS/04.26/0391 | C375: 46120 | D375: PAM JAYA | K375: Info | N375: =DATEDIF(C375,$Q$1,"Y")&" tahun, "&DATEDIF(C375,$Q$1,"YM")&" bulan, "&DATEDIF(C375,$Q$1,"MD")&" hari" -> 0 tahun, 3 bulan, 7 hari | O375: =TODAY()-C375 -> 98
A376: 376 | B376: ABJ/DIR/EKS/04.26/0392 | C376: 46120 | D376: Soul Creative | E376: Evaluasi Ruang Lingkup Kerjasama | G376: Corporate | H376: Corporate | I376: Kontrak & Legal | K376: Info | L376: Legal | M376: Bahtera N | N376: =DATEDIF(C376,$Q$1,"Y")&" tahun, "&DATEDIF(C376,$Q$1,"YM")&" bulan, "&DATEDIF(C376,$Q$1,"MD")&" hari" -> 0 tahun, 3 bulan, 7 hari | O376: =TODAY()-C376 -> 98
A377: 377 | B377: ABJ/DIR/EKS/04.26/0393 | C377: 46120 | D377: PT Bank OCBC NISP Tbk. – Agency & Trust Services | E377: Penyampaian Salinan Asli Polis Asuransi | G377: Project | H377: Project | I377: Kontrak & Legal | K377: Info | L377: Finance | M377: Nurul S | N377: =DATEDIF(C377,$Q$1,"Y")&" tahun, "&DATEDIF(C377,$Q$1,"YM")&" bulan, "&DATEDIF(C377,$Q$1,"MD")&" hari" -> 0 tahun, 3 bulan, 7 hari | O377: =TODAY()-C377 -> 98
A378: 378 | B378: ABJ/DIR/EKS/04.26/0394 | C378: 46120 | D378: PAM JAYA | E378: Gangguan Operasional IPA Buaran 1 dan IPA Buaran 2 Pada Tanggal 26 Maret 2026 | G378: Produksi | H378: Buaran 1 & 2 | I378: Operation & Maintenance | K378: Info | L378: Produksi | M378: Wahyudian | N378: =DATEDIF(C378,$Q$1,"Y")&" tahun, "&DATEDIF(C378,$Q$1,"YM")&" bulan, "&DATEDIF(C378,$Q$1,"MD")&" hari" -> 0 tahun, 3 bulan, 7 hari | O378: =TODAY()-C378 -> 98
A379: 379 | B379: ABJ/DIR/EKS/04.26/0395 | C379: 46120 | D379: PAM JAYA | E379: Penjelasan Kondisi Eksternal Penyebab Keterlambatan Pemasangan dan Pengembalian Field Activity (“FA”) Sambungan Langsung (“SL”) as per 08 April 2026 | G379: Project | H379: Greenfield | I379: Sambungan Langsung | K379: Info | L379: PMO NC | M379: Angelika | N379: =DATEDIF(C379,$Q$1,"Y")&" tahun, "&DATEDIF(C379,$Q$1,"YM")&" bulan, "&DATEDIF(C379,$Q$1,"MD")&" hari" -> 0 tahun, 3 bulan, 7 hari | O379: =TODAY()-C379 -> 98
A380: 380 | B380: ABJ/DIR/EKS/04.26/0396 | C380: 46120 | D380: Camat Kecamatan Pancoran | E380: Pelaksanaan Pekerjaan Pemasangan Pipa Air Minum di Kecamatan Pancoran, Jakarta Selatan. | G380: Project | H380: Greenfield | I380: Koordinasi & Sosialisasi | K380: Info | L380: Corcomm | M380: Ninuk | N380: =DATEDIF(C380,$Q$1,"Y")&" tahun, "&DATEDIF(C380,$Q$1,"YM")&" bulan, "&DATEDIF(C380,$Q$1,"MD")&" hari" -> 0 tahun, 3 bulan, 7 hari | O380: =TODAY()-C380 -> 98
A381: 381 | B381: ABJ/DIR/EKS/04.26/0397 | C381: 46120 | D381: Camat Kecamatan Cipayung | E381: Pelaksanaan Pekerjaan Pemasangan Pipa Air Minum di Kecamatan Cipayung, Jakarta Timur | G381: Project | H381: Greenfield | I381: Koordinasi & Sosialisasi | K381: Info | L381: Corcomm | M381: Ninuk | N381: =DATEDIF(C381,$Q$1,"Y")&" tahun, "&DATEDIF(C381,$Q$1,"YM")&" bulan, "&DATEDIF(C381,$Q$1,"MD")&" hari" -> 0 tahun, 3 bulan, 7 hari | O381: =TODAY()-C381 -> 98
A382: 382 | B382: ABJ/DIR/EKS/04.26/0398 | C382: 46120 | D382: PAM JAYA | E382: Penyampaian Biaya Analisa Laboratorium Independen terkait Dispute Sample | G382: Project | H382: Produksi | I382: Keuangan, Pembayaran, Investasi | K382: Info | L382: WQA | M382: Novi | N382: =DATEDIF(C382,$Q$1,"Y")&" tahun, "&DATEDIF(C382,$Q$1,"YM")&" bulan, "&DATEDIF(C382,$Q$1,"MD")&" hari" -> 0 tahun, 3 bulan, 7 hari | O382: =TODAY()-C382 -> 98
A383: 383 | B383: ABJ/DIR/EKS/04.26/0399 | C383: 46121 | D383: PAM JAYA | E383: Usulan Pembatalan Rencana Proyek Pemasangan Pipa Puskesmas Pembantu Kembangan Selatan | G383: Project | H383: Greenfield | I383: Perencanaan Program Greenfield | K383: Info | L383: Planning | M383: Aji S | N383: =DATEDIF(C383,$Q$1,"Y")&" tahun, "&DATEDIF(C383,$Q$1,"YM")&" bulan, "&DATEDIF(C383,$Q$1,"MD")&" hari" -> 0 tahun, 3 bulan, 6 hari | O383: =TODAY()-C383 -> 97
A384: 384 | B384: ABJ/DIR/EKS/04.26/0400 | C384: 46121 | D384: Disnaker | E384: Laporan P2K3 kuartal 4 th 2025 | G384: Project | H384: Corporate | I384: HSE | K384: Info | L384: HSE | M384: Irsan | N384: =DATEDIF(C384,$Q$1,"Y")&" tahun, "&DATEDIF(C384,$Q$1,"YM")&" bulan, "&DATEDIF(C384,$Q$1,"MD")&" hari" -> 0 tahun, 3 bulan, 6 hari | O384: =TODAY()-C384 -> 97
A385: 385 | B385: ABJ/DIR/EKS/04.26/0401 | C385: 46121 | D385: PAM JAYA | E385: Permintaan Izin Pembobokan Sementara Pagar Pembatas Terhadap Pengangkutan Aset Terdahulu Program Rehabilitasi Tahun 2025 | G385: Project | H385: Cyclical | I385: Konstruksi Program Rehabilitasi | K385: Info | L385: Compliance | M385: A. Levi | N385: =DATEDIF(C385,$Q$1,"Y")&" tahun, "&DATEDIF(C385,$Q$1,"YM")&" bulan, "&DATEDIF(C385,$Q$1,"MD")&" hari" -> 0 tahun, 3 bulan, 6 hari | O385: =TODAY()-C385 -> 97
A386: 386 | B386: ABJ/DIR/EKS/04.26/0402 | C386: 46121 | D386: PAM JAYA | E386: Permohonan Penegasan dan Arahan Terkait Acuan Spesifikasi/Kriteria Teknis untuk NC CC | G386: Project | H386: Greenfield | I386: Sambungan Langsung | K386: Info | L386: PMO NC | M386: Angelika | N386: =DATEDIF(C386,$Q$1,"Y")&" tahun, "&DATEDIF(C386,$Q$1,"YM")&" bulan, "&DATEDIF(C386,$Q$1,"MD")&" hari" -> 0 tahun, 3 bulan, 6 hari | O386: =TODAY()-C386 -> 97
A387: 387 | B387: ABJ/DIR/EKS/04.26/0403 | C387: 46121 | D387: PAM JAYA | E387: Penjelasan Kondisi Eksternal Penyebab Keterlambatan Pemasangan dan Pengembalian Field Activity (“FA”) Sambungan Langsung (“SL”) as per 09 April 2026 | G387: Project | H387: Greenfield | I387: Sambungan Langsung | K387: Info | L387: PMO NC | M387: Angelika | N387: =DATEDIF(C387,$Q$1,"Y")&" tahun, "&DATEDIF(C387,$Q$1,"YM")&" bulan, "&DATEDIF(C387,$Q$1,"MD")&" hari" -> 0 tahun, 3 bulan, 6 hari | O387: =TODAY()-C387 -> 97
... A441: 441 | B441: ABJ/DIR/EKS/04.26/0456 | C441: 46135 | D441: PAM JAYA | E441: Penjelasan Kondisi Eksternal Penyebab Keterlambatan Pemasangan dan Pengembalian Field Activity (“FA”) Sambungan Langsung (“SL”) as per 23 April 2026 | G441: Project | H441: Greenfield | I441: Sambungan Langsung | K441: Info | L441: PMO NC | M441: Angelika | N441: =DATEDIF(C441,$Q$1,"Y")&" tahun, "&DATEDIF(C441,$Q$1,"YM")&" bulan, "&DATEDIF(C441,$Q$1,"MD")&" hari" -> 0 tahun, 2 bulan, 22 hari | O441: =TODAY()-C441 -> 83
A442: 442 | B442: ABJ/DIR/SCM/04.26/0457 | C442: 46136 | D442: PT Samoa Bersaudara Abadi | E442: Pembuatan Kontrak Jasa Pengangkutan Sampah ABJ bu | F442: SPH | G442: Corporate | H442: Corporate | I442: Kontrak & Legal | K442: Info | L442: SCM | M442: Wahyu Mardika | N442: =DATEDIF(C442,$Q$1,"Y")&" tahun, "&DATEDIF(C442,$Q$1,"YM")&" bulan, "&DATEDIF(C442,$Q$1,"MD")&" hari" -> 0 tahun, 2 bulan, 21 hari | O442: =TODAY()-C442 -> 82
A443: 443 | B443: ABJ/DIR/EKS/04.26/0458 | C443: 46136 | D443: PAM JAYA | E443: Penjelasan Kondisi Eksternal Penyebab Keterlambatan Pemasangan dan Pengembalian Field Activity (“FA”) Sambungan Langsung (“SL”) as per 24 April 2026 | G443: Project | H443: Greenfield | I443: Sambungan Langsung | K443: Info | L443: PMO NC | M443: Angelika | N443: =DATEDIF(C443,$Q$1,"Y")&" tahun, "&DATEDIF(C443,$Q$1,"YM")&" bulan, "&DATEDIF(C443,$Q$1,"MD")&" hari" -> 0 tahun, 2 bulan, 21 hari | O443: =TODAY()-C443 -> 82
A444: 444 | B444: ABJ/DIR/EKS/04.26/0459 | C444: 46136 | D444: PT CSM Corporatama (Indorent) | E444: Pembuatan Kontrak Jasa Sewa Mobil ABJ ke Indorent | G444: Corporate | H444: Corporate | I444: Kontrak & Legal | K444: Info | L444: SCM | M444: Wahyu Mardika | N444: =DATEDIF(C444,$Q$1,"Y")&" tahun, "&DATEDIF(C444,$Q$1,"YM")&" bulan, "&DATEDIF(C444,$Q$1,"MD")&" hari" -> 0 tahun, 2 bulan, 21 hari | O444: =TODAY()-C444 -> 82
A445: 445 | B445: ABJ/DIR/EKS/04.26/0461 | C445: 46139 | D445: PAM JAYA | E445: Tanggapan atas Surat PAM JAYA Nomor PJ 1324/PP.01.02-EKST-IV-2026 Terkait Teguran Atas Keterlambatan Pelaksanaan Program Rehabilitasi Proyek Brownfield Tahun 2026 | G445: Project | H445: Brownfield | I445: Konstruksi Program Rehabilitasi | K445: Info | L445: PMO Cyclical | M445: Agus H | N445: =DATEDIF(C445,$Q$1,"Y")&" tahun, "&DATEDIF(C445,$Q$1,"YM")&" bulan, "&DATEDIF(C445,$Q$1,"MD")&" hari" -> 0 tahun, 2 bulan, 18 hari | O445: =TODAY()-C445 -> 79
A446: 446 | B446: ABJ/DIR/EKS/04.26/0462 | C446: 46139 | D446: PAM JAYA | E446: Pengelolaan Aset Terdahulu Program Rehabilitasi Proyek Brownfield Tahun 2025 | G446: Project | H446: Brownfield | I446: Konstruksi Program Rehabilitasi | K446: Info | L446: PMO Cyclical | M446: Agus H | N446: =DATEDIF(C446,$Q$1,"Y")&" tahun, "&DATEDIF(C446,$Q$1,"YM")&" bulan, "&DATEDIF(C446,$Q$1,"MD")&" hari" -> 0 tahun, 2 bulan, 18 hari | O446: =TODAY()-C446 -> 79
A447: 447 | B447: ABJ/DIR/EKS/04.26/0463 | C447: 46139 | D447: PAM JAYA | E447: Penyampaian Dokumen Pendukung Program Konstruksi SPAM Buaran Hilir – P7, P8, S5, S6 | G447: Project | H447: Buaran 3 Hilir | I447: Konstruksi Program Greenfield | K447: Info | L447: PMO TM | M447: Suci | N447: =DATEDIF(C447,$Q$1,"Y")&" tahun, "&DATEDIF(C447,$Q$1,"YM")&" bulan, "&DATEDIF(C447,$Q$1,"MD")&" hari" -> 0 tahun, 2 bulan, 18 hari | O447: =TODAY()-C447 -> 79
A448: 448 | B448: ABJ/DIR/EKS/04.26/0464 | C448: 46139 | D448: PAM JAYA | E448: Pemberitahuan Penggantian Material Flange Adaptor Multi Joint Menjadi Stub Flang PC 161 JDU & TMCL10 | G448: Project | H448: Greenfield | I448: Konstruksi Program Greenfield | K448: Info | L448: PMO Infill | M448: Danny L | N448: =DATEDIF(C448,$Q$1,"Y")&" tahun, "&DATEDIF(C448,$Q$1,"YM")&" bulan, "&DATEDIF(C448,$Q$1,"MD")&" hari" -> 0 tahun, 2 bulan, 18 hari | O448: =TODAY()-C448 -> 79
A449: 449 | B449: ABJ/DIR/EKS/04.26/0465 | C449: 46139 | D449: PAM JAYA | E449: Penyampaian Informasi Proyek SPAM Jatiluhur Hilir – TMCL 10 Program Ciliwung | G449: Project | H449: Jatiluhur Hilir | I449: Konstruksi Program Greenfield | K449: Closed | L449: PMO Infill | M449: Danny L | N449: =DATEDIF(C449,$Q$1,"Y")&" tahun, "&DATEDIF(C449,$Q$1,"YM")&" bulan, "&DATEDIF(C449,$Q$1,"MD")&" hari" -> 0 tahun, 2 bulan, 18 hari | O449: =TODAY()-C449 -> 79
A450: 450 | B450: ABJ/DIR/EKS/04.26/0466 | C450: 46139 | D450: Soul Creative | E450: Undangan Pembahasan Evaluasi Ruang Lingkup Pekerjaan Soul Creative | G450: Corporate | H450: Corporate | I450: Kontrak & Legal | K450: Info | L450: Legal | M450: Bahtera N | N450: =DATEDIF(C450,$Q$1,"Y")&" tahun, "&DATEDIF(C450,$Q$1,"YM")&" bulan, "&DATEDIF(C450,$Q$1,"MD")&" hari" -> 0 tahun, 2 bulan, 18 hari | O450: =TODAY()-C450 -> 79
A451: 451 | B451: ABJ/DIR/EKS/04.26/0467 | C451: 46139 | D451: PAM JAYA | E451: Penjelasan Kondisi Eksternal Penyebab Keterlambatan Pemasangan dan Pengembalian Field Activity (“FA”) Sambungan Langsung (“SL”) as per 27 April 2026 | G451: Project | H451: Greenfield | I451: Sambungan Langsung | K451: Info | L451: PMO NC | M451: Angelika | N451: =DATEDIF(C451,$Q$1,"Y")&" tahun, "&DATEDIF(C451,$Q$1,"YM")&" bulan, "&DATEDIF(C451,$Q$1,"MD")&" hari" -> 0 tahun, 2 bulan, 18 hari | O451: =TODAY()-C451 -> 79
A452: 452 | B452: ABJ/DIR/EKS/04.26/0468 | C452: 46140 | D452: PAM JAYA | E452: Pembaharuan Informasi TOK Oktober 2026 Akibat Keterbatasan Bahan Baku Pipa HDPE | G452: Project | H452: Greenfield | I452: Perencanaan Program Greenfield | K452: Info | L452: Compliance | M452: A. Levi | N452: =DATEDIF(C452,$Q$1,"Y")&" tahun, "&DATEDIF(C452,$Q$1,"YM")&" bulan, "&DATEDIF(C452,$Q$1,"MD")&" hari" -> 0 tahun, 2 bulan, 17 hari | O452: =TODAY()-C452 -> 78
A453: 453 | B453: ABJ/DIR/EKS/04.26/0469 | C453: 46140 | D453: PAM JAYA | E453: Permintaan Adendum Sebagai Akibat Pekerjaan Non Master Schedule | G453: Project | H453: Greenfield | I453: Perencanaan Program Greenfield | K453: Open | L453: Compliance | M453: A. Levi | N453: =DATEDIF(C453,$Q$1,"Y")&" tahun, "&DATEDIF(C453,$Q$1,"YM")&" bulan, "&DATEDIF(C453,$Q$1,"MD")&" hari" -> 0 tahun, 2 bulan, 17 hari | O453: =TODAY()-C453 -> 78
A454: 454 | B454: ABJ/DIR/EKS/04.26/0470 | C454: 46140 | D454: PAM JAYA | E454: Permohonan Pengecualian Denda Keterlambatan Akibat Terlambatnya Penerbitan Izin | G454: Project | H454: Greenfield | I454: Konstruksi Program Greenfield | K454: Info | L454: Compliance | M454: A. Levi | N454: =DATEDIF(C454,$Q$1,"Y")&" tahun, "&DATEDIF(C454,$Q$1,"YM")&" bulan, "&DATEDIF(C454,$Q$1,"MD")&" hari" -> 0 tahun, 2 bulan, 17 hari | O454: =TODAY()-C454 -> 78
... A520: 520 | B520: ABJ/DIR/EKS/05.26/0538 | C520: 46157 | D520: PAM JAYA | E520: Pemberitahuan Uji Komisioning Program Rehabilitasi 46330A | G520: Project | H520: Brownfield | I520: Konstruksi Program Rehabilitasi | K520: Info | L520: PMO Cyclical | M520: Agus H | N520: =DATEDIF(C520,$Q$1,"Y")&" tahun, "&DATEDIF(C520,$Q$1,"YM")&" bulan, "&DATEDIF(C520,$Q$1,"MD")&" hari" -> 0 tahun, 2 bulan, 0 hari | O520: =TODAY()-C520 -> 61
A521: 521 | B521: 0008/AAJ/EKS//V/2026 | C521: 46157 | E521: Permohonan Perbaikan Data Email dan Nomor Telepon PT Aetra Air Jakarta | G521: Corporate | H521: Corporate | I521: Kontrak & Legal | K521: Info | L521: Legal | M521: Bahtera N | N521: =DATEDIF(C521,$Q$1,"Y")&" tahun, "&DATEDIF(C521,$Q$1,"YM")&" bulan, "&DATEDIF(C521,$Q$1,"MD")&" hari" -> 0 tahun, 2 bulan, 0 hari | O521: =TODAY()-C521 -> 61
A522: 522 | B522: ABJ/DIR/EKS/05.26/0539 | C522: 46157 | D522: Moya Indonesia | E522: Debit Note Iuran Driver BoD | G522: Corporate | H522: Corporate | I522: Keuangan, Pembayaran, Investasi | K522: Info | L522: Finance | M522: Nurul S | N522: =DATEDIF(C522,$Q$1,"Y")&" tahun, "&DATEDIF(C522,$Q$1,"YM")&" bulan, "&DATEDIF(C522,$Q$1,"MD")&" hari" -> 0 tahun, 2 bulan, 0 hari | O522: =TODAY()-C522 -> 61
A523: 523 | B523: ABJ/DIR/EKS/05.26/0540 | C523: 46157 | D523: Management Sakura Garden City | E523: Permohonan Izin Penggunaan Jalan di Kawasan Sakura Garden City | G523: Project | H523: Greenfield | I523: Perizinan | K523: Info | L523: Permit | M523: Rudy | N523: =DATEDIF(C523,$Q$1,"Y")&" tahun, "&DATEDIF(C523,$Q$1,"YM")&" bulan, "&DATEDIF(C523,$Q$1,"MD")&" hari" -> 0 tahun, 2 bulan, 0 hari | O523: =TODAY()-C523 -> 61
A524: 524 | B524: ABJ/DIR/EKS/05.26/0541 | C524: 46157 | D524: PAM JAYA | E524: Penjelasan Kondisi Eksternal Penyebab Keterlambatan Pemasangan dan Pengembalian Field Activity (“FA”) Sambungan Langsung (“SL”) as per 15 Mei 2026 | G524: Project | H524: Greenfield | I524: Sambungan Langsung | K524: Info | L524: PMO NC | M524: Angelika | N524: =DATEDIF(C524,$Q$1,"Y")&" tahun, "&DATEDIF(C524,$Q$1,"YM")&" bulan, "&DATEDIF(C524,$Q$1,"MD")&" hari" -> 0 tahun, 2 bulan, 0 hari | O524: =TODAY()-C524 -> 61
A525: 525 | B525: ABJ/DIR/EKS/05.26/0542 | C525: 46160 | D525: PAM JAYA | E525: SPAM Buaran III Hulu – Perubahan Program Pekerjaan Pembangunan Sarana Penunjang | G525: Project | H525: Buaran 3 Hulu | I525: Konstruksi Program Greenfield | K525: Info | L525: PMO | M525: A. Yudi | N525: =DATEDIF(C525,$Q$1,"Y")&" tahun, "&DATEDIF(C525,$Q$1,"YM")&" bulan, "&DATEDIF(C525,$Q$1,"MD")&" hari" -> 0 tahun, 1 bulan, 27 hari | O525: =TODAY()-C525 -> 58
A526: 526 | B526: ABJ/DIR/EKS/05.26/0543 | C526: 46160 | D526: PAM JAYA | E526: Undangan Uji Komisioning P001 Ruswandi | G526: Project | H526: Jatiluhur Hilir | I526: Konstruksi Program Greenfield | K526: Info | L526: PMO Infill | M526: Yodi | N526: =DATEDIF(C526,$Q$1,"Y")&" tahun, "&DATEDIF(C526,$Q$1,"YM")&" bulan, "&DATEDIF(C526,$Q$1,"MD")&" hari" -> 0 tahun, 1 bulan, 27 hari | O526: =TODAY()-C526 -> 58
A527: 527 | B527: ABJ/DIR/EKS/05.26/0544 | C527: 46160 | D527: Kejati DKJ | E527: Permintaan Advis Terkait Pembayaran Kontrak Bebasis Angsuran PT ABJ | G527: Corporate | H527: Corporate | I527: Kontrak & Legal | K527: Open | L527: Legal | M527: Bahtera N | N527: =DATEDIF(C527,$Q$1,"Y")&" tahun, "&DATEDIF(C527,$Q$1,"YM")&" bulan, "&DATEDIF(C527,$Q$1,"MD")&" hari" -> 0 tahun, 1 bulan, 27 hari | O527: =TODAY()-C527 -> 58
A528: 528 | B528: ABJ/DIR/EKS/05.26/0545 | C528: 46160 | D528: PAM JAYA | E528: Penjelasan Kondisi Eksternal Penyebab Keterlambatan Pemasangan dan Pengembalian Field Activity (“FA”) Sambungan Langsung (“SL”) as per 18 Mei 2026 | G528: Project | H528: Greenfield | I528: Sambungan Langsung | K528: Info | L528: PMO NC | M528: Angelika | N528: =DATEDIF(C528,$Q$1,"Y")&" tahun, "&DATEDIF(C528,$Q$1,"YM")&" bulan, "&DATEDIF(C528,$Q$1,"MD")&" hari" -> 0 tahun, 1 bulan, 27 hari | O528: =TODAY()-C528 -> 58
A529: 529 | B529: ABJ/DIR/EKS/05.26/0546 | C529: 46160 | D529: Bapak/Ibu Pimpinan Kebayoran Lama 3 First Mile Hub (SPX Express) | E529: Permohonan Izin Pelaksanaan Pekerjaan Pemasangan Jaringan Pipa (Open Cut) | G529: Project | H529: Greenfield | I529: Perizinan | K529: Info | L529: Permit | M529: Rudy | N529: =DATEDIF(C529,$Q$1,"Y")&" tahun, "&DATEDIF(C529,$Q$1,"YM")&" bulan, "&DATEDIF(C529,$Q$1,"MD")&" hari" -> 0 tahun, 1 bulan, 27 hari | O529: =TODAY()-C529 -> 58
...

Sheet Incoming 2026
A1: No | B1: Nomor Surat | C1: Tanggal Diterima | D1: Tanggal Surat | E1: Pengirim | F1: Perihal | G1: Deskripsi | H1: Produksi/Project | I1: Lokasi | J1: Kategori | K1: Due Date | L1: Status | M1: Level Status | N1: DIC | O1: PIC | P1: Durasi | Q1: Durasi (hari) | S1: Durasi Keterlambatan | T1: Durasi Deadline | U1: Keterangan | W1: =TODAY() -> 46218
A2: 1 | B2: 144/SCI-KPI/I/2026 | C2: 46027 | D2: 46024 | E2: KPI - Sucofindo | F2: Tanggapan atas Surat PT Air Bersih Jakarta No. ABJ/DIR/EKS/12.25/1126 Tentang Penyampaian Laporan Penyelesaian Uji Komisioning Project Greenfield - SPAM Karian Serpong Hilir Program Arman, Puspa, Porto | G2: Dokumen yang belum lengkap agar dilengkapi pada saat MC100 | H2: Project | I2: Karian Serpong Hilir | J2: Konstruksi Program Greenfield | L2: Info | M2: Info | N2: PMO Infill | O2: Ervin Y | P2: =DATEDIF(C2,$W$1,"Y")&" tahun, "&DATEDIF(C2,$W$1,"YM")&" bulan, "&DATEDIF(C2,$W$1,"MD")&" hari" -> 0 tahun, 6 bulan, 10 hari | Q2: =DATEDIF(C2,Summary!$A$1,"d") -> 191 | S2: {=_xlfn.IFS(Q2<=T2,T2,Q2<=T2*2,T2*2,Q2<=T2*3,T2*3,Q2>T2*3,">"&T2*3)} -> Info | T2: {=_xlfn.IFS(M2="Level 1",7,M2="Level 2",14,M2="Level 3","30",M2="Info","Info",M2="Closed","Closed")} -> Info
A3: 2 | B3: e-70214/PP.00.02 | C3: 46028 | D3: 46009 | E3: PAM JAYA | F3: Pemutakhiran Desain Akhir JDU JDB JDL dan SL Proyek Greenfield Regional Barat, Selatan, Utara, Pusat | G3: PAM JAYA meminta ABJ untuk melakukan survey sesuai lokasi pada surat terlampir | H3: Project | I3: Greenfield | J3: Perencanaan Program Greenfield | L3: Open | M3: Level 2 | N3: PMO Infill | O3: Danny L | P3: =DATEDIF(C3,$W$1,"Y")&" tahun, "&DATEDIF(C3,$W$1,"YM")&" bulan, "&DATEDIF(C3,$W$1,"MD")&" hari" -> 0 tahun, 6 bulan, 9 hari | Q3: =DATEDIF(C3,Summary!$A$1,"d") -> 190 | R3: lewat 30d | S3: {=_xlfn.IFS(Q3<=T3,T3,Q3<=T3*2,T3*2,Q3<=T3*3,T3*3,Q3>T3*3,">"&T3*3)} -> >42 | T3: {=_xlfn.IFS(M3="Level 1",7,M3="Level 2",14,M3="Level 3","30",M3="Info","Info",M3="Closed","Closed")} -> 14
A4: 3 | B4: e-70215/PS.00.04 | C4: 46028 | D4: 46008 | E4: PAM JAYA | F4: Permintaan Bukti Penyimpanan Dokumen | G4: PAM JAYA meminta bukti penyimpanan dokumen selambatnya 7 hari sejak surat diterima | H4: Corporate | I4: Corporate | J4: Administrasi & Dokumentasi | L4: Closed | M4: Closed | N4: Compliance | O4: Indradi | P4: =DATEDIF(C4,$W$1,"Y")&" tahun, "&DATEDIF(C4,$W$1,"YM")&" bulan, "&DATEDIF(C4,$W$1,"MD")&" hari" -> 0 tahun, 6 bulan, 9 hari | Q4: =DATEDIF(C4,Summary!$A$1,"d") -> 190 | S4: {=_xlfn.IFS(Q4<=T4,T4,Q4<=T4*2,T4*2,Q4<=T4*3,T4*3,Q4>T4*3,">"&T4*3)} -> Closed | T4: {=_xlfn.IFS(M4="Level 1",7,M4="Level 2",14,M4="Level 3","30",M4="Info","Info",M4="Closed","Closed")} -> Closed | U4: Dibalas surat ABJ/DIR/EKS/01.26/0044
A5: 4 | B5: e-70217/PP.00.02 | C5: 46028 | D5: 46013 | E5: PAM JAYA | F5: Percepatan Pelaksanaan Program JDU+JDB+JDL dan Sambungan Langsung di Area Prioritas Regional Utara (Pantai Mutiara, Kp. Muka, Kp. Kerang Hijau Muara Angke) | G5: PAM JAYA meminta percepatan pekerjaan dan SL pada lokasi surat terlampir | H5: Project | I5: Greenfield | J5: Sambungan Langsung | L5: Open | M5: Level 2 | N5: PMO Infill | O5: Danny L | P5: =DATEDIF(C5,$W$1,"Y")&" tahun, "&DATEDIF(C5,$W$1,"YM")&" bulan, "&DATEDIF(C5,$W$1,"MD")&" hari" -> 0 tahun, 6 bulan, 9 hari | Q5: =DATEDIF(C5,Summary!$A$1,"d") -> 190 | R5: lewat 30d | S5: {=_xlfn.IFS(Q5<=T5,T5,Q5<=T5*2,T5*2,Q5<=T5*3,T5*3,Q5>T5*3,">"&T5*3)} -> >42 | T5: {=_xlfn.IFS(M5="Level 1",7,M5="Level 2",14,M5="Level 3","30",M5="Info","Info",M5="Closed","Closed")} -> 14
A6: 5 | B6: e-70229/PP.00.02 | C6: 46028 | D6: 46013 | E6: PAM JAYA | F6: Pemutakhiran Desain Akhir Proyek Greenfield IPA Portable Semanan | G6: PAM JAYA meminta untuk dilakukan survei bersama pada lokasi terlampir | H6: Project | I6: Greenfield | J6: Perencanaan Program Greenfield | L6: Open | M6: Level 2 | N6: PMO Infill | O6: Danny L | P6: =DATEDIF(C6,$W$1,"Y")&" tahun, "&DATEDIF(C6,$W$1,"YM")&" bulan, "&DATEDIF(C6,$W$1,"MD")&" hari" -> 0 tahun, 6 bulan, 9 hari | Q6: =DATEDIF(C6,Summary!$A$1,"d") -> 190 | R6: lewat 30d | S6: {=_xlfn.IFS(Q6<=T6,T6,Q6<=T6*2,T6*2,Q6<=T6*3,T6*3,Q6>T6*3,">"&T6*3)} -> >42 | T6: {=_xlfn.IFS(M6="Level 1",7,M6="Level 2",14,M6="Level 3","30",M6="Info","Info",M6="Closed","Closed")} -> 14
A7: 6 | B7: e-68122/PP.00.02 | C7: 46028 | D7: 45987 | E7: PAM JAYA | F7: Pemutakhiran Desain Akhir JDU JDB JDL dan SL Proyek Greenfield Corporate Customer Regional Timur | G7: PAM JAYA meminta untuk dilakukan survei bersama pada lokasi di surat terlampir | H7: Project | I7: Greenfield | J7: Perencanaan Program Greenfield | L7: Open | M7: Level 2 | N7: PMO Infill | O7: Danny L | P7: =DATEDIF(C7,$W$1,"Y")&" tahun, "&DATEDIF(C7,$W$1,"YM")&" bulan, "&DATEDIF(C7,$W$1,"MD")&" hari" -> 0 tahun, 6 bulan, 9 hari | Q7: =DATEDIF(C7,Summary!$A$1,"d") -> 190 | R7: lewat 30d | S7: {=_xlfn.IFS(Q7<=T7,T7,Q7<=T7*2,T7*2,Q7<=T7*3,T7*3,Q7>T7*3,">"&T7*3)} -> >42 | T7: {=_xlfn.IFS(M7="Level 1",7,M7="Level 2",14,M7="Level 3","30",M7="Info","Info",M7="Closed","Closed")} -> 14
A8: 7 | B8: e-70620/PP.00.02 | C8: 46028 | E8: PAM JAYA | F8: Pemutakhiran Desain Akhir JDU JDB JDL dan SL Proyek Greenfield Regional Utara dan Selatan | H8: Project | I8: Greenfield | J8: Perencanaan Program Greenfield | L8: Open | M8: Level 2 | N8: PMO Infill | O8: Danny L | P8: =DATEDIF(C8,$W$1,"Y")&" tahun, "&DATEDIF(C8,$W$1,"YM")&" bulan, "&DATEDIF(C8,$W$1,"MD")&" hari" -> 0 tahun, 6 bulan, 9 hari | Q8: =DATEDIF(C8,Summary!$A$1,"d") -> 190 | R8: lewat 30d | S8: {=_xlfn.IFS(Q8<=T8,T8,Q8<=T8*2,T8*2,Q8<=T8*3,T8*3,Q8>T8*3,">"&T8*3)} -> >42 | T8: {=_xlfn.IFS(M8="Level 1",7,M8="Level 2",14,M8="Level 3","30",M8="Info","Info",M8="Closed","Closed")} -> 14
A9: 8 | B9: 4720/PP.01.03/EKST/XII/2025 | C9: 46028 | D9: 46022 | E9: PAM JAYA | F9: Permintaan Pemenuhan Kewajiban Penyelesaian Paket Pekerjaan Kedua Proyek Greenfield pada saat Tanggal Operasi Komersial atau 5 Oktober 2025 | G9: Informasi project TOK 5 Oktober dan PAM JAYA meminta untuk memenuhi seluruh pekerjaan dan seluruh dokumen | H9: Project | I9: Greenfield | J9: Konstruksi Program Greenfield | L9: Info | M9: Info | N9: PMO Infill | O9: Danny L | P9: =DATEDIF(C9,$W$1,"Y")&" tahun, "&DATEDIF(C9,$W$1,"YM")&" bulan, "&DATEDIF(C9,$W$1,"MD")&" hari" -> 0 tahun, 6 bulan, 9 hari | Q9: =DATEDIF(C9,Summary!$A$1,"d") -> 190 | S9: {=_xlfn.IFS(Q9<=T9,T9,Q9<=T9*2,T9*2,Q9<=T9*3,T9*3,Q9>T9*3,">"&T9*3)} -> Info | T9: {=_xlfn.IFS(M9="Level 1",7,M9="Level 2",14,M9="Level 3","30",M9="Info","Info",M9="Closed","Closed")} -> Info
A10: 9 | B10: e-70216/PS.04.03 | C10: 46028 | D10: 46007 | E10: PAM JAYA | F10: Konfirmasi Perpanjangan Polis Asuransi Project Brownfield & Greenfield | G10: Konfirmasi rencana perpanjangan polis dalam jangka waktu 3 hari kalender | H10: Project | I10: Project | J10: Kontrak & Legal | L10: Closed | M10: Closed | N10: Finance | O10: Nurul S | P10: =DATEDIF(C10,$W$1,"Y")&" tahun, "&DATEDIF(C10,$W$1,"YM")&" bulan, "&DATEDIF(C10,$W$1,"MD")&" hari" -> 0 tahun, 6 bulan, 9 hari | Q10: =DATEDIF(C10,Summary!$A$1,"d") -> 190 | S10: {=_xlfn.IFS(Q10<=T10,T10,Q10<=T10*2,T10*2,Q10<=T10*3,T10*3,Q10>T10*3,">"&T10*3)} -> Closed | T10: {=_xlfn.IFS(M10="Level 1",7,M10="Level 2",14,M10="Level 3","30",M10="Info","Info",M10="Closed","Closed")} -> Closed | U10: Dibalas Surat ABJ/DIR/EKS/01.26/0046
A11: 10 | B11: 4719/PP.01.02/EKST/XII/2025 | C11: 46028 | D11: 46022 | E11: PAM JAYA | F11: Teguran terhadap Pengawasan Konsultan Pengawas Independen pada Dokumen Amandemen dan Pernyataan kembali Perjanjian Kerjasama Bundling | G11: Surat PAM JAYA kepada KPI SCI terkait teguran terhadap pengawasan pekerjaan, HSE, dan dokumentasi bahwa KPI belum optimal dalam peran sebagai Konsultan Pengawas Independen | H11: Project | I11: Project | J11: Kontrak & Legal | L11: Info | M11: Info | N11: Compliance | O11: Indradi | P11: =DATEDIF(C11,$W$1,"Y")&" tahun, "&DATEDIF(C11,$W$1,"YM")&" bulan, "&DATEDIF(C11,$W$1,"MD")&" hari" -> 0 tahun, 6 bulan, 9 hari | Q11: =DATEDIF(C11,Summary!$A$1,"d") -> 190 | S11: {=_xlfn.IFS(Q11<=T11,T11,Q11<=T11*2,T11*2,Q11<=T11*3,T11*3,Q11>T11*3,">"&T11*3)} -> Info | T11: {=_xlfn.IFS(M11="Level 1",7,M11="Level 2",14,M11="Level 3","30",M11="Info","Info",M11="Closed","Closed")} -> Info
A12: 11 | B12: e-70362/PM.01.00 | C12: 46028 | D12: 46007 | E12: PAM JAYA | F12: Permohonan Pemasangan Sambungan Langsung Air Minum Perpipaan di area Halim Perdana Kusuma | G12: Surat PAM JAYA kepada Komandan Pangkalan TNI AU perihal pemasangan SL di area Halim | H12: Project | I12: Greenfield | J12: Sambungan Langsung | L12: Info | M12: Info | N12: PMO NC | O12: A. Levi | P12: =DATEDIF(C12,$W$1,"Y")&" tahun, "&DATEDIF(C12,$W$1,"YM")&" bulan, "&DATEDIF(C12,$W$1,"MD")&" hari" -> 0 tahun, 6 bulan, 9 hari | Q12: =DATEDIF(C12,Summary!$A$1,"d") -> 190 | S12: {=_xlfn.IFS(Q12<=T12,T12,Q12<=T12*2,T12*2,Q12<=T12*3,T12*3,Q12>T12*3,">"&T12*3)} -> Info | T12: {=_xlfn.IFS(M12="Level 1",7,M12="Level 2",14,M12="Level 3","30",M12="Info","Info",M12="Closed","Closed")} -> Info
A13: 12 | B13: 012/S/DIR/BPM-ABJ/I/2026 | C13: 46029 | D13: 46028 | E13: BPM | F13: Penagihan Pekerjaan Sambungan Langsung | G13: Konfirmasi pihak ABJ terhadap pengendaan denda terhadap keterlambatan SL | H13: Project | I13: Greenfield | J13: Sambungan Langsung | L13: Open | M13: Level 1 | N13: PMO NC | O13: A. Levi | P13: =DATEDIF(C13,$W$1,"Y")&" tahun, "&DATEDIF(C13,$W$1,"YM")&" bulan, "&DATEDIF(C13,$W$1,"MD")&" hari" -> 0 tahun, 6 bulan, 8 hari | Q13: =DATEDIF(C13,Summary!$A$1,"d") -> 189 | R13: lewat 30d | S13: {=_xlfn.IFS(Q13<=T13,T13,Q13<=T13*2,T13*2,Q13<=T13*3,T13*3,Q13>T13*3,">"&T13*3)} -> >21 | T13: {=_xlfn.IFS(M13="Level 1",7,M13="Level 2",14,M13="Level 3","30",M13="Info","Info",M13="Closed","Closed")} -> 7
A14: 13 | B14: 4722/PS.04.03/EKST/XII/2025 | C14: 46031 | D14: 46022 | E14: PAM JAYA | F14: Tanggapan Pengiriman Dokumen Desain Akhir Program Rehabilitasi Proyek Brownfield Tahun 2026 | G14: PAM JAYA meminta ABJ untuk klarifikasi atas desain akhir maksimal 30 hari kerja sejak dokumen ditanggapi PAM/KPI | H14: Project | I14: Cyclical | J14: Perencanaan Program Greenfield | L14: Closed | M14: Closed | N14: PMO Cyclical | O14: Agus H | P14: =DATEDIF(C14,$W$1,"Y")&" tahun, "&DATEDIF(C14,$W$1,"YM")&" bulan, "&DATEDIF(C14,$W$1,"MD")&" hari" -> 0 tahun, 6 bulan, 6 hari | Q14: =DATEDIF(C14,Summary!$A$1,"d") -> 187 | S14: {=_xlfn.IFS(Q14<=T14,T14,Q14<=T14*2,T14*2,Q14<=T14*3,T14*3,Q14>T14*3,">"&T14*3)} -> Closed | T14: {=_xlfn.IFS(M14="Level 1",7,M14="Level 2",14,M14="Level 3","30",M14="Info","Info",M14="Closed","Closed")} -> Closed | U14: Dibalas Surat ABJ/DIR/EKS/01.26/0076
A15: 14 | B15: e-69888/PP.01.05 | C15: 46031 | D15: 46008 | E15: PAM JAYA | F15: Teguran atas Pelaksanaan Pemenuhan Perizinan Proyek Bundling | G15: PAM JAYA meminta ABJ untuk menyelesaikan pemenuhan kewajiban perizinan keseluruhan project bundling dan menyampaikan progress perizinan setiap kamis pukul 15.00 | H15: Project | I15: Greenfield | J15: Konstruksi Program Greenfield | L15: Info | M15: Info | N15: PMO; Permit | O15: Danny L; Rais S | P15: =DATEDIF(C15,$W$1,"Y")&" tahun, "&DATEDIF(C15,$W$1,"YM")&" bulan, "&DATEDIF(C15,$W$1,"MD")&" hari" -> 0 tahun, 6 bulan, 6 hari | Q15: =DATEDIF(C15,Summary!$A$1,"d") -> 187 | S15: {=_xlfn.IFS(Q15<=T15,T15,Q15<=T15*2,T15*2,Q15<=T15*3,T15*3,Q15>T15*3,">"&T15*3)} -> Info | T15: {=_xlfn.IFS(M15="Level 1",7,M15="Level 2",14,M15="Level 3","30",M15="Info","Info",M15="Closed","Closed")} -> Info
A16: 15 | B16: e-70776/PP.01.04 | C16: 46031 | D16: 46007 | E16: PAM JAYA | F16: Sanksi Denda atas Kegagalan Kinerja Periode Bulan November 2025 | G16: Denda kegagalan kinerja tekanan IPA Pejompongan 1 (11 November 2025) senilai Rp1.030.742 | H16: Produksi | I16: PJP 1 | J16: Denda & Kegagalan | L16: Closed | M16: Closed | N16: Compliance | O16: Indradi | P16: =DATEDIF(C16,$W$1,"Y")&" tahun, "&DATEDIF(C16,$W$1,"YM")&" bulan, "&DATEDIF(C16,$W$1,"MD")&" hari" -> 0 tahun, 6 bulan, 6 hari | Q16: =DATEDIF(C16,Summary!$A$1,"d") -> 187 | S16: {=_xlfn.IFS(Q16<=T16,T16,Q16<=T16*2,T16*2,Q16<=T16*3,T16*3,Q16>T16*3,">"&T16*3)} -> Closed | T16: {=_xlfn.IFS(M16="Level 1",7,M16="Level 2",14,M16="Level 3","30",M16="Info","Info",M16="Closed","Closed")} -> Closed | U16: Dibalas Surat ABJ/DIR/EKS/01.26/0037
A17: 16 | B17: e-70749/PP.00.02 | C17: 46035 | D17: 46024 | E17: PAM JAYA | F17: Pemutakhiran Desain Akhir JDU JDB JDL dan SL Proyek Greenfield Corporate Customer Regional Utara dan Selatan | G17: PAM JAYA meminta ABJ untuk pemutakhiran DED pada lokasi terlampir | H17: Project | I17: Greenfield | J17: Perencanaan Program Greenfield | L17: Open | M17: Level 2 | N17: PMO Infill | O17: Danny L | P17: =DATEDIF(C17,$W$1,"Y")&" tahun, "&DATEDIF(C17,$W$1,"YM")&" bulan, "&DATEDIF(C17,$W$1,"MD")&" hari" -> 0 tahun, 6 bulan, 2 hari | Q17: =DATEDIF(C17,Summary!$A$1,"d") -> 183 | R17: lewat 30d | S17: {=_xlfn.IFS(Q17<=T17,T17,Q17<=T17*2,T17*2,Q17<=T17*3,T17*3,Q17>T17*3,">"&T17*3)} -> >42 | T17: {=_xlfn.IFS(M17="Level 1",7,M17="Level 2",14,M17="Level 3","30",M17="Info","Info",M17="Closed","Closed")} -> 14
A18: 17 | B18: 153/SCI-KPI/I/2026 | C18: 46041 | D18: 46037 | E18: KPI - Sucofindo | F18: Penyampaian Laporan Penyelesaian Uji Komisioning Project Greenfield – SPAM Jatiluhur Hilir 9 Program | G18: Dapat dilanjutkan ke MC100 | H18: Project | I18: Jatiluhur Hilir | J18: Konstruksi Program Greenfield | L18: Info | M18: Info | N18: PMO Infill | O18: Muhrojin | P18: =DATEDIF(C18,$W$1,"Y")&" tahun, "&DATEDIF(C18,$W$1,"YM")&" bulan, "&DATEDIF(C18,$W$1,"MD")&" hari" -> 0 tahun, 5 bulan, 26 hari | Q18: =DATEDIF(C18,Summary!$A$1,"d") -> 177 | S18: {=_xlfn.IFS(Q18<=T18,T18,Q18<=T18*2,T18*2,Q18<=T18*3,T18*3,Q18>T18*3,">"&T18*3)} -> Info | T18: {=_xlfn.IFS(M18="Level 1",7,M18="Level 2",14,M18="Level 3","30",M18="Info","Info",M18="Closed","Closed")} -> Info
A19: 18 | B19: 016/Dir/Ity/I/2026 | C19: 46049 | D19: 46044 | E19: PT Infra Tama Yakti | F19: Surat Peringatan Akibat Kegagalan Perencanaan Oleh Infratama | G19: Penyampaian bahwa kegagalan disebabkan keterbatasan data eksisting | H19: Project | I19: Project | J19: Perencanaan Program Greenfield | L19: Info | M19: Info | N19: PGO | O19: Angelika | P19: =DATEDIF(C19,$W$1,"Y")&" tahun, "&DATEDIF(C19,$W$1,"YM")&" bulan, "&DATEDIF(C19,$W$1,"MD")&" hari" -> 0 tahun, 5 bulan, 18 hari | Q19: =DATEDIF(C19,Summary!$A$1,"d") -> 169 | S19: {=_xlfn.IFS(Q19<=T19,T19,Q19<=T19*2,T19*2,Q19<=T19*3,T19*3,Q19>T19*3,">"&T19*3)} -> Info | T19: {=_xlfn.IFS(M19="Level 1",7,M19="Level 2",14,M19="Level 3","30",M19="Info","Info",M19="Closed","Closed")} -> Info
A20: 19 | B20: 156/SCI-KPI/I/2026 | C20: 46048 | D20: 46014 | E20: KPI - Sucofindo | F20: Tanggapan atas Surat PT Air Bersih Jakarta No. ABJ/DIR/EKS/01.26/0064 Perihal Penyampaian Laporan Penyelesaian Uji Komisioning Project Greenfield – SPAM Jatiluhur Hilir 2 Program | G20: Dapat dilanjutkan ke MC100 | H20: Project | I20: Jatiluhur Hilir | J20: Konstruksi Program Greenfield | L20: Info | M20: Info | N20: PMO Infill | O20: Muhrojin | P20: =DATEDIF(C20,$W$1,"Y")&" tahun, "&DATEDIF(C20,$W$1,"YM")&" bulan, "&DATEDIF(C20,$W$1,"MD")&" hari" -> 0 tahun, 5 bulan, 19 hari | Q20: =DATEDIF(C20,Summary!$A$1,"d") -> 170 | S20: {=_xlfn.IFS(Q20<=T20,T20,Q20<=T20*2,T20*2,Q20<=T20*3,T20*3,Q20>T20*3,">"&T20*3)} -> Info | T20: {=_xlfn.IFS(M20="Level 1",7,M20="Level 2",14,M20="Level 3","30",M20="Info","Info",M20="Closed","Closed")} -> Info
A21: 20 | B21: e-71304/PP.00.02 | C21: 46049 | D21: 46035 | E21: PAM JAYA | F21: Pemutakhiran Desain Akhir JDU JDB JDL dan SL Proyek Greenfield Regional Selatan dan Utara | G21: PAM JAYA meminta ABJ untuk pemutakhiran DED pada lokasi terlampir | H21: Project | I21: Greenfield | J21: Perencanaan Program Greenfield | L21: Open | M21: Level 2 | N21: PMO Infill | O21: Danny L | P21: =DATEDIF(C21,$W$1,"Y")&" tahun, "&DATEDIF(C21,$W$1,"YM")&" bulan, "&DATEDIF(C21,$W$1,"MD")&" hari" -> 0 tahun, 5 bulan, 18 hari | Q21: =DATEDIF(C21,Summary!$A$1,"d") -> 169 | R21: lewat 30d | S21: {=_xlfn.IFS(Q21<=T21,T21,Q21<=T21*2,T21*2,Q21<=T21*3,T21*3,Q21>T21*3,">"&T21*3)} -> >42 | T21: {=_xlfn.IFS(M21="Level 1",7,M21="Level 2",14,M21="Level 3","30",M21="Info","Info",M21="Closed","Closed")} -> 14
A22: 21 | B22: e-71127/PP.00.06 | C22: 46049 | D22: 46030 | E22: PAM JAYA | F22: Permintaan Pemenuhan Perizinan Pekerjaan TOK 5 April 2026 | G22: PAM JAYA meminta ABJ untuk menyelesaikan dan melakukan pemenuhan kewajiban terkait perizinan proyek bundling TOK April 2026 | H22: Project | I22: Greenfield | J22: Konstruksi Program Greenfield | L22: Open | M22: Level 2 | N22: Pernit | O22: Rais A | P22: =DATEDIF(C22,$W$1,"Y")&" tahun, "&DATEDIF(C22,$W$1,"YM")&" bulan, "&DATEDIF(C22,$W$1,"MD")&" hari" -> 0 tahun, 5 bulan, 18 hari | Q22: =DATEDIF(C22,Summary!$A$1,"d") -> 169 | R22: lewat 30d | S22: {=_xlfn.IFS(Q22<=T22,T22,Q22<=T22*2,T22*2,Q22<=T22*3,T22*3,Q22>T22*3,">"&T22*3)} -> >42 | T22: {=_xlfn.IFS(M22="Level 1",7,M22="Level 2",14,M22="Level 3","30",M22="Info","Info",M22="Closed","Closed")} -> 14
A23: 22 | B23: e-71126/PP.01.02 | C23: 46049 | D23: 46022 | E23: PAM JAYA | F23: Teguran Penerapan Aspek Keselamtan dan Kesehatan Kerja (K3) pada Proyek Greenfield dan Brownfield | G23: PAM JAYA meminta ABJ untuk memastikan ABJ melakukan pemeriksaan atas kewajiban implementasi K3 | H23: Project | I23: Project | J23: HSE | L23: Closed | M23: Closed | N23: HSE | O23: Irsan | P23: =DATEDIF(C23,$W$1,"Y")&" tahun, "&DATEDIF(C23,$W$1,"YM")&" bulan, "&DATEDIF(C23,$W$1,"MD")&" hari" -> 0 tahun, 5 bulan, 18 hari | Q23: =DATEDIF(C23,Summary!$A$1,"d") -> 169 | S23: {=_xlfn.IFS(Q23<=T23,T23,Q23<=T23*2,T23*2,Q23<=T23*3,T23*3,Q23>T23*3,">"&T23*3)} -> Closed | T23: {=_xlfn.IFS(M23="Level 1",7,M23="Level 2",14,M23="Level 3","30",M23="Info","Info",M23="Closed","Closed")} -> Closed | U23: Dibalas Surat ABJ26 0140
A24: 23 | B24: e-71125/PP.01.02 | C24: 46049 | D24: 46021 | E24: PAM JAYA | F24: Teguran Keterlambatan Realisasi Pemasangan Sambungan Langsung Bulan Desember 2025 | G24: PAM JAYA meminta ABJ untuk pemenuhan pemasangan SL selambatnya 5 hari kalender | H24: Project | I24: Greenfield | J24: Sambungan Langsung | K24: =C24+5 -> 46054 | L24: Open | M24: Level 1 | N24: PMO NC | O24: A. Levi | P24: =DATEDIF(C24,$W$1,"Y")&" tahun, "&DATEDIF(C24,$W$1,"YM")&" bulan, "&DATEDIF(C24,$W$1,"MD")&" hari" -> 0 tahun, 5 bulan, 18 hari | Q24: =DATEDIF(C24,Summary!$A$1,"d") -> 169 | R24: lewat 30d | S24: {=_xlfn.IFS(Q24<=T24,T24,Q24<=T24*2,T24*2,Q24<=T24*3,T24*3,Q24>T24*3,">"&T24*3)} -> >21 | T24: {=_xlfn.IFS(M24="Level 1",7,M24="Level 2",14,M24="Level 3","30",M24="Info","Info",M24="Closed","Closed")} -> 7
A25: 24 | B25: 300.1.4/61-Kc.PG-Trantib | C25: 46050 | D25: 46034 | E25: Pemkot Bekasi Kecamatan Pondok Gede | F25: Legalitas Perijinan | G25: Perihal legalitas perizinan terkait penampungn/pembuangan tanah di Jl Jatiwaringin | H25: Project | I25: Greenfield | J25: Koordinasi & Sosialisasi | L25: Info | M25: Info | N25: Permit | O25: Rais A | P25: =DATEDIF(C25,$W$1,"Y")&" tahun, "&DATEDIF(C25,$W$1,"YM")&" bulan, "&DATEDIF(C25,$W$1,"MD")&" hari" -> 0 tahun, 5 bulan, 17 hari | Q25: =DATEDIF(C25,Summary!$A$1,"d") -> 168 | S25: {=_xlfn.IFS(Q25<=T25,T25,Q25<=T25*2,T25*2,Q25<=T25*3,T25*3,Q25>T25*3,">"&T25*3)} -> Info | T25: {=_xlfn.IFS(M25="Level 1",7,M25="Level 2",14,M25="Level 3","30",M25="Info","Info",M25="Closed","Closed")} -> Info
A26: 25 | B26: 158/SCI-KPI/I/2026 | C26: 46052 | E26: KPI - Sucofindo | F26: Surat Pengantar Revisi Laporan Bulanan Proyek Bundling SPAM DKI Jakarta - Konsultan Pengawas Independen Periode Desember 2025 | G26: Laporan Bulanan Desember 2025 | H26: Project | I26: Project | J26: Monitoring & Pelaporan | L26: Info | M26: Info | N26: Compliance | O26: Indradi | P26: =DATEDIF(C26,$W$1,"Y")&" tahun, "&DATEDIF(C26,$W$1,"YM")&" bulan, "&DATEDIF(C26,$W$1,"MD")&" hari" -> 0 tahun, 5 bulan, 15 hari | Q26: =DATEDIF(C26,Summary!$A$1,"d") -> 166 | S26: {=_xlfn.IFS(Q26<=T26,T26,Q26<=T26*2,T26*2,Q26<=T26*3,T26*3,Q26>T26*3,">"&T26*3)} -> Info | T26: {=_xlfn.IFS(M26="Level 1",7,M26="Level 2",14,M26="Level 3","30",M26="Info","Info",M26="Closed","Closed")} -> Info
A27: 26 | B27: 173/SCI-KPI/I/2026 | C27: 46052 | D27: 46048 | E27: KPI - Sucofindo | F27: Tanggapan atas Surat PT Air Bersih Jakarta No. ABJ/DIR/EKS/01.26/0070 Tentang Penyampaian Laporan Penyelesaian Uji Komisioning Project Greenfield - SPAM Buaran 3 Hilir Program Anwar Burhanudin | G27: Dapat dilanjutkan ke MC100 | H27: Project | I27: Buaran 3 Hilir | J27: Konstruksi Program Greenfield | L27: Info | M27: Info | N27: PMO Infill | O27: Topan | P27: =DATEDIF(C27,$W$1,"Y")&" tahun, "&DATEDIF(C27,$W$1,"YM")&" bulan, "&DATEDIF(C27,$W$1,"MD")&" hari" -> 0 tahun, 5 bulan, 15 hari | Q27: =DATEDIF(C27,Summary!$A$1,"d") -> 166 | S27: {=_xlfn.IFS(Q27<=T27,T27,Q27<=T27*2,T27*2,Q27<=T27*3,T27*3,Q27>T27*3,">"&T27*3)} -> Info | T27: {=_xlfn.IFS(M27="Level 1",7,M27="Level 2",14,M27="Level 3","30",M27="Info","Info",M27="Closed","Closed")} -> Info
A28: 27 | B28: e-70219/PP.00.02 | C28: 46055 | D28: 46044 | E28: PAM JAYA | F28: Pemutakhiran Desain Akhir JDU JDB JDL dan SL Proyek Greenfield Regional Barat, Selatan, Utara, Pusat | G28: Agar dilakukan survey bersama dan penyelarasan desain akhir | H28: Project | I28: Greenfield | J28: Perencanaan Program Greenfield | L28: Open | M28: Level 2 | N28: PMO Infill | O28: Danny L | P28: =DATEDIF(C28,$W$1,"Y")&" tahun, "&DATEDIF(C28,$W$1,"YM")&" bulan, "&DATEDIF(C28,$W$1,"MD")&" hari" -> 0 tahun, 5 bulan, 13 hari | Q28: =DATEDIF(C28,Summary!$A$1,"d") -> 163 | R28: lewat 30d | S28: {=_xlfn.IFS(Q28<=T28,T28,Q28<=T28*2,T28*2,Q28<=T28*3,T28*3,Q28>T28*3,">"&T28*3)} -> >42 | T28: {=_xlfn.IFS(M28="Level 1",7,M28="Level 2",14,M28="Level 3","30",M28="Info","Info",M28="Closed","Closed")} -> 14
A29: 28 | B29: e-72121/KU.01.15 | C29: 46055 | D29: 46045 | E29: PAM JAYA | F29: Permintaan Penyampaian Laporan Keuangan Audited Tahun 2025 dan Pemenuhan Kewajiban Penyetoran Ekuitas Tahun 2026 | G29: PAM JAYA meminta ABJ untuk melakukan kewajiban penyetoran ekuitas dan menyampaikan laporan keuangan audited 2025 | H29: Corporate | I29: Corporate | J29: Keuangan, Pembayaran, Investasi | L29: Open | M29: Level 2 | N29: Finance | O29: Nurul S | P29: =DATEDIF(C29,$W$1,"Y")&" tahun, "&DATEDIF(C29,$W$1,"YM")&" bulan, "&DATEDIF(C29,$W$1,"MD")&" hari" -> 0 tahun, 5 bulan, 13 hari | Q29: =DATEDIF(C29,Summary!$A$1,"d") -> 163 | R29: lewat 30d | S29: {=_xlfn.IFS(Q29<=T29,T29,Q29<=T29*2,T29*2,Q29<=T29*3,T29*3,Q29>T29*3,">"&T29*3)} -> >42 | T29: {=_xlfn.IFS(M29="Level 1",7,M29="Level 2",14,M29="Level 3","30",M29="Info","Info",M29="Closed","Closed")} -> 14
A30: 29 | B30: e-72122/PP.00.02 | C30: 46055 | D30: 46043 | E30: PAM JAYA | F30: Pembaharuan Informasi Proyek Greenfield JDU JDB JDL dan SL Regional Selatan, Barat, dan Timur | G30: PAM JAYA meminta ABJ untuk menindaklanjuti lokasi rencana sebagaimana surat terlampir | H30: Project | I30: Greenfield | J30: Perencanaan Program Greenfield | L30: Open | M30: Level 2 | N30: PMO Infill | O30: Danny L | P30: =DATEDIF(C30,$W$1,"Y")&" tahun, "&DATEDIF(C30,$W$1,"YM")&" bulan, "&DATEDIF(C30,$W$1,"MD")&" hari" -> 0 tahun, 5 bulan, 13 hari | Q30: =DATEDIF(C30,Summary!$A$1,"d") -> 163 | R30: lewat 30d | S30: {=_xlfn.IFS(Q30<=T30,T30,Q30<=T30*2,T30*2,Q30<=T30*3,T30*3,Q30>T30*3,">"&T30*3)} -> >42 | T30: {=_xlfn.IFS(M30="Level 1",7,M30="Level 2",14,M30="Level 3","30",M30="Info","Info",M30="Closed","Closed")} -> 14
A31: 30 | B31: e-72124/PP.00.02 | C31: 46055 | D31: 46044 | E31: PAM JAYA | F31: Pembaharuan Informasi Proyek Greenfield JDU JDB JDL dan SL Regional Utara | G31: PAM JAYA meminta ABJ untuk menindaklanjuti rencana lokasi sesuai surat terlampir | H31: Project | I31: Greenfield | J31: Perencanaan Program Greenfield | L31: Open | M31: Level 2 | N31: PMO Infill | O31: Danny L | P31: =DATEDIF(C31,$W$1,"Y")&" tahun, "&DATEDIF(C31,$W$1,"YM")&" bulan, "&DATEDIF(C31,$W$1,"MD")&" hari" -> 0 tahun, 5 bulan, 13 hari | Q31: =DATEDIF(C31,Summary!$A$1,"d") -> 163 | R31: lewat 30d | S31: {=_xlfn.IFS(Q31<=T31,T31,Q31<=T31*2,T31*2,Q31<=T31*3,T31*3,Q31>T31*3,">"&T31*3)} -> >42 | T31: {=_xlfn.IFS(M31="Level 1",7,M31="Level 2",14,M31="Level 3","30",M31="Info","Info",M31="Closed","Closed")} -> 14
A32: 31 | B32: e-72125/PP.00.02 | C32: 46055 | D32: 46045 | E32: PAM JAYA | F32: Pemutakhiran Desain Akhir JDU JDB JDL dan SL Proyek Greenfield Warga Muara Baru Gg. Elektro | G32: PAM JAYA meminta ABJ untuk menindaklanjuti lokasi rencana pekerjaan pada surat terlampir | H32: Project | I32: Greenfield | J32: Perencanaan Program Greenfield | L32: Open | M32: Level 2 | N32: PMO Infill | O32: Danny L | P32: =DATEDIF(C32,$W$1,"Y")&" tahun, "&DATEDIF(C32,$W$1,"YM")&" bulan, "&DATEDIF(C32,$W$1,"MD")&" hari" -> 0 tahun, 5 bulan, 13 hari | Q32: =DATEDIF(C32,Summary!$A$1,"d") -> 163 | R32: lewat 30d | S32: {=_xlfn.IFS(Q32<=T32,T32,Q32<=T32*2,T32*2,Q32<=T32*3,T32*3,Q32>T32*3,">"&T32*3)} -> >42 | T32: {=_xlfn.IFS(M32="Level 1",7,M32="Level 2",14,M32="Level 3","30",M32="Info","Info",M32="Closed","Closed")} -> 14
A33: 32 | B33: e-72126/PP.00.02 | C33: 46055 | D33: 46045 | E33: PAM JAYA | F33: Pemutakhiran Desain Akhir JDU JDB JDL dan SL Proyek Greenfield Bank Rakyat Indonesia (Gudang BRI) | G33: PAM JAYA meminta ABJ untuk menindaklanjuti lokasi rencana pada surat terlampir | H33: Project | I33: Greenfield | J33: Perencanaan Program Greenfield | L33: Open | M33: Level 2 | N33: PMO Infill | O33: Danny L | P33: =DATEDIF(C33,$W$1,"Y")&" tahun, "&DATEDIF(C33,$W$1,"YM")&" bulan, "&DATEDIF(C33,$W$1,"MD")&" hari" -> 0 tahun, 5 bulan, 13 hari | Q33: =DATEDIF(C33,Summary!$A$1,"d") -> 163 | R33: lewat 30d | S33: {=_xlfn.IFS(Q33<=T33,T33,Q33<=T33*2,T33*2,Q33<=T33*3,T33*3,Q33>T33*3,">"&T33*3)} -> >42 | T33: {=_xlfn.IFS(M33="Level 1",7,M33="Level 2",14,M33="Level 3","30",M33="Info","Info",M33="Closed","Closed")} -> 14
A34: 33 | B34: e-72203/PP.00.02 | C34: 46055 | D34: 46079 | E34: PAM JAYA | F34: Pemutakhiran Desain Akhir JDU JDB JDL dan SL Proyek Greenfield Perumahan Bumi Karang Indah | G34: PAM JAYA meminta ABJ untuk menindaklanjuti lokasi rencana pada surat terlampir | H34: Project | I34: Greenfield | J34: Perencanaan Program Greenfield | L34: Open | M34: Level 2 | N34: PMO Infill | O34: Danny L | P34: =DATEDIF(C34,$W$1,"Y")&" tahun, "&DATEDIF(C34,$W$1,"YM")&" bulan, "&DATEDIF(C34,$W$1,"MD")&" hari" -> 0 tahun, 5 bulan, 13 hari | Q34: =DATEDIF(C34,Summary!$A$1,"d") -> 163 | R34: lewat 30d | S34: {=_xlfn.IFS(Q34<=T34,T34,Q34<=T34*2,T34*2,Q34<=T34*3,T34*3,Q34>T34*3,">"&T34*3)} -> >42 | T34: {=_xlfn.IFS(M34="Level 1",7,M34="Level 2",14,M34="Level 3","30",M34="Info","Info",M34="Closed","Closed")} -> 14
A35: 34 | B35: e-72204/PP.00.02 | C35: 46055 | D35: 46048 | E35: PAM JAYA | F35: Pemutakhiran Desain Akhir JDU JDB JDL dan SL Proyek Greenfield Jl. Papanggo II Gg Mangga dan Gg Rambutan dan RW 005 Kelurahan Cilandak | G35: PAM JAYA meminta ABJ untuk menindaklanjuti lokasi rencana pada surat terlampir | H35: Project | I35: Greenfield | J35: Perencanaan Program Greenfield | L35: Open | M35: Level 2 | N35: PMO Infill | O35: Danny L | P35: =DATEDIF(C35,$W$1,"Y")&" tahun, "&DATEDIF(C35,$W$1,"YM")&" bulan, "&DATEDIF(C35,$W$1,"MD")&" hari" -> 0 tahun, 5 bulan, 13 hari | Q35: =DATEDIF(C35,Summary!$A$1,"d") -> 163 | R35: lewat 30d | S35: {=_xlfn.IFS(Q35<=T35,T35,Q35<=T35*2,T35*2,Q35<=T35*3,T35*3,Q35>T35*3,">"&T35*3)} -> >42 | T35: {=_xlfn.IFS(M35="Level 1",7,M35="Level 2",14,M35="Level 3","30",M35="Info","Info",M35="Closed","Closed")} -> 14
A36: 35 | B36: e-72146/PP.03.05 | C36: 46055 | D36: 46041 | E36: PAM JAYA | F36: Penyampaian Hasil Inspeksi K3L Terjadwal di IPA Pulogadung Tahun 2025 | G36: ABJ untuk menyampaikan rencana perbaikan selambatnya 14 hari kalender | H36: Produksi | I36: Pulogadung | J36: HSE | L36: Closed | M36: Closed | N36: HSE | O36: Irsan | P36: =DATEDIF(C36,$W$1,"Y")&" tahun, "&DATEDIF(C36,$W$1,"YM")&" bulan, "&DATEDIF(C36,$W$1,"MD")&" hari" -> 0 tahun, 5 bulan, 13 hari | Q36: =DATEDIF(C36,Summary!$A$1,"d") -> 163 | S36: {=_xlfn.IFS(Q36<=T36,T36,Q36<=T36*2,T36*2,Q36<=T36*3,T36*3,Q36>T36*3,">"&T36*3)} -> Closed | T36: {=_xlfn.IFS(M36="Level 1",7,M36="Level 2",14,M36="Level 3","30",M36="Info","Info",M36="Closed","Closed")} -> Closed | U36: Dibalas Surat ABJ26 0106
A37: 36 | B37: e-72147/PP.03.05 | C37: 46055 | D37: 46041 | E37: PAM JAYA | F37: Penyampaian Hasil Inspeksi Aset dan Peralatan di IPA Pulogadung Tanggal 26 Februari 2025, 04 Juli 2025, dan 26 Agustus 2025 | G37: ABJ untuk menyampaikan rencana perbaikan selambat-lambatnya jangka waktu 14 hari kalender | H37: Produksi | I37: Pulogadung | J37: Operation & Maintenance | L37: Closed | M37: Closed | N37: Produksi | O37: Wahyudian | P37: =DATEDIF(C37,$W$1,"Y")&" tahun, "&DATEDIF(C37,$W$1,"YM")&" bulan, "&DATEDIF(C37,$W$1,"MD")&" hari" -> 0 tahun, 5 bulan, 13 hari | Q37: =DATEDIF(C37,Summary!$A$1,"d") -> 163 | S37: {=_xlfn.IFS(Q37<=T37,T37,Q37<=T37*2,T37*2,Q37<=T37*3,T37*3,Q37>T37*3,">"&T37*3)} -> Closed | T37: {=_xlfn.IFS(M37="Level 1",7,M37="Level 2",14,M37="Level 3","30",M37="Info","Info",M37="Closed","Closed")} -> Closed | U37: Dibalas Surat ABJ26 0127
A38: 37 | B38: e-71848.PM.02.03 | C38: 46055 | D38: 46030 | E38: PAM JAYA | F38: Tindak Lanjut Strategi Target Realisasi Pemasangan Sambungan Langsung 2026 | G38: PAM JAYA meminta ABJ untuk melaksanakan pemasangan SL pada lokasi RW yang telah mencapai 50% dari total potensi bangunan non pelanggan dan telah disampaikan data oleh PAM melalui FA online | H38: Project | I38: Greenfield | J38: Sambungan Langsung | L38: Info | M38: Info | N38: PMO NC | O38: A. Levi | P38: =DATEDIF(C38,$W$1,"Y")&" tahun, "&DATEDIF(C38,$W$1,"YM")&" bulan, "&DATEDIF(C38,$W$1,"MD")&" hari" -> 0 tahun, 5 bulan, 13 hari | Q38: =DATEDIF(C38,Summary!$A$1,"d") -> 163 | R38: Lewat 7d | S38: {=_xlfn.IFS(Q38<=T38,T38,Q38<=T38*2,T38*2,Q38<=T38*3,T38*3,Q38>T38*3,">"&T38*3)} -> Info | T38: {=_xlfn.IFS(M38="Level 1",7,M38="Level 2",14,M38="Level 3","30",M38="Info","Info",M38="Closed","Closed")} -> Info
A39: 38 | B39: 164/SCI-KPI/I/2026 | C39: 46055 | D39: 46045 | E39: KPI - Sucofindo | F39: Tanggapan atas Surat PT Air Bersih Jakarta No. ABJ/DIR/EKS/11.25/1025 Tentang DED dan RAB Perluasan Jaringan Untuk 3 Lokasi Infill Ad Hoc Sambungan Baru Proyek SPAM Jatiluhur Hilir dan SPAM Buaran 3 Hilir | G39: Penyampaian hasil pemeriksaan DED RAB Perluasan Jaringan Untuk 3 Lokasi Infill Ad Hoc Sambungan Baru Proyek SPAM Jatiluhur Hilir dan SPAM Buaran 3 Hilir | H39: Project | I39: Greenfield | J39: Perencanaan Program Greenfield | L39: Info | M39: Info | N39: Planning | O39: Aji S | P39: =DATEDIF(C39,$W$1,"Y")&" tahun, "&DATEDIF(C39,$W$1,"YM")&" bulan, "&DATEDIF(C39,$W$1,"MD")&" hari" -> 0 tahun, 5 bulan, 13 hari | Q39: =DATEDIF(C39,Summary!$A$1,"d") -> 163 | S39: {=_xlfn.IFS(Q39<=T39,T39,Q39<=T39*2,T39*2,Q39<=T39*3,T39*3,Q39>T39*3,">"&T39*3)} -> Info | T39: {=_xlfn.IFS(M39="Level 1",7,M39="Level 2",14,M39="Level 3","30",M39="Info","Info",M39="Closed","Closed")} -> Info
A40: 39 | B40: 175/SCI-KPI/I/2026 | C40: 46056 | D40: 46052 | E40: KPI - Sucofindo | F40: Laporan Hasil Verifikasi KPI Terkait Pencairan Dana Cadangan Proyek Greenfield | G40: KPI menyampaikan bahwa tahun 2025 pekerjaan rehabilitasi untuk FPB belum dipersyaratkan untuk dilaksanakan oleh ABJ | H40: Project | I40: Buaran 3 Hulu | J40: Administrasi & Dokumentasi | L40: Info | M40: Info | N40: Compliance | O40: Indradi | P40: =DATEDIF(C40,$W$1,"Y")&" tahun, "&DATEDIF(C40,$W$1,"YM")&" bulan, "&DATEDIF(C40,$W$1,"MD")&" hari" -> 0 tahun, 5 bulan, 12 hari | Q40: =DATEDIF(C40,Summary!$A$1,"d") -> 162 | S40: {=_xlfn.IFS(Q40<=T40,T40,Q40<=T40*2,T40*2,Q40<=T40*3,T40*3,Q40>T40*3,">"&T40*3)} -> Info | T40: {=_xlfn.IFS(M40="Level 1",7,M40="Level 2",14,M40="Level 3","30",M40="Info","Info",M40="Closed","Closed")} -> Info
A41: 40 | B41: e-72469/PS.04.03 | C41: 46056 | D41: 46052 | E41: PAM JAYA | F41: Klarifikasi dan Permintaan Bukti Asuransi terhadap Kewajiban A&PK Bundling | G41: Undangan PAM JAYA kepada ABJ terkait pembahasan klarifikasi dan pemetaan polis asuransi | H41: Project | I41: Project | J41: Kontrak & Legal | L41: Open | M41: Level 2 | N41: PMO Infill | O41: Aan H | P41: =DATEDIF(C41,$W$1,"Y")&" tahun, "&DATEDIF(C41,$W$1,"YM")&" bulan, "&DATEDIF(C41,$W$1,"MD")&" hari" -> 0 tahun, 5 bulan, 12 hari | Q41: =DATEDIF(C41,Summary!$A$1,"d") -> 162 | R41: lewat 30d | S41: {=_xlfn.IFS(Q41<=T41,T41,Q41<=T41*2,T41*2,Q41<=T41*3,T41*3,Q41>T41*3,">"&T41*3)} -> >42 | T41: {=_xlfn.IFS(M41="Level 1",7,M41="Level 2",14,M41="Level 3","30",M41="Info","Info",M41="Closed","Closed")} -> 14
A42: 41 | B42: 167/SCI-KPI/I/2026 | C42: 46056 | D42: 46045 | E42: KPI - Sucofindo | F42: Tanggapan atas Surat PT Air Bersih Jakarta No. ABJ/DIR/EKS/11.25/0996 Tentang Pembaharuan DED dan RAB Desain Akhir Untuk Mater Meter Binton Silaen Proyek SPAM Jatiluhur Hilir | G42: Penyampaian KPI terhadap Pembaharuan DED dan RAB Desain Akhir Untuk Mater Meter Binton Silaen Proyek SPAM Jatiluhur Hilir | H42: Project | I42: Greenfield | J42: Perencanaan Program Greenfield | L42: Info | M42: Info | N42: Planning | O42: Aji S | P42: =DATEDIF(C42,$W$1,"Y")&" tahun, "&DATEDIF(C42,$W$1,"YM")&" bulan, "&DATEDIF(C42,$W$1,"MD")&" hari" -> 0 tahun, 5 bulan, 12 hari | Q42: =DATEDIF(C42,Summary!$A$1,"d") -> 162 | S42: {=_xlfn.IFS(Q42<=T42,T42,Q42<=T42*2,T42*2,Q42<=T42*3,T42*3,Q42>T42*3,">"&T42*3)} -> Info | T42: {=_xlfn.IFS(M42="Level 1",7,M42="Level 2",14,M42="Level 3","30",M42="Info","Info",M42="Closed","Closed")} -> Info
A43: 42 | B43: 147/SCI-KPI/I/2026 | C43: 46056 | D43: 46043 | E43: KPI - Sucofindo | F43: Tanggapan atas Surat PT Air Bersih Jakarta No. ABJ/DIR/EKS/11.25/1004 Tentang DED dan RAB Perluasan Jaringan Untuk 2 Lokasi Infill Ad Hoc Sambungan Baru Proyek SPAM Jatiluhur Hilir dan SPAM Karian Serpong Hilir | G43: Penyampaian KPI terhadap hasil DED dan RAB Perluasan Jaringan Untuk 2 Lokasi Infill Ad Hoc Sambungan Baru Proyek SPAM Jatiluhur Hilir dan SPAM Karian Serpong Hilir | H43: Project | I43: Greenfield | J43: Perencanaan Program Greenfield | L43: Info | M43: Info | N43: Planning | O43: Aji S | P43: =DATEDIF(C43,$W$1,"Y")&" tahun, "&DATEDIF(C43,$W$1,"YM")&" bulan, "&DATEDIF(C43,$W$1,"MD")&" hari" -> 0 tahun, 5 bulan, 12 hari | Q43: =DATEDIF(C43,Summary!$A$1,"d") -> 162 | S43: {=_xlfn.IFS(Q43<=T43,T43,Q43<=T43*2,T43*2,Q43<=T43*3,T43*3,Q43>T43*3,">"&T43*3)} -> Info | T43: {=_xlfn.IFS(M43="Level 1",7,M43="Level 2",14,M43="Level 3","30",M43="Info","Info",M43="Closed","Closed")} -> Info
A44: 43 | B44: 165/SCI-KPI/I/2026 | C44: 46057 | D44: 46045 | E44: KPI - Sucofindo | F44: Tanggapan atas Surat PT Air Bersih Jakarta No. ABJ/DIR/EKS/11.25/0994 Tentang DED dan RAB Perluasan Jaringan Untuk Proyek Tambah Infill Ad Hoc Perumahan Tanjung Mas Raya SPAM Jatiluhur Hilir | G44: Hasil pemeriksaan KPI terhadap DED dan RAB Perluasan Jaringan Untuk Proyek Tambah Infill Ad Hoc Perumahan Tanjung Mas Raya SPAM Jatiluhur Hilir | H44: Project | I44: Greenfield | J44: Perencanaan Program Greenfield | L44: Info | M44: Info | N44: Planning | O44: Aji S | P44: =DATEDIF(C44,$W$1,"Y")&" tahun, "&DATEDIF(C44,$W$1,"YM")&" bulan, "&DATEDIF(C44,$W$1,"MD")&" hari" -> 0 tahun, 5 bulan, 11 hari | Q44: =DATEDIF(C44,Summary!$A$1,"d") -> 161 | S44: {=_xlfn.IFS(Q44<=T44,T44,Q44<=T44*2,T44*2,Q44<=T44*3,T44*3,Q44>T44*3,">"&T44*3)} -> Info | T44: {=_xlfn.IFS(M44="Level 1",7,M44="Level 2",14,M44="Level 3","30",M44="Info","Info",M44="Closed","Closed")} -> Info
A45: 44 | B45: 166/SCI-KPI/I/2026 | C45: 46057 | D45: 46045 | E45: KPI - Sucofindo | F45: Tanggapan atas Surat PT Air Bersih Jakarta No. ABJ/DIR/EKS/11.25/0969 Tentang Pembaharuan DED dan RAB Proyek SPAM Pesanggrahan Hilir – Tahap Kedua | G45: Penyampaian KPI terhadap hasil pembaharuan DED dan RAB Proyek SPAM Pesanggrahan Hilir – Tahap Kedua | H45: Project | I45: Greenfield | J45: Perencanaan Program Greenfield | L45: Info | M45: Info | N45: Planning | O45: Aji S | P45: =DATEDIF(C45,$W$1,"Y")&" tahun, "&DATEDIF(C45,$W$1,"YM")&" bulan, "&DATEDIF(C45,$W$1,"MD")&" hari" -> 0 tahun, 5 bulan, 11 hari | Q45: =DATEDIF(C45,Summary!$A$1,"d") -> 161 | S45: {=_xlfn.IFS(Q45<=T45,T45,Q45<=T45*2,T45*2,Q45<=T45*3,T45*3,Q45>T45*3,">"&T45*3)} -> Info | T45: {=_xlfn.IFS(M45="Level 1",7,M45="Level 2",14,M45="Level 3","30",M45="Info","Info",M45="Closed","Closed")} -> Info
A46: 45 | B46: 171/SCI-KPI/I/2026 | C46: 46057 | D46: 46045 | E46: KPI - Sucofindo | F46: Tanggapan atas Surat PT Air Bersih Jakarta No. ABJ/DIR/EKS/11.25/1024 Tentang DED dan RAB Perluasan Jaringan Untuk Proyek Tambah Infill Ad Hoc Jl. Perjuangan SPAM Jatiluhur Hilir | G46: Penyampaian KPI terhadap DED dan RAB Perluasan Jaringan Untuk Proyek Tambah Infill Ad Hoc Jl. Perjuangan SPAM Jatiluhur Hilir | H46: Project | I46: Greenfield | J46: Perencanaan Program Greenfield | L46: Info | M46: Info | N46: Planning | O46: Aji S | P46: =DATEDIF(C46,$W$1,"Y")&" tahun, "&DATEDIF(C46,$W$1,"YM")&" bulan, "&DATEDIF(C46,$W$1,"MD")&" hari" -> 0 tahun, 5 bulan, 11 hari | Q46: =DATEDIF(C46,Summary!$A$1,"d") -> 161 | S46: {=_xlfn.IFS(Q46<=T46,T46,Q46<=T46*2,T46*2,Q46<=T46*3,T46*3,Q46>T46*3,">"&T46*3)} -> Info | T46: {=_xlfn.IFS(M46="Level 1",7,M46="Level 2",14,M46="Level 3","30",M46="Info","Info",M46="Closed","Closed")} -> Info
A47: 46 | B47: 176/SCI-KPI/II/2026 | C47: 46057 | D47: 46055 | E47: KPI - Sucofindo | F47: Tanggapan atas Surat PT Air Bersih Jakarta No. ABJ/DIR/EKS/01.26/0074 perihal Penyampaian Laporan Penyelesaian Uji Komisioning Project Greenfield – SPAM Jatiluhur Hilir PC 054 Rawa Badung RW 07 | G47: Dapat dilanjutkan ke MC100 | H47: Project | I47: Jatiluhur Hilir | J47: Konstruksi Program Greenfield | L47: Info | M47: Info | N47: PMO Infill | O47: Muhrojin | P47: =DATEDIF(C47,$W$1,"Y")&" tahun, "&DATEDIF(C47,$W$1,"YM")&" bulan, "&DATEDIF(C47,$W$1,"MD")&" hari" -> 0 tahun, 5 bulan, 11 hari | Q47: =DATEDIF(C47,Summary!$A$1,"d") -> 161 | S47: {=_xlfn.IFS(Q47<=T47,T47,Q47<=T47*2,T47*2,Q47<=T47*3,T47*3,Q47>T47*3,">"&T47*3)} -> Info | T47: {=_xlfn.IFS(M47="Level 1",7,M47="Level 2",14,M47="Level 3","30",M47="Info","Info",M47="Closed","Closed")} -> Info
A48: 47 | B48: 120/S/DIR/BPM/II/2026 | C48: 46063 | D48: 46056 | E48: BPM | F48: Permohonan Persetujuan Perubahan Spesifikasi Material Tee DCI menjadi Tee Steel | G48: BPM mengajukan permohonan persetujuan perubahan spesifikasi material dari tee DCI menjadi tee steel dalam keterbatasan kapasitas produksi tee DCI | H48: Project | I48: Greenfield | J48: Konstruksi Program Greenfield | L48: Open | M48: Level 1 | N48: PMO Infill/PMO TM | O48: Danny L / Suci | P48: =DATEDIF(C48,$W$1,"Y")&" tahun, "&DATEDIF(C48,$W$1,"YM")&" bulan, "&DATEDIF(C48,$W$1,"MD")&" hari" -> 0 tahun, 5 bulan, 5 hari | Q48: =DATEDIF(C48,Summary!$A$1,"d") -> 155 | R48: lewat 30d | S48: {=_xlfn.IFS(Q48<=T48,T48,Q48<=T48*2,T48*2,Q48<=T48*3,T48*3,Q48>T48*3,">"&T48*3)} -> >21 | T48: {=_xlfn.IFS(M48="Level 1",7,M48="Level 2",14,M48="Level 3","30",M48="Info","Info",M48="Closed","Closed")} -> 7
A49: 48 | B49: e-72803/PP.01.05 | C49: 46063 | D49: 46057 | E49: PAM JAYA | F49: Permintaan Pemenuhan Kewajiban Penyerahan Laporan Fasilitas Distribusi Baru | G49: PAM JAYA mengingatkaan ABJ untuk memenuhi kewajiban PKS Bundling maksimal 5 Februari untuk pengiriman laporan fasilitas distribusi baru | H49: Project | I49: Greenfield | J49: Monitoring & Pelaporan | L49: Closed | M49: Closed | N49: PMO Infill / PMO TM | O49: Danny L / Suci | P49: =DATEDIF(C49,$W$1,"Y")&" tahun, "&DATEDIF(C49,$W$1,"YM")&" bulan, "&DATEDIF(C49,$W$1,"MD")&" hari" -> 0 tahun, 5 bulan, 5 hari | Q49: =DATEDIF(C49,Summary!$A$1,"d") -> 155 | R49: < 7 | S49: {=_xlfn.IFS(Q49<=T49,T49,Q49<=T49*2,T49*2,Q49<=T49*3,T49*3,Q49>T49*3,">"&T49*3)} -> Closed | T49: {=_xlfn.IFS(M49="Level 1",7,M49="Level 2",14,M49="Level 3","30",M49="Info","Info",M49="Closed","Closed")} -> Closed | U49: Dibalas ABJ26 0109, ABJ26 0110
A50: 49 | B50: e-72454/PS.04.06 | C50: 46063 | D50: 46051 | E50: PAM JAYA | F50: Tanggapan atas Surat ABJ No. ABJ/ DIR/EKS/11.25/1023 perihal Proyek Reservoir Pejompongan 2 | G50: PAM JAYA meminta ABJ untuk menetapkan pembangunan reservoir baru IPA Pejompongan 2 dan relokasi gedung CM PAM yang merupakan bagian rehabilitasi | H50: Project | I50: Cyclical | J50: Perencanaan Program Greenfield | L50: Closed | M50: Closed | N50: Planning | O50: Andriani | P50: =DATEDIF(C50,$W$1,"Y")&" tahun, "&DATEDIF(C50,$W$1,"YM")&" bulan, "&DATEDIF(C50,$W$1,"MD")&" hari" -> 0 tahun, 5 bulan, 5 hari | Q50: =DATEDIF(C50,Summary!$A$1,"d") -> 155 | R50: lewat 30d | S50: {=_xlfn.IFS(Q50<=T50,T50,Q50<=T50*2,T50*2,Q50<=T50*3,T50*3,Q50>T50*3,">"&T50*3)} -> Closed | T50: {=_xlfn.IFS(M50="Level 1",7,M50="Level 2",14,M50="Level 3","30",M50="Info","Info",M50="Closed","Closed")} -> Closed
A51: 50 | B51: e-72123/PP.00.02 | C51: 46063 | D51: 46043 | E51: PAM JAYA | F51: Pembaharuan Informasi Proyek Greenfield JDU JDB JDL dan SL Regional Utara | G51: PAM JAYA meminta ABJ untuk menindaklanjuti lokasi rencana pekerjaan sesuai surat terlampir | H51: Project | I51: Greenfield | J51: Perencanaan Program Greenfield | L51: Open | M51: Level 2 | N51: Planning | O51: Aji S | P51: =DATEDIF(C51,$W$1,"Y")&" tahun, "&DATEDIF(C51,$W$1,"YM")&" bulan, "&DATEDIF(C51,$W$1,"MD")&" hari" -> 0 tahun, 5 bulan, 5 hari | Q51: =DATEDIF(C51,Summary!$A$1,"d") -> 155 | R51: lewat 30d | S51: {=_xlfn.IFS(Q51<=T51,T51,Q51<=T51*2,T51*2,Q51<=T51*3,T51*3,Q51>T51*3,">"&T51*3)} -> >42 | T51: {=_xlfn.IFS(M51="Level 1",7,M51="Level 2",14,M51="Level 3","30",M51="Info","Info",M51="Closed","Closed")} -> 14
A52: 51 | B52: e-72455/PS.04.00 | C52: 46063 | D52: 46050 | E52: PAM JAYA | F52: Permintaan Pemenuhan Realisasi Investasi Amandemen dan Pernyataan Kembali Perjanjian Brownfield Periode Tahun 2026 | G52: PAM JAYA mengingatkan ABJ untuk memenuhi kewajiban investasi sebagaimana PKS A&R Brownfield | H52: Project | I52: Cyclical | J52: Keuangan, Pembayaran, Investasi | L52: Closed | M52: Closed | N52: Planning / PGO | O52: Andriani / Angelika | P52: =DATEDIF(C52,$W$1,"Y")&" tahun, "&DATEDIF(C52,$W$1,"YM")&" bulan, "&DATEDIF(C52,$W$1,"MD")&" hari" -> 0 tahun, 5 bulan, 5 hari | Q52: =DATEDIF(C52,Summary!$A$1,"d") -> 155 | R52: lewat 30d | S52: {=_xlfn.IFS(Q52<=T52,T52,Q52<=T52*2,T52*2,Q52<=T52*3,T52*3,Q52>T52*3,">"&T52*3)} -> Closed | T52: {=_xlfn.IFS(M52="Level 1",7,M52="Level 2",14,M52="Level 3","30",M52="Info","Info",M52="Closed","Closed")} -> Closed
A53: 52 | B53: e-72456/PS.04.00 | C53: 46063 | D53: 46050 | E53: PAM JAYA | F53: Permintaan Pemenuhan Realisasi Investasi Amandemen dan Pernyataan Kembali Perjanjian Greenfield Periode Tahun 2026 | G53: PAM JAYA mengingatkan ABJ untuk memenuhi kewajiban investasi sebagaimana PKS A&R Greenfield | H53: Project | I53: Greenfield | J53: Keuangan, Pembayaran, Investasi | L53: Open | M53: Level 1 | N53: Planning / PGO | O53: Aji S / Angelika | P53: =DATEDIF(C53,$W$1,"Y")&" tahun, "&DATEDIF(C53,$W$1,"YM")&" bulan, "&DATEDIF(C53,$W$1,"MD")&" hari" -> 0 tahun, 5 bulan, 5 hari | Q53: =DATEDIF(C53,Summary!$A$1,"d") -> 155 | R53: lewat 30d | S53: {=_xlfn.IFS(Q53<=T53,T53,Q53<=T53*2,T53*2,Q53<=T53*3,T53*3,Q53>T53*3,">"&T53*3)} -> >21 | T53: {=_xlfn.IFS(M53="Level 1",7,M53="Level 2",14,M53="Level 3","30",M53="Info","Info",M53="Closed","Closed")} -> 7
A54: 53 | B54: e-72732/PP.01.02 | C54: 46063 | D54: 46056 | E54: PAM JAYA | F54: Teguran Pemenuhan Kewajiban Penyelesaian Paket Pekerjaaan Kedua Proyek Greenfield Pada Saat Tanggal Operasi Komersial atau 5 Oktober 2025 | G54: Teguran PAM JAYA kepada ABJ terhadap 25 program TOK Oktober 2025 yang belum selesai dan PAM JAYA meminta ABJ untuk memenuhi seluruh ketentuan PKS A&R | H54: Project | I54: Greenfield | J54: Konstruksi Program Greenfield | L54: Open | M54: Level 1 | N54: PMO Infill/PMO TM | O54: Danny L / Suci | P54: =DATEDIF(C54,$W$1,"Y")&" tahun, "&DATEDIF(C54,$W$1,"YM")&" bulan, "&DATEDIF(C54,$W$1,"MD")&" hari" -> 0 tahun, 5 bulan, 5 hari | Q54: =DATEDIF(C54,Summary!$A$1,"d") -> 155 | R54: lewat 30d | S54: {=_xlfn.IFS(Q54<=T54,T54,Q54<=T54*2,T54*2,Q54<=T54*3,T54*3,Q54>T54*3,">"&T54*3)} -> >21 | T54: {=_xlfn.IFS(M54="Level 1",7,M54="Level 2",14,M54="Level 3","30",M54="Info","Info",M54="Closed","Closed")} -> 7
A55: 54 | B55: e-72733/PS.04.06 | C55: 46063 | D55: 46055 | E55: PAM JAYA | F55: Tanggapan Atas Surat ABJ No. ABJ/ DIR/EKS/12.25/1113 perihal Pemasangan Ramset Program Master Meter Binton | G55: PAM JAYA meminta ABJ untuk menyampaikan secara tertulis kronologis permohonan izin dan kendala selama proses perizinan | H55: Project | I55: Jatiluhur Hilir | J55: Konstruksi Program Greenfield | L55: Open | M55: Level 1 | N55: PMO Infill | O55: Muhrojin | P55: =DATEDIF(C55,$W$1,"Y")&" tahun, "&DATEDIF(C55,$W$1,"YM")&" bulan, "&DATEDIF(C55,$W$1,"MD")&" hari" -> 0 tahun, 5 bulan, 5 hari | Q55: =DATEDIF(C55,Summary!$A$1,"d") -> 155 | R55: lewat 30d | S55: {=_xlfn.IFS(Q55<=T55,T55,Q55<=T55*2,T55*2,Q55<=T55*3,T55*3,Q55>T55*3,">"&T55*3)} -> >21 | T55: {=_xlfn.IFS(M55="Level 1",7,M55="Level 2",14,M55="Level 3","30",M55="Info","Info",M55="Closed","Closed")} -> 7
A56: 55 | B56: e-72734/PS.04.00 | C56: 46063 | D56: 46050 | E56: PAM JAYA | F56: Tanggapan atas Surat ABJ No.: ABJ/ DIR/EKS/01.26/0035 Tertangal 12 Januari 2026 Perihal Usulan Penyederhanaan Workflow Desain Akhir, Proposal Modifikasi, dan Closing melalui BIM | G56: PAM JAYA meminta untuk komitmen terhadap penyampaian dokumen dalam CDE BIM dan hanya dilakukan oleh pihak ABJ (non MK), ABJ untuk memastikan konsistensi antar dokumen | H56: Project | I56: Project | J56: Administrasi & Dokumentasi | L56: Info | M56: Info | N56: PGO | O56: Angelika | P56: =DATEDIF(C56,$W$1,"Y")&" tahun, "&DATEDIF(C56,$W$1,"YM")&" bulan, "&DATEDIF(C56,$W$1,"MD")&" hari" -> 0 tahun, 5 bulan, 5 hari | Q56: =DATEDIF(C56,Summary!$A$1,"d") -> 155 | R56: < 8 | S56: {=_xlfn.IFS(Q56<=T56,T56,Q56<=T56*2,T56*2,Q56<=T56*3,T56*3,Q56>T56*3,">"&T56*3)} -> Info | T56: {=_xlfn.IFS(M56="Level 1",7,M56="Level 2",14,M56="Level 3","30",M56="Info","Info",M56="Closed","Closed")} -> Info
A57: 56 | B57: 168/SCI-KPI/I/2026 | C57: 46064 | D57: 46045 | E57: KPI - Sucofindo | F57: Tanggapan atas Surat PT Air Bersih Jakarta No. ABJ/DIR/EKS/12.25/1082 Tentang DED dan RAB Perluasan Jaringan Untuk Proyek Tambahan Infill Ad Hoc Pesanggrahan Tahap 1 SPAM Karian Serpong Hilir | G57: Tanggapan atas DED RAB Perluasan Jaringan Untuk Proyek Tambahan Infill Ad Hoc Pesanggrahan Tahap 1 SPAM Karian Serpong Hilir | H57: Project | I57: Karian Serpong Hilir | J57: Perencanaan Program Greenfield | L57: Info | M57: Info | N57: Planning | O57: Aji S | P57: =DATEDIF(C57,$W$1,"Y")&" tahun, "&DATEDIF(C57,$W$1,"YM")&" bulan, "&DATEDIF(C57,$W$1,"MD")&" hari" -> 0 tahun, 5 bulan, 4 hari | Q57: =DATEDIF(C57,Summary!$A$1,"d") -> 154 | R57: < 9 | S57: {=_xlfn.IFS(Q57<=T57,T57,Q57<=T57*2,T57*2,Q57<=T57*3,T57*3,Q57>T57*3,">"&T57*3)} -> Info | T57: {=_xlfn.IFS(M57="Level 1",7,M57="Level 2",14,M57="Level 3","30",M57="Info","Info",M57="Closed","Closed")} -> Info
A58: 57 | B58: e-73256/PP.01.05 | C58: 46065 | D58: 46058 | E58: PAM JAYA | F58: Teguran Pemenuhan Kewajiban Penyerahan Laporan Fasilitas Distribusi Baru | G58: Teguran PAM JAYA terhadap tidak dipenuhinya dokumen penyerahan Fasilitas Distribusi Baru Paket Pekerjaan Ketiga | H58: Project | I58: Greenfield | J58: Konstruksi Program Greenfield | L58: Closed | M58: Closed | N58: PMO Infill / PMO TM | O58: Danny L / Suci | P58: =DATEDIF(C58,$W$1,"Y")&" tahun, "&DATEDIF(C58,$W$1,"YM")&" bulan, "&DATEDIF(C58,$W$1,"MD")&" hari" -> 0 tahun, 5 bulan, 3 hari | Q58: =DATEDIF(C58,Summary!$A$1,"d") -> 153 | R58: < 7 | S58: {=_xlfn.IFS(Q58<=T58,T58,Q58<=T58*2,T58*2,Q58<=T58*3,T58*3,Q58>T58*3,">"&T58*3)} -> Closed | T58: {=_xlfn.IFS(M58="Level 1",7,M58="Level 2",14,M58="Level 3","30",M58="Info","Info",M58="Closed","Closed")} -> Closed | U58: Dibalas ABJ26 0109, ABJ26 0110
A59: 58 | B59: e-73094/PP.00.02 | C59: 46065 | D59: 46058 | E59: PAM JAYA | F59: Pemutakhiran Program Konstruksi dan Desain Akhir DC Pegadungan dan JDU JDB JDL Citra Extension | G59: PAM JAYA meminta ABJ untuk menyampaikan usulan modifikasi Reservoir DC Pegadungan dan melakukan pemutakhiran Desain Akhir | H59: Project | I59: Greenfield | J59: Perencanaan Program Greenfield | L59: Open | M59: Level 2 | N59: Planning | O59: Aji S | P59: =DATEDIF(C59,$W$1,"Y")&" tahun, "&DATEDIF(C59,$W$1,"YM")&" bulan, "&DATEDIF(C59,$W$1,"MD")&" hari" -> 0 tahun, 5 bulan, 3 hari | Q59: =DATEDIF(C59,Summary!$A$1,"d") -> 153 | R59: lewat 7d | S59: {=_xlfn.IFS(Q59<=T59,T59,Q59<=T59*2,T59*2,Q59<=T59*3,T59*3,Q59>T59*3,">"&T59*3)} -> >42 | T59: {=_xlfn.IFS(M59="Level 1",7,M59="Level 2",14,M59="Level 3","30",M59="Info","Info",M59="Closed","Closed")} -> 14
A60: 59 | B60: e-73095/PP.00.02 | C60: 46065 | D60: 46059 | E60: PAM JAYA | F60: Pemutakhiran Desain Akhir JDU JDB JDL dan SL Proyek Greenfield Master Meter Khoirul Rokhim | G60: PAM JAYA meminta ABJ untuk menindaklanjuti lokasi rencana dan pemutakhiran DED dan pemodelan hidrolis | H60: Project | I60: Greenfield | J60: Perencanaan Program Greenfield | L60: Open | M60: Level 2 | N60: Planning | O60: Aji S | P60: =DATEDIF(C60,$W$1,"Y")&" tahun, "&DATEDIF(C60,$W$1,"YM")&" bulan, "&DATEDIF(C60,$W$1,"MD")&" hari" -> 0 tahun, 5 bulan, 3 hari | Q60: =DATEDIF(C60,Summary!$A$1,"d") -> 153 | R60: lewat 7d | S60: {=_xlfn.IFS(Q60<=T60,T60,Q60<=T60*2,T60*2,Q60<=T60*3,T60*3,Q60>T60*3,">"&T60*3)} -> >42 | T60: {=_xlfn.IFS(M60="Level 1",7,M60="Level 2",14,M60="Level 3","30",M60="Info","Info",M60="Closed","Closed")} -> 14
A61: 60 | B61: e-73146/PS.04.03 | C61: 46065 | D61: 46056 | E61: PAM JAYA | F61: Permintaan Pemenuhan Dokumen Pendukung Program Konstruksi untuk pekerjaan Fasilitas Distribusi Baru TOK Oktober 2025 | G61: PAM JAYA menyampaikan belum adanya dokumen DPPK untuk program TOK Oktober 2025 | H61: Project | I61: Greenfield | J61: Konstruksi Program Greenfield | L61: Closed | M61: Closed | N61: PMO Infill / PMO TM | O61: Danny L / Suci | P61: =DATEDIF(C61,$W$1,"Y")&" tahun, "&DATEDIF(C61,$W$1,"YM")&" bulan, "&DATEDIF(C61,$W$1,"MD")&" hari" -> 0 tahun, 5 bulan, 3 hari | Q61: =DATEDIF(C61,Summary!$A$1,"d") -> 153 | R61: lewat 7d | S61: {=_xlfn.IFS(Q61<=T61,T61,Q61<=T61*2,T61*2,Q61<=T61*3,T61*3,Q61>T61*3,">"&T61*3)} -> Closed | T61: {=_xlfn.IFS(M61="Level 1",7,M61="Level 2",14,M61="Level 3","30",M61="Info","Info",M61="Closed","Closed")} -> Closed | U61: Dibalas ABJ/DIR/EKS/03.26/0227
A62: 61 | B62: e-73147/PP.00.02 | C62: 46065 | D62: 46057 | E62: PAM JAYA | F62: Pemutakhiran Desain Akhir JDU JDB JDL dan SL Proyek Greenfield Regional Utara dan Selatan | G62: PAM JAYA meminta ABJ untuk menindaklanjuti lokasi rencana dan pemutakhiran DED dan pemodelan hidrolis | H62: Project | I62: Greenfield | J62: Perencanaan Program Greenfield | L62: Open | M62: Level 2 | N62: Planning | O62: Aji S | P62: =DATEDIF(C62,$W$1,"Y")&" tahun, "&DATEDIF(C62,$W$1,"YM")&" bulan, "&DATEDIF(C62,$W$1,"MD")&" hari" -> 0 tahun, 5 bulan, 3 hari | Q62: =DATEDIF(C62,Summary!$A$1,"d") -> 153 | R62: lewat 7d | S62: {=_xlfn.IFS(Q62<=T62,T62,Q62<=T62*2,T62*2,Q62<=T62*3,T62*3,Q62>T62*3,">"&T62*3)} -> >42 | T62: {=_xlfn.IFS(M62="Level 1",7,M62="Level 2",14,M62="Level 3","30",M62="Info","Info",M62="Closed","Closed")} -> 14
A63: 62 | B63: 009/BLLS/SI/II/2026 | C63: 46065 | D63: 46062 | E63: PT. Bina Lestari Lingkungan Sejahtera (BLLS) | F63: Penyampaian Informasi Keterlambatan Progres Aktual Pelaksanaan Project | G63: Penyampaian informasi project TOK April 2025 dan TOK Oktober 2025 serta progres TOK April 2026 | H63: Project | I63: Greenfield | J63: Konstruksi Program Greenfield | L63: Info | M63: Info | N63: PGO | O63: Angelika | P63: =DATEDIF(C63,$W$1,"Y")&" tahun, "&DATEDIF(C63,$W$1,"YM")&" bulan, "&DATEDIF(C63,$W$1,"MD")&" hari" -> 0 tahun, 5 bulan, 3 hari | Q63: =DATEDIF(C63,Summary!$A$1,"d") -> 153 | R63: < 15 | S63: {=_xlfn.IFS(Q63<=T63,T63,Q63<=T63*2,T63*2,Q63<=T63*3,T63*3,Q63>T63*3,">"&T63*3)} -> Info | T63: {=_xlfn.IFS(M63="Level 1",7,M63="Level 2",14,M63="Level 3","30",M63="Info","Info",M63="Closed","Closed")} -> Info
A64: 63 | B64: 185/SCI-KPI/II/2026 | C64: 46066 | D64: 46063 | E64: KPI - Sucofindo | F64: Tanggapan atas Surat PT Air Bersih Jakarta No. ABJ/DIR/EKS/02.26/0117 perihal Penyampaian Laporan Penyelesaian Uji Komisioning Project Greenfield – SPAM Buaran 3 Hilir Program PC 162 Centex | G64: Program PC 162 Centex belum dapat dilanjutkan MC100 karena masih ada kekurangan dokumen | H64: Project | I64: Buaran 3 Hilir | J64: Konstruksi Program Greenfield | L64: Info | M64: Info | N64: PMO Infill | O64: Topan | P64: =DATEDIF(C64,$W$1,"Y")&" tahun, "&DATEDIF(C64,$W$1,"YM")&" bulan, "&DATEDIF(C64,$W$1,"MD")&" hari" -> 0 tahun, 5 bulan, 2 hari | Q64: =DATEDIF(C64,Summary!$A$1,"d") -> 152 | R64: < 16 | S64: {=_xlfn.IFS(Q64<=T64,T64,Q64<=T64*2,T64*2,Q64<=T64*3,T64*3,Q64>T64*3,">"&T64*3)} -> Info | T64: {=_xlfn.IFS(M64="Level 1",7,M64="Level 2",14,M64="Level 3","30",M64="Info","Info",M64="Closed","Closed")} -> Info
A65: 64 | B65: 188/SCI-KPI/II/2026 | C65: 46066 | D65: 46066 | E65: KPI - Sucofindo | F65: Pemberitahuan Libur Nasional dan Cuti Bersama Tahun Baru Imlek | G65: Pemberitahuan Libur Nasional dan Cuti Bersama Tahun Baru Imlek | H65: Project | I65: Project | J65: Monitoring & Pelaporan | L65: Info | M65: Info | N65: Compliance | O65: Indradi | P65: =DATEDIF(C65,$W$1,"Y")&" tahun, "&DATEDIF(C65,$W$1,"YM")&" bulan, "&DATEDIF(C65,$W$1,"MD")&" hari" -> 0 tahun, 5 bulan, 2 hari | Q65: =DATEDIF(C65,Summary!$A$1,"d") -> 152 | R65: < 17 | S65: {=_xlfn.IFS(Q65<=T65,T65,Q65<=T65*2,T65*2,Q65<=T65*3,T65*3,Q65>T65*3,">"&T65*3)} -> Info | T65: {=_xlfn.IFS(M65="Level 1",7,M65="Level 2",14,M65="Level 3","30",M65="Info","Info",M65="Closed","Closed")} -> Info
A66: 65 | B66: 192/SCI-KPI/II/2026 | C66: 46076 | D66: 46073 | E66: KPI - Sucofindo | F66: Penyampaian Laporan Penyelesaian Uji Komisioning Project Greenfield – SPAM Jatiluhur Hilir 3 Program Tertanggal 12 Februari 2026 | G66: Program dapat dilanjutkan ke MC100 | H66: Project | I66: Jatiluhur Hilir | J66: Konstruksi Program Greenfield | L66: Info | M66: Info | N66: PMO Infill | O66: Muhrojin | P66: =DATEDIF(C66,$W$1,"Y")&" tahun, "&DATEDIF(C66,$W$1,"YM")&" bulan, "&DATEDIF(C66,$W$1,"MD")&" hari" -> 0 tahun, 4 bulan, 22 hari | Q66: =DATEDIF(C66,Summary!$A$1,"d") -> 142 | R66: < 18 | S66: {=_xlfn.IFS(Q66<=T66,T66,Q66<=T66*2,T66*2,Q66<=T66*3,T66*3,Q66>T66*3,">"&T66*3)} -> Info | T66: {=_xlfn.IFS(M66="Level 1",7,M66="Level 2",14,M66="Level 3","30",M66="Info","Info",M66="Closed","Closed")} -> Info
A67: 66 | B67: e-73685/PS.04.03 | C67: 46077 | D67: 46065 | E67: PAM JAYA | F67: Pemenuhan Kewajiban Penyampaian Pembaharuan Daftar Asset Periode Kedua 2025 | G67: PAM JAYA meminta ABJ untuk menyerahkan pembaruan daftar aset dengan data yang sudah diverifikasi bersama PAM JAYA | H67: Project | I67: Cyclical | J67: Aset Management | L67: Closed | M67: Closed | N67: Compliance | O67: Indradi | P67: =DATEDIF(C67,$W$1,"Y")&" tahun, "&DATEDIF(C67,$W$1,"YM")&" bulan, "&DATEDIF(C67,$W$1,"MD")&" hari" -> 0 tahun, 4 bulan, 21 hari | Q67: =DATEDIF(C67,Summary!$A$1,"d") -> 141 | R67: < 19 | S67: {=_xlfn.IFS(Q67<=T67,T67,Q67<=T67*2,T67*2,Q67<=T67*3,T67*3,Q67>T67*3,">"&T67*3)} -> Closed | T67: {=_xlfn.IFS(M67="Level 1",7,M67="Level 2",14,M67="Level 3","30",M67="Info","Info",M67="Closed","Closed")} -> Closed
A68: 67 | B68: e-73689/PP.00.02 | C68: 46077 | D68: 46065 | E68: PAM JAYA | F68: Pemutakhiran Desain Akhir JDU JDB JDL dan SL Proyek Greenfield Sekolah Citra Kasih Don Bosco dan RW 003 Cilandak Barat | G68: PAM JAYA meminta ABJ untuk pemutakhiran desain akhir pada lokasi terlampir | H68: Project | I68: Greenfield | J68: Perencanaan Program Greenfield | L68: Open | M68: Level 2 | N68: Planning | O68: Aji S | P68: =DATEDIF(C68,$W$1,"Y")&" tahun, "&DATEDIF(C68,$W$1,"YM")&" bulan, "&DATEDIF(C68,$W$1,"MD")&" hari" -> 0 tahun, 4 bulan, 21 hari | Q68: =DATEDIF(C68,Summary!$A$1,"d") -> 141 | R68: < 20 | S68: {=_xlfn.IFS(Q68<=T68,T68,Q68<=T68*2,T68*2,Q68<=T68*3,T68*3,Q68>T68*3,">"&T68*3)} -> >42 | T68: {=_xlfn.IFS(M68="Level 1",7,M68="Level 2",14,M68="Level 3","30",M68="Info","Info",M68="Closed","Closed")} -> 14
A69: 68 | B69: e-73687/KH.01.00 | C69: 46077 | D69: 46065 | E69: PAM JAYA | F69: Pengiriman Jadwal Calender of Event Program Rehabilitasi Tahun 2026 | G69: PAM JAYA meminta ABJ untuk menyampaikan sifat gangguan dan jangka waktu gangguan pada saat CoE; mengidentifikasi jadwal pelaksanaan CoE selama periode libur panjang 2026 | H69: Project | I69: Cyclical | J69: Perencanaan Program Rehabilitasi | L69: Info | M69: Info | N69: PMO Cyclical | O69: Agus H | P69: =DATEDIF(C69,$W$1,"Y")&" tahun, "&DATEDIF(C69,$W$1,"YM")&" bulan, "&DATEDIF(C69,$W$1,"MD")&" hari" -> 0 tahun, 4 bulan, 21 hari | Q69: =DATEDIF(C69,Summary!$A$1,"d") -> 141 | R69: < 21 | S69: {=_xlfn.IFS(Q69<=T69,T69,Q69<=T69*2,T69*2,Q69<=T69*3,T69*3,Q69>T69*3,">"&T69*3)} -> Info | T69: {=_xlfn.IFS(M69="Level 1",7,M69="Level 2",14,M69="Level 3","30",M69="Info","Info",M69="Closed","Closed")} -> Info
A70: 69 | B70: e-73798/PP.01.02 | C70: 46077 | D70: 46065 | E70: PAM JAYA | F70: Teguran atas Keterlambatan Pelaksanaan Program Rehabilitasi Proyek Brownfield Tahun 2026 | G70: PAM JAYA meminta ABJ untuk menyampaikan pembaharuan jadwal pelaksanaan cyclical 2026 program 46204 dan 46325 | H70: Project | I70: Cyclical | J70: Perencanaan Program Rehabilitasi | L70: Closed | M70: Closed | N70: PMO Cyclical | O70: Agus H | P70: =DATEDIF(C70,$W$1,"Y")&" tahun, "&DATEDIF(C70,$W$1,"YM")&" bulan, "&DATEDIF(C70,$W$1,"MD")&" hari" -> 0 tahun, 4 bulan, 21 hari | Q70: =DATEDIF(C70,Summary!$A$1,"d") -> 141 | R70: < 22 | S70: {=_xlfn.IFS(Q70<=T70,T70,Q70<=T70*2,T70*2,Q70<=T70*3,T70*3,Q70>T70*3,">"&T70*3)} -> Closed | T70: {=_xlfn.IFS(M70="Level 1",7,M70="Level 2",14,M70="Level 3","30",M70="Info","Info",M70="Closed","Closed")} -> Closed | U70: Dibalas surat ABJ26 0567
A71: 70 | B71: e-73829/PP.01.05 | C71: 46077 | D71: 46066 | E71: PAM JAYA | F71: Permintaan Pemenuhan Kewajiban Penyelesaian Paket Pekerjaan Ketiga atau Tanggal Operasi Komersial 5 April 2026 | G71: PAM JAYA meminta ABJ untuk menyelesaikan seluruh pekerjaan TOK April 2026; Tidak adanya keterlambatan; Melakukan pembaharuan informasi dan memastikan pemenuhan perizinan | H71: Project | I71: Greenfield | J71: Konstruksi Program Greenfield | L71: Info | M71: Info | N71: PMO Infill; PMO TM | O71: Danny L; Suci | P71: =DATEDIF(C71,$W$1,"Y")&" tahun, "&DATEDIF(C71,$W$1,"YM")&" bulan, "&DATEDIF(C71,$W$1,"MD")&" hari" -> 0 tahun, 4 bulan, 21 hari | Q71: =DATEDIF(C71,Summary!$A$1,"d") -> 141 | R71: < 23 | S71: {=_xlfn.IFS(Q71<=T71,T71,Q71<=T71*2,T71*2,Q71<=T71*3,T71*3,Q71>T71*3,">"&T71*3)} -> Info | T71: {=_xlfn.IFS(M71="Level 1",7,M71="Level 2",14,M71="Level 3","30",M71="Info","Info",M71="Closed","Closed")} -> Info
A72: 71 | B72: e-73656/PP.01.05 | C72: 46079 | D72: 46059 | E72: PAM JAYA | F72: Tanggapan atas Surat Dinas Bina Marga Prov DKI Jakarta No. 266/KR.02.00 tanggal 23 Jan 2026 | G72: Surat PAM JAYA kepada Kementerian PU terkait permohanan arahan atas tindak lanjut serah terima pembangunan sarana prasarana di komplek pengairan Kota Bekasi | H72: Project | I72: Greenfield | J72: Perizinan | L72: Info | M72: Info | N72: Permit | O72: Rais A | P72: =DATEDIF(C72,$W$1,"Y")&" tahun, "&DATEDIF(C72,$W$1,"YM")&" bulan, "&DATEDIF(C72,$W$1,"MD")&" hari" -> 0 tahun, 4 bulan, 19 hari | Q72: =DATEDIF(C72,Summary!$A$1,"d") -> 139 | R72: < 24 | S72: {=_xlfn.IFS(Q72<=T72,T72,Q72<=T72*2,T72*2,Q72<=T72*3,T72*3,Q72>T72*3,">"&T72*3)} -> Info | T72: {=_xlfn.IFS(M72="Level 1",7,M72="Level 2",14,M72="Level 3","30",M72="Info","Info",M72="Closed","Closed")} -> Info
A73: 72 | B73: 889/PS.04.04/EKST/II/2026 | C73: 46080 | D73: 46079 | E73: PAM JAYA | F73: Peringatan | G73: PAM JAYA meminta ABJ untuk menyelesaikan seluruh perbaikan paling lambat 7 hari kalender sejak surat diterima | H73: Project | I73: Greenfield | J73: Konstruksi Program Greenfield | L73: Closed | M73: Closed | N73: PMO Infill | O73: Danny L | P73: =DATEDIF(C73,$W$1,"Y")&" tahun, "&DATEDIF(C73,$W$1,"YM")&" bulan, "&DATEDIF(C73,$W$1,"MD")&" hari" -> 0 tahun, 4 bulan, 18 hari | Q73: =DATEDIF(C73,Summary!$A$1,"d") -> 138 | R73: < 25 | S73: {=_xlfn.IFS(Q73<=T73,T73,Q73<=T73*2,T73*2,Q73<=T73*3,T73*3,Q73>T73*3,">"&T73*3)} -> Closed | T73: {=_xlfn.IFS(M73="Level 1",7,M73="Level 2",14,M73="Level 3","30",M73="Info","Info",M73="Closed","Closed")} -> Closed
A74: 73 | B74: 894/PP.01.02/EKST/II/2026 | C74: 46080 | D74: 46079 | E74: PAM JAYA | F74: Teguran Penerapan Aspek Keselamatan dan Kesehatan Kerja (K3) pada Proyek Greenfield | G74: PAM JAYA meminta ABJ untuk memastikan ABJ menindaklanjuti temuan inspeksi PAM | H74: Project | I74: Greenfield | J74: HSE | L74: Closed | M74: Closed | N74: HSE | O74: Irsan | P74: =DATEDIF(C74,$W$1,"Y")&" tahun, "&DATEDIF(C74,$W$1,"YM")&" bulan, "&DATEDIF(C74,$W$1,"MD")&" hari" -> 0 tahun, 4 bulan, 18 hari | Q74: =DATEDIF(C74,Summary!$A$1,"d") -> 138 | R74: < 26 | S74: {=_xlfn.IFS(Q74<=T74,T74,Q74<=T74*2,T74*2,Q74<=T74*3,T74*3,Q74>T74*3,">"&T74*3)} -> Closed | T74: {=_xlfn.IFS(M74="Level 1",7,M74="Level 2",14,M74="Level 3","30",M74="Info","Info",M74="Closed","Closed")} -> Closed
A75: 74 | B75: 197/SCI-KPI/II/2026 | C75: 46082 | D75: 46080 | E75: KPI - Sucofindo | F75: Surat Pengantar Laporan Bulanan Proyek Bundling SPAM DKI Jakarta - Konsultan Pengawas Independen Periode Januari 2026 | G75: Laporan Bulanan Proyek Bundling SPAM DKI Jakarta - Konsultan Pengawas Independen Periode Januari 2026 | H75: Project | I75: Greenfield | J75: Monitoring & Pelaporan | L75: Info | M75: Info | N75: Compliance | O75: A. Levi | P75: =DATEDIF(C75,$W$1,"Y")&" tahun, "&DATEDIF(C75,$W$1,"YM")&" bulan, "&DATEDIF(C75,$W$1,"MD")&" hari" -> 0 tahun, 4 bulan, 14 hari | Q75: =DATEDIF(C75,Summary!$A$1,"d") -> 136 | R75: < 27 | S75: {=_xlfn.IFS(Q75<=T75,T75,Q75<=T75*2,T75*2,Q75<=T75*3,T75*3,Q75>T75*3,">"&T75*3)} -> Info | T75: {=_xlfn.IFS(M75="Level 1",7,M75="Level 2",14,M75="Level 3","30",M75="Info","Info",M75="Closed","Closed")} -> Info
A76: 75 | B76: 199/SCI-KPI/III/2026 | C76: 46084 | D76: 46083 | E76: KPI - Sucofindo | F76: Rekomendasi Metode Sampling Cyble dan Sambungan Langsung (SL) | G76: Rekomendasi metode Sampling Cyble dan Sambungan Langsung (SL) dari KPI | H76: Project | I76: Greenfield | J76: Sambungan Langsung | L76: Info | M76: Info | N76: PMO NC | O76: Angelika | P76: =DATEDIF(C76,$W$1,"Y")&" tahun, "&DATEDIF(C76,$W$1,"YM")&" bulan, "&DATEDIF(C76,$W$1,"MD")&" hari" -> 0 tahun, 4 bulan, 12 hari | Q76: =DATEDIF(C76,Summary!$A$1,"d") -> 134 | R76: < 28 | S76: {=_xlfn.IFS(Q76<=T76,T76,Q76<=T76*2,T76*2,Q76<=T76*3,T76*3,Q76>T76*3,">"&T76*3)} -> Info | T76: {=_xlfn.IFS(M76="Level 1",7,M76="Level 2",14,M76="Level 3","30",M76="Info","Info",M76="Closed","Closed")} -> Info
A77: 76 | B77: 200/SCI-KPI/III/2026 | C77: 46084 | D77: 46083 | E77: KPI - Sucofindo | F77: Rekomendasi Konsultan Pengawas Independen (“KPI”) Terkait Metode Verifikasi Data Sambungan Langsung (SL) | G77: Rekomendasi KPI terhadap metode verifikasi data SL : 1. Verifikasi dilakukan berdasarkan kesesuaian data titik koordinat; 2. Verifikasi data pembayaran pelanggan mengacu pada kode pelanggan | H77: Project | I77: Greenfield | J77: Sambungan Langsung | L77: Info | M77: Info | N77: PMO NC | O77: Angelika | P77: =DATEDIF(C77,$W$1,"Y")&" tahun, "&DATEDIF(C77,$W$1,"YM")&" bulan, "&DATEDIF(C77,$W$1,"MD")&" hari" -> 0 tahun, 4 bulan, 12 hari | Q77: =DATEDIF(C77,Summary!$A$1,"d") -> 134 | R77: < 29 | S77: {=_xlfn.IFS(Q77<=T77,T77,Q77<=T77*2,T77*2,Q77<=T77*3,T77*3,Q77>T77*3,">"&T77*3)} -> Info | T77: {=_xlfn.IFS(M77="Level 1",7,M77="Level 2",14,M77="Level 3","30",M77="Info","Info",M77="Closed","Closed")} -> Info
A78: 77 | B78: 184/SCI-KPI/II/2026 | C78: 46085 | D78: 46063 | E78: KPI - Sucofindo | F78: Rekomendasi Perpanjangan Masa Konstruksi Selama 90 (Sembilan Puluh) Hari Untuk Program-Program Yang Belum Selesai Tahap Konstruksi Serta Terkait Perizinan | G78: Rekomendasi KPI yaitu ABJ dapat menyampaikan jadwal pelaksanaan perpanjangan konstruksi 90 hari dan justek terhadap keterlambatan proyek | H78: Project | I78: Greenfield | J78: Konstruksi Program Greenfield | L78: Info | M78: Info | N78: PMO Infill; PMO TM | O78: Danny L; Suci | P78: =DATEDIF(C78,$W$1,"Y")&" tahun, "&DATEDIF(C78,$W$1,"YM")&" bulan, "&DATEDIF(C78,$W$1,"MD")&" hari" -> 0 tahun, 4 bulan, 11 hari | Q78: =DATEDIF(C78,Summary!$A$1,"d") -> 133 | R78: < 30 | S78: {=_xlfn.IFS(Q78<=T78,T78,Q78<=T78*2,T78*2,Q78<=T78*3,T78*3,Q78>T78*3,">"&T78*3)} -> Info | T78: {=_xlfn.IFS(M78="Level 1",7,M78="Level 2",14,M78="Level 3","30",M78="Info","Info",M78="Closed","Closed")} -> Info
A79: 78 | B79: e-74540/PP.01.02 | C79: 46086 | D79: 46078 | E79: PAM JAYA | F79: Permintaan Pemenuhan Dokumen untuk Paket Pekerjaan Ketiga (TOK 5 April 2026) | G79: PAM JAYA meminta ABJ untuk menyampaikan kekurangan DPPP sebanyak 17 sub program paling lambat 5 hari setelah MC100 | H79: Project | I79: Greenfield | J79: Administrasi & Dokumentasi Program Greenfield | L79: Closed | M79: Closed | N79: PGO | O79: Lusian F | P79: =DATEDIF(C79,$W$1,"Y")&" tahun, "&DATEDIF(C79,$W$1,"YM")&" bulan, "&DATEDIF(C79,$W$1,"MD")&" hari" -> 0 tahun, 4 bulan, 10 hari | Q79: =DATEDIF(C79,Summary!$A$1,"d") -> 132 | R79: < 31 | S79: {=_xlfn.IFS(Q79<=T79,T79,Q79<=T79*2,T79*2,Q79<=T79*3,T79*3,Q79>T79*3,">"&T79*3)} -> Closed | T79: {=_xlfn.IFS(M79="Level 1",7,M79="Level 2",14,M79="Level 3","30",M79="Info","Info",M79="Closed","Closed")} -> Closed
A80: 79 | B80: e-74543/PP.01.02 | C80: 46086 | D80: 46078 | E80: PAM JAYA | F80: Teguran Permintaan Pemenuhan Kewajiban Penyelesaian Paket Pekerjaan Ketiga atau Tanggal Operasi Komersial 5 April 2026 | G80: 3 program belum terdapat DPPK | H80: Project | I80: Greenfield | J80: Perencanaan Program Greenfield | L80: Open | M80: Level 2 | N80: PMO Infill | O80: Danny L | P80: =DATEDIF(C80,$W$1,"Y")&" tahun, "&DATEDIF(C80,$W$1,"YM")&" bulan, "&DATEDIF(C80,$W$1,"MD")&" hari" -> 0 tahun, 4 bulan, 10 hari | Q80: =DATEDIF(C80,Summary!$A$1,"d") -> 132 | R80: < 32 | S80: {=_xlfn.IFS(Q80<=T80,T80,Q80<=T80*2,T80*2,Q80<=T80*3,T80*3,Q80>T80*3,">"&T80*3)} -> >42 | T80: {=_xlfn.IFS(M80="Level 1",7,M80="Level 2",14,M80="Level 3","30",M80="Info","Info",M80="Closed","Closed")} -> 14
A81: 80 | B81: 947/PP.00.06/EKST/III/2026 | C81: 46087 | D81: 46084 | E81: PAM JAYA | F81: Permohonan Ijin Dispensasi Angkutan selama Libur Hari Raya Idul Fitri 1447 H | G81: Surat PAM JAYA kepada DisHub DKI Jakarta perihal Permohonan Ijin Dispensasi Angkutan selama Libur Hari Raya Idul Fitri 1447 H | H81: Produksi | I81: ALL WTP | J81: Operation & Maintenance | L81: Info | M81: Info | N81: Produksi | O81: Irawan | P81: =DATEDIF(C81,$W$1,"Y")&" tahun, "&DATEDIF(C81,$W$1,"YM")&" bulan, "&DATEDIF(C81,$W$1,"MD")&" hari" -> 0 tahun, 4 bulan, 9 hari | Q81: =DATEDIF(C81,Summary!$A$1,"d") -> 131 | R81: < 33 | S81: {=_xlfn.IFS(Q81<=T81,T81,Q81<=T81*2,T81*2,Q81<=T81*3,T81*3,Q81>T81*3,">"&T81*3)} -> Info | T81: {=_xlfn.IFS(M81="Level 1",7,M81="Level 2",14,M81="Level 3","30",M81="Info","Info",M81="Closed","Closed")} -> Info
A82: 81 | B82: 207/SCI-KPI/III/2026 | C82: 46090 | D82: 46087 | E82: KPI - Sucofindo | F82: Tanggapan atas Surat PT Air Bersih Jakarta No. ABJ/DIR/EKS/03.26/0228 perihal Penyampaian Laporan Penyelesaian Uji Komisioning Project Greenfield – SPAM Jatiluhur Hilir Program PC 070 Jl. Inspeksi Kirana dan S010 Pancoran Barat VI B | G82: Dapat dilanjutkan MC100 | H82: Project | I82: Jatiluhur Hilir | J82: Konstruksi Program Greenfield | L82: Info | M82: Info | N82: PMO Infill | O82: Muhrojin | P82: =DATEDIF(C82,$W$1,"Y")&" tahun, "&DATEDIF(C82,$W$1,"YM")&" bulan, "&DATEDIF(C82,$W$1,"MD")&" hari" -> 0 tahun, 4 bulan, 6 hari | Q82: =DATEDIF(C82,Summary!$A$1,"d") -> 128 | R82: < 34 | S82: {=_xlfn.IFS(Q82<=T82,T82,Q82<=T82*2,T82*2,Q82<=T82*3,T82*3,Q82>T82*3,">"&T82*3)} -> Info | T82: {=_xlfn.IFS(M82="Level 1",7,M82="Level 2",14,M82="Level 3","30",M82="Info","Info",M82="Closed","Closed")} -> Info
... A108: 107 | B108: E-75940/PP.01.02 | C108: 46106 | D108: 46087 | E108: PAM JAYA | F108: Teguran atas keterlambatan Pelaksanaan Program Rehabilitasi Proyek Brownfield Tahun 2026 | G108: Teguran atas keterlambatan Program Rehabilitasi 2026 (29 kegiatan belum Kick Off/MC 0) dan meminta penjelasan, pembaruan jadwal, pengiriman undangan Kick Off & MC 0, serta kepatuhan pelaksanaan sesuai perjanjian | H108: Project | I108: Cyclical | J108: Konstruksi Program Rehabilitasi | L108: Closed | M108: Closed | N108: PMO Cyclical | O108: Agus H | P108: =DATEDIF(C108,$W$1,"Y")&" tahun, "&DATEDIF(C108,$W$1,"YM")&" bulan, "&DATEDIF(C108,$W$1,"MD")&" hari" -> 0 tahun, 3 bulan, 20 hari | Q108: =DATEDIF(C108,Summary!$A$1,"d") -> 112 | R108: < 64 | S108: {=_xlfn.IFS(Q108<=T108,T108,Q108<=T108*2,T108*2,Q108<=T108*3,T108*3,Q108>T108*3,">"&T108*3)} -> Closed | T108: {=_xlfn.IFS(M108="Level 1",7,M108="Level 2",14,M108="Level 3","30",M108="Info","Info",M108="Closed","Closed")} -> Closed
A109: 108 | B109: E-75951/PP.03.05 | C109: 46106 | D109: 46090 | E109: PAM JAYA | F109: Penyampaian Hasil Inspeksi Aset dan Peralatan di IPA Pulogadung Tanggal 04 Februari 2026 | G109: temuan hasil inspeksi aset dan peralatan di IPA Pulogadung (15 temuan) ABJ diminta menyampaikan rencana perbaikan dalam 14 hari kalender | H109: Produksi | I109: Pulogadung | J109: Operation & Maintenance | L109: Closed | M109: Closed | N109: Produksi | O109: Supriyanto | P109: =DATEDIF(C109,$W$1,"Y")&" tahun, "&DATEDIF(C109,$W$1,"YM")&" bulan, "&DATEDIF(C109,$W$1,"MD")&" hari" -> 0 tahun, 3 bulan, 20 hari | Q109: =DATEDIF(C109,Summary!$A$1,"d") -> 112 | R109: < 65 | S109: {=_xlfn.IFS(Q109<=T109,T109,Q109<=T109*2,T109*2,Q109<=T109*3,T109*3,Q109>T109*3,">"&T109*3)} -> Closed | T109: {=_xlfn.IFS(M109="Level 1",7,M109="Level 2",14,M109="Level 3","30",M109="Info","Info",M109="Closed","Closed")} -> Closed | U109: Dibalas surat ABJ26 0565
A110: 109 | B110: E-74540/PP.01.02 | C110: 46106 | D110: 46106 | E110: PAM JAYA | F110: Permintaan Pemenuhan Dokumen untuk Paket Pekerjaan Ketiga (TOK 5 April 2026) | G110: ABJ diminta untuk melengkapi kekurangan dokumen DPPP TOK di BIM, memperbaiki ketidaksesuaian dokumen, dan memastikan kepatuhan terhadap ketentuan perjanjian. | H110: Project | I110: Greenfield | J110: Administrasi & Dokumentasi Program Greenfield | L110: Open | M110: Level 1 | N110: PMO/PGO | O110: Suci/Lusian F | P110: =DATEDIF(C110,$W$1,"Y")&" tahun, "&DATEDIF(C110,$W$1,"YM")&" bulan, "&DATEDIF(C110,$W$1,"MD")&" hari" -> 0 tahun, 3 bulan, 20 hari | Q110: =DATEDIF(C110,Summary!$A$1,"d") -> 112 | R110: < 66 | S110: {=_xlfn.IFS(Q110<=T110,T110,Q110<=T110*2,T110*2,Q110<=T110*3,T110*3,Q110>T110*3,">"&T110*3)} -> >21 | T110: {=_xlfn.IFS(M110="Level 1",7,M110="Level 2",14,M110="Level 3","30",M110="Info","Info",M110="Closed","Closed")} -> 7
A111: 110 | B111: E-75952/PP.01.02 | C111: 46106 | D111: 46090 | E111: PAM JAYA | F111: Teguran atas Kegagalan Operasional Pompa Blower di IPA Pejompongan 1 pada tanggal 04 Maret 2026 | G111: ABJ dinilai lalai dalam pengawasan operasional IPA Pejompongan 1 hingga menyebabkan kerusakan pompa blower dan asap di ruang pompa, serta meminta tindak lanjut, pengawasan optimal, dan penyampaian CAR dalam 14 hari. | H111: Produksi | I111: PJP 1 | J111: Operation & Maintenance | L111: Closed | M111: Closed | N111: Produksi | O111: Wahdi Putra | P111: =DATEDIF(C111,$W$1,"Y")&" tahun, "&DATEDIF(C111,$W$1,"YM")&" bulan, "&DATEDIF(C111,$W$1,"MD")&" hari" -> 0 tahun, 3 bulan, 20 hari | Q111: =DATEDIF(C111,Summary!$A$1,"d") -> 112 | R111: < 67 | S111: {=_xlfn.IFS(Q111<=T111,T111,Q111<=T111*2,T111*2,Q111<=T111*3,T111*3,Q111>T111*3,">"&T111*3)} -> Closed | T111: {=_xlfn.IFS(M111="Level 1",7,M111="Level 2",14,M111="Level 3","30",M111="Info","Info",M111="Closed","Closed")} -> Closed | U111: Dibalas surat ABJ26 0581
A112: 111 | B112: e-76093/PP.01.02 | C112: 46106 | D112: 46092 | E112: PAM JAYA | F112: Teguran atas Pengawasan Aspek Keselamatan dan Kesehatan Kerja (K3) pada Proyek Bundling | G112: PAM JAYA menilai pengawasan K3 oleh KPI belum optimal dan meminta KPI memperketat pengawasan serta memastikan kepatuhan K3 pada seluruh proyek bundling. | H112: Project | I112: Greenfield | J112: HSE | L112: Open | M112: Level 1 | N112: HSE | O112: Irsan | P112: =DATEDIF(C112,$W$1,"Y")&" tahun, "&DATEDIF(C112,$W$1,"YM")&" bulan, "&DATEDIF(C112,$W$1,"MD")&" hari" -> 0 tahun, 3 bulan, 20 hari | Q112: =DATEDIF(C112,Summary!$A$1,"d") -> 112 | R112: < 68 | S112: {=_xlfn.IFS(Q112<=T112,T112,Q112<=T112*2,T112*2,Q112<=T112*3,T112*3,Q112>T112*3,">"&T112*3)} -> >21 | T112: {=_xlfn.IFS(M112="Level 1",7,M112="Level 2",14,M112="Level 3","30",M112="Info","Info",M112="Closed","Closed")} -> 7
A113: 112 | B113: E-76094/PP.03.05 | C113: 46106 | D113: 46092 | E113: PAM JAYA | F113: Penyampaian Hasil Inspeksi Perawatan Peralatan di IPA Pejompongan 1 dan 2 Periode Bulan Februari 2026 | G113: temuan hasil inspeksi peralatan IPA Pejompongan 1 dan 2 (13 temuan) ABJ diminta menyampaikan rencana perbaikan dalam 14 hari kalender | H113: Produksi | I113: PJP 1 & 2 | J113: HSE | L113: Closed | M113: Closed | N113: Produksi | O113: Wahdi Putra/Ahmad Fandhi | P113: =DATEDIF(C113,$W$1,"Y")&" tahun, "&DATEDIF(C113,$W$1,"YM")&" bulan, "&DATEDIF(C113,$W$1,"MD")&" hari" -> 0 tahun, 3 bulan, 20 hari | Q113: =DATEDIF(C113,Summary!$A$1,"d") -> 112 | R113: < 69 | S113: {=_xlfn.IFS(Q113<=T113,T113,Q113<=T113*2,T113*2,Q113<=T113*3,T113*3,Q113>T113*3,">"&T113*3)} -> Closed | T113: {=_xlfn.IFS(M113="Level 1",7,M113="Level 2",14,M113="Level 3","30",M113="Info","Info",M113="Closed","Closed")} -> Closed | U113: Dibalas surat ABJ26 0577
A114: 113 | B114: e-76170/PD.03.08 | C114: 46106 | D114: 46094 | E114: PAM JAYA | F114: Pemberitahuan atas akan Berakhirnya Jaminan Pelaksanaan Tahap II | G114: PAM JAYA mengingatkan beberapa Jaminan Pelaksanaan PT ABJ segera berakhir, meminta perpanjangan dan penyerahan dokumen asli Bank Garansi, serta penyediaan Jaminan Pelaksanaan Tahap II Tahun 2026 sesuai ketentuan perjanjian. | H114: Project | I114: Project | J114: Administrasi & Dokumentasi Program Greenfield | L114: Closed | M114: Closed | N114: Compliance | O114: A. Levi | P114: =DATEDIF(C114,$W$1,"Y")&" tahun, "&DATEDIF(C114,$W$1,"YM")&" bulan, "&DATEDIF(C114,$W$1,"MD")&" hari" -> 0 tahun, 3 bulan, 20 hari | Q114: =DATEDIF(C114,Summary!$A$1,"d") -> 112 | R114: < 70 | S114: {=_xlfn.IFS(Q114<=T114,T114,Q114<=T114*2,T114*2,Q114<=T114*3,T114*3,Q114>T114*3,">"&T114*3)} -> Closed | T114: {=_xlfn.IFS(M114="Level 1",7,M114="Level 2",14,M114="Level 3","30",M114="Info","Info",M114="Closed","Closed")} -> Closed | U114: Dibalas ABJ/DIR/EKS/06.26/0635
A115: 114 | B115: e-76185/PS.04.06 | C115: 46106 | D115: 46097 | E115: PAM JAYA | F115: Permintaan Pengamanan Pekerjaan Selama Cuti Bersama Hari Raya Idul Fitri 1447H 2026 M | G115: ABJ diminta memperketat penerapan dan pengawasan K3, menyiapkan PIC siaga di lokasi pekerjaan, serta memastikan keamanan pekerjaan dan masyarakat selama periode Idul Fitri 2026. | H115: Project | I115: Project | J115: Koordinasi & Sosialisasi | L115: Info | M115: Info | N115: PGO | O115: Lusian F | P115: =DATEDIF(C115,$W$1,"Y")&" tahun, "&DATEDIF(C115,$W$1,"YM")&" bulan, "&DATEDIF(C115,$W$1,"MD")&" hari" -> 0 tahun, 3 bulan, 20 hari | Q115: =DATEDIF(C115,Summary!$A$1,"d") -> 112 | R115: < 71 | S115: {=_xlfn.IFS(Q115<=T115,T115,Q115<=T115*2,T115*2,Q115<=T115*3,T115*3,Q115>T115*3,">"&T115*3)} -> Info | T115: {=_xlfn.IFS(M115="Level 1",7,M115="Level 2",14,M115="Level 3","30",M115="Info","Info",M115="Closed","Closed")} -> Info
A116: 115 | B116: e-76222/PP.01.02 | C116: 46106 | D116: 46098 | E116: PAM JAYA | F116: Teguran Permintaan Pemenuhan Kewajiban Penyelesaian Paket Pekerjaan Ketiga atau Tanggal Operasi Komersial 5 April 2026 | G116: PAM JAYA menyampaikan progres TOK 5 April 2026, di mana dari 108 program terdapat 18 program batal, 30 selesai, dan 60 masih berjalan, serta meminta PT ABJ memastikan penyelesaian pekerjaan, kelengkapan dokumen, perizinan, dan pembaruan progres sesuai ketentuan. | H116: Project | I116: Greenfield | J116: Konstruksi Program Greenfield | L116: Open | M116: Level 1 | N116: PMO/PGO | O116: Suci/Lusian F | P116: =DATEDIF(C116,$W$1,"Y")&" tahun, "&DATEDIF(C116,$W$1,"YM")&" bulan, "&DATEDIF(C116,$W$1,"MD")&" hari" -> 0 tahun, 3 bulan, 20 hari | Q116: =DATEDIF(C116,Summary!$A$1,"d") -> 112 | R116: < 72 | S116: {=_xlfn.IFS(Q116<=T116,T116,Q116<=T116*2,T116*2,Q116<=T116*3,T116*3,Q116>T116*3,">"&T116*3)} -> >21 | T116: {=_xlfn.IFS(M116="Level 1",7,M116="Level 2",14,M116="Level 3","30",M116="Info","Info",M116="Closed","Closed")} -> 7
A117: 116 | B117: 1186/PS.04.04/EKST/III/2026 | C117: 46106 | D117: 46097 | E117: PAM JAYA | F117: Tanggapan atas Surat ABJ No. ABJ/DIR/EKS/03.26/0216 perihal Permintaan Pembayaran atas Realisasi Kontrak Berbasis Angsuran Tahun 2025 | G117: PAM JAYA belum dapat memproses pembayaran KBA karena menilai PT ABJ belum memenuhi kewajiban investasi dan kelengkapan dokumen administrasi sesuai perjanjian. | H117: Project | I117: Greenfield | J117: Keuangan, Pembayaran, Investasi | L117: Closed | M117: Closed | N117: Compliance | O117: A. Levi | P117: =DATEDIF(C117,$W$1,"Y")&" tahun, "&DATEDIF(C117,$W$1,"YM")&" bulan, "&DATEDIF(C117,$W$1,"MD")&" hari" -> 0 tahun, 3 bulan, 20 hari | Q117: =DATEDIF(C117,Summary!$A$1,"d") -> 112 | R117: < 73 | S117: {=_xlfn.IFS(Q117<=T117,T117,Q117<=T117*2,T117*2,Q117<=T117*3,T117*3,Q117>T117*3,">"&T117*3)} -> Closed | T117: {=_xlfn.IFS(M117="Level 1",7,M117="Level 2",14,M117="Level 3","30",M117="Info","Info",M117="Closed","Closed")} -> Closed
A118: 117 | B118: 224/SCI-KPI/III/2026 | C118: 46107 | D118: 46099 | E118: KPI - Sucofindo | F118: Laporan Analisa Hasil Inspeksi Persiapan Lapangan dan Spot Witness Material Infill PT Pestapora Abadi (Mie Gacoan) SPAM Jatiluhur Hilir. | G118: Inspeksi pada tanggal 9 Maret 2026 oleh KPI dengan kesimpulan hasil secara umum adalah Lulus | H118: Project | I118: Jatiluhur Hilir | J118: Konstruksi Program Greenfield | L118: Info | M118: Info | N118: PMO | O118: Suci | P118: =DATEDIF(C118,$W$1,"Y")&" tahun, "&DATEDIF(C118,$W$1,"YM")&" bulan, "&DATEDIF(C118,$W$1,"MD")&" hari" -> 0 tahun, 3 bulan, 19 hari | Q118: =DATEDIF(C118,Summary!$A$1,"d") -> 111 | R118: < 74 | S118: {=_xlfn.IFS(Q118<=T118,T118,Q118<=T118*2,T118*2,Q118<=T118*3,T118*3,Q118>T118*3,">"&T118*3)} -> Info | T118: {=_xlfn.IFS(M118="Level 1",7,M118="Level 2",14,M118="Level 3","30",M118="Info","Info",M118="Closed","Closed")} -> Info
A119: 118 | B119: e-76210/PP.01.02 | C119: 46107 | D119: 46080 | E119: PAM JAYA | F119: Teguran Penerapan Aspek Keselamatan dan Kesehatan Kerja (K3) pada proyek Buaran Hilir | G119: Teguran berulang ke ABJ atas pelanggaran K3 di proyek Buaran Hilir, seperti penggunaan APD, road barrier, rambu proyek, housekeeping, dan dokumen kerja yang tidak sesuai. | H119: Project | I119: Buaran 3 Hilir | J119: HSE | L119: Open | M119: Level 1 | N119: HSE | O119: Irsan | P119: =DATEDIF(C119,$W$1,"Y")&" tahun, "&DATEDIF(C119,$W$1,"YM")&" bulan, "&DATEDIF(C119,$W$1,"MD")&" hari" -> 0 tahun, 3 bulan, 19 hari | Q119: =DATEDIF(C119,Summary!$A$1,"d") -> 111 | R119: < 75 | S119: {=_xlfn.IFS(Q119<=T119,T119,Q119<=T119*2,T119*2,Q119<=T119*3,T119*3,Q119>T119*3,">"&T119*3)} -> >21 | T119: {=_xlfn.IFS(M119="Level 1",7,M119="Level 2",14,M119="Level 3","30",M119="Info","Info",M119="Closed","Closed")} -> 7
A120: 119 | B120: e-75059/PP.01.05 | C120: 46107 | D120: 46105 | E120: PAM JAYA | F120: Permintaan Penjelasan dan Klarifikasi atas permasalahan pada Proyek SPAM Buaran Hulu di RW 03 Kelurahan Margahayu Kecamatan Bekasi Timur Kota Bekasi | G120: ABJ diminta menyelesaikan permasalahan, perizinan, dan koordinasi proyek SPAM Buaran Hulu serta memastikan kepatuhan terhadap ketentuan yang berlaku. | H120: Project | I120: Buaran 3 Hulu | J120: Perizinan | L120: Open | M120: Level 1 | N120: Permit | O120: Rudy | P120: =DATEDIF(C120,$W$1,"Y")&" tahun, "&DATEDIF(C120,$W$1,"YM")&" bulan, "&DATEDIF(C120,$W$1,"MD")&" hari" -> 0 tahun, 3 bulan, 19 hari | Q120: =DATEDIF(C120,Summary!$A$1,"d") -> 111 | R120: < 76 | S120: {=_xlfn.IFS(Q120<=T120,T120,Q120<=T120*2,T120*2,Q120<=T120*3,T120*3,Q120>T120*3,">"&T120*3)} -> >21 | T120: {=_xlfn.IFS(M120="Level 1",7,M120="Level 2",14,M120="Level 3","30",M120="Info","Info",M120="Closed","Closed")} -> 7
A121: 120 | B121: 1211/PS.04.04/EKST/III/2026 | C121: 46108 | D121: 46098 | E121: PAM JAYA | F121: Teguran Keterlambatan Penyampaian Perbaikan Desain Akhir Pekerjaan Rehabilitas Tahun 2026. | G121: keterlambatan penyampaian perbaikan Desain Akhir Pekerjaan Rehabilitasi 2026 melalui BIM. PAM JAYA meminta PT ABJ segera menyampaikan seluruh perbaikan, memperbarui jadwal pekerjaan, memastikan kesesuaian teknis, dan mematuhi ketentuan perjanjian bundling. | H121: Project | I121: Brownfield | J121: Perencanaan Program Rehabilitasi | L121: Open | M121: Level 1 | N121: Planning | O121: Andriani | P121: =DATEDIF(C121,$W$1,"Y")&" tahun, "&DATEDIF(C121,$W$1,"YM")&" bulan, "&DATEDIF(C121,$W$1,"MD")&" hari" -> 0 tahun, 3 bulan, 18 hari | Q121: =DATEDIF(C121,Summary!$A$1,"d") -> 110 | R121: < 78 | S121: {=_xlfn.IFS(Q121<=T121,T121,Q121<=T121*2,T121*2,Q121<=T121*3,T121*3,Q121>T121*3,">"&T121*3)} -> >21 | T121: {=_xlfn.IFS(M121="Level 1",7,M121="Level 2",14,M121="Level 3","30",M121="Info","Info",M121="Closed","Closed")} -> 7
A122: 121 | B122: e-76341/PP.01.02 | C122: 46111 | D122: 46098 | E122: PAM JAYA | F122: Teguran atas Ketidak-sesuaian Pelaksanaan Pengurugan dan Perbaikan Bekas Galian yang Berdampak pada Gangguan Lalu Lintas, Keterlambatan Penyelesaian Proyek, serta Kewajiban Penggantian Kompensasi Pohon Terdampak Pekerjaan Pemasangan Pipa pada Program Infill SPAM Buaran III | G122: PT ABJ dinilai belum optimal dalam pelaksanaan pekerjaan, mitigasi lalu lintas, K3, dan perizinan. PAM JAYA menegur dan meminta PT ABJ untuk segera menindaklanjuti perbaikan 98 temuan, mengganti pohon terdampak, mempercepat penyelesaian proyek, meningkatkan keselamatan kerja | H122: Project | I122: Buaran 3 Hilir | J122: Konstruksi Program Greenfield | L122: Open | M122: Level 1 | N122: PMO/Permit | O122: Rudy | P122: =DATEDIF(C122,$W$1,"Y")&" tahun, "&DATEDIF(C122,$W$1,"YM")&" bulan, "&DATEDIF(C122,$W$1,"MD")&" hari" -> 0 tahun, 3 bulan, 15 hari | Q122: =DATEDIF(C122,Summary!$A$1,"d") -> 107 | R122: < 79 | S122: {=_xlfn.IFS(Q122<=T122,T122,Q122<=T122*2,T122*2,Q122<=T122*3,T122*3,Q122>T122*3,">"&T122*3)} -> >21 | T122: {=_xlfn.IFS(M122="Level 1",7,M122="Level 2",14,M122="Level 3","30",M122="Info","Info",M122="Closed","Closed")} -> 7
A123: 122 | B123: 1162/PS.04.01/EKST/III/2026 | C123: 46111 | D123: 46094 | E123: PAM JAYA | F123: Pembangunan Jaringan Pipa Pendukung Sistem DC Semanan SPAM Karian Serpong Hilir di Jakarta | G123: ABJ diminta menyampaikan usulan modifikasi program konstruksi pesanggrahan hilir | H123: Project | I123: Karian Serpong Hilir | J123: Konstruksi Program Greenfield | L123: Closed | M123: Closed | N123: PMO Infill | O123: Ervin Y | P123: =DATEDIF(C123,$W$1,"Y")&" tahun, "&DATEDIF(C123,$W$1,"YM")&" bulan, "&DATEDIF(C123,$W$1,"MD")&" hari" -> 0 tahun, 3 bulan, 15 hari | Q123: =DATEDIF(C123,Summary!$A$1,"d") -> 107 | R123: < 80 | S123: {=_xlfn.IFS(Q123<=T123,T123,Q123<=T123*2,T123*2,Q123<=T123*3,T123*3,Q123>T123*3,">"&T123*3)} -> Closed | T123: {=_xlfn.IFS(M123="Level 1",7,M123="Level 2",14,M123="Level 3","30",M123="Info","Info",M123="Closed","Closed")} -> Closed
A124: 123 | B124: e-76340/PS.04.06 | C124: 46112 | D124: 46098 | E124: PAM JAYA | F124: Permintaan Program Kepastian Kualitas terkait Kualitas Pekerjaan pada Proyek Bundling | G124: ABJ diminta menyampaikan dan menjalankan program kepastian kualitas (SOP, ITP, checklist) untuk seluruh tahap proyek, serta memastikan pekerjaan sesuai standar dan mematuhi perjanjian dengan PAM JAYA. | H124: Project | I124: Project | J124: Administrasi & Dokumentasi | L124: Open | M124: Level 1 | N124: Compliance; PGO; QMS | O124: A. Levi; Lusian F; Sri H | P124: =DATEDIF(C124,$W$1,"Y")&" tahun, "&DATEDIF(C124,$W$1,"YM")&" bulan, "&DATEDIF(C124,$W$1,"MD")&" hari" -> 0 tahun, 3 bulan, 14 hari | Q124: =DATEDIF(C124,Summary!$A$1,"d") -> 106 | R124: < 81 | S124: {=_xlfn.IFS(Q124<=T124,T124,Q124<=T124*2,T124*2,Q124<=T124*3,T124*3,Q124>T124*3,">"&T124*3)} -> >21 | T124: {=_xlfn.IFS(M124="Level 1",7,M124="Level 2",14,M124="Level 3","30",M124="Info","Info",M124="Closed","Closed")} -> 7
A125: 124 | B125: 226/SCI-KPI/III/2026 | C125: 46112 | D125: 46112 | E125: KPI - Sucofindo | F125: Surat Pengantar Laporan Bulanan Proyek Bundling SPAM DKI Jakarta – Konsultan Pengawas Independen Periode Februari 2026 | G125: Laporan Bulanan Periode Februari 2026 | H125: Project | I125: Project | J125: Monitoring & Pelaporan | L125: Info | M125: Info | N125: Compliance | O125: A. Levi | P125: =DATEDIF(C125,$W$1,"Y")&" tahun, "&DATEDIF(C125,$W$1,"YM")&" bulan, "&DATEDIF(C125,$W$1,"MD")&" hari" -> 0 tahun, 3 bulan, 14 hari | Q125: =DATEDIF(C125,Summary!$A$1,"d") -> 106 | R125: < 82 | S125: {=_xlfn.IFS(Q125<=T125,T125,Q125<=T125*2,T125*2,Q125<=T125*3,T125*3,Q125>T125*3,">"&T125*3)} -> Info | T125: {=_xlfn.IFS(M125="Level 1",7,M125="Level 2",14,M125="Level 3","30",M125="Info","Info",M125="Closed","Closed")} -> Info
...

Sheet Outgoing 2025
A1: No | B1: Nomor Surat | C1: Tanggal Surat | D1: Penerima | E1: Perihal | F1: Deskripsi | G1: Produksi/Project | H1: Lokasi | I1: Kategori | J1: Due Date | K1: Status | L1: DIC | M1: PIC | N1: Durasi | O1: Durasi (Hari) | P1: Attachment | Q1: Keterangan
A2: 1 | B2: ABJ/DIR/EKS/01.25/0003 | C2: 45663 | D2: PAM JAYA | E2: Tagihan Air Curah Periode Desember 2024 | G2: Corporate | H2: Corporate | I2: Tagihan | K2: Info | L2: Compliance | M2: Indradi | N2: =DATEDIF(C2,'Outgoing 2023'!$L$2,"Y")&" tahun, "&DATEDIF(C2,'Outgoing 2023'!$L$2,"YM")&" bulan, "&DATEDIF(C2,'Outgoing 2023'!$L$2,"MD")&" hari" -> 1 tahun, 6 bulan, 9 hari | O2: =TODAY()-C2 -> 555 | S2: {=_xlfn.UNIQUE(I2:I1159)} -> Tagihan | T2: =COUNTIF($I$2:$I$1159,S2) -> 26
A3: 2 | B3: ABJ/DIR/EKS/01.25/0004 | C3: 45663 | D3: PAM JAYA | E3: Pengiriman Ke-3 Tanggapan Atas Hasil Review PAM dan KPI Terhadap Dokumen Desain Akhir Program Rehabilitasi Tahun 2025 | G3: Project | H3: Cyclical | I3: DED/RAB | K3: Info | L3: PMO | M3: Aan Hendra | N3: =DATEDIF(C3,'Outgoing 2023'!$L$2,"Y")&" tahun, "&DATEDIF(C3,'Outgoing 2023'!$L$2,"YM")&" bulan, "&DATEDIF(C3,'Outgoing 2023'!$L$2,"MD")&" hari" -> 1 tahun, 6 bulan, 9 hari | O3: =TODAY()-C3 -> 555 | S3: DED/RAB | T3: =COUNTIF($I$2:$I$1159,S3) -> 146
A4: 3 | B4: ABJ/DIR/EKS/01.25/0005 | C4: 45663 | D4: PAM JAYA | E4: Laporan Bulanan Kualitas Air Baku dan Air Curah Periode Desember 2024 | G4: Produksi | H4: ALL WTP | I4: Laporan Periodik | K4: Info | L4: WQA | M4: Novi | N4: =DATEDIF(C4,'Outgoing 2023'!$L$2,"Y")&" tahun, "&DATEDIF(C4,'Outgoing 2023'!$L$2,"YM")&" bulan, "&DATEDIF(C4,'Outgoing 2023'!$L$2,"MD")&" hari" -> 1 tahun, 6 bulan, 9 hari | O4: =TODAY()-C4 -> 555 | S4: Laporan Periodik | T4: =COUNTIF($I$2:$I$1159,S4) -> 48
A5: 4 | B5: ABJ/DIR/EKS/01.25/0006 | C5: 45663 | D5: PAM JAYA | E5: Pengiriman Risalah Rapat Pre Construction Meeting SPAM Buaran 3 Hilir, PC162 EZ 02 Jl. Manunggal 1A, PC163 EZ05 Jl. IntisariRaya dan PC159 EZ 01 Jl. Dato Tonggara | G5: Project | H5: Buaran 3 Hilir | I5: MoM | K5: Info | L5: PMO | M5: Puji R | N5: =DATEDIF(C5,'Outgoing 2023'!$L$2,"Y")&" tahun, "&DATEDIF(C5,'Outgoing 2023'!$L$2,"YM")&" bulan, "&DATEDIF(C5,'Outgoing 2023'!$L$2,"MD")&" hari" -> 1 tahun, 6 bulan, 9 hari | O5: =TODAY()-C5 -> 555 | S5: MoM | T5: =COUNTIF($I$2:$I$1159,S5) -> 16
A6: 5 | B6: ABJ/DIR/EKS/01.25/0007 | C6: 45663 | D6: Bank BTPN | E6: Pencairan Deposito | G6: Corporate | H6: Corporate | I6: Finance | K6: Info | L6: Finance | M6: Wahyu Tjahyadi | N6: =DATEDIF(C6,'Outgoing 2023'!$L$2,"Y")&" tahun, "&DATEDIF(C6,'Outgoing 2023'!$L$2,"YM")&" bulan, "&DATEDIF(C6,'Outgoing 2023'!$L$2,"MD")&" hari" -> 1 tahun, 6 bulan, 9 hari | O6: =TODAY()-C6 -> 555 | S6: Finance | T6: =COUNTIF($I$2:$I$1159,S6) -> 39
A7: 6 | B7: ABJ/DIR/EKS/01.25/0008 | C7: 45663 | D7: Kepala Dinas Perhubungan Kota Bekasi | E7: Permohonan Rekayasa Lalu Lintas terkait Proyek SPAM Buaran 3 Hulu | G7: Project | H7: Buaran 3 Hulu | I7: Jadwal Pekerjaan | K7: Info | L7: Permit | M7: Rais A | N7: =DATEDIF(C7,'Outgoing 2023'!$L$2,"Y")&" tahun, "&DATEDIF(C7,'Outgoing 2023'!$L$2,"YM")&" bulan, "&DATEDIF(C7,'Outgoing 2023'!$L$2,"MD")&" hari" -> 1 tahun, 6 bulan, 9 hari | O7: =TODAY()-C7 -> 555 | S7: Jadwal Pekerjaan | T7: =COUNTIF($I$2:$I$1159,S7) -> 45
A8: 7 | B8: ABJ/DIR/EKS/01.25/0009 | C8: 45664 | D8: Perum Jasa Tirta II - General Manajer Unit Wilayah I | E8: Permohonan Rekayasa Lalu Lintas terkait Proyek SPAM Buaran 3 Hulu | G8: Produksi | H8: Corporate | I8: Permohonan | K8: Info | L8: Permit | M8: Rais A | N8: =DATEDIF(C8,'Outgoing 2023'!$L$2,"Y")&" tahun, "&DATEDIF(C8,'Outgoing 2023'!$L$2,"YM")&" bulan, "&DATEDIF(C8,'Outgoing 2023'!$L$2,"MD")&" hari" -> 1 tahun, 6 bulan, 8 hari | O8: =TODAY()-C8 -> 554 | S8: Permohonan | T8: =COUNTIF($I$2:$I$1159,S8) -> 11
A9: 8 | B9: ABJ/DIR/EKS/01.25/0010 | C9: 45665 | D9: PAM JAYA | E9: Pengiriman Ke-4 Tanggapan Atas Hasil Review PAM dan KPI Terhadap Dokumen Desain Akhir Program Rehabilitasi Tahun 2025 | G9: Project | H9: Cyclical | I9: DED/RAB | K9: Info | L9: PMO | M9: Aan Hendra | N9: =DATEDIF(C9,'Outgoing 2023'!$L$2,"Y")&" tahun, "&DATEDIF(C9,'Outgoing 2023'!$L$2,"YM")&" bulan, "&DATEDIF(C9,'Outgoing 2023'!$L$2,"MD")&" hari" -> 1 tahun, 6 bulan, 7 hari | O9: =TODAY()-C9 -> 553 | S9: Asuransi | T9: =COUNTIF($I$2:$I$1159,S9) -> 2
A10: 9 | B10: ABJ/DIR/EKS/01.25/0011 | C10: 45665 | D10: PAM JAYA | E10: Permohonan Pembelian Sparepart Standby Untuk Operasional IPA Pejompongan 2 | G10: Project | H10: Cyclical | I10: Permohonan | K10: Info | L10: PMO | M10: Johnson | N10: =DATEDIF(C10,'Outgoing 2023'!$L$2,"Y")&" tahun, "&DATEDIF(C10,'Outgoing 2023'!$L$2,"YM")&" bulan, "&DATEDIF(C10,'Outgoing 2023'!$L$2,"MD")&" hari" -> 1 tahun, 6 bulan, 7 hari | O10: =TODAY()-C10 -> 553 | S10: Komisioning/Pengoperasian | T10: =COUNTIF($I$2:$I$1159,S10) -> 229
A11: 10 | B11: ABJ/DIR/EKS/01.25/0012 | C11: 45665 | D11: Bank OCBC NISP | E11: Penyampaian Salinan Asli Polis Asuransi | G11: Corporate | H11: Corporate | I11: Asuransi | K11: Info | L11: Finance | M11: Wahyu Tjahyadi | N11: =DATEDIF(C11,'Outgoing 2023'!$L$2,"Y")&" tahun, "&DATEDIF(C11,'Outgoing 2023'!$L$2,"YM")&" bulan, "&DATEDIF(C11,'Outgoing 2023'!$L$2,"MD")&" hari" -> 1 tahun, 6 bulan, 7 hari | O11: =TODAY()-C11 -> 553 | S11: HSE | T11: =COUNTIF($I$2:$I$1159,S11) -> 27
A12: 11 | B12: ABJ/DIR/EKS/01.25/0013 | C12: 45666 | D12: PAM JAYA | E12: Pemberitahuan Uji Komisioning SPAM Jatiluhur Hilir – Infill C03 Kebon Kosong | G12: Project | H12: Jatiluhur Hilir | I12: Komisioning/Pengoperasian | K12: Info | L12: PMO | M12: Juny Jety | N12: =DATEDIF(C12,'Outgoing 2023'!$L$2,"Y")&" tahun, "&DATEDIF(C12,'Outgoing 2023'!$L$2,"YM")&" bulan, "&DATEDIF(C12,'Outgoing 2023'!$L$2,"MD")&" hari" -> 1 tahun, 6 bulan, 6 hari | O12: =TODAY()-C12 -> 552 | S12: Manajemen Risiko | T12: =COUNTIF($I$2:$I$1159,S12) -> 9
A13: 12 | B13: ABJ/DIR/EKS/01.25/0014 | C13: 45666 | D13: PAM JAYA | E13: Laporan Bulanan Kuantitas Air Baku dan Air Curah Periode Desember 2024 | G13: Produksi | H13: ALL WTP | I13: Laporan Periodik | K13: Info | L13: Compliance | M13: Indradi | N13: =DATEDIF(C13,'Outgoing 2023'!$L$2,"Y")&" tahun, "&DATEDIF(C13,'Outgoing 2023'!$L$2,"YM")&" bulan, "&DATEDIF(C13,'Outgoing 2023'!$L$2,"MD")&" hari" -> 1 tahun, 6 bulan, 6 hari | O13: =TODAY()-C13 -> 552 | S13: Sambungan Rumah/Sambungan Baru | T13: =COUNTIF($I$2:$I$1159,S13) -> 22
A14: 13 | B14: ABJ/DIR/EKS/01.25/0015 | C14: 45666 | D14: PAM JAYA | E14: Tanggapan atas Surat PAM JAYA No. e-31298/KM.02.25 tentang Penyampaian Hasil Inspeksi Aset dan Peralatan di IPA Buaran Bulan Oktober 2024 | G14: Project | H14: Buaran 1 & 2 | I14: HSE | K14: Info | L14: HSE | M14: Irsan | N14: =DATEDIF(C14,'Outgoing 2023'!$L$2,"Y")&" tahun, "&DATEDIF(C14,'Outgoing 2023'!$L$2,"YM")&" bulan, "&DATEDIF(C14,'Outgoing 2023'!$L$2,"MD")&" hari" -> 1 tahun, 6 bulan, 6 hari | O14: =TODAY()-C14 -> 552 | S14: Pemberitahuan | T14: =COUNTIF($I$2:$I$1159,S14) -> 147
... A33: 32 | B33: ABJ/DIR/EKS/01.25/0034 | C33: 45677 | D33: PAM JAYA | E33: Tanggapan Permohonan Penyusunan Desain Akhir Infill Sambungan Baru Jl. Timor | G33: Project | H33: Greenfield | I33: DED/RAB | K33: Info | L33: Planning | M33: Aji S | N33: =DATEDIF(C33,'Outgoing 2023'!$L$2,"Y")&" tahun, "&DATEDIF(C33,'Outgoing 2023'!$L$2,"YM")&" bulan, "&DATEDIF(C33,'Outgoing 2023'!$L$2,"MD")&" hari" -> 1 tahun, 5 bulan, 25 hari | O33: =TODAY()-C33 -> 541 | S33: DPPP | T33: =COUNTIF($I$2:$I$1159,S33) -> 2
A34: 33 | B34: ABJ/DIR/EKS/01.25/0035 | C34: 45677 | D34: PAM JAYA | E34: Pengiriman Risalah Rapat Pre Construction Meeting Program Rehabilitasi Periode 6 – 12 Januari 2025 | G34: Project | H34: Cyclical | I34: MoM | K34: Info | L34: PMO | M34: Project Manager | N34: =DATEDIF(C34,'Outgoing 2023'!$L$2,"Y")&" tahun, "&DATEDIF(C34,'Outgoing 2023'!$L$2,"YM")&" bulan, "&DATEDIF(C34,'Outgoing 2023'!$L$2,"MD")&" hari" -> 1 tahun, 5 bulan, 25 hari | O34: =TODAY()-C34 -> 541 | S34: 0 | T34: =COUNTIF($I$2:$I$1159,S34) -> 0
A35: 34 | B35: ABJ/DIR/EKS/01.25/0036 | C35: 45678 | D35: PAM JAYA | E35: Penyampaian DED dan RAB Perluasan Jaringan Untuk Sambungan Baru Proyek SPAM Jatiluhur Hilir dan Buaran 3 Hilir | G35: Project | H35: Greenfield | I35: DED/RAB | K35: Info | L35: Planning | M35: Aji S | N35: =DATEDIF(C35,'Outgoing 2023'!$L$2,"Y")&" tahun, "&DATEDIF(C35,'Outgoing 2023'!$L$2,"YM")&" bulan, "&DATEDIF(C35,'Outgoing 2023'!$L$2,"MD")&" hari" -> 1 tahun, 5 bulan, 24 hari | O35: =TODAY()-C35 -> 540 | S35: Kendala Proyek | T35: =COUNTIF($I$2:$I$1159,S35) -> 32
A36: 35 | B36: ABJ/DIR/EKS/01.25/0037 | C36: 45678 | D36: Bapak Rasikin - Lurah Kelurahan Pondok Kelapa | E36: Permohonan Bantuan Fasilitasi untuk Kegiatan Sosialisasi Pekerjaan Pemasangan Pipa di Area Kompleks Kavling Marinir, Kelurahan Pondok Kelapa, Kecamatan Duren Sawit, Jakarta Timur | G36: Corporate | H36: Corporate | I36: Permohonan | K36: Info | L36: Corcom | M36: Valent | N36: =DATEDIF(C36,'Outgoing 2023'!$L$2,"Y")&" tahun, "&DATEDIF(C36,'Outgoing 2023'!$L$2,"YM")&" bulan, "&DATEDIF(C36,'Outgoing 2023'!$L$2,"MD")&" hari" -> 1 tahun, 5 bulan, 24 hari | O36: =TODAY()-C36 -> 540 | S36: Produksi | T36: =COUNTIF($I$2:$I$1159,S36) -> 2
A37: 36 | B37: ABJ/DIR/EKS/01.25/0038 | C37: 45678 | D37: PAM JAYA | E37: Usulan Kepada PAM JAYA Terkait Pencapaian Target Sambungan Baru | G37: Project | H37: Greenfield | I37: Sambungan Rumah/Sambungan Baru | K37: Info | L37: PMO NC | M37: A. Levi | N37: =DATEDIF(C37,'Outgoing 2023'!$L$2,"Y")&" tahun, "&DATEDIF(C37,'Outgoing 2023'!$L$2,"YM")&" bulan, "&DATEDIF(C37,'Outgoing 2023'!$L$2,"MD")&" hari" -> 1 tahun, 5 bulan, 24 hari | O37: =TODAY()-C37 -> 540 | S37: DPPK | T37: =COUNTIF($I$2:$I$1159,S37) -> 23
A38: 37 | B38: ABJ/DIR/EKS/01.25/0039 | C38: 45679 | D38: PAM JAYA | E38: Shop Drawing Proyek SPAM Jatiluhur Hilir Panel PLC MC CDC | G38: Project | H38: Jatiluhur Hilir | I38: Shop Drawing | K38: Info | L38: PMO | M38: Juny Jety | N38: =DATEDIF(C38,'Outgoing 2023'!$L$2,"Y")&" tahun, "&DATEDIF(C38,'Outgoing 2023'!$L$2,"YM")&" bulan, "&DATEDIF(C38,'Outgoing 2023'!$L$2,"MD")&" hari" -> 1 tahun, 5 bulan, 23 hari | O38: =TODAY()-C38 -> 539 | S38: Inspeksi | T38: =COUNTIF($I$2:$I$1159,S38) -> 10
A39: 38 | B39: ABJ/DIR/SCM/01.25/0040 | C39: 45680 | D39: PT. Karsa Buana Lestari | E39: Kontrak Uji Air Limbah periode 23 Januari 2025- 31 Desember 2026 (2 tahun) | G39: Corporate | H39: Corporate | I39: SCM | K39: Info | L39: SCM | M39: Wahyu S | N39: =DATEDIF(C39,'Outgoing 2023'!$L$2,"Y")&" tahun, "&DATEDIF(C39,'Outgoing 2023'!$L$2,"YM")&" bulan, "&DATEDIF(C39,'Outgoing 2023'!$L$2,"MD")&" hari" -> 1 tahun, 5 bulan, 22 hari | O39: =TODAY()-C39 -> 538 | S39: PKS | T39: =COUNTIF($I$2:$I$1159,S39) -> 7
A40: 39 | B40: ABJ/DIR/EKS/01.25/0041 | C40: 45681 | D40: PAM JAYA | E40: Tanggapan atas Surat PAM JAYA No. e-37092/PP.03.02 Tanggal 16 Desember 2024 | G40: Project | H40: Project | I40: HSE | K40: Info | L40: HSE | M40: Irsan | N40: =DATEDIF(C40,'Outgoing 2023'!$L$2,"Y")&" tahun, "&DATEDIF(C40,'Outgoing 2023'!$L$2,"YM")&" bulan, "&DATEDIF(C40,'Outgoing 2023'!$L$2,"MD")&" hari" -> 1 tahun, 5 bulan, 21 hari | O40: =TODAY()-C40 -> 537 | S40: Berita Acara | T40: =COUNTIF($I$2:$I$1159,S40) -> 2
A41: 40 | B41: ABJ/DIR/EKS/01.25/0042 | C41: 45681 | D41: PAM JAYA | E41: Tanggapan Permohonan Penyusunan Desain Akhir Infill Sambungan Baru Jl. Kalisari (Pak Endriartono) | G41: Project | H41: Greenfield | I41: DED/RAB | K41: Info | L41: Planning | M41: Aji S | N41: =DATEDIF(C41,'Outgoing 2023'!$L$2,"Y")&" tahun, "&DATEDIF(C41,'Outgoing 2023'!$L$2,"YM")&" bulan, "&DATEDIF(C41,'Outgoing 2023'!$L$2,"MD")&" hari" -> 1 tahun, 5 bulan, 21 hari | O41: =TODAY()-C41 -> 537 | S41: Polis Asuransi | T41: =COUNTIF($I$2:$I$1159,S41) -> 2
A42: 41 | B42: ABJ/DIR/EKS/01.25/0043 | C42: 45681 | D42: PAM JAYA | E42: Shop Drawing Proyek SPAM Jatiluhur Hilir Bulk Water Delivering 4000 Lps – A2.2 Pondok Kopi – By Pass | G42: Project | H42: Jatiluhur Hilir | I42: Shop Drawing | K42: Info | L42: PMO | M42: Juny Jety | N42: =DATEDIF(C42,'Outgoing 2023'!$L$2,"Y")&" tahun, "&DATEDIF(C42,'Outgoing 2023'!$L$2,"YM")&" bulan, "&DATEDIF(C42,'Outgoing 2023'!$L$2,"MD")&" hari" -> 1 tahun, 5 bulan, 21 hari | O42: =TODAY()-C42 -> 537 | S42: Perawatan | T42: =COUNTIF($I$2:$I$1159,S42) -> 15
A43: 42 | B43: ABJ/DIR/EKS/01.25/0044 | C43: 45681 | D43: PAM JAYA | E43: Shop Drawing & Justifikasi Proyek SPAM Jatiluhur Hilir Jalur A2 Phase 1b (Hot Tapping) | G43: Project | H43: Jatiluhur Hilir | I43: Shop Drawing | K43: Open | L43: PMO | M43: Juny Jety | N43: =DATEDIF(C43,'Outgoing 2023'!$L$2,"Y")&" tahun, "&DATEDIF(C43,'Outgoing 2023'!$L$2,"YM")&" bulan, "&DATEDIF(C43,'Outgoing 2023'!$L$2,"MD")&" hari" -> 1 tahun, 5 bulan, 21 hari | O43: =TODAY()-C43 -> 537 | S43: Proposal Modifikasi | T43: =COUNTIF($I$2:$I$1159,S43) -> 2
A44: 43 | B44: ABJ/DIR/EKS/01.25/0045 | C44: 45681 | D44: PAM JAYA | E44: Penyampaian Dokumen Polis Asuransi | G44: Corporate | H44: Corporate | I44: Finance | K44: Info | L44: Finance | M44: Wahyu Tjahyadi | N44: =DATEDIF(C44,'Outgoing 2023'!$L$2,"Y")&" tahun, "&DATEDIF(C44,'Outgoing 2023'!$L$2,"YM")&" bulan, "&DATEDIF(C44,'Outgoing 2023'!$L$2,"MD")&" hari" -> 1 tahun, 5 bulan, 21 hari | O44: =TODAY()-C44 -> 537 | S44: Sosialisasi | T44: =COUNTIF($I$2:$I$1159,S44) -> 15
A45: 44 | B45: ABJ/DIR/EKS/01.25/0046 | C45: 45681 | D45: PAM JAYA | E45: Tanggapan Surat PAM Jaya No 10447/KM.01.11/EKST/XII/2024 terkait Tanggapan surat ABJ No ABJ/DIR/EKS/10.24/0858 | G45: Produksi | H45: PJP 2 | I45: Denda | K45: Open | L45: Produksi | M45: Ahmad Fandhi | N45: =DATEDIF(C45,'Outgoing 2023'!$L$2,"Y")&" tahun, "&DATEDIF(C45,'Outgoing 2023'!$L$2,"YM")&" bulan, "&DATEDIF(C45,'Outgoing 2023'!$L$2,"MD")&" hari" -> 1 tahun, 5 bulan, 21 hari | O45: =TODAY()-C45 -> 537 | S45: Proposal Substitusi | T45: =COUNTIF($I$2:$I$1159,S45) -> 1
A46: 45 | B46: ABJ/DIR/EKS/01.25/0047 | C46: 45684 | D46: PAM JAYA | E46: Pemberitahuan Uji Komisioning SPAM Jatiluhur Hilir – Infill Adhoc PC 86 EZ 01, Infill Adhoc PC 80 EZ 03, Infill Adhoc PC 70 EZ 09, Infill Adhoc PC 055 EZ 13 | G46: Project | H46: Jatiluhur Hilir | I46: Komisioning/Pengoperasian | K46: Info | L46: PMO | M46: Muhrojin | N46: =DATEDIF(C46,'Outgoing 2023'!$L$2,"Y")&" tahun, "&DATEDIF(C46,'Outgoing 2023'!$L$2,"YM")&" bulan, "&DATEDIF(C46,'Outgoing 2023'!$L$2,"MD")&" hari" -> 1 tahun, 5 bulan, 18 hari | O46: =TODAY()-C46 -> 534 | S46: COE | T46: =COUNTIF($I$2:$I$1159,S46) -> 8
... A51: 50 | B51: ABJ/DIR/EKS/01.25/0052 | C51: 45687 | D51: PAM JAYA | E51: Tanggapan Atas Surat PAM JAYA No.e-39800/PM.01.02 Tanggal 23 Januari 2025 | G51: Corporate | H51: Corporate | I51: Pemberitahuan | K51: Info | L51: Planning | M51: Aji S | N51: =DATEDIF(C51,'Outgoing 2023'!$L$2,"Y")&" tahun, "&DATEDIF(C51,'Outgoing 2023'!$L$2,"YM")&" bulan, "&DATEDIF(C51,'Outgoing 2023'!$L$2,"MD")&" hari" -> 1 tahun, 5 bulan, 15 hari | O51: =TODAY()-C51 -> 531 | S51: Transfer Knowledge | T51: =COUNTIF($I$2:$I$1159,S51) -> 2
A52: 51 | B52: ABJ/DIR/EKS/01.25/0053 | C52: 45687 | D52: PAM JAYA | E52: Tanggapan atas surat PAM Jaya No e.39066/PM.01.00 | F52: perubahan schedule line B dan line F | G52: Project | H52: Buaran 3 Hulu | I52: Jadwal Pekerjaan | K52: Info | L52: PMO | M52: Danny L | N52: =DATEDIF(C52,'Outgoing 2023'!$L$2,"Y")&" tahun, "&DATEDIF(C52,'Outgoing 2023'!$L$2,"YM")&" bulan, "&DATEDIF(C52,'Outgoing 2023'!$L$2,"MD")&" hari" -> 1 tahun, 5 bulan, 15 hari | O52: =TODAY()-C52 -> 531 | S52: Ekuitas | T52: =COUNTIF($I$2:$I$1159,S52) -> 1
A53: 52 | B53: ABJ/DIR/EKS/01.25/0054 | C53: 45688 | D53: PAM JAYA | E53: RAB Untuk Konsultan DED Reservoir IPA Pejompongan 2 dan Fasilitas terkait | G53: Project | H53: Brownfield | I53: DED/RAB | K53: Open | L53: Planning | M53: Aji S | N53: =DATEDIF(C53,'Outgoing 2023'!$L$2,"Y")&" tahun, "&DATEDIF(C53,'Outgoing 2023'!$L$2,"YM")&" bulan, "&DATEDIF(C53,'Outgoing 2023'!$L$2,"MD")&" hari" -> 1 tahun, 5 bulan, 14 hari | O53: =TODAY()-C53 -> 530 | S53: KBA | T53: =COUNTIF($I$2:$I$1159,S53) -> 2
A54: 53 | B54: ABJ/DIR/EKS/01.25/0055 | C54: 45688 | D54: PAM JAYA | E54: Penyampaian Dokumen SOP IPA Buaran 3 dan Revisi SOP IPA Buaran 1&2, IPA Pejompongan 1&2 dan IPA Pulogadung | G54: Produksi | H54: Produksi | I54: SOP | K54: Info | L54: Produksi | M54: Rika I | N54: =DATEDIF(C54,'Outgoing 2023'!$L$2,"Y")&" tahun, "&DATEDIF(C54,'Outgoing 2023'!$L$2,"YM")&" bulan, "&DATEDIF(C54,'Outgoing 2023'!$L$2,"MD")&" hari" -> 1 tahun, 5 bulan, 14 hari | O54: =TODAY()-C54 -> 530 | T54: =COUNTIF($I$2:$I$1159,S54) -> 0
A55: 54 | B55: ABJ/DIR/EKS/01.25/0056 | C55: 45688 | D55: PAM JAYA | E55: DED dan RAB Perluasan Jaringan Untuk Sambungan Baru Master Meter Syamsudin | G55: Project | H55: Greenfield | I55: DED/RAB | K55: Info | L55: Planning | M55: Aji S | N55: =DATEDIF(C55,'Outgoing 2023'!$L$2,"Y")&" tahun, "&DATEDIF(C55,'Outgoing 2023'!$L$2,"YM")&" bulan, "&DATEDIF(C55,'Outgoing 2023'!$L$2,"MD")&" hari" -> 1 tahun, 5 bulan, 14 hari | O55: =TODAY()-C55 -> 530
A56: 55 | B56: ABJ/DIR/EKS/01.25/0057 | C56: 45688 | D56: PAM JAYA | E56: Permohonan Bantuan Terkait Pengajuan Surat Permohonan Relokasi Utilitas Kepada DBM | G56: Project | H56: Jatiluhur Hilir | I56: Permohonan | K56: Open | L56: PMO | M56: Muhrojin | N56: =DATEDIF(C56,'Outgoing 2023'!$L$2,"Y")&" tahun, "&DATEDIF(C56,'Outgoing 2023'!$L$2,"YM")&" bulan, "&DATEDIF(C56,'Outgoing 2023'!$L$2,"MD")&" hari" -> 1 tahun, 5 bulan, 14 hari | O56: =TODAY()-C56 -> 530
A57: 56 | B57: ABJ/DIR/EKS/01.25/0058 | C57: 45688 | D57: PAM JAYA | E57: Pengiriman Ke-6 Tanggapan Atas Hasil Review PAM dan KPI Terhadap Dokumen Desain Akhir Program Rehabilitasi Proyek Brownfield Tahun 2025 | G57: Project | H57: Cyclical | I57: DED/RAB | K57: Info | L57: PMO | M57: Aan Hendra | N57: =DATEDIF(C57,'Outgoing 2023'!$L$2,"Y")&" tahun, "&DATEDIF(C57,'Outgoing 2023'!$L$2,"YM")&" bulan, "&DATEDIF(C57,'Outgoing 2023'!$L$2,"MD")&" hari" -> 1 tahun, 5 bulan, 14 hari | O57: =TODAY()-C57 -> 530
A58: 57 | B58: ABJ/DIR/EKS/01.25/0059 | C58: 45688 | D58: PT. Jakarta Setiabudi, Tbk | E58: Permohonan Pengembalian Security Deposit HO ABJ Setiabudi | G58: Corporate | H58: Corporate | I58: Permohonan | K58: Info | L58: HC | M58: Cucum | N58: =DATEDIF(C58,'Outgoing 2023'!$L$2,"Y")&" tahun, "&DATEDIF(C58,'Outgoing 2023'!$L$2,"YM")&" bulan, "&DATEDIF(C58,'Outgoing 2023'!$L$2,"MD")&" hari" -> 1 tahun, 5 bulan, 14 hari | O58: =TODAY()-C58 -> 530
A59: 58 | B59: ABJ/DIR/EKS/01.25/0060 | C59: 45688 | D59: PAM JAYA | E59: Undangan Pengecekan Hasil Uji Kebocoran (Leak Test) Bangunan Reservoir B | G59: Project | H59: Buaran 3 Hulu | I59: Undangan | K59: Info | L59: PMO | M59: Danny L | N59: =DATEDIF(C59,'Outgoing 2023'!$L$2,"Y")&" tahun, "&DATEDIF(C59,'Outgoing 2023'!$L$2,"YM")&" bulan, "&DATEDIF(C59,'Outgoing 2023'!$L$2,"MD")&" hari" -> 1 tahun, 5 bulan, 14 hari | O59: =TODAY()-C59 -> 530
A60: 59 | B60: ABJ/DIR/EKS/01.25/0061 | C60: 45688 | D60: SIINas | E60: Laporan Triwulan 3 Tahun 2024 | G60: Project | H60: Project | I60: Laporan Periodik | K60: Info | L60: PMO | M60: Johnson | N60: =DATEDIF(C60,'Outgoing 2023'!$L$2,"Y")&" tahun, "&DATEDIF(C60,'Outgoing 2023'!$L$2,"YM")&" bulan, "&DATEDIF(C60,'Outgoing 2023'!$L$2,"MD")&" hari" -> 1 tahun, 5 bulan, 14 hari | O60: =TODAY()-C60 -> 530
A61: 60 | B61: ABJ/DIR/EKS/01.25/0062 | C61: 45688 | D61: SIINas | E61: Laporan Triwulan 4 tahun 2024 | G61: Project | H61: Project | I61: Laporan Periodik | K61: Info | L61: PMO | M61: Johnson | N61: =DATEDIF(C61,'Outgoing 2023'!$L$2,"Y")&" tahun, "&DATEDIF(C61,'Outgoing 2023'!$L$2,"YM")&" bulan, "&DATEDIF(C61,'Outgoing 2023'!$L$2,"MD")&" hari" -> 1 tahun, 5 bulan, 14 hari | O61: =TODAY()-C61 -> 530
A62: 61 | B62: ABJ/DIR/EKS/01.25/0063 | C62: 45691 | D62: PAM JAYA | E62: Penyampaian Bukti Sertifikasi ISO/IEC 17025:2017 | G62: Corporate | H62: Corporate | I62: Sertifikasi | K62: Info | L62: WQA | M62: Novi | N62: =DATEDIF(C62,'Outgoing 2023'!$L$2,"Y")&" tahun, "&DATEDIF(C62,'Outgoing 2023'!$L$2,"YM")&" bulan, "&DATEDIF(C62,'Outgoing 2023'!$L$2,"MD")&" hari" -> 1 tahun, 5 bulan, 12 hari | O62: =TODAY()-C62 -> 527
A63: 62 | B63: ABJ/DIR/EKS/01.25/0064 | C63: 45691 | D63: PAM JAYA | E63: Biaya Persiapan Proyek Greenfield Tahun 2025-2031 (Diluar Proyek SPAM Buaran 3 Hulu) | G63: Project | H63: Greenfield | I63: DED/RAB | K63: Info | L63: Planning | M63: Aji S | N63: =DATEDIF(C63,'Outgoing 2023'!$L$2,"Y")&" tahun, "&DATEDIF(C63,'Outgoing 2023'!$L$2,"YM")&" bulan, "&DATEDIF(C63,'Outgoing 2023'!$L$2,"MD")&" hari" -> 1 tahun, 5 bulan, 12 hari | O63: =TODAY()-C63 -> 527
A64: 63 | B64: ABJ/DIR/EKS/01.25/0065 | C64: 45692 | D64: PAM JAYA | E64: Pembaharuan Desain Akhir Pekerjaan Greenfield SPAM Jatiluhur Infill Kebon Kosong C04 | G64: Project | H64: Jatiluhur Hilir | I64: DED/RAB | K64: Info | L64: Planning | M64: Aji S | N64: =DATEDIF(C64,'Outgoing 2023'!$L$2,"Y")&" tahun, "&DATEDIF(C64,'Outgoing 2023'!$L$2,"YM")&" bulan, "&DATEDIF(C64,'Outgoing 2023'!$L$2,"MD")&" hari" -> 1 tahun, 5 bulan, 11 hari | O64: =TODAY()-C64 -> 526
A65: 64 | B65: ABJ/DIR/EKS/01.25/0066 | C65: 45692 | D65: PAM JAYA | E65: Penyampaian DED dan RAB Perluasan Jaringan Untuk Sambungan Baru Master Meter Proyek SPAM Jatiluhur Hilir | G65: Project | H65: Jatiluhur Hilir | I65: DED/RAB | K65: Info | L65: Planning | M65: Aji S | N65: =DATEDIF(C65,'Outgoing 2023'!$L$2,"Y")&" tahun, "&DATEDIF(C65,'Outgoing 2023'!$L$2,"YM")&" bulan, "&DATEDIF(C65,'Outgoing 2023'!$L$2,"MD")&" hari" -> 1 tahun, 5 bulan, 11 hari | O65: =TODAY()-C65 -> 526
A66: 65 | B66: ABJ/DIR/EKS/01.25/0067 | C66: 45693 | D66: PAM JAYA | E66: Tagihan Air Curah Periode Januari 2025 | G66: Corporate | H66: Corporate | I66: Tagihan | K66: Open | L66: Compliance | M66: Indradi | N66: =DATEDIF(C66,'Outgoing 2023'!$L$2,"Y")&" tahun, "&DATEDIF(C66,'Outgoing 2023'!$L$2,"YM")&" bulan, "&DATEDIF(C66,'Outgoing 2023'!$L$2,"MD")&" hari" -> 1 tahun, 5 bulan, 10 hari | O66: =TODAY()-C66 -> 525
... A113: 112 | B113: ABJ/DIR/EKS/02.25/0114 | C113: 45708 | D113: PT. Bestindo Putra Mandiri | E113: Tanggapan atas Surat Peringatan I | G113: Project | H113: Buaran 3 Hilir | I113: Peringatan | K113: Closed | L113: PMO | M113: Puji R | N113: =DATEDIF(C113,'Outgoing 2023'!$L$2,"Y")&" tahun, "&DATEDIF(C113,'Outgoing 2023'!$L$2,"YM")&" bulan, "&DATEDIF(C113,'Outgoing 2023'!$L$2,"MD")&" hari" -> 1 tahun, 4 bulan, 25 hari | O113: =TODAY()-C113 -> 510
A114: 113 | B114: ABJ/DIR/EKS/02.25/0115 | C114: 45708 | D114: PAM JAYA | E114: Tanggapan Atas Surat PAM JAYA Nomor : e-35018/KM.03.04 Hal: Penyampaian Hasil Uji Petik Operasional Pulsator dan Elektrikal di IPA Pejompongan 2 | G114: Project | H114: PJP 2 | I114: Pemberitahuan | L114: Produksi | M114: Ahmad Fandhi | N114: =DATEDIF(C114,'Outgoing 2023'!$L$2,"Y")&" tahun, "&DATEDIF(C114,'Outgoing 2023'!$L$2,"YM")&" bulan, "&DATEDIF(C114,'Outgoing 2023'!$L$2,"MD")&" hari" -> 1 tahun, 4 bulan, 25 hari | O114: =TODAY()-C114 -> 510
A115: 114 | B115: ABJ/DIR/EKS/02.25/0116 | C115: 45708 | D115: Kelurahan Pondok Kelapa, Jakarta Timur | E115: Keterangan Proses Perijinan Infill Jl. Marinir, Pondok Kelapa | G115: Project | H115: Greenfield | I115: Perizinan | K115: Info | L115: Permit | M115: Rais A | N115: =DATEDIF(C115,'Outgoing 2023'!$L$2,"Y")&" tahun, "&DATEDIF(C115,'Outgoing 2023'!$L$2,"YM")&" bulan, "&DATEDIF(C115,'Outgoing 2023'!$L$2,"MD")&" hari" -> 1 tahun, 4 bulan, 25 hari | O115: =TODAY()-C115 -> 510
A116: 115 | B116: ABJ/DIR/EKS/02.25/0117 | C116: 45709 | D116: PAM JAYA | E116: Permohonan Pemakaian Air PAM JAYA untuk Pengetesan Pipa SPAM Buaran 3 Hilir Program P1 dan P2 | G116: Project | H116: Buaran 3 Hilir | I116: Flushing | K116: Info | L116: PMO | M116: Puji R | N116: =DATEDIF(C116,'Outgoing 2023'!$L$2,"Y")&" tahun, "&DATEDIF(C116,'Outgoing 2023'!$L$2,"YM")&" bulan, "&DATEDIF(C116,'Outgoing 2023'!$L$2,"MD")&" hari" -> 1 tahun, 4 bulan, 24 hari | O116: =TODAY()-C116 -> 509
A117: 116 | B117: ABJ/DIR/EKS/02.25/0118 | C117: 45709 | D117: PAM JAYA | E117: Penyampaian Laporan Penyelesaian Uji Komisioning Project Greenfield - SPAM Jatiluhur Hilir PC 147 | G117: Project | H117: Jatiluhur Hilir | I117: Komisioning/Pengoperasian | K117: Info | L117: PMO | M117: Muhrojin | N117: =DATEDIF(C117,'Outgoing 2023'!$L$2,"Y")&" tahun, "&DATEDIF(C117,'Outgoing 2023'!$L$2,"YM")&" bulan, "&DATEDIF(C117,'Outgoing 2023'!$L$2,"MD")&" hari" -> 1 tahun, 4 bulan, 24 hari | O117: =TODAY()-C117 -> 509
A118: 117 | B118: ABJ/DIR/EKS/02.25/0119 | C118: 45709 | D118: PAM JAYA | E118: Pemberitahuan Kembali Terkait Pekerjaan Pemeliharaan Peralatan IPA Pejompongan 2 - Pengurasan Pulsator No 1 | G118: Project | H118: PJP 2 | I118: Pemberitahuan | K118: Info | L118: Produksi | M118: Ahmad Fandhi | N118: =DATEDIF(C118,'Outgoing 2023'!$L$2,"Y")&" tahun, "&DATEDIF(C118,'Outgoing 2023'!$L$2,"YM")&" bulan, "&DATEDIF(C118,'Outgoing 2023'!$L$2,"MD")&" hari" -> 1 tahun, 4 bulan, 24 hari | O118: =TODAY()-C118 -> 509
A119: 118 | B119: ABJ/DIR/EKS/02.25/0120 | C119: 45709 | D119: PAM JAYA | E119: Penyampaian Laporan Penyelesaian Uji Komisioning Project Greenfield - SPAM Jatiluhur Hilir A2 dan A6 | G119: Project | H119: Jatiluhur Hilir | I119: Komisioning/Pengoperasian | K119: Info | L119: PMO | M119: Muhrojin | N119: =DATEDIF(C119,'Outgoing 2023'!$L$2,"Y")&" tahun, "&DATEDIF(C119,'Outgoing 2023'!$L$2,"YM")&" bulan, "&DATEDIF(C119,'Outgoing 2023'!$L$2,"MD")&" hari" -> 1 tahun, 4 bulan, 24 hari | O119: =TODAY()-C119 -> 509
A120: 119 | B120: ABJ/DIR/EKS/02.25/0121 | C120: 45709 | D120: PAM JAYA | E120: Gangguan Koneksi SCADA di IPA Pejompongan I tanggal 20 Februari 2025 | G120: Produksi | H120: PJP 1 | I120: Gangguan | K120: Info | L120: Produksi | M120: Wahdi P | N120: =DATEDIF(C120,'Outgoing 2023'!$L$2,"Y")&" tahun, "&DATEDIF(C120,'Outgoing 2023'!$L$2,"YM")&" bulan, "&DATEDIF(C120,'Outgoing 2023'!$L$2,"MD")&" hari" -> 1 tahun, 4 bulan, 24 hari | O120: =TODAY()-C120 -> 509
A121: 120 | B121: ABJ/DIR/EKS/02.25/0122 | C121: 45709 | D121: PAM JAYA | E121: Pemberitahuan Uji Komisioning SPAM Jatiluhur Hilir – PC 055 EZ 09, 10, 11, 12, 13, 14, 15 dan PC 151 EZ 03, 05, 06 | G121: Project | H121: Jatiluhur Hilir | I121: Komisioning/Pengoperasian | K121: Info | L121: PMO | M121: Muhrojin | N121: =DATEDIF(C121,'Outgoing 2023'!$L$2,"Y")&" tahun, "&DATEDIF(C121,'Outgoing 2023'!$L$2,"YM")&" bulan, "&DATEDIF(C121,'Outgoing 2023'!$L$2,"MD")&" hari" -> 1 tahun, 4 bulan, 24 hari | O121: =TODAY()-C121 -> 509
A122: 121 | B122: ABJ/DIR/EKS/02.25/0123 | C122: 45709 | D122: PAM JAYA | E122: Shop Drawing Proyek SPAM Jatiluhur Hilir IBP Halim dan PC 054 | G122: Project | H122: Jatiluhur Hilir | I122: Shop Drawing | K122: Info | L122: PMO | M122: Juny Jety | N122: =DATEDIF(C122,'Outgoing 2023'!$L$2,"Y")&" tahun, "&DATEDIF(C122,'Outgoing 2023'!$L$2,"YM")&" bulan, "&DATEDIF(C122,'Outgoing 2023'!$L$2,"MD")&" hari" -> 1 tahun, 4 bulan, 24 hari | O122: =TODAY()-C122 -> 509
A123: 122 | B123: ABJ/DIR/EKS/02.25/0124 | C123: 45709 | D123: PAM JAYA | E123: DED dan RAB Perluasan Jaringan Untuk 14 Lokasi Infill Ad hoc Sambungan Baru Proyek SPAM Jatiluhur Hilir dan SPAM Karian Serpong Hilir | G123: Project | H123: Greenfield | I123: DED/RAB | K123: Info | L123: Planning | M123: Aji S | N123: =DATEDIF(C123,'Outgoing 2023'!$L$2,"Y")&" tahun, "&DATEDIF(C123,'Outgoing 2023'!$L$2,"YM")&" bulan, "&DATEDIF(C123,'Outgoing 2023'!$L$2,"MD")&" hari" -> 1 tahun, 4 bulan, 24 hari | O123: =TODAY()-C123 -> 509
A124: 123 | B124: ABJ/DIR/EKS/02.25/0125 | C124: 45712 | D124: PAM JAYA | E124: Penyampaian Laporan Keuangan Unaudited | G124: Corporate | H124: Corporate | I124: Laporan Keuangan | K124: Info | L124: Finance | M124: Finance | N124: =DATEDIF(C124,'Outgoing 2023'!$L$2,"Y")&" tahun, "&DATEDIF(C124,'Outgoing 2023'!$L$2,"YM")&" bulan, "&DATEDIF(C124,'Outgoing 2023'!$L$2,"MD")&" hari" -> 1 tahun, 4 bulan, 21 hari | O124: =TODAY()-C124 -> 506
A125: 124 | B125: ABJ/DIR/EKS/02.25/0126 | C125: 45712 | D125: PAM JAYA | E125: Penyampaian Laporan Penyelesaian Uji Komisioning Project Greenfield - SPAM Karian Serpong Hilir | G125: Project | H125: Karian Serpong Hilir | I125: Komisioning/Pengoperasian | K125: Info | L125: PMO | M125: Ervin Y | N125: =DATEDIF(C125,'Outgoing 2023'!$L$2,"Y")&" tahun, "&DATEDIF(C125,'Outgoing 2023'!$L$2,"YM")&" bulan, "&DATEDIF(C125,'Outgoing 2023'!$L$2,"MD")&" hari" -> 1 tahun, 4 bulan, 21 hari | O125: =TODAY()-C125 -> 506
A126: 125 | B126: ABJ/DIR/EKS/02.25/0127 | C126: 45713 | D126: PAM JAYA | E126: TOK SPAM Buaran 3 Hulu - Site Plan HC Training, Toilet & Ruang Ganti dan Lapangan Tenis | G126: Project | H126: Buaran 3 Hulu | I126: TOK | K126: Info | L126: PMO | M126: Angelika | N126: =DATEDIF(C126,'Outgoing 2023'!$L$2,"Y")&" tahun, "&DATEDIF(C126,'Outgoing 2023'!$L$2,"YM")&" bulan, "&DATEDIF(C126,'Outgoing 2023'!$L$2,"MD")&" hari" -> 1 tahun, 4 bulan, 20 hari | O126: =TODAY()-C126 -> 505
... A132: 131 | B132: ABJ/DIR/EKS/02.25/0133 | C132: 45714 | D132: PAM JAYA | E132: Pemberitahuan Uji Komisioning SPAM Jatiluhur Hilir – Infill 070 Green Garden, Infill 068 Boulevard Sedayu, Infil 054 Rawa Badung RT 08, Infil 054 Rawa Badung RT 11, Infil 150 Kampung Bulak Timur 1 | G132: Project | H132: Jatiluhur Hilir | I132: Komisioning/Pengoperasian | K132: Info | L132: Project | M132: Muhrojin | N132: =DATEDIF(C132,'Outgoing 2023'!$L$2,"Y")&" tahun, "&DATEDIF(C132,'Outgoing 2023'!$L$2,"YM")&" bulan, "&DATEDIF(C132,'Outgoing 2023'!$L$2,"MD")&" hari" -> 1 tahun, 4 bulan, 19 hari | O132: =TODAY()-C132 -> 504
A133: 132 | B133: ABJ/DIR/EKS/02.25/0134 | C133: 45716 | E133: Untuk Backdate | N133: =DATEDIF(C133,'Outgoing 2023'!$L$2,"Y")&" tahun, "&DATEDIF(C133,'Outgoing 2023'!$L$2,"YM")&" bulan, "&DATEDIF(C133,'Outgoing 2023'!$L$2,"MD")&" hari" -> 1 tahun, 4 bulan, 17 hari | O133: =TODAY()-C133 -> 502
A134: 133 | B134: ABJ/DIR/EKS/02.25/0135 | C134: 45716 | D134: Pam Jaya | E134: DED dan RAB Perluasan Jaringan Untuk Sambungan Baru H.Syahroni | G134: Project | H134: Greenfield | I134: DED/RAB | K134: info | L134: Planning | M134: Aji S | N134: =DATEDIF(C134,'Outgoing 2023'!$L$2,"Y")&" tahun, "&DATEDIF(C134,'Outgoing 2023'!$L$2,"YM")&" bulan, "&DATEDIF(C134,'Outgoing 2023'!$L$2,"MD")&" hari" -> 1 tahun, 4 bulan, 17 hari | O134: =TODAY()-C134 -> 502
A135: 134 | B135: ABJ/DIR/EKS/02.25/0136 | C135: 45716 | D135: Agen Fasilitas PT Bank Central Asia Tbk | E135: Pemberitahuan Peningkatan terhadap Perjanjian Fasilitas Senior Yang Dijamin sebesar Rp 8.874.000.000.000,- kepada PT Air Bersih Jakarta tertanggal 17 Februari 2023 (“Perjanjian Fasilitas”) | G135: Corporate | H135: Corporate | I135: Finance | L135: Legal | M135: Bahtera N | N135: =DATEDIF(C135,'Outgoing 2023'!$L$2,"Y")&" tahun, "&DATEDIF(C135,'Outgoing 2023'!$L$2,"YM")&" bulan, "&DATEDIF(C135,'Outgoing 2023'!$L$2,"MD")&" hari" -> 1 tahun, 4 bulan, 17 hari | O135: =TODAY()-C135 -> 502
A136: 135 | B136: ABJ/DIR/EKS/02.25/0137 | C136: 45716 | D136: Agen Fasilitas PT Bank Central Asia Tbk | E136: Permohonan Persetujuan Para Kredit Terkait Usulan Perubahan Periode Ketersediaan, Perhitungan Suku Bunga, Biaya Komitmen | G136: Corporate | H136: Corporate | I136: Finance | L136: Legal | M136: Bahtera N | N136: =DATEDIF(C136,'Outgoing 2023'!$L$2,"Y")&" tahun, "&DATEDIF(C136,'Outgoing 2023'!$L$2,"YM")&" bulan, "&DATEDIF(C136,'Outgoing 2023'!$L$2,"MD")&" hari" -> 1 tahun, 4 bulan, 17 hari | O136: =TODAY()-C136 -> 502
A137: 136 | B137: ABJ/DIR/EKS/02.25/0138 | C137: 45719 | D137: PAM JAYA | E137: DED dan RAB Perluasan Jaringan Untuk 6 Lokasi Infill Ad hoc Sambungan Baru Proyek SPAM Jatiluhur Hilir | G137: Project | H137: Jatiluhur Hilir | I137: DED/RAB | K137: info | L137: Planning | M137: Aji S | N137: =DATEDIF(C137,'Outgoing 2023'!$L$2,"Y")&" tahun, "&DATEDIF(C137,'Outgoing 2023'!$L$2,"YM")&" bulan, "&DATEDIF(C137,'Outgoing 2023'!$L$2,"MD")&" hari" -> 1 tahun, 4 bulan, 12 hari | O137: =TODAY()-C137 -> 499
A138: 137 | B138: ABJ/DIR/EKS/02.25/0139 | C138: 45719 | D138: PAM JAYA | E138: DED dan RAB Perluasan Jaringan Untuk Sambungan Baru Kebon Kosong Tambahan RT 07 & 08 RW 06 | G138: Project | H138: Greenfield | I138: DED/RAB | K138: info | L138: Planning | M138: Aji S | N138: =DATEDIF(C138,'Outgoing 2023'!$L$2,"Y")&" tahun, "&DATEDIF(C138,'Outgoing 2023'!$L$2,"YM")&" bulan, "&DATEDIF(C138,'Outgoing 2023'!$L$2,"MD")&" hari" -> 1 tahun, 4 bulan, 12 hari | O138: =TODAY()-C138 -> 499
A139: 138 | B139: ABJ/DIR/EKS/02.25/0140 | C139: 45719 | D139: PAM JAYA | E139: Pemberitahuan Uji Komisioning SPAM Jatiluhur Hilir – PC 153 EZ 01, EZ 05, EZ 06 | G139: Project | H139: Jatiluhur Hilir | I139: Komisioning/Pengoperasian | K139: info | L139: PMO | M139: Muhrojin | N139: =DATEDIF(C139,'Outgoing 2023'!$L$2,"Y")&" tahun, "&DATEDIF(C139,'Outgoing 2023'!$L$2,"YM")&" bulan, "&DATEDIF(C139,'Outgoing 2023'!$L$2,"MD")&" hari" -> 1 tahun, 4 bulan, 12 hari | O139: =TODAY()-C139 -> 499
A140: 139 | B140: ABJ/DIR/EKS/02.25/0141 | C140: 45719 | D140: PAM JAYA | E140: Penyampaian Laporan Persiapan Penyerahan Fasilitas Distribusi Baru Proyek Greenfield – SPAM Buaran 3 Hilir | G140: Project | H140: Buaran 3 Hilir | I140: Laporan Periodik | K140: info | L140: PMO | M140: Puji R | N140: =DATEDIF(C140,'Outgoing 2023'!$L$2,"Y")&" tahun, "&DATEDIF(C140,'Outgoing 2023'!$L$2,"YM")&" bulan, "&DATEDIF(C140,'Outgoing 2023'!$L$2,"MD")&" hari" -> 1 tahun, 4 bulan, 12 hari | O140: =TODAY()-C140 -> 499
A141: 140 | B141: ABJ/DIR/EKS/02.25/0142 | C141: 45719 | D141: General Manager Wilayah 1, Perum Jasa Tirta II | E141: Pemberitahuan Pemanfaatan Air Saluran Tarum Barat | G141: Produksi | H141: Produksi | I141: Pemberitahuan | K141: info | L141: Produksi | M141: Siswo | N141: =DATEDIF(C141,'Outgoing 2023'!$L$2,"Y")&" tahun, "&DATEDIF(C141,'Outgoing 2023'!$L$2,"YM")&" bulan, "&DATEDIF(C141,'Outgoing 2023'!$L$2,"MD")&" hari" -> 1 tahun, 4 bulan, 12 hari | O141: =TODAY()-C141 -> 499
A142: 141 | B142: ABJ/DIR/EKS/02.25/0143 | C142: 45719 | D142: PAM JAYA | E142: Pemberitahuan Uji Komisioning SPAM Buaran 3 Hilir – Infil 161 Masjid Al-Khairot | G142: Project | H142: Buaran 3 Hilir | I142: Komisioning/Pengoperasian | K142: info | L142: PMO | M142: Puji R | N142: =DATEDIF(C142,'Outgoing 2023'!$L$2,"Y")&" tahun, "&DATEDIF(C142,'Outgoing 2023'!$L$2,"YM")&" bulan, "&DATEDIF(C142,'Outgoing 2023'!$L$2,"MD")&" hari" -> 1 tahun, 4 bulan, 12 hari | O142: =TODAY()-C142 -> 499
A143: 142 | B143: ABJ/DIR/EKS/02.25/0144 | C143: 45719 | D143: PAM JAYA | E143: DED dan RAB Perluasan Jaringan Untuk 14 Lokasi Infill Ad hoc Sambungan Baru Proyek SPAM Jatiluhur Hilir, SPAM Karian Serpong Hilir, dan SPAM Buaran 3 Hilir | G143: Project | H143: Greenfield | I143: DED/RAB | K143: info | L143: Planning | M143: Aji S | N143: =DATEDIF(C143,'Outgoing 2023'!$L$2,"Y")&" tahun, "&DATEDIF(C143,'Outgoing 2023'!$L$2,"YM")&" bulan, "&DATEDIF(C143,'Outgoing 2023'!$L$2,"MD")&" hari" -> 1 tahun, 4 bulan, 12 hari | O143: =TODAY()-C143 -> 499
A144: 143 | B144: ABJ/DIR/EKS/02.25/0145 | C144: 45720 | D144: PAM JAYA | E144: Permohonan Waktu Konsultasi Penyerahan Fasilitas Distribusi Baru – TOK April 2025 | G144: Corporate | H144: Greenfield | I144: TOK | K144: info | L144: Compliance | M144: Indradi | N144: =DATEDIF(C144,'Outgoing 2023'!$L$2,"Y")&" tahun, "&DATEDIF(C144,'Outgoing 2023'!$L$2,"YM")&" bulan, "&DATEDIF(C144,'Outgoing 2023'!$L$2,"MD")&" hari" -> 1 tahun, 4 bulan, 11 hari | O144: =TODAY()-C144 -> 498
A145: 144 | B145: ABJ/DIR/EKS/02.25/0146 | C145: 45720 | D145: PAM JAYA | E145: Penyampaian Laporan Penyelesaian Uji Komisioning Project Greenfield - SPAM Jatiluhur Hilir PC 055 dan PC 153 | G145: Project | H145: Jatiluhur Hilir | I145: Komisioning/Pengoperasian | K145: info | L145: PMO | M145: Muhrojin | N145: =DATEDIF(C145,'Outgoing 2023'!$L$2,"Y")&" tahun, "&DATEDIF(C145,'Outgoing 2023'!$L$2,"YM")&" bulan, "&DATEDIF(C145,'Outgoing 2023'!$L$2,"MD")&" hari" -> 1 tahun, 4 bulan, 11 hari | O145: =TODAY()-C145 -> 498
A146: 145 | B146: ABJ/DIR/EKS/02.25/0147 | C146: 45720 | D146: PAM JAYA | E146: Gangguan Koneksi SCADA di IPA Pejompongan I tanggal 20 Februari 2025 | G146: Produksi | H146: PJP 1 | I146: Gangguan | K146: info | L146: Produksi | M146: Wahdi P | N146: =DATEDIF(C146,'Outgoing 2023'!$L$2,"Y")&" tahun, "&DATEDIF(C146,'Outgoing 2023'!$L$2,"YM")&" bulan, "&DATEDIF(C146,'Outgoing 2023'!$L$2,"MD")&" hari" -> 1 tahun, 4 bulan, 11 hari | O146: =TODAY()-C146 -> 498
A147: 146 | B147: ABJ/DIR/EKS/02.25/0148 | C147: 45720 | D147: PAM JAYA | E147: Penyampaian Informasi Perkembangan Proyek Greenfiled – SPAM Hilir | G147: Project | H147: Greenfield | I147: Kendala Proyek | K147: info | L147: PMO | M147: Angelika | N147: =DATEDIF(C147,'Outgoing 2023'!$L$2,"Y")&" tahun, "&DATEDIF(C147,'Outgoing 2023'!$L$2,"YM")&" bulan, "&DATEDIF(C147,'Outgoing 2023'!$L$2,"MD")&" hari" -> 1 tahun, 4 bulan, 11 hari | O147: =TODAY()-C147 -> 498
A148: 147 | B148: ABJ/DIR/EKS/02.25/0149 | C148: 45720 | D148: PAM JAYA | E148: Tanggapan Surat PAM JAYA e-40783.KM.03.04 (Penggantian Pressure Transmitter Manifold) | G148: Produksi | H148: PJP 1 | I148: Pemberitahuan | K148: info | L148: Produksi | M148: Wahdi P | N148: =DATEDIF(C148,'Outgoing 2023'!$L$2,"Y")&" tahun, "&DATEDIF(C148,'Outgoing 2023'!$L$2,"YM")&" bulan, "&DATEDIF(C148,'Outgoing 2023'!$L$2,"MD")&" hari" -> 1 tahun, 4 bulan, 11 hari | O148: =TODAY()-C148 -> 498
... A157: 156 | B157: ABJ/DIR/EKS/02.25/0158 | C157: 45721 | D157: PAM JAYA | E157: Laporan Bulanan Kualitas Air Baku dan Air Curah Periode Februari 2025 | G157: Project | H157: Produksi | I157: Laporan Periodik | K157: info | L157: WQA | M157: Novi | N157: =DATEDIF(C157,'Outgoing 2023'!$L$2,"Y")&" tahun, "&DATEDIF(C157,'Outgoing 2023'!$L$2,"YM")&" bulan, "&DATEDIF(C157,'Outgoing 2023'!$L$2,"MD")&" hari" -> 1 tahun, 4 bulan, 10 hari | O157: =TODAY()-C157 -> 497
A158: 157 | B158: ABJ/DIR/EKS/02.25/0159 | C158: 45721 | D158: Bank Mega | E158: Pencairan Deposito | G158: Corporate | H158: Corporate | I158: Finance | L158: Finance | M158: Wahyu Tjahyadi | N158: =DATEDIF(C158,'Outgoing 2023'!$L$2,"Y")&" tahun, "&DATEDIF(C158,'Outgoing 2023'!$L$2,"YM")&" bulan, "&DATEDIF(C158,'Outgoing 2023'!$L$2,"MD")&" hari" -> 1 tahun, 4 bulan, 10 hari | O158: =TODAY()-C158 -> 497
A159: 158 | B159: ABJ/DIR/EKS/02.25/0160 | C159: 45721 | D159: Bank INA | E159: Pencairan Deposito | G159: Corporate | H159: Corporate | I159: Finance | L159: Finance | M159: Wahyu Tjahyadi | N159: =DATEDIF(C159,'Outgoing 2023'!$L$2,"Y")&" tahun, "&DATEDIF(C159,'Outgoing 2023'!$L$2,"YM")&" bulan, "&DATEDIF(C159,'Outgoing 2023'!$L$2,"MD")&" hari" -> 1 tahun, 4 bulan, 10 hari | O159: =TODAY()-C159 -> 497
A160: 159 | B160: ABJ/DIR/EKS/02.25/0161 | C160: 45721 | D160: PAM JAYA | E160: Penyampaian Laporan Persiapan Penyerahan Fasilitas Distribusi Baru Proyek Greenfield SPAM Buaran 3 Hilir – Jl Dato Tonggara III | G160: Project | H160: Buaran 3 Hilir | I160: Laporan Distribusi Baru | K160: info | L160: PMO | M160: Puji R | N160: =DATEDIF(C160,'Outgoing 2023'!$L$2,"Y")&" tahun, "&DATEDIF(C160,'Outgoing 2023'!$L$2,"YM")&" bulan, "&DATEDIF(C160,'Outgoing 2023'!$L$2,"MD")&" hari" -> 1 tahun, 4 bulan, 10 hari | O160: =TODAY()-C160 -> 497
A161: 160 | B161: ABJ/DIR/EKS/02.25/0162 | C161: 45722 | D161: PAM JAYA | E161: DED dan RAB Perluasan Jaringan Untuk 6 Lokasi Infill Ad hoc Sambungan Baru Proyek SPAM Jatiluhur Hilir, SPAM Karian Serpong Hilir, dan SPAM Buaran 3 Hilir | G161: Project | H161: Greenfield | I161: DED/RAB | K161: info | L161: Planning | M161: Aji S | N161: =DATEDIF(C161,'Outgoing 2023'!$L$2,"Y")&" tahun, "&DATEDIF(C161,'Outgoing 2023'!$L$2,"YM")&" bulan, "&DATEDIF(C161,'Outgoing 2023'!$L$2,"MD")&" hari" -> 1 tahun, 4 bulan, 9 hari | O161: =TODAY()-C161 -> 496
A162: 161 | B162: ABJ/DIR/EKS/02.25/0163 | C162: 45722 | D162: PAM JAYA | E162: Undangan Pelaksanaan Tes Fungsi Terkait Proyek SPAM Jatiluhur Hilir | G162: Project | H162: Jatiluhur Hilir | I162: Komisioning/Pengoperasian | K162: info | L162: PMO | M162: Juny Jety | N162: =DATEDIF(C162,'Outgoing 2023'!$L$2,"Y")&" tahun, "&DATEDIF(C162,'Outgoing 2023'!$L$2,"YM")&" bulan, "&DATEDIF(C162,'Outgoing 2023'!$L$2,"MD")&" hari" -> 1 tahun, 4 bulan, 9 hari | O162: =TODAY()-C162 -> 496
A163: 162 | B163: ABJ/DIR/EKS/02.25/0164 | C163: 45723 | D163: Kelurahan Tugu Utara | E163: Surat Pemberitahuan dan Permohonan Ijin Pelaksanaan Pekerjaan Pemasangan Pipa di Jl Tipar Cakung Kelurahan Tugu Utara Kecamatan Koja Jakarta Utara | G163: Project | H163: Greenfield | I163: Perizinan | K163: Info | L163: Corcom | M163: Ninuk | N163: =DATEDIF(C163,'Outgoing 2023'!$L$2,"Y")&" tahun, "&DATEDIF(C163,'Outgoing 2023'!$L$2,"YM")&" bulan, "&DATEDIF(C163,'Outgoing 2023'!$L$2,"MD")&" hari" -> 1 tahun, 4 bulan, 8 hari | O163: =TODAY()-C163 -> 495
A164: 163 | B164: ABJ/DIR/EKS/02.25/0165 | C164: 45723 | D164: PT. Samoa Bersaudara Abadi | E164: Amandemen Kontrak Jasa pengangkutan sampah ABJ periode Kontrak 1 Juli 2024 - 31 Juni 2025 | K164: Info | L164: SCM | M164: Wahyu S | N164: =DATEDIF(C164,'Outgoing 2023'!$L$2,"Y")&" tahun, "&DATEDIF(C164,'Outgoing 2023'!$L$2,"YM")&" bulan, "&DATEDIF(C164,'Outgoing 2023'!$L$2,"MD")&" hari" -> 1 tahun, 4 bulan, 8 hari | O164: =TODAY()-C164 -> 495
A165: 164 | B165: ABJ/DIR/EKS/02.25/0166 | C165: 45723 | D165: PAM JAYA | E165: Pemberitahuan Uji Komisioning SPAM Buaran 3 Hilir – Infil 159 Dato Tonggara III | G165: Project | H165: Buaran 3 Hilir | I165: Komisioning/Pengoperasian | K165: Info | L165: PMO | M165: Puji R | N165: =DATEDIF(C165,'Outgoing 2023'!$L$2,"Y")&" tahun, "&DATEDIF(C165,'Outgoing 2023'!$L$2,"YM")&" bulan, "&DATEDIF(C165,'Outgoing 2023'!$L$2,"MD")&" hari" -> 1 tahun, 4 bulan, 8 hari | O165: =TODAY()-C165 -> 495
A166: 165 | B166: ABJ/DIR/EKS/03.25/0167 | C166: 45726 | D166: Pam Jaya | E166: Dispensasi Pengiriman Bahan Kimia Selama Periode Arus Mudik dan Arus Balik Lebaran Tahun 2025 | G166: Produksi | H166: Produksi | I166: Produksi | K166: Info | L166: Produksi | M166: Rika | N166: =DATEDIF(C166,'Outgoing 2023'!$L$2,"Y")&" tahun, "&DATEDIF(C166,'Outgoing 2023'!$L$2,"YM")&" bulan, "&DATEDIF(C166,'Outgoing 2023'!$L$2,"MD")&" hari" -> 1 tahun, 4 bulan, 5 hari | O166: =TODAY()-C166 -> 492
A167: 166 | B167: ABJ/DIR/EKS/03.25/0168 | C167: 45727 | D167: PAM JAYA | E167: Permohonan Ijin Interkoneksi Pipa Eksisting Dia, 400mm PC 055 EZ 03 dan 3C | G167: Project | H167: Jatiluhur Hilir | I167: Perizinan | K167: Info | L167: PMO | M167: Muhrojin | N167: =DATEDIF(C167,'Outgoing 2023'!$L$2,"Y")&" tahun, "&DATEDIF(C167,'Outgoing 2023'!$L$2,"YM")&" bulan, "&DATEDIF(C167,'Outgoing 2023'!$L$2,"MD")&" hari" -> 1 tahun, 4 bulan, 4 hari | O167: =TODAY()-C167 -> 491
