Workbook

Sheet Dashboard

Sheet Summary
A1: =TODAY() -> 46304
M2: Monitoring Surat 2026
A3: Keterangan | M3: Keterangan | N3: Compliance | O3: Corcom | P3: Finance | Q3: HC | R3: HSE | V3: Maintenance | W3: Permit | X3: Planning | Y3: PMO | Z3: Produksi | AA3: SCM | AB3: QMS | AC3: WQA
A4: Level 1 | B4: Perlu dibalas dengan tenggat waktu (max 7 hari) | M4: Incoming Open | N4: =COUNTIFS('Incoming 2026'!L:L,$B$19,'Incoming 2026'!R:R,N3) -> 1 | O4: =COUNTIFS('Incoming 2026'!L:L,$B$19,'Incoming 2026'!R:R,"$O$3") -> 0 | P4: =COUNTIFS('Incoming 2026'!L:L,$B$19,'Incoming 2026'!R:R,"HC") -> 0 | Q4: =COUNTIFS('Incoming 2026'!L:L,$B$19,'Incoming 2026'!R:R,"HC") -> 0 | R4: =COUNTIFS('Incoming 2026'!L:L,$B$19,'Incoming 2026'!R:R,"HSE") -> 13 | V4: =COUNTIFS('Incoming 2026'!L:L,$B$19,'Incoming 2026'!R:R,"maintenance") -> 0 | W4: =COUNTIFS('Incoming 2026'!L:L,$B$19,'Incoming 2026'!R:R,"permit") -> 7 | X4: =COUNTIFS('Incoming 2026'!L:L,$B$19,'Incoming 2026'!R:R,"Planning") -> 19 | Y4: =COUNTIFS('Incoming 2026'!L:L,$B$19,'Incoming 2026'!R:R,"PMO") -> 2 | Z4: =COUNTIFS('Incoming 2026'!L:L,$B$19,'Incoming 2026'!R:R,"Produksi") -> 0 | AA4: =COUNTIFS('Incoming 2024'!L:L,$B$19,'Incoming 2024'!N:N,"SCM") -> 0 | AB4: =COUNTIFS('Incoming 2024'!L:L,$B$19,'Incoming 2024'!N:N,"QMS") -> 0 | AC4: =COUNTIFS('Incoming 2024'!L:L,$B$19,'Incoming 2024'!N:N,"WQA") -> 0
A5: Level 2 | B5: Perlu dibalas dengan tenggat waktu (Max 14 hari) | M5: Incoming Closed | N5: =COUNTIFS('Incoming 2026'!L:L,Summary!$B$20,'Incoming 2026'!R:R,Summary!N3) -> 21 | O5: =COUNTIFS('Incoming 2026'!L:L,Summary!$B$20,'Incoming 2026'!R:R,Summary!O3) -> 0 | P5: =COUNTIFS('Incoming 2026'!L:L,Summary!$B$20,'Incoming 2026'!R:R,Summary!P3) -> 7 | Q5: =COUNTIFS('Incoming 2026'!L:L,Summary!$B$20,'Incoming 2026'!R:R,Summary!Q3) -> 1 | R5: =COUNTIFS('Incoming 2026'!L:L,Summary!$B$20,'Incoming 2026'!R:R,Summary!R3) -> 121 | V5: =COUNTIFS('Incoming 2026'!L:L,Summary!$B$20,'Incoming 2026'!R:R,Summary!V3) -> 0 | W5: =COUNTIFS('Incoming 2026'!L:L,Summary!$B$20,'Incoming 2026'!R:R,Summary!W3) -> 4 | X5: =COUNTIFS('Incoming 2026'!L:L,Summary!$B$20,'Incoming 2026'!R:R,Summary!X3) -> 15 | Y5: =COUNTIFS('Incoming 2026'!L:L,Summary!$B$20,'Incoming 2026'!R:R,Summary!Y3) -> 0 | Z5: =COUNTIFS('Incoming 2026'!L:L,Summary!$B$20,'Incoming 2026'!R:R,Summary!Z3) -> 13 | AA5: =COUNTIFS('Incoming 2024'!L:L,Summary!$B$20,'Incoming 2024'!N:N,Summary!AA3) -> 0 | AB5: =COUNTIFS('Incoming 2024'!L:L,Summary!$B$20,'Incoming 2024'!N:N,Summary!AB3) -> 1 | AC5: =COUNTIFS('Incoming 2024'!L:L,Summary!$B$20,'Incoming 2024'!N:N,Summary!AC3) -> 2
A6: Level 3 | B6: Perlu dibalas dengan tenggat waktu (Max 30 hari) | M6: Outgoing Open | N6: =COUNTIFS('Outgoing 2026'!L:L,$B$19,'Outgoing 2026'!M:M,"compliance") -> 17 | O6: =COUNTIFS('Outgoing 2026'!L:L,$B$19,'Outgoing 2026'!M:M,"corcom") -> 0 | P6: =COUNTIFS('Outgoing 2026'!L:L,$B$19,'Outgoing 2026'!M:M,"Finance") -> 2 | Q6: =COUNTIFS('Outgoing 2026'!L:L,$B$19,'Outgoing 2026'!M:M,"HC") -> 0 | R6: =COUNTIFS('Outgoing 2026'!L:L,$B$19,'Outgoing 2026'!M:M,"HSE") -> 2 | V6: =COUNTIFS('Outgoing 2026'!L:L,$B$19,'Outgoing 2026'!M:M,"Maintenance") -> 0 | W6: =COUNTIFS('Outgoing 2026'!L:L,$B$19,'Outgoing 2026'!M:M,"Permit") -> 6 | X6: =COUNTIFS('Outgoing 2026'!L:L,$B$19,'Outgoing 2026'!M:M,"Planning") -> 6 | Y6: =COUNTIFS('Outgoing 2026'!L:L,$B$19,'Outgoing 2026'!M:M,$Y$3) -> 0 | Z6: =COUNTIFS('Outgoing 2026'!L:L,$B$19,'Outgoing 2026'!M:M,$Z$3) -> 3 | AA6: =COUNTIFS('Outgoing 2024'!K:K,$B$19,'Outgoing 2024'!L:L,$AA$3) -> 0 | AB6: =COUNTIFS('Outgoing 2024'!K:K,$B$19,'Outgoing 2024'!L:L,$AB$3) -> 0 | AC6: =COUNTIFS('Outgoing 2024'!K:K,$B$19,'Outgoing 2024'!L:L,$AC$3) -> 0
M7: Outgoing Closed | N7: =COUNTIFS('Outgoing 2026'!L:L,$B$20,'Outgoing 2026'!M:M,"compliance") -> 24 | O7: =COUNTIFS('Outgoing 2026'!L:L,$B$20,'Outgoing 2026'!M:M,"corcom") -> 0 | P7: =COUNTIFS('Outgoing 2026'!L:L,$B$20,'Outgoing 2026'!M:M,"Finance") -> 0 | Q7: =COUNTIFS('Outgoing 2026'!L:L,$B$20,'Outgoing 2026'!M:M,"HC") -> 0 | R7: =COUNTIFS('Outgoing 2026'!L:L,$B$20,'Outgoing 2026'!M:M,"HSE") -> 0 | V7: =COUNTIFS('Outgoing 2026'!L:L,$B$20,'Outgoing 2026'!M:M,"Maintenance") -> 0 | W7: =COUNTIFS('Outgoing 2026'!L:L,$B$20,'Outgoing 2026'!M:M,"Permit") -> 0 | X7: =COUNTIFS('Outgoing 2026'!L:L,$B$20,'Outgoing 2026'!M:M,"Planning") -> 2 | Y7: =COUNTIFS('Outgoing 2026'!L:L,$B$20,'Outgoing 2026'!M:M,$Y$3) -> 0 | Z7: =COUNTIFS('Outgoing 2026'!L:L,$B$20,'Outgoing 2026'!M:M,$Z$3) -> 0 | AA7: =COUNTIFS('Outgoing 2024'!K:K,$B$20,'Outgoing 2024'!L:L,$AA$3) -> 0 | AB7: =COUNTIFS('Outgoing 2024'!K:K,$B$20,'Outgoing 2024'!L:L,$AB$3) -> 0 | AC7: =COUNTIFS('Outgoing 2024'!K:K,$B$20,'Outgoing 2024'!L:L,$AC$3) -> 1
A8: 1) Total Surat | B8: 2023 | C8: Incoming | D8: =SUBTOTAL(3,'Incoming 2023'!D:D) -> 439
C9: Outgoing | D9: =SUBTOTAL(3,'Outgoing 2023'!B:B) -> 531
B10: 2024 | C10: Incoming | D10: =SUBTOTAL(3,'Incoming 2024'!B:B) -> 2
C11: Outgoing | D11: =SUBTOTAL(3,'Outgoing 2024'!A:A) -> 975
B12: 2025 | C12: Incoming | D12: =SUBTOTAL(3,'Incoming 2025'!B2:B2001) -> 502
C13: Outgoing | D13: =SUBTOTAL(3,'Outgoing 2025'!B2:B1898) -> 1158
B14: 2026 | C14: Incoming | D14: =SUBTOTAL(3,'Incoming 2026'!B2:B1984) -> 558
C15: Outgoing | D15: =SUBTOTAL(3,'Outgoing 2026'!B2:B1500) -> 1298
B18: Surat Masuk | C18: 2026 | D18: 2025 | E18: 2024 | F18: 2023 | I18: Surat Keluar | J18: 2026 | K18: 2025 | L18: 2024
B19: Open | C19: =COUNTIF('Incoming 2026'!L2:L1982,Summary!B19) -> 78 | D19: =COUNTIF('Incoming 2025'!L2:L2001,Summary!B19) -> 39 | E19: =COUNTIF('Incoming 2024'!L:L,"open") -> 37 | F19: =COUNTIF('Incoming 2023'!I:I,"open") -> 9 | I19: Open | J19: =COUNTIF('Outgoing 2026'!$L$2:$L$952,Summary!I19) -> 38 | K19: =COUNTIF('Outgoing 2025'!K2:K963,Summary!I19) -> 11 | L19: =COUNTIF('Outgoing 2024'!K:K,"Open") -> 2
B20: Closed | C20: =COUNTIF('Incoming 2026'!L2:L1982,Summary!B20) -> 247 | D20: =COUNTIF('Incoming 2025'!L3:L2001,Summary!B20) -> 116 | E20: =COUNTIF('Incoming 2024'!L:L,"closed") -> 244 | F20: =COUNTIF('Incoming 2023'!I:I,"closed") -> 252 | I20: Closed | J20: =COUNTIF('Outgoing 2026'!$L$2:$L$952,Summary!I20) -> 35 | K20: =COUNTIF('Outgoing 2025'!K3:K963,Summary!I20) -> 7 | L20: =COUNTIF('Outgoing 2024'!K:K,"Closed") -> 177
B21: Info | C21: =COUNTIF('Incoming 2026'!L2:L1983,Summary!B21) -> 233 | D21: =COUNTIF('Incoming 2025'!L4:L1001,Summary!B21) -> 338 | E21: =COUNTIF('Incoming 2024'!L:L,"info") -> 553 | F21: =COUNTIF('Incoming 2023'!I:I,"info") -> 177 | I21: Info | J21: =COUNTIF('Outgoing 2026'!$L$2:$L$952,Summary!I21) -> 877 | K21: =COUNTIF('Outgoing 2025'!K4:K963,Summary!I21) -> 639 | L21: =COUNTIF('Outgoing 2024'!K:K,"Info") -> 777
M34: Jumlah surat masuk berdasarkan Durasi Keterlambatan
N35: 7 | O35: 14 | P35: 21 | Q35: 30
M36: Level 1 | N36: =COUNTIF('Incoming 2026'!M2:M191,Summary!M36) -> 10 | O36: =COUNTIFS('Incoming 2026'!M:M,Summary!M36,'Incoming 2026'!W:W,Summary!O35) -> 0 | P36: =COUNTIFS('Incoming 2026'!M:M,Summary!M36,'Incoming 2026'!W:W,Summary!P35) -> 0 | Q36: =COUNTIFS('Incoming 2026'!M:M,Summary!N36,'Incoming 2026'!W:W,Summary!Q35) -> 0
M37: Level 2 | N37: =COUNTIF('Incoming 2026'!M3:M192,Summary!M37) -> 20 | O37: =COUNTIFS('Incoming 2026'!M:M,Summary!M37,'Incoming 2026'!W:W,Summary!O35) -> 0 | P37: =COUNTIFS('Incoming 2026'!M:M,Summary!M37,'Incoming 2026'!W:W,Summary!P35) -> 0 | Q37: =COUNTIFS('Incoming 2026'!M:M,Summary!M37,'Incoming 2026'!W:W,Summary!Q35) -> 0
M38: Level 3 | N38: =COUNTIF('Incoming 2026'!M4:M193,Summary!M38) -> 2 | O38: =COUNTIFS('Incoming 2026'!M:M,Summary!M38,'Incoming 2026'!W:W,Summary!O35) -> 0 | P38: =COUNTIFS('Incoming 2026'!M:M,Summary!M38,'Incoming 2026'!W:W,Summary!P35) -> 0 | Q38: =COUNTIFS('Incoming 2026'!M:M,Summary!M38,'Incoming 2026'!W:W,Summary!Q35) -> 2
A40: Kategori Surat
A41: TOK | B41: =COUNTIF('Incoming 2026'!#REF!,A41) -> #REF!
A42: DED/RAB | B42: =COUNTIF('Incoming 2026'!#REF!,A42) -> #REF!
A43: PKS | B43: =COUNTIF('Incoming 2026'!#REF!,A43) -> #REF!
A44: Dokumentasi | B44: =COUNTIF('Incoming 2026'!#REF!,A44) -> #REF!
A45: Denda | B45: =COUNTIF('Incoming 2026'!#REF!,A45) -> #REF!
A46: Perizinan | B46: =COUNTIF('Incoming 2026'!#REF!,A46) -> #REF!
A47: Sambungan Rumah/Sambungan Baru | B47: =COUNTIF('Incoming 2026'!#REF!,A47) -> #REF!
A48: Teguran | B48: =COUNTIF('Incoming 2026'!#REF!,A48) -> #REF!
A49: Komisioning/Pengoperasian | B49: =COUNTIF('Incoming 2026'!#REF!,A49) -> #REF!
A50: Spesifikasi Teknis/Metode Kerja | B50: =COUNTIF('Incoming 2026'!#REF!,A50) -> #REF!
A51: Inspeksi | B51: =COUNTIF('Incoming 2026'!#REF!,A51) -> #REF!
A53: Pengadaan | B53: =COUNTIF('Incoming 2026'!#REF!,A53) -> #REF!
... A56: Rencana Pekerjaan | B56: =COUNTIF('Incoming 2026'!#REF!,A56) -> #REF!
A59: Kategori Surat Masuk "Open"
A60: Shop Drawing | B60: =COUNTIFS('Incoming 2025'!L:L,Summary!$B$19,'Incoming 2025'!J:J,Summary!A60) -> 0
A61: DED/RAB | B61: =COUNTIFS('Incoming 2025'!L:L,Summary!$B$19,'Incoming 2025'!J:J,Summary!A61) -> 9
A62: PKS | B62: =COUNTIFS('Incoming 2025'!L:L,Summary!$B$19,'Incoming 2025'!J:J,Summary!A62) -> 2
A63: Laporan Bulanan | B63: =COUNTIFS('Incoming 2025'!L:L,Summary!$B$19,'Incoming 2025'!J:J,Summary!A63) -> 0
A64: Denda | B64: =COUNTIFS('Incoming 2025'!L:L,Summary!$B$19,'Incoming 2025'!J:J,Summary!A64) -> 0
A65: Perizinan | B65: =COUNTIFS('Incoming 2025'!L:L,Summary!$B$19,'Incoming 2025'!J:J,Summary!A65) -> 5
A66: MoM | B66: =COUNTIFS('Incoming 2025'!L:L,Summary!$B$19,'Incoming 2025'!J:J,Summary!A66) -> 0
A67: Tagihan | B67: =COUNTIFS('Incoming 2025'!L:L,Summary!$B$19,'Incoming 2025'!J:J,Summary!A67) -> 0
A68: Gangguan | B68: =COUNTIFS('Incoming 2025'!L:L,Summary!$B$19,'Incoming 2025'!J:J,Summary!A68) -> 0
A69: Spesifikasi Teknis/Metode Kerja | B69: =COUNTIFS('Incoming 2025'!L:L,Summary!$B$19,'Incoming 2025'!J:J,Summary!A69) -> 1
A70: Inspeksi | B70: =COUNTIFS('Incoming 2025'!L:L,Summary!$B$19,'Incoming 2025'!J:J,Summary!A70) -> 1
A71: Komisioning/Pengoperasian | B71: =COUNTIFS('Incoming 2025'!L:L,Summary!$B$19,'Incoming 2025'!J:J,Summary!A71) -> 0
... A75: Rencana Pekerjaan | B75: =COUNTIFS('Incoming 2025'!L:L,Summary!$B$19,'Incoming 2025'!J:J,Summary!A75) -> 0
A77: 2026
N78: PIC Surat Keluar 2026
A79: Surat kategori | B79: Incoming | C79: Outgoing | O79: Incoming | P79: Outgoing
A80: Brownfield | N80: {=_xlfn.UNIQUE('Incoming 2026'!R2:R17)} -> PMO Infill | O80: =COUNTIF('Incoming 2026'!$R$2:$R$984,Summary!N80) -> 109 | P80: =COUNTIF('Outgoing 2026'!$M$2:$M$900,Summary!N80) -> 165
A81: Operation & Maintenance | B81: =COUNTIF('Incoming 2026'!$J$2:$J$984,Summary!A81) -> 23 | C81: =COUNTIF('Outgoing 2026'!$J$2:$J$906,Summary!A81) -> 49 | N81: Planning | O81: =COUNTIF('Incoming 2026'!$R$2:$R$984,Summary!N81) -> 50 | P81: =COUNTIF('Outgoing 2026'!$M$2:$M$900,Summary!N81) -> 49
A82: Denda & Kegagalan | B82: =COUNTIF('Incoming 2026'!$J$2:$J$984,Summary!A82) -> 3 | C82: =COUNTIF('Outgoing 2026'!$J$2:$J$906,Summary!A82) -> 2 | N82: Compliance | O82: =COUNTIF('Incoming 2026'!$R$2:$R$984,Summary!N82) -> 62 | P82: =COUNTIF('Outgoing 2026'!$M$2:$M$900,Summary!N82) -> 71
A83: Perencanaan Program Rehabilitasi | B83: =COUNTIF('Incoming 2026'!$J$2:$J$984,Summary!A83) -> 7 | C83: =COUNTIF('Outgoing 2026'!$J$2:$J$906,Summary!A83) -> 27 | N83: Finance | O83: =COUNTIF('Incoming 2026'!$R$2:$R$984,Summary!N83) -> 7 | P83: =COUNTIF('Outgoing 2026'!$M$2:$M$900,Summary!N83) -> 35
A84: Konstruksi Program Brownfield | B84: =COUNTIF('Incoming 2026'!$J$2:$J$984,Summary!A84) -> 0 | C84: =COUNTIF('Outgoing 2026'!$J$2:$J$906,Summary!A84) -> 0 | N84: PMO NC | O84: =COUNTIF('Incoming 2026'!$R$2:$R$984,Summary!N84) -> 28 | P84: =COUNTIF('Outgoing 2026'!$M$2:$M$900,Summary!N84) -> 201
A85: Administrasi & Dokumentasi | B85: =COUNTIF('Incoming 2026'!$J$2:$J$984,Summary!A85) -> 3 | C85: =COUNTIF('Outgoing 2026'!$J$2:$J$906,Summary!A85) -> 4 | N85: PMO Cyclical | O85: =COUNTIF('Incoming 2026'!$R$2:$R$984,Summary!N85) -> 19 | P85: =COUNTIF('Outgoing 2026'!$M$2:$M$900,Summary!N85) -> 51
A86: Greenfield | N86: PMO/Permit | O86: =COUNTIF('Incoming 2026'!$R$2:$R$984,Summary!N86) -> 2 | P86: =COUNTIF('Outgoing 2026'!$M$2:$M$900,Summary!N86) -> 0
A87: Perencanaan Program Greenfield | B87: =COUNTIF('Incoming 2026'!$J$2:$J$984,Summary!A87) -> 46 | C87: =COUNTIF('Outgoing 2026'!$J$2:$J$906,Summary!A87) -> 48 | N87: PGO | O87: =COUNTIF('Incoming 2026'!$R$2:$R$984,Summary!N87) -> 22 | P87: =COUNTIF('Outgoing 2026'!$M$2:$M$900,Summary!N87) -> 21
A88: Konstruksi Program Greenfield | B88: =COUNTIF('Incoming 2026'!$J$2:$J$984,Summary!A88) -> 166 | C88: =COUNTIF('Outgoing 2026'!$J$2:$J$906,Summary!A88) -> 259 | N88: WQA | O88: =COUNTIF('Incoming 2026'!$R$2:$R$984,Summary!N88) -> 2 | P88: =COUNTIF('Outgoing 2026'!$M$2:$M$900,Summary!N88) -> 11
A89: Administrasi & Dokumentasi | B89: =COUNTIF('Incoming 2026'!$J$2:$J$984,Summary!A89) -> 3 | C89: =COUNTIF('Outgoing 2026'!$J$2:$J$906,Summary!A89) -> 4 | N89: Legal | O89: =COUNTIF('Incoming 2026'!$R$2:$R$984,Summary!N89) -> 2 | P89: =COUNTIF('Outgoing 2026'!$M$2:$M$900,Summary!N89) -> 21
A90: Sambungan Langsung | B90: =COUNTIF('Incoming 2026'!$J$2:$J$984,Summary!A90) -> 29 | C90: =COUNTIF('Outgoing 2026'!$J$2:$J$906,Summary!A90) -> 198 | N90: Permit | O90: =COUNTIF('Incoming 2026'!$R$2:$R$984,Summary!N90) -> 26 | P90: =COUNTIF('Outgoing 2026'!$M$2:$M$900,Summary!N90) -> 35
A91: Support
A92: Kontrak & Legal | B92: =COUNTIF('Incoming 2026'!$J$2:$J$984,Summary!A92) -> 20 | C92: =COUNTIF('Outgoing 2026'!$J$2:$J$906,Summary!A92) -> 31 | N92: GF
A93: Keuangan & Pembayaran | B93: =COUNTIF('Incoming 2026'!$J$2:$J$984,Summary!A93) -> 0 | C93: =COUNTIF('Outgoing 2026'!$J$2:$J$906,Summary!A93) -> 0
A94: Perizinan | B94: =COUNTIF('Incoming 2026'!$J$2:$J$984,Summary!A94) -> 10 | C94: =COUNTIF('Outgoing 2026'!$J$2:$J$906,Summary!A94) -> 33
A95: Monitoring & Pelaporan | B95: =COUNTIF('Incoming 2026'!$J$2:$J$984,Summary!A95) -> 37 | C95: =COUNTIF('Outgoing 2026'!$J$2:$J$906,Summary!A95) -> 29
A96: HSE | B96: =COUNTIF('Incoming 2026'!$J$2:$J$984,Summary!A96) -> 140 | C96: =COUNTIF('Outgoing 2026'!$J$2:$J$906,Summary!A96) -> 30
A97: Koordinasi & Sosialisasi | B97: =COUNTIF('Incoming 2026'!$J$2:$J$984,Summary!A97) -> 16 | C97: =COUNTIF('Outgoing 2026'!$J$2:$J$906,Summary!A97) -> 63
A98: Manajemen risiko | B98: =COUNTIF('Incoming 2026'!$J$2:$J$984,Summary!A98) -> 0 | C98: =COUNTIF('Outgoing 2026'!$J$2:$J$906,Summary!A98) -> 2
A104: PIC Surat Keluar 2026
A105: Dept | B105: Incoming | C105: Open | D105: Level 1 | E105: Level 2 | F105: lewat 30d | G105: lewat 14d | H105: lewat 7d | I105: > 30 | J105: > 14 | K105: > 7 | L105: < 7
A106: PMO Infill | B106: =COUNTIF('Incoming 2026'!$R$2:$R$984,Summary!A106) -> 109 | C106: =COUNTIFS('Incoming 2026'!$R$2:$R$984,Summary!A106,'Incoming 2026'!$L$2:$L$984,$C$105) -> 11 | D106: =COUNTIFS('Incoming 2026'!$R$2:$R$984,Summary!A106,'Incoming 2026'!$M$2:$M$984,$D$105) -> 8 | E106: =COUNTIFS('Incoming 2026'!$R$2:$R$984,Summary!A106,'Incoming 2026'!$M$2:$M$984,$E$105) -> 3 | F106: =COUNTIFS('Incoming 2026'!$R$2:$R$984,Summary!A106,'Incoming 2026'!$V$2:$V$984,$F$105) -> 2 | G106: =COUNTIFS('Incoming 2026'!$R$2:$R$984,Summary!A106,'Incoming 2026'!$V$2:$V$984,$G$105) -> 0 | H106: =COUNTIFS('Incoming 2026'!$R$2:$R$984,Summary!A106,'Incoming 2026'!$V$2:$V$984,$H$105) -> 0 | I106: 16 | J106: 15 | K106: 1
A107: Compliance | B107: =COUNTIF('Incoming 2026'!$R$2:$R$984,Summary!A107) -> 62 | C107: =COUNTIFS('Incoming 2026'!$R$2:$R$984,Summary!A107,'Incoming 2026'!$L$2:$L$984,$C$105) -> 1 | D107: =COUNTIFS('Incoming 2026'!$R$2:$R$984,Summary!A107,'Incoming 2026'!$M$2:$M$984,$D$105) -> 1 | E107: =COUNTIFS('Incoming 2026'!$R$2:$R$984,Summary!A107,'Incoming 2026'!$M$2:$M$984,$E$105) -> 0 | F107: =COUNTIFS('Incoming 2026'!$R$2:$R$984,Summary!A107,'Incoming 2026'!$V$2:$V$984,$F$105) -> 0 | G107: =COUNTIFS('Incoming 2026'!$R$2:$R$984,Summary!A107,'Incoming 2026'!$V$2:$V$984,$G$105) -> 0 | H107: =COUNTIFS('Incoming 2026'!$R$2:$R$984,Summary!A107,'Incoming 2026'!$V$2:$V$984,$H$105) -> 0 | I107: 0 | J107: 0 | K107: 0
A108: Finance | B108: =COUNTIF('Incoming 2026'!$R$2:$R$984,Summary!A108) -> 7 | C108: =COUNTIFS('Incoming 2026'!$R$2:$R$984,Summary!A108,'Incoming 2026'!$L$2:$L$984,$C$105) -> 0 | D108: =COUNTIFS('Incoming 2026'!$R$2:$R$984,Summary!A108,'Incoming 2026'!$M$2:$M$984,$D$105) -> 0 | E108: =COUNTIFS('Incoming 2026'!$R$2:$R$984,Summary!A108,'Incoming 2026'!$M$2:$M$984,$E$105) -> 0 | F108: =COUNTIFS('Incoming 2026'!$R$2:$R$984,Summary!A108,'Incoming 2026'!$V$2:$V$984,$F$105) -> 1 | G108: =COUNTIFS('Incoming 2026'!$R$2:$R$984,Summary!A108,'Incoming 2026'!$V$2:$V$984,$G$105) -> 0 | H108: =COUNTIFS('Incoming 2026'!$R$2:$R$984,Summary!A108,'Incoming 2026'!$V$2:$V$984,$H$105) -> 0 | I108: 1 | J108: 1 | K108: 0
A109: PMO NC | B109: =COUNTIF('Incoming 2026'!$R$2:$R$984,Summary!A109) -> 28 | C109: =COUNTIFS('Incoming 2026'!$R$2:$R$984,Summary!A109,'Incoming 2026'!$L$2:$L$984,$C$105) -> 1 | D109: =COUNTIFS('Incoming 2026'!$R$2:$R$984,Summary!A109,'Incoming 2026'!$M$2:$M$984,$D$105) -> 0 | E109: =COUNTIFS('Incoming 2026'!$R$2:$R$984,Summary!A109,'Incoming 2026'!$M$2:$M$984,$E$105) -> 1 | F109: =COUNTIFS('Incoming 2026'!$R$2:$R$984,Summary!A109,'Incoming 2026'!$V$2:$V$984,$F$105) -> 2 | G109: =COUNTIFS('Incoming 2026'!$R$2:$R$984,Summary!A109,'Incoming 2026'!$V$2:$V$984,$G$105) -> 0 | H109: =COUNTIFS('Incoming 2026'!$R$2:$R$984,Summary!A109,'Incoming 2026'!$V$2:$V$984,$H$105) -> 1 | I109: 2 | J109: 0 | K109: 2
A110: PMO Cyclical | B110: =COUNTIF('Incoming 2026'!$R$2:$R$984,Summary!A110) -> 19 | C110: =COUNTIFS('Incoming 2026'!$R$2:$R$984,Summary!A110,'Incoming 2026'!$L$2:$L$984,$C$105) -> 1 | D110: =COUNTIFS('Incoming 2026'!$R$2:$R$984,Summary!A110,'Incoming 2026'!$M$2:$M$984,$D$105) -> 1 | E110: =COUNTIFS('Incoming 2026'!$R$2:$R$984,Summary!A110,'Incoming 2026'!$M$2:$M$984,$E$105) -> 0 | F110: =COUNTIFS('Incoming 2026'!$R$2:$R$984,Summary!A110,'Incoming 2026'!$V$2:$V$984,$F$105) -> 0 | G110: =COUNTIFS('Incoming 2026'!$R$2:$R$984,Summary!A110,'Incoming 2026'!$V$2:$V$984,$G$105) -> 0 | H110: =COUNTIFS('Incoming 2026'!$R$2:$R$984,Summary!A110,'Incoming 2026'!$V$2:$V$984,$H$105) -> 0 | I110: 0 | J110: 0 | K110: 0
A111: PMO; Permit | B111: =COUNTIF('Incoming 2026'!$R$2:$R$984,Summary!A111) -> 0 | C111: =COUNTIFS('Incoming 2026'!$R$2:$R$984,Summary!A111,'Incoming 2026'!$L$2:$L$984,$C$105) -> 0 | D111: =COUNTIFS('Incoming 2026'!$R$2:$R$984,Summary!A111,'Incoming 2026'!$M$2:$M$984,$D$105) -> 0 | E111: =COUNTIFS('Incoming 2026'!$R$2:$R$984,Summary!A111,'Incoming 2026'!$M$2:$M$984,$E$105) -> 0 | F111: =COUNTIFS('Incoming 2026'!$R$2:$R$984,Summary!A111,'Incoming 2026'!$V$2:$V$984,$F$105) -> 0 | G111: =COUNTIFS('Incoming 2026'!$R$2:$R$984,Summary!A111,'Incoming 2026'!$V$2:$V$984,$G$105) -> 0 | H111: =COUNTIFS('Incoming 2026'!$R$2:$R$984,Summary!A111,'Incoming 2026'!$V$2:$V$984,$H$105) -> 0 | I111: 0 | J111: 0 | K111: 0
A112: Planning | B112: =COUNTIF('Incoming 2026'!$R$2:$R$984,Summary!A112) -> 50 | C112: =COUNTIFS('Incoming 2026'!$R$2:$R$984,Summary!A112,'Incoming 2026'!$L$2:$L$984,$C$105) -> 19 | D112: =COUNTIFS('Incoming 2026'!$R$2:$R$984,Summary!A112,'Incoming 2026'!$M$2:$M$984,$D$105) -> 0 | E112: =COUNTIFS('Incoming 2026'!$R$2:$R$984,Summary!A112,'Incoming 2026'!$M$2:$M$984,$E$105) -> 17 | F112: =COUNTIFS('Incoming 2026'!$R$2:$R$984,Summary!A112,'Incoming 2026'!$V$2:$V$984,$F$105) -> 16 | G112: =COUNTIFS('Incoming 2026'!$R$2:$R$984,Summary!A112,'Incoming 2026'!$V$2:$V$984,$G$105) -> 0 | H112: =COUNTIFS('Incoming 2026'!$R$2:$R$984,Summary!A112,'Incoming 2026'!$V$2:$V$984,$H$105) -> 3 | I112: 2 | J112: 8 | K112: 0
A113: PGO | B113: =COUNTIF('Incoming 2026'!$R$2:$R$984,Summary!A113) -> 22 | C113: =COUNTIFS('Incoming 2026'!$R$2:$R$984,Summary!A113,'Incoming 2026'!$L$2:$L$984,$C$105) -> 7 | D113: =COUNTIFS('Incoming 2026'!$R$2:$R$984,Summary!A113,'Incoming 2026'!$M$2:$M$984,$D$105) -> 7 | E113: =COUNTIFS('Incoming 2026'!$R$2:$R$984,Summary!A113,'Incoming 2026'!$M$2:$M$984,$E$105) -> 0 | F113: =COUNTIFS('Incoming 2026'!$R$2:$R$984,Summary!A113,'Incoming 2026'!$V$2:$V$984,$F$105) -> 1 | G113: =COUNTIFS('Incoming 2026'!$R$2:$R$984,Summary!A113,'Incoming 2026'!$V$2:$V$984,$G$105) -> 0 | H113: =COUNTIFS('Incoming 2026'!$R$2:$R$984,Summary!A113,'Incoming 2026'!$V$2:$V$984,$H$105) -> 0 | I113: 0 | J113: 0 | K113: 0
A114: WQA | B114: =COUNTIF('Incoming 2026'!$R$2:$R$984,Summary!A114) -> 2 | C114: =COUNTIFS('Incoming 2026'!$R$2:$R$984,Summary!A114,'Incoming 2026'!$L$2:$L$984,$C$105) -> 0 | D114: =COUNTIFS('Incoming 2026'!$R$2:$R$984,Summary!A114,'Incoming 2026'!$M$2:$M$984,$D$105) -> 0 | E114: =COUNTIFS('Incoming 2026'!$R$2:$R$984,Summary!A114,'Incoming 2026'!$M$2:$M$984,$E$105) -> 0 | F114: =COUNTIFS('Incoming 2026'!$R$2:$R$984,Summary!A114,'Incoming 2026'!$V$2:$V$984,$F$105) -> 0 | G114: =COUNTIFS('Incoming 2026'!$R$2:$R$984,Summary!A114,'Incoming 2026'!$V$2:$V$984,$G$105) -> 0 | H114: =COUNTIFS('Incoming 2026'!$R$2:$R$984,Summary!A114,'Incoming 2026'!$V$2:$V$984,$H$105) -> 0 | I114: 0 | J114: 0 | K114: 0
A115: Legal | B115: =COUNTIF('Incoming 2026'!$R$2:$R$984,Summary!A115) -> 2 | C115: =COUNTIFS('Incoming 2026'!$R$2:$R$984,Summary!A115,'Incoming 2026'!$L$2:$L$984,$C$105) -> 0 | D115: =COUNTIFS('Incoming 2026'!$R$2:$R$984,Summary!A115,'Incoming 2026'!$M$2:$M$984,$D$105) -> 0 | E115: =COUNTIFS('Incoming 2026'!$R$2:$R$984,Summary!A115,'Incoming 2026'!$M$2:$M$984,$E$105) -> 0 | F115: =COUNTIFS('Incoming 2026'!$R$2:$R$984,Summary!A115,'Incoming 2026'!$V$2:$V$984,$F$105) -> 0 | G115: =COUNTIFS('Incoming 2026'!$R$2:$R$984,Summary!A115,'Incoming 2026'!$V$2:$V$984,$G$105) -> 0 | H115: =COUNTIFS('Incoming 2026'!$R$2:$R$984,Summary!A115,'Incoming 2026'!$V$2:$V$984,$H$105) -> 0 | I115: 0 | J115: 0 | K115: 0
A116: Permit | B116: =COUNTIF('Incoming 2026'!$R$2:$R$984,Summary!A116) -> 26 | C116: =COUNTIFS('Incoming 2026'!$R$2:$R$984,Summary!A116,'Incoming 2026'!$L$2:$L$984,$C$105) -> 7 | D116: =COUNTIFS('Incoming 2026'!$R$2:$R$984,Summary!A116,'Incoming 2026'!$M$2:$M$984,$D$105) -> 3 | E116: =COUNTIFS('Incoming 2026'!$R$2:$R$984,Summary!A116,'Incoming 2026'!$M$2:$M$984,$E$105) -> 4 | F116: =COUNTIFS('Incoming 2026'!$R$2:$R$984,Summary!A116,'Incoming 2026'!$V$2:$V$984,$F$105) -> 1 | G116: =COUNTIFS('Incoming 2026'!$R$2:$R$984,Summary!A116,'Incoming 2026'!$V$2:$V$984,$G$105) -> 0 | H116: =COUNTIFS('Incoming 2026'!$R$2:$R$984,Summary!A116,'Incoming 2026'!$V$2:$V$984,$H$105) -> 0 | I116: 0 | J116: 0 | K116: 0
A117: PMO Infill / PMO TM | B117: =COUNTIF('Incoming 2026'!$R$2:$R$984,Summary!A117) -> 0 | C117: =COUNTIFS('Incoming 2026'!$R$2:$R$984,Summary!A117,'Incoming 2026'!$L$2:$L$984,$C$105) -> 0 | D117: =COUNTIFS('Incoming 2026'!$R$2:$R$984,Summary!A117,'Incoming 2026'!$M$2:$M$984,$D$105) -> 0 | E117: =COUNTIFS('Incoming 2026'!$R$2:$R$984,Summary!A117,'Incoming 2026'!$M$2:$M$984,$E$105) -> 0 | F117: =COUNTIFS('Incoming 2026'!$R$2:$R$984,Summary!A117,'Incoming 2026'!$V$2:$V$984,$F$105) -> 0 | G117: =COUNTIFS('Incoming 2026'!$R$2:$R$984,Summary!A117,'Incoming 2026'!$V$2:$V$984,$G$105) -> 0 | H117: =COUNTIFS('Incoming 2026'!$R$2:$R$984,Summary!A117,'Incoming 2026'!$V$2:$V$984,$H$105) -> 0 | I117: 2 | J117: 0 | K117: 2
... A119: HSE | B119: =COUNTIF('Incoming 2026'!$R$2:$R$984,Summary!A119) -> 135 | C119: =COUNTIFS('Incoming 2026'!$R$2:$R$984,Summary!A119,'Incoming 2026'!$L$2:$L$984,$C$105) -> 13 | D119: =COUNTIFS('Incoming 2026'!$R$2:$R$984,Summary!A119,'Incoming 2026'!$M$2:$M$984,$D$105) -> 13 | E119: =COUNTIFS('Incoming 2026'!$R$2:$R$984,Summary!A119,'Incoming 2026'!$M$2:$M$984,$E$105) -> 0 | F119: =COUNTIFS('Incoming 2026'!$R$2:$R$984,Summary!A119,'Incoming 2026'!$V$2:$V$984,$F$105) -> 0 | G119: =COUNTIFS('Incoming 2026'!$R$2:$R$984,Summary!A119,'Incoming 2026'!$V$2:$V$984,$G$105) -> 0 | H119: =COUNTIFS('Incoming 2026'!$R$2:$R$984,Summary!A119,'Incoming 2026'!$V$2:$V$984,$H$105) -> 0 | I119: 0 | J119: 1 | K119: 3

Sheet Reminder
A1: Reminder Surat Masuk
A2: No | B2: Nomor Surat | C2: Perihal | D2: Keterangan | E2: PIC | F2: Due Date | G2: Status
A3: 1 | B3: e-80724/PP.01.02 | C3: Teguran atas Ketidaksesuaian Pelaksanaan Pengurugan dan Perbaikan Bekas Galian yang Berdampak pada Gangguan Lalu Lintas dan Keterlambatan Penyelesaian Proyek pada Program Infill SPAM Buaran III | D3: PAM JAYA menemukan 168 titik bekas galian yang belum diperbaiki sesuai standar, penerapan K3 yang belum memadai, gangguan lalu lintas, serta pekerjaan yang menimbulkan keluhan masyarakat dan pemberitaan negatif pada PAMJAYA (wilayah condet) | ABJ diminta untuk segera perbaikin hal tersebut | E3: PMO Infill - Topan | F3: 46224 | G3: =_xlfn.XLOOKUP(B3,'Incoming 2026'!$B$2:$B$531,'Incoming 2026'!$L$2:$L$531) -> Open
A4: 2 | B4: e-81788/PP.01.05 | C4: Permintaan Klarifikasi Pelaksanaan Pekerjaan IBP Basura | D4: PAM JAYA mempertanyakan dan meminta justifikasi teknis yang lengkap atas perubahan desain pompa pada proyek IBP Basura dari pompa sentrifugal menjadi pompa submersible, karena perubahan tersebut dinilai belum didukung penjelasan dan dokumen yang memadai. | E4: PMO Infill-Yodi | F4: 46224 | G4: =_xlfn.XLOOKUP(B4,'Incoming 2026'!$B$2:$B$531,'Incoming 2026'!$L$2:$L$531) -> Open
A5: 3 | B5: 2633/PS.04.04/EKST/VI/2026 | C5: Teguran Pemenuhan Kewajiban Penyelesaian Paket Pekerjaaan Ketiga Proyek Greenfield Pada Saat Tanggal Operasi Komersial atau 5 April 2026 | D5: PAM JAYA menegaskan bahwa dari 108 pekerjaan hanya 91 yang diakui selesai, masih terdapat 42 pekerjaan yang belum selesai, dan meminta PT ABJ segera menuntaskan seluruh pekerjaan beserta pemenuhan dokumen, kualitas, dan pelaporan progres. | E5: PMO Infill-Suci | F5: 46224 | G5: =_xlfn.XLOOKUP(B5,'Incoming 2026'!$B$2:$B$531,'Incoming 2026'!$L$2:$L$531) -> Open
A6: 4 | B6: E-73652/PP.01.05 | C6: Teguran atas Bina Marga Nomor 266/KR.02.00 perihal Pelaksanaan Pekerjaan Galian Utilitas Pipa Air Bersih | D6: Teguran atas Bina Marga Nomor 266/KR.02.00 perihal Pelaksanaan Pekerjaan Galian Utilitas Pipa Air Bersih | E6: PMO Infill; PMO TM-Suci; Jusman | F6: 46224 | G6: =_xlfn.XLOOKUP(B6,'Incoming 2026'!$B$2:$B$531,'Incoming 2026'!$L$2:$L$531) -> Open
A7: 5 | B7: e-76093/PP.01.02 | C7: Teguran atas Pengawasan Aspek Keselamatan dan Kesehatan Kerja (K3) pada Proyek Bundling | D7: PAM JAYA menilai pengawasan K3 oleh KPI belum optimal dan meminta KPI memperketat pengawasan serta memastikan kepatuhan K3 pada seluruh proyek bundling. | E7: HSE-Irsan | F7: 46224 | G7: =_xlfn.XLOOKUP(B7,'Incoming 2026'!$B$2:$B$531,'Incoming 2026'!$L$2:$L$531) -> Open
A8: 6 | B8: e-75059/PP.01.05 | C8: Permintaan Penjelasan dan Klarifikasi atas permasalahan pada Proyek SPAM Buaran Hulu di RW 03 Kelurahan Margahayu Kecamatan Bekasi Timur Kota Bekasi | D8: ABJ diminta menyelesaikan permasalahan, perizinan, dan koordinasi proyek SPAM Buaran Hulu serta memastikan kepatuhan terhadap ketentuan yang berlaku. | E8: PMO B3 Hulu - A. Yudi | F8: 46224 | G8: =_xlfn.XLOOKUP(B8,'Incoming 2026'!$B$2:$B$531,'Incoming 2026'!$L$2:$L$531) -> Open
A9: 7 | B9: e-76341/PP.01.02 | C9: Teguran atas Ketidak-sesuaian Pelaksanaan Pengurugan dan Perbaikan Bekas Galian yang Berdampak pada Gangguan Lalu Lintas, Keterlambatan Penyelesaian Proyek, serta Kewajiban Penggantian Kompensasi Pohon Terdampak Pekerjaan Pemasangan Pipa pada Program Infill SPAM Buaran III | D9: PT ABJ dinilai belum optimal dalam pelaksanaan pekerjaan, mitigasi lalu lintas, K3, dan perizinan. PAM JAYA menegur dan meminta PT ABJ untuk segera menindaklanjuti perbaikan 98 temuan, mengganti pohon terdampak, mempercepat penyelesaian proyek, meningkatkan keselamatan kerja | E9: PMO Infill - Topan | F9: 46224 | G9: =_xlfn.XLOOKUP(B9,'Incoming 2026'!$B$2:$B$531,'Incoming 2026'!$L$2:$L$531) -> Open
A10: 8 | B10: e-76737/PP.01.02 | C10: Teguran atas Kelalaian PT ABJ atas Pelaksanaan Pekerjaan Yang Tidak Sesuai dengan Praktik Industri Yang Baik pada di Jalan Raya Taman Mini pada Proyek Buaran Hilir | D10: ABJ dinilai lalai dalam proyek Buaran Hilir menyebabkan banjir dan gangguan lalu lintas, Penyebab: tidak sesuai prosedur, kurang pengecekan, dan lambat penanganan. Pelanggaran akan ditindaklanjuti sesuai perjanjian. | E10: PMO Infill-Topan | F10: 46224 | G10: =_xlfn.XLOOKUP(B10,'Incoming 2026'!$B$2:$B$531,'Incoming 2026'!$L$2:$L$531) -> Open
A11: 9 | B11: e-80737/PS.04.06 | C11: Pembangunan Sistem Hilir IPA Condet dan Sistem Hilir IPA Semanan | D11: ABJ diminta menyampaikan usulan program konstruksi untuk sistem hilir IPA Semanan dan IPA Condet dan memberikan rekomendasi pemodelan hidrolis jaringan dan skenario desain jaringan pipa yang terintegrasi | E11: Planning - Aji S | F11: 46224 | G11: =_xlfn.XLOOKUP(B11,'Incoming 2026'!$B$2:$B$531,'Incoming 2026'!$L$2:$L$531) -> Open
A12: 10 | B12: 328/SCI-KPI/VII/2026 | C12: Permohonan Informasi Terkait Insiden Kecelakaan Kerja Lokasi Chamber P6 STA 2+200 Jalan Raya Mabes Hankam – Buaran 3 Hilir | D12: ABJ diminta menyampaikan informasi lengkap terkait insiden fatality, hasil investigasi, kepatuhan K3, dan rencana tindak lanjut. | E12: HSE - Suhendro PMO TM - Jusman | F12: 46241 | G12: =_xlfn.XLOOKUP(B12,'Incoming 2026'!$B$2:$B$531,'Incoming 2026'!$L$2:$L$531) -> Open
A13: 11 | B13: 2448/PS.04.02/EKST/VI/2026 | C13: Tindak Lanjut Pemenuhan Kewajiban Asuransi Berdasarkan A&PK Bundling | D13: ABJ diminta untuk menyampaikan seluruh dokumen dan melakukan perbaikan sebagaimana dimaksud dalam surat ini paling lambat 7 hari setelah surat ini diterima | E13: PMO Infill - Suci PMO TM - Jusman | F13: 46241 | G13: =_xlfn.XLOOKUP(B13,'Incoming 2026'!$B$2:$B$531,'Incoming 2026'!$L$2:$L$531) -> Open
A14: 12 | B14: e-84089/PP.01.05 | C14: Permintaan Kepatuhan Terkait Tahapan Pekerjaan Konstruksi Pada Proyek Greenfield | D14: ABJ diminta berkomitmen melaksanakan pekerjaan konstruksi Fasilitas Baru sesuai ketentuan Perjanjian Kerja Sama Bundling dan peraturan yang berlaku, serta menegaskan bahwa setiap pelanggaran akan ditindaklanjuti sesuai ketentuan perjanjian. | E14: PMO Infill - Suci PMO TM - Jusman | F14: 46241 | G14: =_xlfn.XLOOKUP(B14,'Incoming 2026'!$B$2:$B$531,'Incoming 2026'!$L$2:$L$531) -> Open
... A26: 24 | B26: 4407/KU.01.08/EKST/IX/2026 | C26: Permohonan Pembayaran atas Pemanfaatan Lahan milik PPPK Kemayoran untuk Pembangunan Reservoir Kebon Kosong Project SPAM Jatiluhur Hilir | D26: PAM JAYA meminta ABJ untuk: (a) Melakukan pembayaran atas pemanfaatan lahan sesuai Amandemen & Perjanjian Kerja Sama Bundling, paling lambat 29 September 2026. (b) Menyampaikan bukti pembayaran ke PAM JAYA maksimal 3 hari setelah pembayaran dilakukan. (c) Memastikan pemenuhan perizinan agar pelaksanaan proyek tidak terlambat/terganggu (kewajiban ABJ). | E26: Permit - Rudy | F26: 46296 | G26: =_xlfn.XLOOKUP(B26,'Incoming 2026'!$B$2:$B$531,'Incoming 2026'!$L$2:$L$531) -> Open
A27: 25 | B27: 4398/PS.04.01/EKST/IX/2026 | C27: Permintaan Tindak Lanjut Pembangunan Jaringan Pipa Pendukung Sistem DC Semanan SPAM Karian Serpong Hilir | E27: PMO Infill - Ervin | F27: 46296 | G27: =_xlfn.XLOOKUP(B27,'Incoming 2026'!$B$2:$B$531,'Incoming 2026'!$L$2:$L$531) -> Open
A28: 26 | B28: 4521/PS.04.04/EKST/IX/2026 | C28: Teguran Penerapan Aspek Keselamatan dan Kesehatan Kerja ("K3") Proyek Greenfield Jatiluhur Hilir | D28: Inspeksi K3 15 Sep 2026. Temuan: pit galian tidak memperhatikan aspek lingkungan; proteksi galian tidak standar; kerapian area; rambu belum lengkap; flagman tidak memadai (1 personel); pekerja tanpa APD; pengawasan kontraktor tidak berkala; bekas galian belum dirapikan. | E28: HSE - Suhendro | F28: 46296 | G28: =_xlfn.XLOOKUP(B28,'Incoming 2026'!$B$2:$B$531,'Incoming 2026'!$L$2:$L$531) -> Open
A29: 27 | B29: 4520/PS.04.04/EKST/IX/2026 | C29: Teguran Penerapan Aspek Keselamatan dan Kesehatan Kerja ("K3") Proyek Jatiluhur Hilir Infil Paket 070 Rorotan 9, Malaka 1,2,3 & Rorotan 11 dan 077 | D29: Inspeksi K3 15 Sep 2026. Temuan: stiker belum sesuai kesepakatan; housekeeping tanah galian; pengaman galian tidak sesuai standar PAM JAYA; rambu belum lengkap; tidak ada flagman. | E29: HSE - Suhendro | F29: 46296 | G29: =_xlfn.XLOOKUP(B29,'Incoming 2026'!$B$2:$B$531,'Incoming 2026'!$L$2:$L$531) -> Open
A30: 28 | B30: 4532/PS.04.04/EKST/IX/2026 | C30: Teguran atas pelaksanaan pemenuhan perizinan proyek bundling TOK 5 Oktober 2026 | D30: Hasil monitoring dashboard 3 Sep 2026: IPPJU 97 terbit, 5 upload Jakevo, 3 tidak perlu; Crossing Sungai BBWS Cilcis: 1 pemenuhan data, 2 tunggu survei, 5 proses rekomtek, 1 terbit; Crossing Kali Jakarta (SDA DKI): 2 tunggu survei UP4, 4 proses SSRD, 35 proses rekomtek, 12 rekomtek terbit; Crossing Tol 2 terbit; Crossing Rel KA 2 terbit. | E30: Permit - Rudy | F30: 46296 | G30: =_xlfn.XLOOKUP(B30,'Incoming 2026'!$B$2:$B$531,'Incoming 2026'!$L$2:$L$531) -> Open
A31: 29 | B31: 4523/PS.04.04/EKST/IX/2026 | C31: Teguran Keras Penerapan Aspek Keselamatan dan Kesehatan Kerja ("K3") Proyek Greenfield Jatiluhur Hilir | D31: Inspeksi K3 11–12 Sep 2026. Temuan: proteksi galian belum standar; kerapian area; rambu belum lengkap; insiden kendaraan amblas di area kerja akibat ketidakpatuhan K3. | E31: HSE - Suhendro | F31: 46296 | G31: =_xlfn.XLOOKUP(B31,'Incoming 2026'!$B$2:$B$531,'Incoming 2026'!$L$2:$L$531) -> Open
A32: 30 | B32: 4647/PS.04.01/EKST/IX/2026 | C32: Permintaan Kelengkapan Dokumen atas Permohonan Sewa Infrastruktur pada Satuan Kerja BBWS Pekerjaan Jenderal Citarum Umum Sumber Kementerian Direktorat Daya Air | D32: Menindaklanjuti Surat Kementerian PU PS0301-AV/964 (20 Okt 2025) atas usulan sewa BMN (tanah untuk jalan nasional) untuk intake Buaran 3 Hulu. PAM JAYA diminta melengkapi: usulan faktor penyesuai sewa (dgn pertimbangan instansi teknis), proposal/studi kelayakan (rencana usaha, operasional, keuangan, desain & layout bangunan), dan surat rekomendasi kelayakan dari instansi teknis. | E32: PMO B3 Hulu - A. Yudi | F32: 46296 | G32: =_xlfn.XLOOKUP(B32,'Incoming 2026'!$B$2:$B$531,'Incoming 2026'!$L$2:$L$531) -> Open
A33: 31 | B33: 4621/PS.04.04/EKST/IX/2026 | C33: Teguran Penerapan Aspek Keselamatan dan Kesehatan Kerja ("K3") Proyek Greenfield Jatiluhur Hilir | D33: Inspeksi K3 15 Sep 2026. Temuan: pit galian tidak memperhatikan aspek lingkungan; proteksi galian tidak standar; kerapian area; rambu belum lengkap; flagman tidak memadai (1 personel); pekerja tanpa APD; pengawasan kontraktor tidak berkala; bekas galian belum dirapikan. | E33: HSE - Suhendro | F33: 46296 | G33: =_xlfn.XLOOKUP(B33,'Incoming 2026'!$B$2:$B$531,'Incoming 2026'!$L$2:$L$531) -> Open
A34: 32 | B34: 4622/PS.04.04/EKST/IX/2026 | C34: Teguran Penerapan Aspek Keselamatan dan Kesehatan Kerja ("K3") Proyek Jatiluhur Hilir | D34: Temuan inspeksi K3 tanggal 16 September 2026. Temuan : Pagar Proyek Daur Ulang (PPDU) belum sesuai standar PAM JAYA; APD; Galian; Rambu K3; Papan informasi proyek belum ada | E34: HSE - Suhendro | F34: 46296 | G34: =_xlfn.XLOOKUP(B34,'Incoming 2026'!$B$2:$B$531,'Incoming 2026'!$L$2:$L$531) -> Open
A35: 33 | B35: 3821/PS.04.01/EKSI/VIII/2026 | C35: Permintaan Pembaharuan Program Konstruksi | D35: Suplai air curah SPAM Karian-Serpong (jadwal Lampiran 24 A&R Greenfield: April 2027) terlambat menurut Surat PUPR 751, belum ada kepastian. Mengacu Pergub 48/2025 & Rencana Bisnis PAM JAYA 2025–2029, PAM JAYA menargetkan IPA baru: IPA Semanan 200 lps, IPA Condet 1.000 lps, IPA Polor 1.500 lps. (Menjawab Surat ABJ 0821 tgl 7 Okt 2025 yg meminta arahan program konstruksi terkait suplai Karian-Serpong.) | E35: Planning - Aji S | F35: 46296 | G35: =_xlfn.XLOOKUP(B35,'Incoming 2026'!$B$2:$B$531,'Incoming 2026'!$L$2:$L$531) -> Info
A36: 34 | B36: 4690/PS.04.04/EKSI/IX/2026 | C36: Surat Teguran atas Kelalaian PT ABJ atas Pelaksanaan Pekerjaan Yang Tidak Sesuai dengan Praktik Industri Yang Baik pada di Jalan Elang dan Jalan Merpati pada Proyek Buaran III Hilir | D36: teguran atas insiden banjir/genangan akibat pekerjaan interkoneksi JDU–JDB–JDL dan meminta ABJ melakukan investigasi akar masalah, menyusun serta melaksanakan tindakan perbaikan dan pencegahan, melakukan pengecekan sarana secara berkala, meningkatkan kehati-hatian dan respons terhadap insiden, memastikan kejadian tidak terulang, serta menyampaikan dokumentasi sebelum dan sesudah perbaikan. | E36: PMO Infill - Topan
A37: 35 | B37: 4689/PS.04.04/EKSI/IX/2026 | C37: Teguran Pelaksanaan Pekerjaan Pemasangan Pipa Yang Tidak Sesuai Standar pada Trunkmain P7 dan S5 SPAM Buaran III Hilir | D37: teguran atas pelaksanaan pekerjaan pemasangan pipa Trunkmain P7 dan S5 yang mengubah metode menjadi open cut tanpa menyampaikan Justifikasi Teknis dan Finansial terlebih dahulu, serta meminta ABJ menghentikan sementara pekerjaan DN 800 open cut, melakukan evaluasi internal, menyampaikan corrective & preventive action, dan memastikan setiap perubahan pekerjaan mendapat justifikasi serta persetujuan sesuai ketentuan PKS Bundling | E37: PMO TM - Jusman
A38: 36 | B38: 4080/PS.04.01/EKST/VIII/2026 | C38: Permintaan Klarifikasi terhadap Perbedaan Ukuran Material Pada Program Rehabilitasi 46331 | D38: ABJ diminta mengklarifikasi perbedaan ukuran material antara desain MC-0 dan kondisi aktual pada Program Rehabilitasi 46331, serta melengkapi dokumen factory, metode handling, justifikasi teknis dan finansial, perhitungan dalam BIM, serta memastikan proses quality control dan pemeriksaan material on-site sesuai ketentuan | E38: PMO Cyclical - Agus H
A39: 37 | B39: 4551/PS.04.01/EKST/IX/2026 | C39: 1(satu) Berkas Permintaan Tindak Lanjut atas Surat PAM JAYA Nomor: 4167/PP.01.02/EKST/IX/2026 Tanggal 2 September 2026 dan Permintaan Rencana Pemenuhan Kewajiban Knowledge Transfer Tanggal Operasi Komersial Fasilitas Distribusi Baru Paket Pekerjaan Keempat – TOK Oktober 2026 | D39: ABJ diminta menindaklanjuti kewajiban Knowledge Transfer kepada karyawan PAM JAYA sesuai PKS Greenfield, memberikan klarifikasi atas Surat ABJ 1064, serta memenuhi seluruh permintaan yang telah disampaikan melalui Surat PAM JAYA 4167 dan e-83482 | E39: Compliance - A. Levi
A40: 38 | B40: 4669/PS.04.04/EKST/IX/2026 | C40: Teguran atas Keterlambatan Penyampaian Dokumen Persyaratan Penyelesaian Proyek Greenfield atas seluruh Pekerjaan Fasilitas Distribusi Baru Yang Dijadwalkan untuk Paket Pekerjaan Kedua Tanggal Operasi Komersial 5 Oktober 2025 | D40: Teguran atas atas keterlambatan penyampaian DP3 untuk pekerjaan Fasilitas Distribusi Baru TOK 5 Oktober 2025, di mana dari 82 subprogram yang telah MC 100, baru 81 DP3 disampaikan dan 54 di antaranya melewati SLA. ABJ diminta segera menyelesaikan seluruh pekerjaan, menyampaikan 1 DP3 yang masih tertunda melalui BIM, serta memastikan tidak terjadi keterlambatan penyelesaian pekerjaan. | E40: PGO - Lusian F
A41: 39 | B41: 4670/PS.04.04/EKST/IX/2026 | C41: Teguran atas Keterlambatan Penyampaian Dokumen Persyaratan Penyelesaian Proyek Greenfield atas seluruh Pekerjaan Fasilitas Distribusi Baru Yang Dijadwalkan untuk Paket Pekerjaan Ketiga Tanggal Operasi Komersial 5 April 2026 | D41: Teguran atas keterlambatan penyampaian DP3 untuk pekerjaan Fasilitas Distribusi Baru TOK 5 April 2026, di mana dari 71 subprogram yang telah MC 100, baru 70 DP3 disampaikan dan 43 di antaranya melewati SLA. ABJ diminta menyelesaikan seluruh pekerjaan, segera menyampaikan 1 DP3 yang masih tertunda melalui BIM, serta memastikan tidak terjadi keterlambatan penyelesaian pekerjaan TOK 5 April 2026. | E41: PGO - Lusian F
A42: 40 | B42: 4654/PS.04.04/EKST/IX/2026 | C42: Teguran Penerapan Aspek Keselamatan dan Kesehatan Kerja ("K3") Proyek Greenfield Jatiluhur Hilir | D42: LOKASI TEMUAN 1. Paket PC 146, Lokasi JL Raden Inten, Jakarta timur | E42: HSE - Suhendro
A43: 41 | B43: 4653/PS.04.04/EKSI/IX/2026 | C43: Teguran Penerapan Aspek Keselamatan dan Kesehatan Kerja ("K3") Proyek Pembangunan Fasilitas Pendukung IPA Buaran 3 | D43: LOKASI TEMUAN 1. Proyek Pembangunan gedung workshop HC&GS area | E43: HSE - Suhendro
A44: 42 | B44: 4772/PS.04.01/EKST/IX/2026 | C44: Permintaan Pemenuhan Kewajiban Penyelesaian Project Greenfield | D44: Teguran atas ketidaksesuaian pelaksanaan Seluruh Paket Pekerjaan dengan dokumen pendukung, dan meminta ABJ menyelesaikan seluruh pekerjaan serta temuan/ketidaksesuaian, mengidentifikasi kendala dan mitigasi, memastikan kualitas pekerjaan, melengkapi dokumen untuk proses tagihan, serta memperbarui progress pekerjaan setiap minggu | E44: PMO Infill/PMO TM - Suci/Jusman
A45: 43 | B45: 4652/PS.04.04/EKST/IX/2026 | C45: Teguran Pemenuhan Kewajiban Penyelesaian Paket Pekerjaaan Keempat Proyek Greenfield Pada Saat Tanggal Operasi Komersial atau 5 Oktober 2026 | D45: Teguran atas ketidaksesuaian pelaksanaan pekerjaan Fasilitas Distribusi Baru TOK 5 Oktober 2026 dengan dokumen pendukung, dan meminta ABJ menyelesaikan seluruh pekerjaan serta temuan, mengidentifikasi kendala dan mitigasi, memastikan kualitas pekerjaan, melengkapi dokumen untuk proses tagihan, serta memperbarui progress pekerjaan setiap minggu. | E45: PMO Infill/PMO TM - Suci/Jusman
A46: 44 | B46: 4499/PS.04.04/EKST/IX/2026 | C46: Permintaan Rekomendasi atas Tindak Lanjut Program yang Tidak Dapat Dilaksanakan pada Setiap Paket Pekerjaaan Fasilitas Distribusi Baru yang Dijadwalkan Periode Tahun 2025-2026 | D46: Surat PAM JAYA ke KPI terkait dari 4 paket dengan target Operasi Komersial (Apr 2025 s/d Okt 2026), ditemukan 45 program tidak terlaksana oleh ABJ per cut off 15 Sept 2026 (Paket I: 9, II: 10, III: 17, IV: 9). PAM JAYA meminta KPI memberikan rekomendasi tindak lanjut atas program yang belum terlaksana. | E46: PGO - Lusian F
A47: 45 | B47: 4398/PS.04.01/EKST/IX/2026 | C47: Permintaan Tindak Lanjut Pembangunan Jaringan Pipa Pendukung Sistem DC Semanan SPAM Karian Serpong Hilir | D47: Pipa pendukung DC Semanan termasuk dalam proyek SPAM Karian Serpong Hilir. PAM JAYA menemukan segmen kritis pada desain ABJ, yaitu pipa eksisting PVC DN 500 di Joglo–Meruya Ilir. Segmen ini sudah mengalirkan 70 lps, dan jika ditambah rencana 178 lps kapasitasnya terlampaui. Head loss-nya mencapai 4 m/km, sedangkan batasnya 2 m/km. PAM JAYA meminta ABJ mengevaluasi ulang desain, memberi rekomendasi pemodelan hidrolis, dan memastikan pekerjaan selesai sebelum uji komisioning DC Semanan pada Mei 2027. | E47: Planning - Aji S
... A64: 62 | B64: 4776/PS.04.04/EKST/IX/2026 | C64: Teguran Penerapan Aspek Keselamatan dan Kesehatan Kerja ("K3") Proyek Greenfield Jatiluhur Hilir | D64: Hasil inspeksi K3 tanggal 28 Sep 2026 di PC 146 (Jl. Raden Inten & Jl. H. Naman, Jakarta Timur). Temuan: penempatan material mengganggu pengguna jalan, area proyek tidak rapi, pekerja tanpa APD, proteksi galian tidak sesuai standar, rambu tidak lengkap. | E64: HSE - Suhendro
A65: 63 | B65: 4759/PS.04.04/EKSI/IX/2026 | C65: Teguran Penerapan Aspek Keselamatan dan Kesehatan Kerja ("K3") Proyek Greenfield Jatiluhur Hilir & Buaran Hilir PC 146 & PC 160 Ez 5 | E65: HSE - Suhendro
A66: 64 | B66: 4758/PS.04.04/EKST/IX/2026 | C66: Teguran Penerapan Aspek Keselamatan dan Kesehatan Kerja ("K3") Proyek Greenfield Jatiluhur Hilir | D66: Hasil inspeksi K3 tanggal 24 Sep 2026 di S01 (Jl. Raya Pasar Minggu) dan S11 (Jl. Pahlawan Kalibata). Temuan: PPDU tidak sesuai standar PAM JAYA, pekerja tanpa APD, sisa tanah galian belum dirapikan, rambu tidak lengkap, water barrier di pit tidak memadai, papan informasi proyek tidak ada, tidak ada flagman, housekeeping tidak dilakukan. PAM JAYA menilai ini kelalaian ABJ yang menimbulkan citra negatif dan keluhan masyarakat (rujukan Pasal 8.11 PKS Greenfield). | E66: HSE - Suhendro
A67: 65 | B67: 4524/PS.04.01/EKST/IX/2026 | C67: Permintaan Pemenuhan Kewajiban | D67: PAM JAYA menyampaikan progres seluruh paket Greenfield per 16 Sep 2026: • TOK 5 Apr 2025: 125 program (107 BAST, 2 konstruksi, 6 pemeriksaan DPPP, 1 verifikasi KPI, 9 tidak dapat dilaksanakan) • TOK 5 Okt 2025: 108 program (17 konstruksi, 81 DPPP, 10 tidak dapat dilaksanakan) • TOK 5 Apr 2026: 108 program (21 konstruksi, 70 DPPP, 17 tidak dapat dilaksanakan) • TOK 5 Okt 2026: 96 program (75 konstruksi, 12 DPPP, 9 tidak dapat dilaksanakan) • Sambungan langsung baru tercapai ±34,73% dari target PKS Bundling (per 1 Sep 2026). PAM JAYA menegur ABJ atas ketidaksesuaian pelaksanaan dengan Program Konstruksi. | E67: PMO/PGO
A68: 66 | B68: 4806/PS.04.04/EKSI/IX/2026 | C68: Teguran Pemenuhan Kewajiban Penyelesaian Paket Pekerjaaan Keempat Proyek Greenfield Pada Saat Tanggal Operasi Komersial atau 5 Oktober 2026 | D68: Per 30 September 2026, dari 96 program Paket Keempat (TOK 5 Oktober 2026), 50 masih tahap konstruksi, 37 tahap DPPP, dan 9 tidak dapat dilaksanakan. Rekomendasi KPI atas 9 program itu juga belum ada. PAM JAYA menegur ABJ dan meminta pekerjaan, temuan inspeksi, mitigasi kendala, perbaikan bekas galian, dan dokumen penagihan segera diselesaikan. | E68: PMO Infill/PMO TM - Suci/Jusman
A69: 67 | B69: 4823/PS.04.04/EKST/X/2026 | C69: Teguran Penerapan Aspek Keselamatan dan Kesehatan Kerja ("K3") Proyek Jatiluhur Hilir | D69: Hasil inspeksi K3 tanggal 29 Sep 2026 di Paket S001 (pelaksana PT Spectra, Jl. Pasar Minggu). Temuan: pekerja tanpa APD lengkap, barrier tidak sesuai standar, area tidak rapi, rambu belum lengkap, stiker PPDU belum sesuai standar, temuan berulang tidak ditindaklanjuti, dan pengawasan K3 tidak diterapkan. | E69: HSE - Suhendro

Sheet Outgoing 2026
A1: No | B1: Nomor Surat | C1: Tanggal Surat | D1: Penerima | E1: Perihal | F1: Deskripsi | G1: Historical | H1: Produksi/Project | I1: Lokasi | J1: Kategori | K1: Due Date | L1: Status | M1: DIC | N1: PIC | O1: Durasi | P1: Durasi (Hari) | R1: =TODAY() -> 46304
A2: 1 | B2: ABJ/DIR/EKS/01.26/0001 | C2: 46024 | D2: PAM JAYA | E2: Usulan Diskusi Mengenai Konsultan Independen atas Perhitungan Tagihan KBA | H2: Project | I2: Greenfield | J2: Keuangan, Pembayaran, Investasi | L2: Closed | M2: Compliance | N2: Indradi | O2: =DATEDIF(C2,$R$1,"Y")&" tahun, "&DATEDIF(C2,$R$1,"YM")&" bulan, "&DATEDIF(C2,$R$1,"MD")&" hari" -> 0 tahun, 9 bulan, 7 hari | P2: =TODAY()-C2 -> 280
A3: 2 | B3: ABJ/DIR/EKS/01.26/0002 | C3: 46024 | D3: PAM JAYA | E3: Penyampaian Progres Penyelesaian Pekerjaan Program TOK 5 Oktober 2025 | H3: Project | I3: Greenfield | J3: Konstruksi Program Greenfield | L3: Info | M3: PGO | N3: Angelika | O3: =DATEDIF(C3,$R$1,"Y")&" tahun, "&DATEDIF(C3,$R$1,"YM")&" bulan, "&DATEDIF(C3,$R$1,"MD")&" hari" -> 0 tahun, 9 bulan, 7 hari | P3: =TODAY()-C3 -> 280
A4: 3 | B4: ABJ/DIR/EKS/01.26/0003 | C4: 46024 | D4: PAM JAYA | E4: Pemasangan Pipa Ramset Pada Program Master Meter Binton | H4: Project | I4: Jatiluhur Hilir | J4: Konstruksi Program Greenfield | L4: Info | M4: PMO Infill | N4: Muhrojin | O4: =DATEDIF(C4,$R$1,"Y")&" tahun, "&DATEDIF(C4,$R$1,"YM")&" bulan, "&DATEDIF(C4,$R$1,"MD")&" hari" -> 0 tahun, 9 bulan, 7 hari | P4: =TODAY()-C4 -> 280
A5: 4 | B5: ABJ/DIR/EKS/01.26/0004 | C5: 46024 | D5: KPI - PT Sucofindo | E5: Permintaan Laporan Verifikasi KPI atas Program Rehabilitasi Proyek Greenfield (IPA Buaran III) | H5: Project | I5: Buaran 3 Hulu | J5: Administrasi & Dokumentasi | L5: Open | M5: Compliance | N5: Indradi | O5: =DATEDIF(C5,$R$1,"Y")&" tahun, "&DATEDIF(C5,$R$1,"YM")&" bulan, "&DATEDIF(C5,$R$1,"MD")&" hari" -> 0 tahun, 9 bulan, 7 hari | P5: =TODAY()-C5 -> 280
A6: 5 | B6: ABJ/DIR/EKS/01.26/0009 | C6: 46027 | D6: Lurah Rawamangun | E6: Surat Pemberitahuan | H6: Project | I6: Greenfield | J6: Konstruksi Program Greenfield | L6: Info | M6: PMO TM | N6: Suci | O6: =DATEDIF(C6,$R$1,"Y")&" tahun, "&DATEDIF(C6,$R$1,"YM")&" bulan, "&DATEDIF(C6,$R$1,"MD")&" hari" -> 0 tahun, 9 bulan, 4 hari | P6: =TODAY()-C6 -> 277
A7: 6 | B7: ABJ/DIR/EKS/01.26/0010 | C7: 46027 | D7: PAM JAYA | E7: Tagihan Air Curah Perjanjian Brownfield – Periode Desember 2025 | H7: Corporate | I7: Corporate | J7: Keuangan, Pembayaran, Investasi | L7: Closed | M7: Compliance | N7: Indradi | O7: =DATEDIF(C7,$R$1,"Y")&" tahun, "&DATEDIF(C7,$R$1,"YM")&" bulan, "&DATEDIF(C7,$R$1,"MD")&" hari" -> 0 tahun, 9 bulan, 4 hari | P7: =TODAY()-C7 -> 277
A8: 7 | B8: ABJ/DIR/EKS/01.26/0011 | C8: 46027 | D8: PAM JAYA | E8: Tagihan Air Curah Perjanjian Greenfield - Periode Desember 2025 | H8: Corporate | I8: Corporate | J8: Keuangan, Pembayaran, Investasi | L8: Closed | M8: Compliance | N8: Indradi | O8: =DATEDIF(C8,$R$1,"Y")&" tahun, "&DATEDIF(C8,$R$1,"YM")&" bulan, "&DATEDIF(C8,$R$1,"MD")&" hari" -> 0 tahun, 9 bulan, 4 hari | P8: =TODAY()-C8 -> 277
A9: 8 | B9: ABJ/DIR/EKS/01.26/0012 | C9: 46027 | D9: PAM JAYA | E9: Pembaharuan Informasi Dokumen Persyaratan Penyelesaian Pekerjaan Fasilitas Distribusi Baru Paket Kedua TOK Oktober 2025 | H9: Project | I9: Greenfield | J9: Administrasi & Dokumentasi | L9: Info | M9: PGO | N9: Angelika | O9: =DATEDIF(C9,$R$1,"Y")&" tahun, "&DATEDIF(C9,$R$1,"YM")&" bulan, "&DATEDIF(C9,$R$1,"MD")&" hari" -> 0 tahun, 9 bulan, 4 hari | P9: =TODAY()-C9 -> 277
A10: 9 | B10: ABJ/DIR/EKS/01.26/0013 | C10: 46027 | D10: PAM JAYA | E10: Laporan Bulanan Kualitas Air Baku dan Air Curah Periode Desember 2025 | H10: Produksi | I10: ALL WTP | J10: Monitoring & Pelaporan | L10: Info | M10: WQA | N10: Novi | O10: =DATEDIF(C10,$R$1,"Y")&" tahun, "&DATEDIF(C10,$R$1,"YM")&" bulan, "&DATEDIF(C10,$R$1,"MD")&" hari" -> 0 tahun, 9 bulan, 4 hari | P10: =TODAY()-C10 -> 277
A11: 10 | B11: ABJ/DIR/EKS/01.26/0014 | C11: 46027 | D11: Direktur Jenderal Administrasi Hukum Umum cq. Direktur Badan Usaha Kementerian Hukum | E11: Permohonan Perbaikan Data Email dan Nomor Telepon PT AIR BERSIH JAKARTA | H11: Corporate | I11: Corporate | J11: Kontrak & Legal | L11: Info | M11: Legal - Moya | N11: Angelina | O11: =DATEDIF(C11,$R$1,"Y")&" tahun, "&DATEDIF(C11,$R$1,"YM")&" bulan, "&DATEDIF(C11,$R$1,"MD")&" hari" -> 0 tahun, 9 bulan, 4 hari | P11: =TODAY()-C11 -> 277
A12: 11 | B12: ABJ/DIR/EKS/01.26/0015 | C12: 46028 | D12: Bank OCBC NISP, Tbk - Agency & Trust Services | E12: Penyampaian Salinan Asli Polis Asuransi | H12: Corporate | I12: Corporate | J12: Keuangan, Pembayaran, Investasi | L12: Info | M12: Finance | N12: Nurul S | O12: =DATEDIF(C12,$R$1,"Y")&" tahun, "&DATEDIF(C12,$R$1,"YM")&" bulan, "&DATEDIF(C12,$R$1,"MD")&" hari" -> 0 tahun, 9 bulan, 3 hari | P12: =TODAY()-C12 -> 276
A13: 12 | B13: ABJ/DIR/EKS/01.26/0016 | C13: 46028 | D13: PT Bank Central Asia Tbk | E13: Permohonan Penghapusan Lampiran 6 Step-In dalam Persyaratan Lebih Lanjut | H13: Corporate | I13: Corporate | J13: Kontrak & Legal | L13: Info | M13: Legal | N13: Bahtera N | O13: =DATEDIF(C13,$R$1,"Y")&" tahun, "&DATEDIF(C13,$R$1,"YM")&" bulan, "&DATEDIF(C13,$R$1,"MD")&" hari" -> 0 tahun, 9 bulan, 3 hari | P13: =TODAY()-C13 -> 276
... A28: 27 | B28: ABJ/DIR/EKS/01.26/0030 | C28: 46031 | D28: PAM JAYA | E28: Undangan Uji Komisioning SPAM Jatiluhur Hilir – JDU JDB JDL PC 054 Oran Danarsio | H28: Project | I28: Jatiluhur Hilir | J28: Konstruksi Program Greenfield | L28: Info | M28: PMO Infill | N28: Muhrojin | O28: =DATEDIF(C28,$R$1,"Y")&" tahun, "&DATEDIF(C28,$R$1,"YM")&" bulan, "&DATEDIF(C28,$R$1,"MD")&" hari" -> 0 tahun, 9 bulan, 0 hari | P28: =TODAY()-C28 -> 273
A29: 28 | B29: ABJ/DIR/EKS/01.26/0031 | C29: 46031 | D29: PAM JAYA | E29: Permintaan Pengembalian Dana Cadangan Terkait Proyek Brownfield | G29: Menanggapi surat masuk: PJ 2495.PS.04.02-EKST.VI.2026 - Tanggapan atas Permintaan Pengembalian Dana Cadangan | H29: Project | I29: Cyclical | J29: Keuangan, Pembayaran, Investasi | L29: Open | M29: Legal | N29: Bahtera N | O29: =DATEDIF(C29,$R$1,"Y")&" tahun, "&DATEDIF(C29,$R$1,"YM")&" bulan, "&DATEDIF(C29,$R$1,"MD")&" hari" -> 0 tahun, 9 bulan, 0 hari | P29: =TODAY()-C29 -> 273
A30: 29 | B30: ABJ/DIR/EKS/01.26/0033 | C30: 46034 | D30: PAM JAYA | E30: Permohonan Pemakaian Air PAM JAYA untuk hydrotest seq 5,6,7 & 8 Proyek SPAM Pesanggrahan (Paket TMPSG Jalur 01) | H30: Project | I30: Karian Serpong Hilir | J30: Konstruksi Program Greenfield | L30: Info | M30: PMO TM | N30: Suci | O30: =DATEDIF(C30,$R$1,"Y")&" tahun, "&DATEDIF(C30,$R$1,"YM")&" bulan, "&DATEDIF(C30,$R$1,"MD")&" hari" -> 0 tahun, 8 bulan, 27 hari | P30: =TODAY()-C30 -> 270
A31: 30 | B31: ABJ/DIR/EKS/01.26/0034 | C31: 46034 | D31: PAM JAYA | E31: Permintaan Target Kesepakatan Mengenai Alur Proses Penyelesaian Sambungan Langsung | H31: Project | I31: Greenfield | J31: Sambungan Langsung | L31: Open | M31: PMO NC | N31: A. Levi | O31: =DATEDIF(C31,$R$1,"Y")&" tahun, "&DATEDIF(C31,$R$1,"YM")&" bulan, "&DATEDIF(C31,$R$1,"MD")&" hari" -> 0 tahun, 8 bulan, 27 hari | P31: =TODAY()-C31 -> 270
A32: 31 | B32: ABJ/DIR/EKS/01.26/0035 | C32: 46034 | D32: PAM JAYA | E32: Usulan Penyederhanaan Workflow Desain Akhir, Proposal Modifikasi, dan Closing melalui BIM | G32: Ditanggapi oleh surat masuk: PJ e-72734.PS.04.00 Tanggapan atas Surat ABJ26 0035 tanggal 12 Januari 2026 Perihal Usulan Penyederhanaan Workflow Desain Akhir, Proposal Modifikasi, dan Closing melalui BIM | H32: Project | I32: Project | J32: Administrasi & Dokumentasi | L32: Closed | M32: PGO | N32: Angelika | O32: =DATEDIF(C32,$R$1,"Y")&" tahun, "&DATEDIF(C32,$R$1,"YM")&" bulan, "&DATEDIF(C32,$R$1,"MD")&" hari" -> 0 tahun, 8 bulan, 27 hari | P32: =TODAY()-C32 -> 270
A33: 32 | B33: ABJ/DIR/EKS/01.26/0036 | C33: 46035 | D33: PT. Bina Lestari Lingkungan Sejahtera | E33: Surat Teguran Atas Pelaksanaan Tugas Konsultan Manajemen Konstruksi | H33: Project | I33: Project | J33: Konstruksi Program Greenfield | L33: Info | M33: PGO | N33: Angelika | O33: =DATEDIF(C33,$R$1,"Y")&" tahun, "&DATEDIF(C33,$R$1,"YM")&" bulan, "&DATEDIF(C33,$R$1,"MD")&" hari" -> 0 tahun, 8 bulan, 26 hari | P33: =TODAY()-C33 -> 269
A34: 33 | B34: ABJ/DIR/EKS/01.26/0037 | C34: 46035 | D34: PAM JAYA | E34: Tanggapan atas Surat PAM JAYA No. e-70776/PP.01.04 Perihal Sanksi Denda atas Kegagalan Kinerja Periode Bulan November 2025 | G34: Menanggapi surat masuk: PJ e-70776.PP.01.04 - Sanksi Denda atas Kegagalan Kinerja Periode Bulan November 2025; PJ e-70776.PP.01.04 Sanksi Denda atas Kegagalan Kinerja Periode Bulan November 2025; PJ e-82079.PP.01.04 - Tanggapan atas Surat ABJ 0714 Perihal Tanggapan Atas Surat PAM JAYA Nomor e-59697 Tentang Sanksi Denda Kegagalan Kinerja Periode Bulan Juni 2025 | H34: Produksi | I34: PJP 1 | J34: Denda & Kegagalan | L34: Info | M34: Compliance | N34: Indradi | O34: =DATEDIF(C34,$R$1,"Y")&" tahun, "&DATEDIF(C34,$R$1,"YM")&" bulan, "&DATEDIF(C34,$R$1,"MD")&" hari" -> 0 tahun, 8 bulan, 26 hari | P34: =TODAY()-C34 -> 269
A35: 34 | B35: ABJ/DIR/EKS/01.26/0038 | C35: 46035 | D35: PAM JAYA | E35: Pembaharuan DED dan RAB Proyek SPAM Ciliwung Hilir – Tahap Kedua | H35: Project | I35: Jatiluhur Hilir | J35: Perencanaan Program Greenfield | L35: Info | M35: Planning | N35: Aji S | O35: =DATEDIF(C35,$R$1,"Y")&" tahun, "&DATEDIF(C35,$R$1,"YM")&" bulan, "&DATEDIF(C35,$R$1,"MD")&" hari" -> 0 tahun, 8 bulan, 26 hari | P35: =TODAY()-C35 -> 269
A36: 35 | B36: ABJ/DIR/EKS/01.26/0039 | C36: 46036 | D36: Kelurahan Pesanggrahan | E36: Pemberitahuan Kegiatan Pekerjaan Galian Pipa di wilayah Kelurahan Pesanggrahan | H36: Project | I36: Karian Serpong Hilir | J36: Koordinasi & Sosialisasi | L36: Info | M36: Permit | N36: Rudy | O36: =DATEDIF(C36,$R$1,"Y")&" tahun, "&DATEDIF(C36,$R$1,"YM")&" bulan, "&DATEDIF(C36,$R$1,"MD")&" hari" -> 0 tahun, 8 bulan, 25 hari | P36: =TODAY()-C36 -> 268
A37: 36 | B37: ABJ/DIR/EKS/01.26/0040 | C37: 46036 | D37: PAM JAYA | E37: Penyampaian Laporan Penyelesaian Uji Komisioning Project Greenfield – SPAM Jatiluhur Hilir 9 Program | G37: Ditanggapi oleh surat masuk: 153/SCI-KPI/I/2026 - Penyampaian Laporan Penyelesaian Uji Komisioning Project Greenfield – SPAM Jatiluhur Hilir 9 Program | H37: Project | I37: Jatiluhur Hilir | J37: Konstruksi Program Greenfield | L37: Info | M37: PMO Infill | N37: Muhrojin | O37: =DATEDIF(C37,$R$1,"Y")&" tahun, "&DATEDIF(C37,$R$1,"YM")&" bulan, "&DATEDIF(C37,$R$1,"MD")&" hari" -> 0 tahun, 8 bulan, 25 hari | P37: =TODAY()-C37 -> 268
A38: 37 | B38: ABJ/DIR/EKS/01.26/0041 | C38: 46036 | D38: PAM JAYA | E38: Percepatan Peningkatan Cakupan Layanan Air Minum melalui Sambungan Langsung DKI Jakarta | H38: Project | I38: Greenfield | J38: Sambungan Langsung | L38: Info | M38: PMO NC | N38: A. Levi | O38: =DATEDIF(C38,$R$1,"Y")&" tahun, "&DATEDIF(C38,$R$1,"YM")&" bulan, "&DATEDIF(C38,$R$1,"MD")&" hari" -> 0 tahun, 8 bulan, 25 hari | P38: =TODAY()-C38 -> 268
A39: 38 | B39: ABJ/DIR/EKS/01.26/0042 | C39: 46036 | D39: Komandan Batalyon Arhanud 10/ABC | E39: Pemberitahuan Kegiatan Pekerjaan Galian Pipa di wilayah Batalyon Arhanud 10/ABC | H39: Project | I39: Greenfield | J39: Koordinasi & Sosialisasi | L39: Info | M39: Permit | N39: Rudy | O39: =DATEDIF(C39,$R$1,"Y")&" tahun, "&DATEDIF(C39,$R$1,"YM")&" bulan, "&DATEDIF(C39,$R$1,"MD")&" hari" -> 0 tahun, 8 bulan, 25 hari | P39: =TODAY()-C39 -> 268
A40: 39 | B40: ABJ/DIR/EKS/01.26/0043 | C40: 46036 | D40: Badan Pengelola Perumahan Cirendeu Permai | E40: Permohonan ijin akses jalan menuju Reservoir DCR 5 | H40: Project | I40: Greenfield | J40: Koordinasi & Sosialisasi | L40: Info | M40: PMO TM | N40: Suci | O40: =DATEDIF(C40,$R$1,"Y")&" tahun, "&DATEDIF(C40,$R$1,"YM")&" bulan, "&DATEDIF(C40,$R$1,"MD")&" hari" -> 0 tahun, 8 bulan, 25 hari | P40: =TODAY()-C40 -> 268
A41: 40 | B41: ABJ/DIR/EKS/01.26/0044 | C41: 46036 | D41: PAM JAYA | E41: Tanggapan atas Surat PAM JAYA No. e-70215/PS.00.04 Perihal Permintaan Bukti Penyimpanan Dokumen | G41: PJ e-70215.PS.00.04 PJ e-84086-PP.01.05 e-74895-PS.04.03 | H41: Corporate | I41: Corporate | J41: Administrasi & Dokumentasi | L41: Info | M41: Compliance | N41: Indradi | O41: =DATEDIF(C41,$R$1,"Y")&" tahun, "&DATEDIF(C41,$R$1,"YM")&" bulan, "&DATEDIF(C41,$R$1,"MD")&" hari" -> 0 tahun, 8 bulan, 25 hari | P41: =TODAY()-C41 -> 268
A42: 41 | B42: ABJ/DIR/EKS/01.26/0045 | C42: 46037 | D42: PAM JAYA | E42: Penundaan Pelaksanaan Proyek Pembangunan Pipa A4 Marunda | H42: Project | I42: Jatiluhur Hilir | J42: Konstruksi Program Greenfield | L42: Info | M42: Planning | N42: Aji S | O42: =DATEDIF(C42,$R$1,"Y")&" tahun, "&DATEDIF(C42,$R$1,"YM")&" bulan, "&DATEDIF(C42,$R$1,"MD")&" hari" -> 0 tahun, 8 bulan, 24 hari | P42: =TODAY()-C42 -> 267
A43: 42 | B43: ABJ/DIR/EKS/01.26/0046 | C43: 46037 | D43: PAM JAYA | E43: Penyampaian Dokumen Polis Asuransi Project Brownfield & Greenfield | G43: Menanggapi surat masuk: e-70216/PS.04.03 - Konfirmasi Perpanjangan Polis Asuransi Project Brownfield & Greenfield | H43: Project | I43: Project | J43: Keuangan, Pembayaran, Investasi | L43: Info | M43: Finance | N43: Nurul s | O43: =DATEDIF(C43,$R$1,"Y")&" tahun, "&DATEDIF(C43,$R$1,"YM")&" bulan, "&DATEDIF(C43,$R$1,"MD")&" hari" -> 0 tahun, 8 bulan, 24 hari | P43: =TODAY()-C43 -> 267
A44: 43 | B44: ABJ/DIR/EKS/01.26/0047 | C44: 46037 | D44: PAM JAYA | E44: Penyampaian Informasi Pembatalan Program Flow Meter Air Baku (Program Cyclical tahun 2026) | H44: Project | I44: Cyclical | J44: Konstruksi Program Greenfield | L44: Info | M44: PMO Cyclical | N44: Agus Herdinand | O44: =DATEDIF(C44,$R$1,"Y")&" tahun, "&DATEDIF(C44,$R$1,"YM")&" bulan, "&DATEDIF(C44,$R$1,"MD")&" hari" -> 0 tahun, 8 bulan, 24 hari | P44: =TODAY()-C44 -> 267
A45: 44 | B45: ABJ/DIR/EKS/01.26/0048 | C45: 46037 | D45: PAM JAYA | E45: Tanggapan Surat PAM JAYA No e-67973/PP.00.04 Perihal Biaya Persiapan Proyek Greenfield Tahun 2025-2031 | G45: e-67973/PP.00.04 | H45: Project | I45: Greenfield | J45: Perencanaan Program Greenfield | L45: Info | M45: Planning | N45: Andriani | O45: =DATEDIF(C45,$R$1,"Y")&" tahun, "&DATEDIF(C45,$R$1,"YM")&" bulan, "&DATEDIF(C45,$R$1,"MD")&" hari" -> 0 tahun, 8 bulan, 24 hari | P45: =TODAY()-C45 -> 267
A46: 45 | B46: ABJ/DIR/EKS/01.26/0049 | C46: 46037 | D46: PT. Bina Lestari Lingkungan Sejahtera | E46: Surat Peringatan Akibat Kegagalan Pengawasan BLLS | H46: Project | I46: Project | J46: Konstruksi Program Greenfield | L46: Info | M46: PMO Infill | N46: Danny L | O46: =DATEDIF(C46,$R$1,"Y")&" tahun, "&DATEDIF(C46,$R$1,"YM")&" bulan, "&DATEDIF(C46,$R$1,"MD")&" hari" -> 0 tahun, 8 bulan, 24 hari | P46: =TODAY()-C46 -> 267
A47: 46 | B47: ABJ/DIR/EKS/01.26/0050 | C47: 46037 | D47: PT. Infratama Yakti | E47: Surat Peringatan Akibat Kegagalan Infratama | H47: Project | I47: Project | J47: Konstruksi Program Greenfield | L47: Info | M47: PMO Infill | N47: Danny L | O47: =DATEDIF(C47,$R$1,"Y")&" tahun, "&DATEDIF(C47,$R$1,"YM")&" bulan, "&DATEDIF(C47,$R$1,"MD")&" hari" -> 0 tahun, 8 bulan, 24 hari | P47: =TODAY()-C47 -> 267
A48: 47 | B48: ABJ/DIR/EKS/01.26/0051 | C48: 46037 | D48: PAM JAYA | E48: Pengiriman Tanggapan Atas Hasil Review PAM dan KPI Terhadap Dokumen Desain Akhir Program Rehabilitasi Tahun 2026 | H48: Project | I48: Cyclical | J48: Perencanaan Program Rehabilitasi | L48: Info | M48: PMO Cyclical | N48: Agus Herdinand | O48: =DATEDIF(C48,$R$1,"Y")&" tahun, "&DATEDIF(C48,$R$1,"YM")&" bulan, "&DATEDIF(C48,$R$1,"MD")&" hari" -> 0 tahun, 8 bulan, 24 hari | P48: =TODAY()-C48 -> 267
A49: 48 | B49: ABJ/DIR/EKS/01.26/0052 | C49: 46037 | D49: PAM JAYA | E49: Undangan Uji Komisioning SPAM Jatiluhur Hilir – JDU JDB JDL PC 049 Cluster Alexandria, PC 054 H.Sutiyo dan PC 054 Rawa Badung RW 07 | H49: Project | I49: Jatiluhur Hilir | J49: Konstruksi Program Greenfield | L49: Info | M49: PMO Infill | N49: Muhrojin | O49: =DATEDIF(C49,$R$1,"Y")&" tahun, "&DATEDIF(C49,$R$1,"YM")&" bulan, "&DATEDIF(C49,$R$1,"MD")&" hari" -> 0 tahun, 8 bulan, 24 hari | P49: =TODAY()-C49 -> 267
A50: 49 | B50: ABJ/DIR/EKS/01.26/0053 | C50: 46041 | D50: PAM JAYA | E50: Penyampaian Laporan Pengawasan dan Laporan Perkembangan Proyek Kuartal 4 Tahun 2025 | H50: Project | I50: Project | J50: Monitoring & Pelaporan | L50: Info | M50: Compliance | N50: Indradi | O50: =DATEDIF(C50,$R$1,"Y")&" tahun, "&DATEDIF(C50,$R$1,"YM")&" bulan, "&DATEDIF(C50,$R$1,"MD")&" hari" -> 0 tahun, 8 bulan, 20 hari | P50: =TODAY()-C50 -> 263
A51: 50 | B51: ABJ/DIR/EKS/01.26/0054 | C51: 46041 | D51: PAM JAYA | E51: Pemasangan Pipa Ramset Pada Program Master Meter Binton | H51: Project | I51: Jatiluhur Hilir | J51: Konstruksi Program Greenfield | L51: Info | M51: PMO Infill | N51: Muhrojin | O51: =DATEDIF(C51,$R$1,"Y")&" tahun, "&DATEDIF(C51,$R$1,"YM")&" bulan, "&DATEDIF(C51,$R$1,"MD")&" hari" -> 0 tahun, 8 bulan, 20 hari | P51: =TODAY()-C51 -> 263
A52: 51 | B52: ABJ/DIR/EKS/01.26/0055 | C52: 46041 | D52: Dinas Pertamanan dan Hutan Kota | E52: Pernyataan Permohonan Izin Tebang Mendahului & Kesanggupan Penggantian Pohon | H52: Project | I52: Greenfield | J52: Koordinasi & Sosialisasi | L52: Info | M52: PMO TM | N52: Suci | O52: =DATEDIF(C52,$R$1,"Y")&" tahun, "&DATEDIF(C52,$R$1,"YM")&" bulan, "&DATEDIF(C52,$R$1,"MD")&" hari" -> 0 tahun, 8 bulan, 20 hari | P52: =TODAY()-C52 -> 263
A53: 52 | B53: ABJ/DIR/EKS/01.26/0056 | C53: 46041 | D53: PAM JAYA | E53: Penyampaian Biaya Persiapan dan Pembaharuan Nilai Desain Akhir Proyek Greenfield | H53: Project | I53: Greenfield | J53: Perencanaan Program Greenfield | L53: Info | M53: Planning | N53: Aji S | O53: =DATEDIF(C53,$R$1,"Y")&" tahun, "&DATEDIF(C53,$R$1,"YM")&" bulan, "&DATEDIF(C53,$R$1,"MD")&" hari" -> 0 tahun, 8 bulan, 20 hari | P53: =TODAY()-C53 -> 263
A54: 53 | B54: ABJ/DIR/EKS/01.26/0057 | C54: 46041 | D54: PAM JAYA | E54: Undangan Uji Komisioning SPAM Buaran III Hilir – JDU JDB JDL PC 161 Anwar Burhanudin | H54: Project | I54: Buaran 3 Hilir | J54: Konstruksi Program Greenfield | L54: Info | M54: PMO Infill | N54: Topan | O54: =DATEDIF(C54,$R$1,"Y")&" tahun, "&DATEDIF(C54,$R$1,"YM")&" bulan, "&DATEDIF(C54,$R$1,"MD")&" hari" -> 0 tahun, 8 bulan, 20 hari | P54: =TODAY()-C54 -> 263
A55: 54 | B55: ABJ/DIR/EKS/01.26/0058 | C55: 46041 | D55: PT. Bina Lestari Lingkungan Sejahtera | E55: Evaluasi Atas Pelaksanaan Fungsi Konsultan MK | H55: Project | I55: Project | J55: Konstruksi Program Greenfield | L55: Info | M55: PGO | N55: Angelika | O55: =DATEDIF(C55,$R$1,"Y")&" tahun, "&DATEDIF(C55,$R$1,"YM")&" bulan, "&DATEDIF(C55,$R$1,"MD")&" hari" -> 0 tahun, 8 bulan, 20 hari | P55: =TODAY()-C55 -> 263
A56: 55 | B56: ABJ/DIR/EKS/01.26/0059 | C56: 46041 | D56: PAM JAYA | E56: Permohonan Fasilitasi Surat ke PT Jasamarga Related Business terkait Perpanjangan MoU | H56: Project | I56: Greenfield | J56: Konstruksi Program Greenfield | L56: Info | M56: PMO TM | N56: Suci | O56: =DATEDIF(C56,$R$1,"Y")&" tahun, "&DATEDIF(C56,$R$1,"YM")&" bulan, "&DATEDIF(C56,$R$1,"MD")&" hari" -> 0 tahun, 8 bulan, 20 hari | P56: =TODAY()-C56 -> 263
A57: 56 | B57: ABJ/DIR/EKS/01.26/0060 | C57: 46042 | D57: PAM JAYA | E57: Tanggapan atas Surat PAM JAYA No. e-69891.TK.03.04 Perihal Pemenuhan Dokumen Monitoring Risk Register ABJ | G57: e-69891.TK.03.04 | H57: Project | I57: Project | J57: Manajemen Risiko | L57: Info | M57: QMS | N57: Agus Cahyadi | O57: =DATEDIF(C57,$R$1,"Y")&" tahun, "&DATEDIF(C57,$R$1,"YM")&" bulan, "&DATEDIF(C57,$R$1,"MD")&" hari" -> 0 tahun, 8 bulan, 19 hari | P57: =TODAY()-C57 -> 262
A58: 57 | B58: ABJ/DIR/EKS/01.26/0061 | C58: 46042 | D58: Camat Kecamatan Pasar Minggu | E58: Informasi Pelaksanaan Pekerjaan Pemasangan Pipa Air Minum di Kelurahan Pejaten Timur, Kecamatan Pasar Minggu, Jakarta Selatan dan Permohonan Pelaksanaan Sosialisasi dengan Pihak terkait. | H58: Project | I58: Greenfield | J58: Koordinasi & Sosialisasi | L58: Info | M58: Corcomm | N58: Ninuk | O58: =DATEDIF(C58,$R$1,"Y")&" tahun, "&DATEDIF(C58,$R$1,"YM")&" bulan, "&DATEDIF(C58,$R$1,"MD")&" hari" -> 0 tahun, 8 bulan, 19 hari | P58: =TODAY()-C58 -> 262
A59: 58 | B59: ABJ/DIR/EKS/01.26/0062 | C59: 46042 | D59: RW 08 Kelurahan Bintaro Kecamatan Pesanggrahan | E59: Pemberitahuan Kegiatan Pekerjaan Galian Pipa di wilayah RW 08 Kelurahan Bintaro | H59: Project | I59: Greenfield | J59: Koordinasi & Sosialisasi | L59: Info | M59: Permit | N59: Rudy | O59: =DATEDIF(C59,$R$1,"Y")&" tahun, "&DATEDIF(C59,$R$1,"YM")&" bulan, "&DATEDIF(C59,$R$1,"MD")&" hari" -> 0 tahun, 8 bulan, 19 hari | P59: =TODAY()-C59 -> 262
A60: 59 | B60: ABJ/DIR/EKS/01.26/0063 | C60: 46042 | D60: PAM JAYA | E60: Permohonan Konfirmasi Penggunaan Lahan untuk Pembangunan Inline Booster Pump (IBP) IPAL B014 | H60: Project | I60: Greenfield | J60: Konstruksi Program Greenfield | L60: Info | M60: Planning | N60: Aji S | O60: =DATEDIF(C60,$R$1,"Y")&" tahun, "&DATEDIF(C60,$R$1,"YM")&" bulan, "&DATEDIF(C60,$R$1,"MD")&" hari" -> 0 tahun, 8 bulan, 19 hari | P60: =TODAY()-C60 -> 262
A61: 60 | B61: ABJ/DIR/EKS/01.26/0064 | C61: 46042 | D61: PAM JAYA | E61: Penyampaian Laporan Penyelesaian Uji Komisioning Project Greenfield – SPAM Jatiluhur Hilir 2 Program | G61: Ditanggapi oleh surat masuk: 156/SCI-KPI/I/2026 - Tanggapan atas Surat PT Air Bersih Jakarta No. ABJ/DIR/EKS/01.26/0064 Perihal Penyampaian Laporan Penyelesaian Uji Komisioning Project Greenfield – SPAM Jatiluhur Hilir 2 Program | H61: Project | I61: Jatiluhur Hilir | J61: Konstruksi Program Greenfield | L61: Info | M61: PMO Infill | N61: Muhrojin | O61: =DATEDIF(C61,$R$1,"Y")&" tahun, "&DATEDIF(C61,$R$1,"YM")&" bulan, "&DATEDIF(C61,$R$1,"MD")&" hari" -> 0 tahun, 8 bulan, 19 hari | P61: =TODAY()-C61 -> 262
A62: 61 | B62: ABJ/DIR/EKS/01.26/0065 | C62: 46042 | D62: PAM JAYA | E62: Permohonan Tindak Lanjut DED dan RAB Final Pembangunan Reservoir IPA Pejompogan 2 dan Gedung CM | H62: Project | I62: Project | J62: Perencanaan Program Rehabilitasi | L62: Info | M62: PMO Infill | N62: Danny L | O62: =DATEDIF(C62,$R$1,"Y")&" tahun, "&DATEDIF(C62,$R$1,"YM")&" bulan, "&DATEDIF(C62,$R$1,"MD")&" hari" -> 0 tahun, 8 bulan, 19 hari | P62: =TODAY()-C62 -> 262
A63: 62 | B63: ABJ/DIR/EKS/01.26/0067 | C63: 46042 | D63: PAM JAYA | E63: Pengecualian Denda Terkait Target Pumping Regime IPA Pejompongan 1 | G63: Menanggapi surat masuk: PJ e-83765.PP.01.04 - Tanggapan atas Surat ABJ No. ABJ-26-0067 Perihal Pengecualian Denda Terkait Target Pumping Regime IPA Pejompongan 1 | H63: Produksi | I63: PJP 1 | J63: Denda & Kegagalan | L63: Info | M63: Produksi | N63: Wahdi Putra | O63: =DATEDIF(C63,$R$1,"Y")&" tahun, "&DATEDIF(C63,$R$1,"YM")&" bulan, "&DATEDIF(C63,$R$1,"MD")&" hari" -> 0 tahun, 8 bulan, 19 hari | P63: =TODAY()-C63 -> 262
A64: 63 | B64: ABJ/DIR/EKS/01.26/0068 | C64: 46043 | D64: PAM JAYA | E64: Penjelasan Kondisi Eksternal Penyebab Keterlambatan dan Pengembalian FA SL | H64: Project | I64: Greenfield | J64: Sambungan Langsung | L64: Info | M64: PMO NC | N64: A. Levi | O64: =DATEDIF(C64,$R$1,"Y")&" tahun, "&DATEDIF(C64,$R$1,"YM")&" bulan, "&DATEDIF(C64,$R$1,"MD")&" hari" -> 0 tahun, 8 bulan, 18 hari | P64: =TODAY()-C64 -> 261
A65: 64 | B65: ABJ/DIR/EKS/01.26/0069 | C65: 46044 | D65: Bank BJB Cabang Bekasi | E65: Surat Permohonan Penutupan Rekening Bank | H65: Corporate | I65: Corporate | J65: Keuangan, Pembayaran, Investasi | L65: Info | M65: Finance | N65: Nurul S | O65: =DATEDIF(C65,$R$1,"Y")&" tahun, "&DATEDIF(C65,$R$1,"YM")&" bulan, "&DATEDIF(C65,$R$1,"MD")&" hari" -> 0 tahun, 8 bulan, 17 hari | P65: =TODAY()-C65 -> 260
A66: 65 | B66: ABJ/DIR/EKS/01.26/0070 | C66: 46045 | D66: PAM JAYA | E66: Penyampaian Laporan Penyelesaian Uji Komisioning Project Greenfield – SPAM Buaran 3 Hilir Program Anwar Burhanudin | G66: Ditanggapi oleh surat masuk: 173/SCI-KPI/I/2026 - Tanggapan atas Surat PT Air Bersih Jakarta No. ABJ/DIR/EKS/01.26/0070 Tentang Penyampaian Laporan Penyelesaian Uji Komisioning Project Greenfield - SPAM Buaran 3 Hilir Program Anwar Burhanudin | H66: Project | I66: Buaran 3 Hilir | J66: Konstruksi Program Greenfield | L66: Info | M66: PMO Infill | N66: Topan | O66: =DATEDIF(C66,$R$1,"Y")&" tahun, "&DATEDIF(C66,$R$1,"YM")&" bulan, "&DATEDIF(C66,$R$1,"MD")&" hari" -> 0 tahun, 8 bulan, 16 hari | P66: =TODAY()-C66 -> 259
A67: 66 | B67: ABJ/DIR/EKS/01.26/0072 | C67: 46045 | D67: PAM JAYA | E67: Pemberitahuan Kegiatan Pekerjaan Galian Pipa di wilayah SDN Pesanggrahan 10 | H67: Project | I67: Karian Serpong Hilir | J67: Konstruksi Program Greenfield | L67: Info | M67: PMO TM | N67: Suci | O67: =DATEDIF(C67,$R$1,"Y")&" tahun, "&DATEDIF(C67,$R$1,"YM")&" bulan, "&DATEDIF(C67,$R$1,"MD")&" hari" -> 0 tahun, 8 bulan, 16 hari | P67: =TODAY()-C67 -> 259
A68: 67 | B68: ABJ/DIR/EKS/01.26/0073 | C68: 46045 | D68: PAM JAYA | E68: Pemberitahuan Kegiatan Pekerjaan Galian Pipa di wilayah RSUD Pesanggrahan | H68: Project | I68: Karian Serpong Hilir | J68: Konstruksi Program Greenfield | L68: Info | M68: PMO TM | N68: Suci | O68: =DATEDIF(C68,$R$1,"Y")&" tahun, "&DATEDIF(C68,$R$1,"YM")&" bulan, "&DATEDIF(C68,$R$1,"MD")&" hari" -> 0 tahun, 8 bulan, 16 hari | P68: =TODAY()-C68 -> 259
A69: 68 | B69: ABJ/DIR/EKS/01.26/0074 | C69: 46048 | D69: PAM JAYA | E69: Penyampaian Laporan Penyelesaian Uji Komisioning Project Greenfield – SPAM Jatiluhur Hilir PC 054 Rawa Badung RW 07 | G69: Ditanggapi oleh surat masuk: 176/SCI-KPI/II/2026 - Tanggapan atas Surat PT Air Bersih Jakarta No. ABJ/DIR/EKS/01.26/0074 perihal Penyampaian Laporan Penyelesaian Uji Komisioning Project Greenfield – SPAM Jatiluhur Hilir PC 054 Rawa Badung RW 07 | H69: Project | I69: Jatiluhur Hilir | J69: Konstruksi Program Greenfield | L69: Info | M69: PMO Infill | N69: Muhrojin | O69: =DATEDIF(C69,$R$1,"Y")&" tahun, "&DATEDIF(C69,$R$1,"YM")&" bulan, "&DATEDIF(C69,$R$1,"MD")&" hari" -> 0 tahun, 8 bulan, 13 hari | P69: =TODAY()-C69 -> 256
A70: 69 | B70: ABJ/DIR/EKS/01.26/0075 | C70: 46048 | D70: PT. Bina Lestari Lingkungan Sejahtera | E70: Penugasan Kerja Lembur Libur Nasional dan Cuti Bersama | H70: Project | I70: Project | J70: Konstruksi Program Greenfield | L70: Info | M70: PMO TM | N70: Suci | O70: =DATEDIF(C70,$R$1,"Y")&" tahun, "&DATEDIF(C70,$R$1,"YM")&" bulan, "&DATEDIF(C70,$R$1,"MD")&" hari" -> 0 tahun, 8 bulan, 13 hari | P70: =TODAY()-C70 -> 256
A71: 70 | B71: ABJ/DIR/EKS/01.26/0076 | C71: 46048 | D71: PAM JAYA | E71: Tanggapan Surat PAM JAYA No 4722/PS.04.03/EKST/XII/2025 Perihal Tanggapan Pengiriman Dokumen Desain Akhir Program Rehabilitasi Proyek Brownfield Tahun 2026 | G71: 4722/PS.04.03/EKST/XII/2025 | H71: Project | I71: Cyclical | J71: Perencanaan Program Rehabilitasi | L71: Info | M71: Planning | N71: Andriani | O71: =DATEDIF(C71,$R$1,"Y")&" tahun, "&DATEDIF(C71,$R$1,"YM")&" bulan, "&DATEDIF(C71,$R$1,"MD")&" hari" -> 0 tahun, 8 bulan, 13 hari | P71: =TODAY()-C71 -> 256
A72: 71 | B72: ABJ/DIR/EKS/01.26/0077 | C72: 46048 | D72: PAM JAYA | E72: Pembaharuan Shop Drawing, Justifikasi Teknis dan Jadwal Pelaksanaan Trunk Main Jatiluhur Paket B2 Ancol | H72: Project | I72: Jatiluhur Hilir | J72: Konstruksi Program Greenfield | L72: Info | M72: PMO TM | N72: Suci | O72: =DATEDIF(C72,$R$1,"Y")&" tahun, "&DATEDIF(C72,$R$1,"YM")&" bulan, "&DATEDIF(C72,$R$1,"MD")&" hari" -> 0 tahun, 8 bulan, 13 hari | P72: =TODAY()-C72 -> 256
A73: 72 | B73: ABJ/DIR/EKS/01.26/0078 | C73: 46048 | D73: PAM JAYA | E73: Penyampaian Dokumen Pendukung Program Konstruksi SPAM Jatiluhur Hilir paket B2 Ancol | H73: Project | I73: Jatiluhur Hilir | J73: Konstruksi Program Greenfield | L73: Info | M73: PMO TM | N73: Suci | O73: =DATEDIF(C73,$R$1,"Y")&" tahun, "&DATEDIF(C73,$R$1,"YM")&" bulan, "&DATEDIF(C73,$R$1,"MD")&" hari" -> 0 tahun, 8 bulan, 13 hari | P73: =TODAY()-C73 -> 256
A74: 73 | B74: ABJ/DIR/EKS/01.26/0079 | C74: 46049 | D74: PAM JAYA | E74: Penyampaian Dokumen Pendukung Program Konstruksi SPAM Jatiluhur Hilir – 18 Program | H74: Project | I74: Jatiluhur Hilir | J74: Konstruksi Program Greenfield | L74: Info | M74: PMO Infill | N74: Danny L | O74: =DATEDIF(C74,$R$1,"Y")&" tahun, "&DATEDIF(C74,$R$1,"YM")&" bulan, "&DATEDIF(C74,$R$1,"MD")&" hari" -> 0 tahun, 8 bulan, 12 hari | P74: =TODAY()-C74 -> 255
A75: 74 | B75: ABJ/DIR/EKS/01.26/0080 | C75: 46049 | D75: PAM JAYA | E75: Penyampaian Dokumen Pendukung Program Konstruksi SPAM Buaran 3 Hilir – PC 162 Hanjuang, PC 162 Jl. Centex Gg. Jengki, PC 162 Heavenly Residence | H75: Project | I75: Buaran 3 Hilir | J75: Konstruksi Program Greenfield | L75: Info | M75: PMO Infill | N75: Topan | O75: =DATEDIF(C75,$R$1,"Y")&" tahun, "&DATEDIF(C75,$R$1,"YM")&" bulan, "&DATEDIF(C75,$R$1,"MD")&" hari" -> 0 tahun, 8 bulan, 12 hari | P75: =TODAY()-C75 -> 255
A76: 75 | B76: ABJ/DIR/EKS/01.26/0081 | C76: 46049 | D76: Dinas Perhubungan | E76: Pemberitahuan Pergeseran Lokasi Starting Pit (STA 0+288 menjadi STA 0+250) pada Pekerjaan Paket S04 Pesanggrahan | H76: Project | I76: Karian Serpong Hilir | J76: Konstruksi Program Greenfield | L76: Info | M76: PMO TM | N76: Suci | O76: =DATEDIF(C76,$R$1,"Y")&" tahun, "&DATEDIF(C76,$R$1,"YM")&" bulan, "&DATEDIF(C76,$R$1,"MD")&" hari" -> 0 tahun, 8 bulan, 12 hari | P76: =TODAY()-C76 -> 255
A77: 76 | B77: ABJ/DIR/EKS/01.26/0082 | C77: 46049 | D77: PAM JAYA | E77: Penyampaian Informasi Kondisi Perizinan pada Proyek SPAM Karian Serpong Hilir Trunk Main Pesanggrahan | H77: Project | I77: Karian Serpong Hilir | J77: Konstruksi Program Greenfield | L77: Info | M77: PMO TM | N77: Suci | O77: =DATEDIF(C77,$R$1,"Y")&" tahun, "&DATEDIF(C77,$R$1,"YM")&" bulan, "&DATEDIF(C77,$R$1,"MD")&" hari" -> 0 tahun, 8 bulan, 12 hari | P77: =TODAY()-C77 -> 255
A78: 77 | B78: ABJ/DIR/EKS/01.26/0083 | C78: 46050 | D78: PAM JAYA | E78: Penyampaian Informasi Pembatalan Paket Proyek – Infill TOK April 2026 | H78: Project | I78: Greenfield | J78: Konstruksi Program Greenfield | L78: Info | M78: PMO Infill | N78: Danny L | O78: =DATEDIF(C78,$R$1,"Y")&" tahun, "&DATEDIF(C78,$R$1,"YM")&" bulan, "&DATEDIF(C78,$R$1,"MD")&" hari" -> 0 tahun, 8 bulan, 11 hari | P78: =TODAY()-C78 -> 254
A79: 78 | B79: ABJ/DIR/EKS/01.26/0084 | C79: 46050 | D79: Kepala Dinas Perhubungan Provinsi DKI Jakarta | E79: Pemberitahuan Pergeseran Lokasi Starting Pit (STA 0+288 menjadi STA 0+250) pada Pekerjaan Paket S04 Pesanggrahan | H79: Project | I79: Karian Serpong Hilir | J79: Konstruksi Program Greenfield | L79: Info | M79: PMO TM | N79: Suci | O79: =DATEDIF(C79,$R$1,"Y")&" tahun, "&DATEDIF(C79,$R$1,"YM")&" bulan, "&DATEDIF(C79,$R$1,"MD")&" hari" -> 0 tahun, 8 bulan, 11 hari | P79: =TODAY()-C79 -> 254
A80: 79 | B80: ABJ/DIR/EKS/01.26/0085 | C80: 46050 | D80: PAM JAYA | E80: Penyampaian Dokumen Pendukung Program Konstruksi SPAM Jatiluhur Hilir – PC 070 Paket kedua, Jl. Malaka 1 Jl. Malaka 2 Jl. Malaka 3 Jl. Rorotan 11, Jl. Rorotan 9, Menteng Metropolitan - Tambun Rengas (Connect dgn JGC) | H80: Project | I80: Jatiluhur Hilir | J80: Konstruksi Program Greenfield | L80: Info | M80: PMO Infill | N80: Muhrojin | O80: =DATEDIF(C80,$R$1,"Y")&" tahun, "&DATEDIF(C80,$R$1,"YM")&" bulan, "&DATEDIF(C80,$R$1,"MD")&" hari" -> 0 tahun, 8 bulan, 11 hari | P80: =TODAY()-C80 -> 254
A81: 80 | B81: ABJ/DIR/EKS/01.26/0086 | C81: 46050 | D81: PAM JAYA | E81: Penyampaian Dokumen Pendukung Program Konstruksi SPAM Karian Serpong Hilir – 12 Program | H81: Project | I81: Karian Serpong Hilir | J81: Konstruksi Program Greenfield | L81: Info | M81: PMO Infill | N81: Ervin Y | O81: =DATEDIF(C81,$R$1,"Y")&" tahun, "&DATEDIF(C81,$R$1,"YM")&" bulan, "&DATEDIF(C81,$R$1,"MD")&" hari" -> 0 tahun, 8 bulan, 11 hari | P81: =TODAY()-C81 -> 254
A82: 81 | B82: ABJ/DIR/EKS/01.26/0087 | C82: 46050 | D82: PAM JAYA | E82: Penyampaian Dokumen Pendukung Program Konstruksi SPAM Karian Serpong Hilir – P009 Jl. Pantai Mutiara | H82: Project | I82: Karian Serpong Hilir | J82: Konstruksi Program Greenfield | L82: Info | M82: PMO Infill | N82: Ervin Y | O82: =DATEDIF(C82,$R$1,"Y")&" tahun, "&DATEDIF(C82,$R$1,"YM")&" bulan, "&DATEDIF(C82,$R$1,"MD")&" hari" -> 0 tahun, 8 bulan, 11 hari | P82: =TODAY()-C82 -> 254
A83: 82 | B83: ABJ/DIR/EKS/01.26/0088 | C83: 46050 | D83: General Manager Perum Jasa Tirta II | E83: Pemberitahuan Penyelesaian Pekerjaan Pipa Air Baku | H83: Project | I83: Greenfield | J83: Konstruksi Program Greenfield | L83: Info | M83: PMO TM | N83: Suci | O83: =DATEDIF(C83,$R$1,"Y")&" tahun, "&DATEDIF(C83,$R$1,"YM")&" bulan, "&DATEDIF(C83,$R$1,"MD")&" hari" -> 0 tahun, 8 bulan, 11 hari | P83: =TODAY()-C83 -> 254
... A99: 98 | B99: ABJ/DIR/EKS/02.26/0105 | C99: 46056 | D99: PAM JAYA | E99: Penjelasan Kondisi Eksternal Penyebab Keterlambatan Pemasangan dan Pengembalian Field Activity (“FA”) Sambungan Langsung (“SL”) as per 03 Februari 2026 | H99: Project | I99: Greenfield | J99: Sambungan Langsung | L99: Info | M99: PMO NC | N99: A. Levi | O99: =DATEDIF(C99,$R$1,"Y")&" tahun, "&DATEDIF(C99,$R$1,"YM")&" bulan, "&DATEDIF(C99,$R$1,"MD")&" hari" -> 0 tahun, 8 bulan, 6 hari | P99: =TODAY()-C99 -> 248
A100: 99 | B100: ABJ/DIR/EKS/02.26/0106 | C100: 46056 | D100: PAM JAYA | E100: Balasan atas surat PAM JAYA No e-72146/PP.03.05 perihal Penyampaian Hasil Inspeksi K3L Terjadwal di IPA Pulogadung Tahun 2025 | G100: PJ e-72146.PP.03.05 | H100: Project | I100: Pulogadung | J100: HSE | L100: Info | M100: HSE | N100: Irsan | O100: =DATEDIF(C100,$R$1,"Y")&" tahun, "&DATEDIF(C100,$R$1,"YM")&" bulan, "&DATEDIF(C100,$R$1,"MD")&" hari" -> 0 tahun, 8 bulan, 6 hari | P100: =TODAY()-C100 -> 248
A101: 100 | B101: ABJ/DIR/EKS/02.26/0107 | C101: 46057 | D101: PAM JAYA | E101: Tindak Lanjut Strategi Target Realisasi Pemasangan Sambungan Langsung Tahun 2026 | G101: Menanggapi surat masuk: PJ e-71848.PM.02.03 | H101: Project | I101: Greenfield | J101: Sambungan Langsung | L101: Info | M101: PMO NC | N101: A. Levi | O101: =DATEDIF(C101,$R$1,"Y")&" tahun, "&DATEDIF(C101,$R$1,"YM")&" bulan, "&DATEDIF(C101,$R$1,"MD")&" hari" -> 0 tahun, 8 bulan, 5 hari | P101: =TODAY()-C101 -> 247
A102: 101 | B102: ABJ/DIR/EKS/02.26/0108 | C102: 46057 | D102: PAM JAYA | E102: Permohonan Diskusi Alternatif Water Meter Itron untuk PAM Jaya | H102: Project | I102: Greenfield | J102: Sambungan Langsung | L102: Info | M102: PMO NC | N102: A. Levi | O102: =DATEDIF(C102,$R$1,"Y")&" tahun, "&DATEDIF(C102,$R$1,"YM")&" bulan, "&DATEDIF(C102,$R$1,"MD")&" hari" -> 0 tahun, 8 bulan, 5 hari | P102: =TODAY()-C102 -> 247
A103: 102 | B103: ABJ/DIR/EKS/02.26/0109 | C103: 46057 | D103: PAM JAYA | E103: Penyampaian Laporan Persiapan Penyerahan Fasilitas Distribusi Baru Proyek Greenfield – Trunk Main SPAM Jatiluhur Hilir dan SPAM Buaran 3 Hilir | G103: Menanggapi surat masuk: e-72803/PP.01.05 - Permintaan Pemenuhan Kewajiban Penyerahan Laporan Fasilitas Distribusi Baru; e-73256/PP.01.05 - Teguran Pemenuhan Kewajiban Penyerahan Laporan Fasilitas Distribusi Baru | H103: Project | I103: Greenfield | J103: Monitoring & Pelaporan | L103: Info | M103: PMO TM | N103: Suci | O103: =DATEDIF(C103,$R$1,"Y")&" tahun, "&DATEDIF(C103,$R$1,"YM")&" bulan, "&DATEDIF(C103,$R$1,"MD")&" hari" -> 0 tahun, 8 bulan, 5 hari | P103: =TODAY()-C103 -> 247
A104: 103 | B104: ABJ/DIR/EKS/02.26/0110 | C104: 46058 | D104: PAM JAYA | E104: Laporan Rencana Penyerahan Fasilitas Distribusi Baru TOK April 2026 - Infill SPAM Jatiluhur Hilir, Karian Serpong Hilir, & Buaran 3 Hilir | G104: Menanggapi surat masuk: e-72803/PP.01.05 - Permintaan Pemenuhan Kewajiban Penyerahan Laporan Fasilitas Distribusi Baru; e-73256/PP.01.05 - Teguran Pemenuhan Kewajiban Penyerahan Laporan Fasilitas Distribusi Baru | H104: Project | I104: Greenfield | J104: Monitoring & Pelaporan | L104: Info | M104: PMO TM | N104: Suci | O104: =DATEDIF(C104,$R$1,"Y")&" tahun, "&DATEDIF(C104,$R$1,"YM")&" bulan, "&DATEDIF(C104,$R$1,"MD")&" hari" -> 0 tahun, 8 bulan, 4 hari | P104: =TODAY()-C104 -> 246
A105: 104 | B105: ABJ/DIR/EKS/02.26/0111 | C105: 46057 | D105: PT. Bestindo Putra Mandiri | E105: Surat Peringatan Keterlambatan Hasil Brinel Test | H105: Project | I105: Greenfield | J105: Konstruksi Program Greenfield | L105: Info | M105: PMO Infill | N105: Aan | O105: =DATEDIF(C105,$R$1,"Y")&" tahun, "&DATEDIF(C105,$R$1,"YM")&" bulan, "&DATEDIF(C105,$R$1,"MD")&" hari" -> 0 tahun, 8 bulan, 5 hari | P105: =TODAY()-C105 -> 247
A106: 105 | B106: ABJ/DIR/EKS/02.26/0112 | C106: 46057 | D106: PAM JAYA | E106: Konfirmasi Pembatalan Proyek SPAM Jatiluhur Hilir | G106: Ditanggapi oleh surat masuk: Kumpulan Surat Terlampir - Tanggapan : Penyampaian Surat PT. Air Bersih Jakarta No. ABJ/DIR/EKS/02.26/0112 perihal Konfirmasi Pembatalan Proyek SPAM Jatiluhur Hilir | H106: Project | I106: Jatiluhur Hilir | J106: Konstruksi Program Greenfield | L106: Closed | M106: PMO Infill | N106: Muhrojin | O106: =DATEDIF(C106,$R$1,"Y")&" tahun, "&DATEDIF(C106,$R$1,"YM")&" bulan, "&DATEDIF(C106,$R$1,"MD")&" hari" -> 0 tahun, 8 bulan, 5 hari | P106: =TODAY()-C106 -> 247
A107: 106 | B107: ABJ/DIR/EKS/02.26/0113 | C107: 46057 | D107: PAM JAYA | E107: Program Master Meter Sardi Pesanggrahan (Blok D1 Komplek Kemayoran) | H107: Project | I107: Jatiluhur Hilir | J107: Konstruksi Program Greenfield | L107: Info | M107: PMO Infill | N107: Muhrojin | O107: =DATEDIF(C107,$R$1,"Y")&" tahun, "&DATEDIF(C107,$R$1,"YM")&" bulan, "&DATEDIF(C107,$R$1,"MD")&" hari" -> 0 tahun, 8 bulan, 5 hari | P107: =TODAY()-C107 -> 247
A108: 107 | B108: ABJ/DIR/EKS/02.26/0114 | C108: 46057 | D108: PAM JAYA | E108: Usulan Lokasi Sementara Ruang Sekretariat Bersama | H108: Project | I108: Buaran 3 Hulu | J108: Perencanaan Program Rehabilitasi | L108: Info | M108: Compliance | N108: Indradi | O108: =DATEDIF(C108,$R$1,"Y")&" tahun, "&DATEDIF(C108,$R$1,"YM")&" bulan, "&DATEDIF(C108,$R$1,"MD")&" hari" -> 0 tahun, 8 bulan, 5 hari | P108: =TODAY()-C108 -> 247
A109: 108 | B109: ABJ/DIR/EKS/02.26/0115 | C109: 46057 | D109: PAM JAYA | E109: Tagihan Air Curah Perjanjian Brownfield – Periode Januari 2026 | H109: Corporate | I109: Corporate | J109: Keuangan, Pembayaran, Investasi | L109: Closed | M109: Compliance | N109: Indradi | O109: =DATEDIF(C109,$R$1,"Y")&" tahun, "&DATEDIF(C109,$R$1,"YM")&" bulan, "&DATEDIF(C109,$R$1,"MD")&" hari" -> 0 tahun, 8 bulan, 5 hari | P109: =TODAY()-C109 -> 247
A110: 109 | B110: ABJ/DIR/EKS/02.26/0116 | C110: 46057 | D110: PAM JAYA | E110: Tagihan Air Curah Perjanjian Greenfield - Periode Januari 2026 | H110: Corporate | I110: Corporate | J110: Keuangan, Pembayaran, Investasi | L110: Closed | M110: Compliance | N110: Indradi | O110: =DATEDIF(C110,$R$1,"Y")&" tahun, "&DATEDIF(C110,$R$1,"YM")&" bulan, "&DATEDIF(C110,$R$1,"MD")&" hari" -> 0 tahun, 8 bulan, 5 hari | P110: =TODAY()-C110 -> 247
A111: 110 | B111: ABJ/DIR/EKS/02.26/0117 | C111: 46057 | D111: PAM JAYA | E111: Penyampaian Laporan Uji Komisioning PC 162 Centex | G111: Ditanggapi oleh surat masuk: 185/SCI-KPI/II/2026 - Tanggapan atas Surat PT Air Bersih Jakarta No. ABJ/DIR/EKS/02.26/0117 perihal Penyampaian Laporan Penyelesaian Uji Komisioning Project Greenfield – SPAM Buaran 3 Hilir Program PC 162 Centex | H111: Project | I111: Buaran 3 Hilir | J111: Konstruksi Program Greenfield | L111: Info | M111: PMO Infill | N111: Topan | O111: =DATEDIF(C111,$R$1,"Y")&" tahun, "&DATEDIF(C111,$R$1,"YM")&" bulan, "&DATEDIF(C111,$R$1,"MD")&" hari" -> 0 tahun, 8 bulan, 5 hari | P111: =TODAY()-C111 -> 247
A112: 111 | B112: ABJ/DIR/EKS/02.26/0118 | C112: 46057 | D112: PAM JAYA | E112: Penjelasan Kondisi Eksternal Penyebab Keterlambatan Pemasangan dan Pengembalian Field Activity (“FA”) Sambungan Langsung (“SL”) as per 04 Februari 2026 | H112: Project | I112: Greenfield | J112: Sambungan Langsung | L112: Info | M112: PMO NC | N112: A. Levi | O112: =DATEDIF(C112,$R$1,"Y")&" tahun, "&DATEDIF(C112,$R$1,"YM")&" bulan, "&DATEDIF(C112,$R$1,"MD")&" hari" -> 0 tahun, 8 bulan, 5 hari | P112: =TODAY()-C112 -> 247
A113: 112 | B113: ABJ/DIR/EKS/02.26/0119 | C113: 46057 | D113: PT. Citra Marga Nusaphala Persada | E113: Undangan Joint Survey MC-0 B2 Ancol Jl. RE. Martadinata | H113: Project | I113: Greenfield | J113: Konstruksi Program Greenfield | L113: Info | M113: PMO TM | N113: Suci | O113: =DATEDIF(C113,$R$1,"Y")&" tahun, "&DATEDIF(C113,$R$1,"YM")&" bulan, "&DATEDIF(C113,$R$1,"MD")&" hari" -> 0 tahun, 8 bulan, 5 hari | P113: =TODAY()-C113 -> 247
A114: 113 | B114: ABJ/DIR/EKS/02.26/0120 | C114: 46057 | D114: PAM JAYA | E114: Tindak Lanjut Prasyarat Perizinan Perlintasan PT KAI DAOP 1 (SPAM Ciliwung & SPAM Pesanggrahan) | H114: Project | I114: Greenfield | J114: Konstruksi Program Greenfield | L114: Info | M114: PMO TM | N114: Suci | O114: =DATEDIF(C114,$R$1,"Y")&" tahun, "&DATEDIF(C114,$R$1,"YM")&" bulan, "&DATEDIF(C114,$R$1,"MD")&" hari" -> 0 tahun, 8 bulan, 5 hari | P114: =TODAY()-C114 -> 247
A115: 114 | B115: ABJ/DIR/EKS/02.26/0121 | C115: 46058 | D115: PAM JAYA | E115: Penyampaian Informasi Proyek SPAM Jatiluhur Hilir - Program Master Meter Basri | H115: Project | I115: Jatiluhur Hilir | J115: Konstruksi Program Greenfield | L115: Info | M115: PMO Infill | N115: Muhrojin | O115: =DATEDIF(C115,$R$1,"Y")&" tahun, "&DATEDIF(C115,$R$1,"YM")&" bulan, "&DATEDIF(C115,$R$1,"MD")&" hari" -> 0 tahun, 8 bulan, 4 hari | P115: =TODAY()-C115 -> 246
A116: 115 | B116: ABJ/DIR/EKS/02.26/0122 | C116: 46058 | D116: PAM JAYA | E116: Penjelasan Kondisi Eksternal Penyebab Keterlambatan Pemasangan dan Pengembalian Field Activity (“FA”) Sambungan Langsung (“SL”) as per 05 Februari 2026 | H116: Project | I116: Greenfield | J116: Sambungan Langsung | L116: Info | M116: PMO NC | N116: A. Levi | O116: =DATEDIF(C116,$R$1,"Y")&" tahun, "&DATEDIF(C116,$R$1,"YM")&" bulan, "&DATEDIF(C116,$R$1,"MD")&" hari" -> 0 tahun, 8 bulan, 4 hari | P116: =TODAY()-C116 -> 246
A117: 116 | B117: ABJ/DIR/EKS/02.26/0123 | C117: 46059 | D117: PAM JAYA | E117: Penyampaian Dokumen Pendukung Program Konstruksi SPAM Buaran 3 Hilir – PC 162 Bapak Sukarno , PC 162 Jl. Tanah Merdeka | H117: Project | I117: Buaran 3 Hilir | J117: Konstruksi Program Greenfield | L117: Info | M117: PMO Infill | N117: Topan | O117: =DATEDIF(C117,$R$1,"Y")&" tahun, "&DATEDIF(C117,$R$1,"YM")&" bulan, "&DATEDIF(C117,$R$1,"MD")&" hari" -> 0 tahun, 8 bulan, 3 hari | P117: =TODAY()-C117 -> 245
A118: 117 | B118: 0002/AAJ/EKS//II/2026 | C118: 46059 | D118: Bank Danamon Indonesia | E118: Rollover Pinjaman atas Fasilitas Kredit Berjangka | H118: Corporate | I118: Corporate | J118: Keuangan, Pembayaran, Investasi | L118: Info | M118: Finance | N118: Nurul s | O118: =DATEDIF(C118,$R$1,"Y")&" tahun, "&DATEDIF(C118,$R$1,"YM")&" bulan, "&DATEDIF(C118,$R$1,"MD")&" hari" -> 0 tahun, 8 bulan, 3 hari | P118: =TODAY()-C118 -> 245
A119: 118 | B119: ABJ/DIR/EKS/02.26/0124 | C119: 46059 | D119: PAM JAYA | E119: Undangan Penyelesaian Pekerjaan di Ruko Bougenville ke : Ketua RT 07/05, Jatibening | H119: Project | I119: Karian Serpong Hilir | J119: Konstruksi Program Greenfield | L119: Info | M119: PMO TM | N119: Suci | O119: =DATEDIF(C119,$R$1,"Y")&" tahun, "&DATEDIF(C119,$R$1,"YM")&" bulan, "&DATEDIF(C119,$R$1,"MD")&" hari" -> 0 tahun, 8 bulan, 3 hari | P119: =TODAY()-C119 -> 245
A120: 119 | B120: ABJ/DIR/EKS/02.26/0125 | C120: 46059 | D120: PAM JAYA | E120: Penjelasan Kondisi Eksternal Penyebab Keterlambatan Pemasangan dan Pengembalian Field Activity (“FA”) Sambungan Langsung (“SL”) as per 06 Februari 2026 | H120: Project | I120: Greenfield | J120: Sambungan Langsung | L120: Info | M120: PMO NC | N120: A. Levi | O120: =DATEDIF(C120,$R$1,"Y")&" tahun, "&DATEDIF(C120,$R$1,"YM")&" bulan, "&DATEDIF(C120,$R$1,"MD")&" hari" -> 0 tahun, 8 bulan, 3 hari | P120: =TODAY()-C120 -> 245
A121: 120 | B121: ABJ/DIR/EKS/02.26/0126 | C121: 46059 | D121: Komandan Resimen Arhanud – 1/F | E121: Pemberitahuan Kegiatan Pekerjaan Galian Pipa di wilayah Resimen Arhanud – 1/F | H121: Project | I121: Greenfield | J121: Koordinasi & Sosialisasi | L121: Info | M121: Permit | N121: Rudy | O121: =DATEDIF(C121,$R$1,"Y")&" tahun, "&DATEDIF(C121,$R$1,"YM")&" bulan, "&DATEDIF(C121,$R$1,"MD")&" hari" -> 0 tahun, 8 bulan, 3 hari | P121: =TODAY()-C121 -> 245
A122: 121 | B122: ABJ/DIR/EKS/02.26/0127 | C122: 46059 | D122: PAM JAYA | E122: Tanggapan Atas Surat PAM JAYA No. e-72147/PP.03.05 | G122: Menanggapi surat masuk: PJ e-72147.PP.03.05 Penyampaian Hasil Inspeksi Aset dan Peralatan di IPA Pulogadung Tanggal 26 Februari 2025, 04 Juli 2025, dan 26 Agustus 2025 | H122: Produksi | I122: Pulogadung | J122: Operation & Maintenance | L122: Info | M122: Produksi | N122: Wahyudian | O122: =DATEDIF(C122,$R$1,"Y")&" tahun, "&DATEDIF(C122,$R$1,"YM")&" bulan, "&DATEDIF(C122,$R$1,"MD")&" hari" -> 0 tahun, 8 bulan, 3 hari | P122: =TODAY()-C122 -> 245
A123: 122 | B123: ABJ/DIR/EKS/02.26/0128 | C123: 46059 | D123: PAM JAYA | E123: Hasil FA Assigned dari PAM JAYA dan Dipasang Januari 2026 | H123: Project | I123: Greenfield | J123: Sambungan Langsung | L123: Info | M123: PMO NC | N123: A. Levi | O123: =DATEDIF(C123,$R$1,"Y")&" tahun, "&DATEDIF(C123,$R$1,"YM")&" bulan, "&DATEDIF(C123,$R$1,"MD")&" hari" -> 0 tahun, 8 bulan, 3 hari | P123: =TODAY()-C123 -> 245
A124: 123 | B124: ABJ/DIR/EKS/02.26/0129 | C124: 46062 | D124: PAM JAYA | E124: Laporan Bulanan PT Air Bersih Jakarta Periode Januari 2026 | H124: Project | I124: Project | J124: Monitoring & Pelaporan | L124: Info | M124: Compliance | N124: Indradi | O124: =DATEDIF(C124,$R$1,"Y")&" tahun, "&DATEDIF(C124,$R$1,"YM")&" bulan, "&DATEDIF(C124,$R$1,"MD")&" hari" -> 0 tahun, 8 bulan, 0 hari | P124: =TODAY()-C124 -> 242
A125: 124 | B125: ABJ/DIR/EKS/02.26/0130 | C125: 46062 | D125: PAM JAYA | E125: Penjelasan Kondisi Eksternal Penyebab Keterlambatan Pemasangan dan Pengembalian Field Activity (“FA”) Sambungan Langsung (“SL”) as per 09 Februari 2026 | H125: Project | I125: Greenfield | J125: Sambungan Langsung | L125: Info | M125: PMO NC | N125: A. Levi | O125: =DATEDIF(C125,$R$1,"Y")&" tahun, "&DATEDIF(C125,$R$1,"YM")&" bulan, "&DATEDIF(C125,$R$1,"MD")&" hari" -> 0 tahun, 8 bulan, 0 hari | P125: =TODAY()-C125 -> 242
A126: 125 | B126: ABJ/DIR/EKS/02.26/0131 | C126: 46063 | D126: PAM JAYA | E126: Undangan Uji Komisioning SPAM Jatiluhur Hilir – Master Meter Hasnawati, Kalo, dan Sudirman – Reinforcement, JDU JDB JDL PC 054 Solikhun, PC 068 Swadaya IV | H126: Project | I126: Greenfield | J126: Konstruksi Program Greenfield | L126: Info | M126: PMO Infill | N126: Muhrojin | O126: =DATEDIF(C126,$R$1,"Y")&" tahun, "&DATEDIF(C126,$R$1,"YM")&" bulan, "&DATEDIF(C126,$R$1,"MD")&" hari" -> 0 tahun, 7 bulan, 29 hari | P126: =TODAY()-C126 -> 241
A127: 126 | B127: ABJ/DIR/EKS/02.26/0132 | C127: 46063 | D127: PAM JAYA | E127: Penyampaian Pembaruan Informasi Perkembangan Proyek Greenfield - SPAM Hilir | H127: Project | I127: Greenfield | J127: Konstruksi Program Greenfield | L127: Info | M127: PMO Infill | N127: Danny L | O127: =DATEDIF(C127,$R$1,"Y")&" tahun, "&DATEDIF(C127,$R$1,"YM")&" bulan, "&DATEDIF(C127,$R$1,"MD")&" hari" -> 0 tahun, 7 bulan, 29 hari | P127: =TODAY()-C127 -> 241
A128: 127 | B128: ABJ/DIR/EKS/02.26/0133 | C128: 46063 | D128: PAM JAYA | E128: Penyampaian Pembaruan Informasi Perkembangan Proyek Greenfield - SPAM Hilir | H128: Project | I128: Greenfield | J128: Konstruksi Program Greenfield | L128: Info | M128: PMO Infill | N128: Danny L | O128: =DATEDIF(C128,$R$1,"Y")&" tahun, "&DATEDIF(C128,$R$1,"YM")&" bulan, "&DATEDIF(C128,$R$1,"MD")&" hari" -> 0 tahun, 7 bulan, 29 hari | P128: =TODAY()-C128 -> 241
A129: 128 | B129: ABJ/DIR/EKS/02.26/0134 | C129: 46063 | D129: PAM JAYA | E129: Penjelasan Kondisi Eksternal Penyebab Keterlambatan Pemasangan dan Pengembalian Field Activity (“FA”) Sambungan Langsung (“SL”) as per 10 Februari 2026 | H129: Project | I129: Greenfield | J129: Sambungan Langsung | L129: Info | M129: PMO NC | N129: A. Levi | O129: =DATEDIF(C129,$R$1,"Y")&" tahun, "&DATEDIF(C129,$R$1,"YM")&" bulan, "&DATEDIF(C129,$R$1,"MD")&" hari" -> 0 tahun, 7 bulan, 29 hari | P129: =TODAY()-C129 -> 241
...

Sheet Incoming 2026
A1: No | B1: Nomor Surat | C1: Tanggal Diterima | D1: Tanggal Surat | E1: Pengirim | F1: Perihal | G1: Deskripsi | H1: Produksi/Project | I1: Lokasi | J1: Kategori | K1: Perlu di balas | L1: Status | M1: Level Status | N1: Tindak Lanjut | O1: Dibalas oleh Surat ABJ Nomor | P1: Historical | Q1: Due Date | R1: DIC | S1: PIC | T1: Durasi | U1: Durasi (hari) | W1: Durasi Keterlambatan | X1: Durasi Deadline | Z1: =TODAY() -> 46304
A2: 1 | B2: 144/SCI-KPI/I/2026 | C2: 46027 | D2: 46024 | E2: KPI - Sucofindo | F2: Tanggapan atas Surat PT Air Bersih Jakarta No. ABJ/DIR/EKS/12.25/1126 Tentang Penyampaian Laporan Penyelesaian Uji Komisioning Project Greenfield - SPAM Karian Serpong Hilir Program Arman, Puspa, Porto | G2: Dokumen yang belum lengkap agar dilengkapi pada saat MC100 | H2: Project | I2: Karian Serpong Hilir | J2: Konstruksi Program Greenfield | K2: Tidak | L2: Info | M2: Info | P2: ABJ/DIR/EKS/12.25/1126 | R2: PMO Infill | S2: Ervin Y | T2: =DATEDIF(C2,$Z$1,"Y")&" tahun, "&DATEDIF(C2,$Z$1,"YM")&" bulan, "&DATEDIF(C2,$Z$1,"MD")&" hari" -> 0 tahun, 9 bulan, 4 hari | U2: =DATEDIF(C2,Summary!$A$1,"d") -> 277 | W2: {=_xlfn.IFS(U2<=X2,X2,U2<=X2*2,X2*2,U2<=X2*3,X2*3,U2>X2*3,">"&X2*3)} -> Info | X2: {=_xlfn.IFS(M2="Level 1",7,M2="Level 2",14,M2="Level 3","30",M2="Info","Info",M2="Closed","Closed")} -> Info
A3: 2 | B3: e-70214/PP.00.02 | C3: 46028 | D3: 46009 | E3: PAM JAYA | F3: Pemutakhiran Desain Akhir JDU JDB JDL dan SL Proyek Greenfield Regional Barat, Selatan, Utara, Pusat | G3: PAM JAYA meminta ABJ untuk melakukan survey sesuai lokasi pada surat terlampir | H3: Project | I3: Greenfield | J3: Perencanaan Program Greenfield | K3: Ya | L3: Closed | M3: Closed | O3: ABJ/DIR/EKS/08.26/0981 , ABJ/DIR/EKS/04.26/0377, ABJ/DIR/EKS/07.26/0845 | P3: ABJ/DIR/EKS/08.26/0981 , ABJ/DIR/EKS/04.26/0377, ABJ/DIR/EKS/07.26/0845 | R3: Planning | S3: Aji S | T3: =DATEDIF(C3,$Z$1,"Y")&" tahun, "&DATEDIF(C3,$Z$1,"YM")&" bulan, "&DATEDIF(C3,$Z$1,"MD")&" hari" -> 0 tahun, 9 bulan, 3 hari | U3: =DATEDIF(C3,Summary!$A$1,"d") -> 276 | V3: lewat 30d | W3: {=_xlfn.IFS(U3<=X3,X3,U3<=X3*2,X3*2,U3<=X3*3,X3*3,U3>X3*3,">"&X3*3)} -> Closed | X3: {=_xlfn.IFS(M3="Level 1",7,M3="Level 2",14,M3="Level 3","30",M3="Info","Info",M3="Closed","Closed")} -> Closed
A4: 3 | B4: e-70215/PS.00.04 | C4: 46028 | D4: 46008 | E4: PAM JAYA | F4: Permintaan Bukti Penyimpanan Dokumen | G4: PAM JAYA meminta bukti penyimpanan dokumen selambatnya 7 hari sejak surat diterima | H4: Corporate | I4: Corporate | J4: Administrasi & Dokumentasi | K4: Ya | L4: Closed | M4: Closed | O4: ABJ/DIR/EKS/01.26/0044 | P4: ABJ/DIR/EKS/01.26/0044 | R4: Compliance | S4: Indradi | T4: =DATEDIF(C4,$Z$1,"Y")&" tahun, "&DATEDIF(C4,$Z$1,"YM")&" bulan, "&DATEDIF(C4,$Z$1,"MD")&" hari" -> 0 tahun, 9 bulan, 3 hari | U4: =DATEDIF(C4,Summary!$A$1,"d") -> 276 | W4: {=_xlfn.IFS(U4<=X4,X4,U4<=X4*2,X4*2,U4<=X4*3,X4*3,U4>X4*3,">"&X4*3)} -> Closed | X4: {=_xlfn.IFS(M4="Level 1",7,M4="Level 2",14,M4="Level 3","30",M4="Info","Info",M4="Closed","Closed")} -> Closed
A5: 4 | B5: e-70217/PP.00.02 | C5: 46028 | D5: 46013 | E5: PAM JAYA | F5: Percepatan Pelaksanaan Program JDU+JDB+JDL dan Sambungan Langsung di Area Prioritas Regional Utara (Pantai Mutiara, Kp. Muka, Kp. Kerang Hijau Muara Angke) | G5: PAM JAYA meminta percepatan pekerjaan dan SL pada lokasi surat terlampir | H5: Project | I5: Greenfield | J5: Sambungan Langsung | K5: Ya | L5: Open | M5: Level 2 | R5: Planning | S5: Aji S | T5: =DATEDIF(C5,$Z$1,"Y")&" tahun, "&DATEDIF(C5,$Z$1,"YM")&" bulan, "&DATEDIF(C5,$Z$1,"MD")&" hari" -> 0 tahun, 9 bulan, 3 hari | U5: =DATEDIF(C5,Summary!$A$1,"d") -> 276 | V5: lewat 30d | W5: {=_xlfn.IFS(U5<=X5,X5,U5<=X5*2,X5*2,U5<=X5*3,X5*3,U5>X5*3,">"&X5*3)} -> >42 | X5: {=_xlfn.IFS(M5="Level 1",7,M5="Level 2",14,M5="Level 3","30",M5="Info","Info",M5="Closed","Closed")} -> 14
A6: 5 | B6: e-70229/PP.00.02 | C6: 46028 | D6: 46013 | E6: PAM JAYA | F6: Pemutakhiran Desain Akhir Proyek Greenfield IPA Portable Semanan | G6: PAM JAYA meminta untuk dilakukan survei bersama pada lokasi terlampir | H6: Project | I6: Greenfield | J6: Perencanaan Program Greenfield | K6: Ya | L6: Open | M6: Level 2 | R6: Planning | S6: Aji S | T6: =DATEDIF(C6,$Z$1,"Y")&" tahun, "&DATEDIF(C6,$Z$1,"YM")&" bulan, "&DATEDIF(C6,$Z$1,"MD")&" hari" -> 0 tahun, 9 bulan, 3 hari | U6: =DATEDIF(C6,Summary!$A$1,"d") -> 276 | V6: lewat 30d | W6: {=_xlfn.IFS(U6<=X6,X6,U6<=X6*2,X6*2,U6<=X6*3,X6*3,U6>X6*3,">"&X6*3)} -> >42 | X6: {=_xlfn.IFS(M6="Level 1",7,M6="Level 2",14,M6="Level 3","30",M6="Info","Info",M6="Closed","Closed")} -> 14
A7: 6 | B7: e-68122/PP.00.02 | C7: 46028 | D7: 45987 | E7: PAM JAYA | F7: Pemutakhiran Desain Akhir JDU JDB JDL dan SL Proyek Greenfield Corporate Customer Regional Timur | G7: PAM JAYA meminta untuk dilakukan survei bersama pada lokasi di surat terlampir | H7: Project | I7: Greenfield | J7: Perencanaan Program Greenfield | K7: Ya | L7: Open | M7: Level 2 | R7: Planning | S7: Aji S | T7: =DATEDIF(C7,$Z$1,"Y")&" tahun, "&DATEDIF(C7,$Z$1,"YM")&" bulan, "&DATEDIF(C7,$Z$1,"MD")&" hari" -> 0 tahun, 9 bulan, 3 hari | U7: =DATEDIF(C7,Summary!$A$1,"d") -> 276 | V7: lewat 30d | W7: {=_xlfn.IFS(U7<=X7,X7,U7<=X7*2,X7*2,U7<=X7*3,X7*3,U7>X7*3,">"&X7*3)} -> >42 | X7: {=_xlfn.IFS(M7="Level 1",7,M7="Level 2",14,M7="Level 3","30",M7="Info","Info",M7="Closed","Closed")} -> 14
A8: 7 | B8: e-70620/PP.00.02 | C8: 46028 | E8: PAM JAYA | F8: Pemutakhiran Desain Akhir JDU JDB JDL dan SL Proyek Greenfield Regional Utara dan Selatan | H8: Project | I8: Greenfield | J8: Perencanaan Program Greenfield | K8: Ya | L8: Open | M8: Level 2 | R8: Planning | S8: Aji S | T8: =DATEDIF(C8,$Z$1,"Y")&" tahun, "&DATEDIF(C8,$Z$1,"YM")&" bulan, "&DATEDIF(C8,$Z$1,"MD")&" hari" -> 0 tahun, 9 bulan, 3 hari | U8: =DATEDIF(C8,Summary!$A$1,"d") -> 276 | V8: lewat 30d | W8: {=_xlfn.IFS(U8<=X8,X8,U8<=X8*2,X8*2,U8<=X8*3,X8*3,U8>X8*3,">"&X8*3)} -> >42 | X8: {=_xlfn.IFS(M8="Level 1",7,M8="Level 2",14,M8="Level 3","30",M8="Info","Info",M8="Closed","Closed")} -> 14
A9: 8 | B9: 4720/PP.01.03/EKST/XII/2025 | C9: 46028 | D9: 46022 | E9: PAM JAYA | F9: Permintaan Pemenuhan Kewajiban Penyelesaian Paket Pekerjaan Kedua Proyek Greenfield pada saat Tanggal Operasi Komersial atau 5 Oktober 2025 | G9: Informasi project TOK 5 Oktober dan PAM JAYA meminta untuk memenuhi seluruh pekerjaan dan seluruh dokumen | H9: Project | I9: Greenfield | J9: Konstruksi Program Greenfield | K9: Tidak | L9: Info | M9: Info | R9: PMO Infill | S9: Danny L | T9: =DATEDIF(C9,$Z$1,"Y")&" tahun, "&DATEDIF(C9,$Z$1,"YM")&" bulan, "&DATEDIF(C9,$Z$1,"MD")&" hari" -> 0 tahun, 9 bulan, 3 hari | U9: =DATEDIF(C9,Summary!$A$1,"d") -> 276 | W9: {=_xlfn.IFS(U9<=X9,X9,U9<=X9*2,X9*2,U9<=X9*3,X9*3,U9>X9*3,">"&X9*3)} -> Info | X9: {=_xlfn.IFS(M9="Level 1",7,M9="Level 2",14,M9="Level 3","30",M9="Info","Info",M9="Closed","Closed")} -> Info
A10: 9 | B10: e-70216/PS.04.03 | C10: 46028 | D10: 46007 | E10: PAM JAYA | F10: Konfirmasi Perpanjangan Polis Asuransi Project Brownfield & Greenfield | G10: Konfirmasi rencana perpanjangan polis dalam jangka waktu 3 hari kalender | H10: Project | I10: Project | J10: Kontrak & Legal | K10: Ya | L10: Closed | M10: Closed | O10: ABJ/DIR/EKS/01.26/0046 | P10: ABJ/DIR/EKS/01.26/0046 | R10: Finance | S10: Nurul S | T10: =DATEDIF(C10,$Z$1,"Y")&" tahun, "&DATEDIF(C10,$Z$1,"YM")&" bulan, "&DATEDIF(C10,$Z$1,"MD")&" hari" -> 0 tahun, 9 bulan, 3 hari | U10: =DATEDIF(C10,Summary!$A$1,"d") -> 276 | W10: {=_xlfn.IFS(U10<=X10,X10,U10<=X10*2,X10*2,U10<=X10*3,X10*3,U10>X10*3,">"&X10*3)} -> Closed | X10: {=_xlfn.IFS(M10="Level 1",7,M10="Level 2",14,M10="Level 3","30",M10="Info","Info",M10="Closed","Closed")} -> Closed
A11: 10 | B11: 4719/PP.01.02/EKST/XII/2025 | C11: 46028 | D11: 46022 | E11: PAM JAYA | F11: Teguran terhadap Pengawasan Konsultan Pengawas Independen pada Dokumen Amandemen dan Pernyataan kembali Perjanjian Kerjasama Bundling | G11: Surat PAM JAYA kepada KPI SCI terkait teguran terhadap pengawasan pekerjaan, HSE, dan dokumentasi bahwa KPI belum optimal dalam peran sebagai Konsultan Pengawas Independen | H11: Project | I11: Project | J11: Kontrak & Legal | K11: Tidak | L11: Info | M11: Info | R11: Compliance | S11: Indradi | T11: =DATEDIF(C11,$Z$1,"Y")&" tahun, "&DATEDIF(C11,$Z$1,"YM")&" bulan, "&DATEDIF(C11,$Z$1,"MD")&" hari" -> 0 tahun, 9 bulan, 3 hari | U11: =DATEDIF(C11,Summary!$A$1,"d") -> 276 | W11: {=_xlfn.IFS(U11<=X11,X11,U11<=X11*2,X11*2,U11<=X11*3,X11*3,U11>X11*3,">"&X11*3)} -> Info | X11: {=_xlfn.IFS(M11="Level 1",7,M11="Level 2",14,M11="Level 3","30",M11="Info","Info",M11="Closed","Closed")} -> Info
A12: 11 | B12: e-70362/PM.01.00 | C12: 46028 | D12: 46007 | E12: PAM JAYA | F12: Permohonan Pemasangan Sambungan Langsung Air Minum Perpipaan di area Halim Perdana Kusuma | G12: Surat PAM JAYA kepada Komandan Pangkalan TNI AU perihal pemasangan SL di area Halim | H12: Project | I12: Greenfield | J12: Sambungan Langsung | K12: Tidak | L12: Info | M12: Info | R12: PMO NC | S12: A. Levi | T12: =DATEDIF(C12,$Z$1,"Y")&" tahun, "&DATEDIF(C12,$Z$1,"YM")&" bulan, "&DATEDIF(C12,$Z$1,"MD")&" hari" -> 0 tahun, 9 bulan, 3 hari | U12: =DATEDIF(C12,Summary!$A$1,"d") -> 276 | W12: {=_xlfn.IFS(U12<=X12,X12,U12<=X12*2,X12*2,U12<=X12*3,X12*3,U12>X12*3,">"&X12*3)} -> Info | X12: {=_xlfn.IFS(M12="Level 1",7,M12="Level 2",14,M12="Level 3","30",M12="Info","Info",M12="Closed","Closed")} -> Info
A13: 12 | B13: 012/S/DIR/BPM-ABJ/I/2026 | C13: 46029 | D13: 46028 | E13: BPM | F13: Penagihan Pekerjaan Sambungan Langsung | G13: Konfirmasi pihak ABJ terhadap pengendaan denda terhadap keterlambatan SL | H13: Project | I13: Greenfield | J13: Sambungan Langsung | K13: Ya | L13: Closed | M13: Closed | O13: ABJ/DIR/EKS/01.26/0032 | P13: ABJ/DIR/EKS/01.26/0032 | R13: PMO NC | S13: A. Levi | T13: =DATEDIF(C13,$Z$1,"Y")&" tahun, "&DATEDIF(C13,$Z$1,"YM")&" bulan, "&DATEDIF(C13,$Z$1,"MD")&" hari" -> 0 tahun, 9 bulan, 2 hari | U13: =DATEDIF(C13,Summary!$A$1,"d") -> 275 | V13: lewat 30d | W13: {=_xlfn.IFS(U13<=X13,X13,U13<=X13*2,X13*2,U13<=X13*3,X13*3,U13>X13*3,">"&X13*3)} -> Closed | X13: {=_xlfn.IFS(M13="Level 1",7,M13="Level 2",14,M13="Level 3","30",M13="Info","Info",M13="Closed","Closed")} -> Closed
A14: 13 | B14: 4722/PS.04.03/EKST/XII/2025 | C14: 46031 | D14: 46022 | E14: PAM JAYA | F14: Tanggapan Pengiriman Dokumen Desain Akhir Program Rehabilitasi Proyek Brownfield Tahun 2026 | G14: PAM JAYA meminta ABJ untuk klarifikasi atas desain akhir maksimal 30 hari kerja sejak dokumen ditanggapi PAM/KPI | H14: Project | I14: Cyclical | J14: Perencanaan Program Greenfield | K14: Ya | L14: Closed | M14: Closed | O14: ABJ/DIR/EKS/01.26/0076 | P14: ABJ/DIR/EKS/01.26/0076 | R14: PMO Cyclical | S14: Agus H | T14: =DATEDIF(C14,$Z$1,"Y")&" tahun, "&DATEDIF(C14,$Z$1,"YM")&" bulan, "&DATEDIF(C14,$Z$1,"MD")&" hari" -> 0 tahun, 9 bulan, 0 hari | U14: =DATEDIF(C14,Summary!$A$1,"d") -> 273 | W14: {=_xlfn.IFS(U14<=X14,X14,U14<=X14*2,X14*2,U14<=X14*3,X14*3,U14>X14*3,">"&X14*3)} -> Closed | X14: {=_xlfn.IFS(M14="Level 1",7,M14="Level 2",14,M14="Level 3","30",M14="Info","Info",M14="Closed","Closed")} -> Closed
A15: 14 | B15: e-69888/PP.01.05 | C15: 46031 | D15: 46008 | E15: PAM JAYA | F15: Teguran atas Pelaksanaan Pemenuhan Perizinan Proyek Bundling | G15: PAM JAYA meminta ABJ untuk menyelesaikan pemenuhan kewajiban perizinan keseluruhan project bundling dan menyampaikan progress perizinan setiap kamis pukul 15.00 | H15: Project | I15: Greenfield | J15: Konstruksi Program Greenfield | K15: Tidak | L15: Info | M15: Info | R15: PMO/Permit | S15: Danny L; Rais S | T15: =DATEDIF(C15,$Z$1,"Y")&" tahun, "&DATEDIF(C15,$Z$1,"YM")&" bulan, "&DATEDIF(C15,$Z$1,"MD")&" hari" -> 0 tahun, 9 bulan, 0 hari | U15: =DATEDIF(C15,Summary!$A$1,"d") -> 273 | W15: {=_xlfn.IFS(U15<=X15,X15,U15<=X15*2,X15*2,U15<=X15*3,X15*3,U15>X15*3,">"&X15*3)} -> Info | X15: {=_xlfn.IFS(M15="Level 1",7,M15="Level 2",14,M15="Level 3","30",M15="Info","Info",M15="Closed","Closed")} -> Info
A16: 15 | B16: e-70776/PP.01.04 | C16: 46031 | D16: 46007 | E16: PAM JAYA | F16: Sanksi Denda atas Kegagalan Kinerja Periode Bulan November 2025 | G16: Denda kegagalan kinerja tekanan IPA Pejompongan 1 (11 November 2025) senilai Rp1.030.742 | H16: Produksi | I16: PJP 1 | J16: Denda & Kegagalan | K16: Ya | L16: Closed | M16: Closed | O16: ABJ/DIR/EKS/01.26/0037 | P16: ABJ/DIR/EKS/01.26/0037 | R16: Compliance | S16: Indradi | T16: =DATEDIF(C16,$Z$1,"Y")&" tahun, "&DATEDIF(C16,$Z$1,"YM")&" bulan, "&DATEDIF(C16,$Z$1,"MD")&" hari" -> 0 tahun, 9 bulan, 0 hari | U16: =DATEDIF(C16,Summary!$A$1,"d") -> 273 | W16: {=_xlfn.IFS(U16<=X16,X16,U16<=X16*2,X16*2,U16<=X16*3,X16*3,U16>X16*3,">"&X16*3)} -> Closed | X16: {=_xlfn.IFS(M16="Level 1",7,M16="Level 2",14,M16="Level 3","30",M16="Info","Info",M16="Closed","Closed")} -> Closed
A17: 16 | B17: e-70749/PP.00.02 | C17: 46035 | D17: 46024 | E17: PAM JAYA | F17: Pemutakhiran Desain Akhir JDU JDB JDL dan SL Proyek Greenfield Corporate Customer Regional Utara dan Selatan | G17: PAM JAYA meminta ABJ untuk pemutakhiran DED pada lokasi terlampir | H17: Project | I17: Greenfield | J17: Perencanaan Program Greenfield | K17: Ya | L17: Open | M17: Level 2 | R17: Planning | S17: Aji S | T17: =DATEDIF(C17,$Z$1,"Y")&" tahun, "&DATEDIF(C17,$Z$1,"YM")&" bulan, "&DATEDIF(C17,$Z$1,"MD")&" hari" -> 0 tahun, 8 bulan, 26 hari | U17: =DATEDIF(C17,Summary!$A$1,"d") -> 269 | V17: lewat 30d | W17: {=_xlfn.IFS(U17<=X17,X17,U17<=X17*2,X17*2,U17<=X17*3,X17*3,U17>X17*3,">"&X17*3)} -> >42 | X17: {=_xlfn.IFS(M17="Level 1",7,M17="Level 2",14,M17="Level 3","30",M17="Info","Info",M17="Closed","Closed")} -> 14
A18: 17 | B18: 153/SCI-KPI/I/2026 | C18: 46041 | D18: 46037 | E18: KPI - Sucofindo | F18: Penyampaian Laporan Penyelesaian Uji Komisioning Project Greenfield – SPAM Jatiluhur Hilir 9 Program | G18: Dapat dilanjutkan ke MC100 | H18: Project | I18: Jatiluhur Hilir | J18: Konstruksi Program Greenfield | K18: Tidak | L18: Info | M18: Info | P18: ABJ/DIR/EKS/01.26/0040 | R18: PMO Infill | S18: Muhrojin | T18: =DATEDIF(C18,$Z$1,"Y")&" tahun, "&DATEDIF(C18,$Z$1,"YM")&" bulan, "&DATEDIF(C18,$Z$1,"MD")&" hari" -> 0 tahun, 8 bulan, 20 hari | U18: =DATEDIF(C18,Summary!$A$1,"d") -> 263 | W18: {=_xlfn.IFS(U18<=X18,X18,U18<=X18*2,X18*2,U18<=X18*3,X18*3,U18>X18*3,">"&X18*3)} -> Info | X18: {=_xlfn.IFS(M18="Level 1",7,M18="Level 2",14,M18="Level 3","30",M18="Info","Info",M18="Closed","Closed")} -> Info
A19: 18 | B19: 016/Dir/Ity/I/2026 | C19: 46049 | D19: 46044 | E19: PT Infra Tama Yakti | F19: Surat Peringatan Akibat Kegagalan Perencanaan Oleh Infratama | G19: Penyampaian bahwa kegagalan disebabkan keterbatasan data eksisting | H19: Project | I19: Project | J19: Perencanaan Program Greenfield | K19: Tidak | L19: Info | M19: Info | R19: PGO | S19: Angelika | T19: =DATEDIF(C19,$Z$1,"Y")&" tahun, "&DATEDIF(C19,$Z$1,"YM")&" bulan, "&DATEDIF(C19,$Z$1,"MD")&" hari" -> 0 tahun, 8 bulan, 12 hari | U19: =DATEDIF(C19,Summary!$A$1,"d") -> 255 | W19: {=_xlfn.IFS(U19<=X19,X19,U19<=X19*2,X19*2,U19<=X19*3,X19*3,U19>X19*3,">"&X19*3)} -> Info | X19: {=_xlfn.IFS(M19="Level 1",7,M19="Level 2",14,M19="Level 3","30",M19="Info","Info",M19="Closed","Closed")} -> Info
A20: 19 | B20: 156/SCI-KPI/I/2026 | C20: 46048 | D20: 46014 | E20: KPI - Sucofindo | F20: Tanggapan atas Surat PT Air Bersih Jakarta No. ABJ/DIR/EKS/01.26/0064 Perihal Penyampaian Laporan Penyelesaian Uji Komisioning Project Greenfield – SPAM Jatiluhur Hilir 2 Program | G20: Dapat dilanjutkan ke MC100 | H20: Project | I20: Jatiluhur Hilir | J20: Konstruksi Program Greenfield | K20: Tidak | L20: Info | M20: Info | P20: ABJ/DIR/EKS/01.26/0064 | R20: PMO Infill | S20: Muhrojin | T20: =DATEDIF(C20,$Z$1,"Y")&" tahun, "&DATEDIF(C20,$Z$1,"YM")&" bulan, "&DATEDIF(C20,$Z$1,"MD")&" hari" -> 0 tahun, 8 bulan, 13 hari | U20: =DATEDIF(C20,Summary!$A$1,"d") -> 256 | W20: {=_xlfn.IFS(U20<=X20,X20,U20<=X20*2,X20*2,U20<=X20*3,X20*3,U20>X20*3,">"&X20*3)} -> Info | X20: {=_xlfn.IFS(M20="Level 1",7,M20="Level 2",14,M20="Level 3","30",M20="Info","Info",M20="Closed","Closed")} -> Info
A21: 20 | B21: e-71304/PP.00.02 | C21: 46049 | D21: 46035 | E21: PAM JAYA | F21: Pemutakhiran Desain Akhir JDU JDB JDL dan SL Proyek Greenfield Regional Selatan dan Utara | G21: PAM JAYA meminta ABJ untuk pemutakhiran DED pada lokasi terlampir | H21: Project | I21: Greenfield | J21: Perencanaan Program Greenfield | K21: Ya | L21: Closed | M21: Closed | O21: ABJ/DIR/EKS/08.26/0981 | P21: ABJ/DIR/EKS/08.26/0981 | R21: Planning | S21: Aji S | T21: =DATEDIF(C21,$Z$1,"Y")&" tahun, "&DATEDIF(C21,$Z$1,"YM")&" bulan, "&DATEDIF(C21,$Z$1,"MD")&" hari" -> 0 tahun, 8 bulan, 12 hari | U21: =DATEDIF(C21,Summary!$A$1,"d") -> 255 | V21: lewat 30d | W21: {=_xlfn.IFS(U21<=X21,X21,U21<=X21*2,X21*2,U21<=X21*3,X21*3,U21>X21*3,">"&X21*3)} -> Closed | X21: {=_xlfn.IFS(M21="Level 1",7,M21="Level 2",14,M21="Level 3","30",M21="Info","Info",M21="Closed","Closed")} -> Closed
A22: 21 | B22: e-71127/PP.00.06 | C22: 46049 | D22: 46030 | E22: PAM JAYA | F22: Permintaan Pemenuhan Perizinan Pekerjaan TOK 5 April 2026 | G22: PAM JAYA meminta ABJ untuk menyelesaikan dan melakukan pemenuhan kewajiban terkait perizinan proyek bundling TOK April 2026 | H22: Project | I22: Greenfield | J22: Konstruksi Program Greenfield | K22: Ya | L22: Open | M22: Level 2 | R22: Permit | S22: Rudy | T22: =DATEDIF(C22,$Z$1,"Y")&" tahun, "&DATEDIF(C22,$Z$1,"YM")&" bulan, "&DATEDIF(C22,$Z$1,"MD")&" hari" -> 0 tahun, 8 bulan, 12 hari | U22: =DATEDIF(C22,Summary!$A$1,"d") -> 255 | V22: lewat 30d | W22: {=_xlfn.IFS(U22<=X22,X22,U22<=X22*2,X22*2,U22<=X22*3,X22*3,U22>X22*3,">"&X22*3)} -> >42 | X22: {=_xlfn.IFS(M22="Level 1",7,M22="Level 2",14,M22="Level 3","30",M22="Info","Info",M22="Closed","Closed")} -> 14
A23: 22 | B23: e-71126/PP.01.02 | C23: 46049 | D23: 46022 | E23: PAM JAYA | F23: Teguran Penerapan Aspek Keselamtan dan Kesehatan Kerja (K3) pada Proyek Greenfield dan Brownfield | G23: PAM JAYA meminta ABJ untuk memastikan ABJ melakukan pemeriksaan atas kewajiban implementasi K3 | H23: Project | I23: Project | J23: HSE | K23: Ya | L23: Closed | M23: Closed | O23: ABJ/DIR/EKS/02.26/0140 | P23: ABJ/DIR/EKS/02.26/0140 | R23: HSE | S23: Irsan | T23: =DATEDIF(C23,$Z$1,"Y")&" tahun, "&DATEDIF(C23,$Z$1,"YM")&" bulan, "&DATEDIF(C23,$Z$1,"MD")&" hari" -> 0 tahun, 8 bulan, 12 hari | U23: =DATEDIF(C23,Summary!$A$1,"d") -> 255 | W23: {=_xlfn.IFS(U23<=X23,X23,U23<=X23*2,X23*2,U23<=X23*3,X23*3,U23>X23*3,">"&X23*3)} -> Closed | X23: {=_xlfn.IFS(M23="Level 1",7,M23="Level 2",14,M23="Level 3","30",M23="Info","Info",M23="Closed","Closed")} -> Closed
A24: 23 | B24: e-71125/PP.01.02 | C24: 46049 | D24: 46021 | E24: PAM JAYA | F24: Teguran Keterlambatan Realisasi Pemasangan Sambungan Langsung Bulan Desember 2025 | G24: PAM JAYA meminta ABJ untuk pemenuhan pemasangan SL selambatnya 5 hari kalender | H24: Project | I24: Greenfield | J24: Sambungan Langsung | K24: Ya | L24: Closed | M24: Closed | O24: ABJ/DIR/EKS/02.26/0160 | P24: ABJ/DIR/EKS/02.26/0160 | R24: PMO NC | S24: A. Levi | T24: =DATEDIF(C24,$Z$1,"Y")&" tahun, "&DATEDIF(C24,$Z$1,"YM")&" bulan, "&DATEDIF(C24,$Z$1,"MD")&" hari" -> 0 tahun, 8 bulan, 12 hari | U24: =DATEDIF(C24,Summary!$A$1,"d") -> 255 | V24: lewat 30d | W24: {=_xlfn.IFS(U24<=X24,X24,U24<=X24*2,X24*2,U24<=X24*3,X24*3,U24>X24*3,">"&X24*3)} -> Closed | X24: {=_xlfn.IFS(M24="Level 1",7,M24="Level 2",14,M24="Level 3","30",M24="Info","Info",M24="Closed","Closed")} -> Closed
A25: 24 | B25: 300.1.4/61-Kc.PG-Trantib | C25: 46050 | D25: 46034 | E25: Pemkot Bekasi Kecamatan Pondok Gede | F25: Legalitas Perijinan | G25: Perihal legalitas perizinan terkait penampungn/pembuangan tanah di Jl Jatiwaringin | H25: Project | I25: Greenfield | J25: Koordinasi & Sosialisasi | K25: Tidak | L25: Info | M25: Info | R25: Permit | S25: Rais A | T25: =DATEDIF(C25,$Z$1,"Y")&" tahun, "&DATEDIF(C25,$Z$1,"YM")&" bulan, "&DATEDIF(C25,$Z$1,"MD")&" hari" -> 0 tahun, 8 bulan, 11 hari | U25: =DATEDIF(C25,Summary!$A$1,"d") -> 254 | W25: {=_xlfn.IFS(U25<=X25,X25,U25<=X25*2,X25*2,U25<=X25*3,X25*3,U25>X25*3,">"&X25*3)} -> Info | X25: {=_xlfn.IFS(M25="Level 1",7,M25="Level 2",14,M25="Level 3","30",M25="Info","Info",M25="Closed","Closed")} -> Info
A26: 25 | B26: 158/SCI-KPI/I/2026 | C26: 46052 | E26: KPI - Sucofindo | F26: Surat Pengantar Revisi Laporan Bulanan Proyek Bundling SPAM DKI Jakarta - Konsultan Pengawas Independen Periode Desember 2025 | G26: Laporan Bulanan Desember 2025 | H26: Project | I26: Project | J26: Monitoring & Pelaporan | K26: Tidak | L26: Info | M26: Info | R26: Compliance | S26: Indradi | T26: =DATEDIF(C26,$Z$1,"Y")&" tahun, "&DATEDIF(C26,$Z$1,"YM")&" bulan, "&DATEDIF(C26,$Z$1,"MD")&" hari" -> 0 tahun, 8 bulan, 9 hari | U26: =DATEDIF(C26,Summary!$A$1,"d") -> 252 | W26: {=_xlfn.IFS(U26<=X26,X26,U26<=X26*2,X26*2,U26<=X26*3,X26*3,U26>X26*3,">"&X26*3)} -> Info | X26: {=_xlfn.IFS(M26="Level 1",7,M26="Level 2",14,M26="Level 3","30",M26="Info","Info",M26="Closed","Closed")} -> Info
A27: 26 | B27: 173/SCI-KPI/I/2026 | C27: 46052 | D27: 46048 | E27: KPI - Sucofindo | F27: Tanggapan atas Surat PT Air Bersih Jakarta No. ABJ/DIR/EKS/01.26/0070 Tentang Penyampaian Laporan Penyelesaian Uji Komisioning Project Greenfield - SPAM Buaran 3 Hilir Program Anwar Burhanudin | G27: Dapat dilanjutkan ke MC100 | H27: Project | I27: Buaran 3 Hilir | J27: Konstruksi Program Greenfield | K27: Tidak | L27: Info | M27: Info | P27: ABJ/DIR/EKS/01.26/0070 | R27: PMO Infill | S27: Topan | T27: =DATEDIF(C27,$Z$1,"Y")&" tahun, "&DATEDIF(C27,$Z$1,"YM")&" bulan, "&DATEDIF(C27,$Z$1,"MD")&" hari" -> 0 tahun, 8 bulan, 9 hari | U27: =DATEDIF(C27,Summary!$A$1,"d") -> 252 | W27: {=_xlfn.IFS(U27<=X27,X27,U27<=X27*2,X27*2,U27<=X27*3,X27*3,U27>X27*3,">"&X27*3)} -> Info | X27: {=_xlfn.IFS(M27="Level 1",7,M27="Level 2",14,M27="Level 3","30",M27="Info","Info",M27="Closed","Closed")} -> Info
A28: 27 | B28: e-70219/PP.00.02 | C28: 46055 | D28: 46044 | E28: PAM JAYA | F28: Pemutakhiran Desain Akhir JDU JDB JDL dan SL Proyek Greenfield Regional Barat, Selatan, Utara, Pusat | G28: Agar dilakukan survey bersama dan penyelarasan desain akhir | H28: Project | I28: Greenfield | J28: Perencanaan Program Greenfield | K28: Ya | L28: Closed | M28: Closed | R28: Planning | S28: Aji S | T28: =DATEDIF(C28,$Z$1,"Y")&" tahun, "&DATEDIF(C28,$Z$1,"YM")&" bulan, "&DATEDIF(C28,$Z$1,"MD")&" hari" -> 0 tahun, 8 bulan, 7 hari | U28: =DATEDIF(C28,Summary!$A$1,"d") -> 249 | V28: lewat 30d | W28: {=_xlfn.IFS(U28<=X28,X28,U28<=X28*2,X28*2,U28<=X28*3,X28*3,U28>X28*3,">"&X28*3)} -> Closed | X28: {=_xlfn.IFS(M28="Level 1",7,M28="Level 2",14,M28="Level 3","30",M28="Info","Info",M28="Closed","Closed")} -> Closed
A29: 28 | B29: e-72121/KU.01.15 | C29: 46055 | D29: 46045 | E29: PAM JAYA | F29: Permintaan Penyampaian Laporan Keuangan Audited Tahun 2025 dan Pemenuhan Kewajiban Penyetoran Ekuitas Tahun 2026 | G29: PAM JAYA meminta ABJ untuk melakukan kewajiban penyetoran ekuitas dan menyampaikan laporan keuangan audited 2025 | H29: Corporate | I29: Corporate | J29: Keuangan, Pembayaran, Investasi | K29: Ya | L29: Closed | M29: Closed | R29: Finance | S29: Nurul S | T29: =DATEDIF(C29,$Z$1,"Y")&" tahun, "&DATEDIF(C29,$Z$1,"YM")&" bulan, "&DATEDIF(C29,$Z$1,"MD")&" hari" -> 0 tahun, 8 bulan, 7 hari | U29: =DATEDIF(C29,Summary!$A$1,"d") -> 249 | V29: lewat 30d | W29: {=_xlfn.IFS(U29<=X29,X29,U29<=X29*2,X29*2,U29<=X29*3,X29*3,U29>X29*3,">"&X29*3)} -> Closed | X29: {=_xlfn.IFS(M29="Level 1",7,M29="Level 2",14,M29="Level 3","30",M29="Info","Info",M29="Closed","Closed")} -> Closed
A30: 29 | B30: e-72122/PP.00.02 | C30: 46055 | D30: 46043 | E30: PAM JAYA | F30: Pembaharuan Informasi Proyek Greenfield JDU JDB JDL dan SL Regional Selatan, Barat, dan Timur | G30: PAM JAYA meminta ABJ untuk menindaklanjuti lokasi rencana sebagaimana surat terlampir | H30: Project | I30: Greenfield | J30: Perencanaan Program Greenfield | K30: Ya | L30: Info | M30: Info | R30: Planning | S30: Aji S | T30: =DATEDIF(C30,$Z$1,"Y")&" tahun, "&DATEDIF(C30,$Z$1,"YM")&" bulan, "&DATEDIF(C30,$Z$1,"MD")&" hari" -> 0 tahun, 8 bulan, 7 hari | U30: =DATEDIF(C30,Summary!$A$1,"d") -> 249 | V30: lewat 30d | W30: {=_xlfn.IFS(U30<=X30,X30,U30<=X30*2,X30*2,U30<=X30*3,X30*3,U30>X30*3,">"&X30*3)} -> Info | X30: {=_xlfn.IFS(M30="Level 1",7,M30="Level 2",14,M30="Level 3","30",M30="Info","Info",M30="Closed","Closed")} -> Info
A31: 30 | B31: e-72124/PP.00.02 | C31: 46055 | D31: 46044 | E31: PAM JAYA | F31: Pembaharuan Informasi Proyek Greenfield JDU JDB JDL dan SL Regional Utara | G31: PAM JAYA meminta ABJ untuk menindaklanjuti rencana lokasi sesuai surat terlampir | H31: Project | I31: Greenfield | J31: Perencanaan Program Greenfield | K31: Ya | L31: Info | M31: Info | R31: Planning | S31: Aji S | T31: =DATEDIF(C31,$Z$1,"Y")&" tahun, "&DATEDIF(C31,$Z$1,"YM")&" bulan, "&DATEDIF(C31,$Z$1,"MD")&" hari" -> 0 tahun, 8 bulan, 7 hari | U31: =DATEDIF(C31,Summary!$A$1,"d") -> 249 | V31: lewat 30d | W31: {=_xlfn.IFS(U31<=X31,X31,U31<=X31*2,X31*2,U31<=X31*3,X31*3,U31>X31*3,">"&X31*3)} -> Info | X31: {=_xlfn.IFS(M31="Level 1",7,M31="Level 2",14,M31="Level 3","30",M31="Info","Info",M31="Closed","Closed")} -> Info
A32: 31 | B32: e-72125/PP.00.02 | C32: 46055 | D32: 46045 | E32: PAM JAYA | F32: Pemutakhiran Desain Akhir JDU JDB JDL dan SL Proyek Greenfield Warga Muara Baru Gg. Elektro | G32: PAM JAYA meminta ABJ untuk menindaklanjuti lokasi rencana pekerjaan pada surat terlampir | H32: Project | I32: Greenfield | J32: Perencanaan Program Greenfield | K32: Ya | L32: Closed | M32: Closed | O32: ABJ/DIR/EKS/08.26/0981 | P32: ABJ/DIR/EKS/08.26/0981 | R32: Planning | S32: Aji S | T32: =DATEDIF(C32,$Z$1,"Y")&" tahun, "&DATEDIF(C32,$Z$1,"YM")&" bulan, "&DATEDIF(C32,$Z$1,"MD")&" hari" -> 0 tahun, 8 bulan, 7 hari | U32: =DATEDIF(C32,Summary!$A$1,"d") -> 249 | V32: lewat 30d | W32: {=_xlfn.IFS(U32<=X32,X32,U32<=X32*2,X32*2,U32<=X32*3,X32*3,U32>X32*3,">"&X32*3)} -> Closed | X32: {=_xlfn.IFS(M32="Level 1",7,M32="Level 2",14,M32="Level 3","30",M32="Info","Info",M32="Closed","Closed")} -> Closed
A33: 32 | B33: e-72126/PP.00.02 | C33: 46055 | D33: 46045 | E33: PAM JAYA | F33: Pemutakhiran Desain Akhir JDU JDB JDL dan SL Proyek Greenfield Bank Rakyat Indonesia (Gudang BRI) | G33: PAM JAYA meminta ABJ untuk menindaklanjuti lokasi rencana pada surat terlampir | H33: Project | I33: Greenfield | J33: Perencanaan Program Greenfield | K33: Ya | L33: Open | M33: Level 2 | R33: Planning | S33: Aji S | T33: =DATEDIF(C33,$Z$1,"Y")&" tahun, "&DATEDIF(C33,$Z$1,"YM")&" bulan, "&DATEDIF(C33,$Z$1,"MD")&" hari" -> 0 tahun, 8 bulan, 7 hari | U33: =DATEDIF(C33,Summary!$A$1,"d") -> 249 | V33: lewat 30d | W33: {=_xlfn.IFS(U33<=X33,X33,U33<=X33*2,X33*2,U33<=X33*3,X33*3,U33>X33*3,">"&X33*3)} -> >42 | X33: {=_xlfn.IFS(M33="Level 1",7,M33="Level 2",14,M33="Level 3","30",M33="Info","Info",M33="Closed","Closed")} -> 14
A34: 33 | B34: e-72203/PP.00.02 | C34: 46055 | D34: 46079 | E34: PAM JAYA | F34: Pemutakhiran Desain Akhir JDU JDB JDL dan SL Proyek Greenfield Perumahan Bumi Karang Indah | G34: PAM JAYA meminta ABJ untuk menindaklanjuti lokasi rencana pada surat terlampir | H34: Project | I34: Greenfield | J34: Perencanaan Program Greenfield | K34: Ya | L34: Closed | M34: Closed | O34: ABJ/DIR/EKS/08.26/0981 | P34: ABJ/DIR/EKS/08.26/0981 | R34: Planning | S34: Aji S | T34: =DATEDIF(C34,$Z$1,"Y")&" tahun, "&DATEDIF(C34,$Z$1,"YM")&" bulan, "&DATEDIF(C34,$Z$1,"MD")&" hari" -> 0 tahun, 8 bulan, 7 hari | U34: =DATEDIF(C34,Summary!$A$1,"d") -> 249 | V34: lewat 30d | W34: {=_xlfn.IFS(U34<=X34,X34,U34<=X34*2,X34*2,U34<=X34*3,X34*3,U34>X34*3,">"&X34*3)} -> Closed | X34: {=_xlfn.IFS(M34="Level 1",7,M34="Level 2",14,M34="Level 3","30",M34="Info","Info",M34="Closed","Closed")} -> Closed
A35: 34 | B35: e-72204/PP.00.02 | C35: 46055 | D35: 46048 | E35: PAM JAYA | F35: Pemutakhiran Desain Akhir JDU JDB JDL dan SL Proyek Greenfield Jl. Papanggo II Gg Mangga dan Gg Rambutan dan RW 005 Kelurahan Cilandak | G35: PAM JAYA meminta ABJ untuk menindaklanjuti lokasi rencana pada surat terlampir | H35: Project | I35: Greenfield | J35: Perencanaan Program Greenfield | K35: Ya | L35: Open | M35: Level 2 | R35: Planning | S35: Aji S | T35: =DATEDIF(C35,$Z$1,"Y")&" tahun, "&DATEDIF(C35,$Z$1,"YM")&" bulan, "&DATEDIF(C35,$Z$1,"MD")&" hari" -> 0 tahun, 8 bulan, 7 hari | U35: =DATEDIF(C35,Summary!$A$1,"d") -> 249 | V35: lewat 30d | W35: {=_xlfn.IFS(U35<=X35,X35,U35<=X35*2,X35*2,U35<=X35*3,X35*3,U35>X35*3,">"&X35*3)} -> >42 | X35: {=_xlfn.IFS(M35="Level 1",7,M35="Level 2",14,M35="Level 3","30",M35="Info","Info",M35="Closed","Closed")} -> 14
A36: 35 | B36: e-72146/PP.03.05 | C36: 46055 | D36: 46041 | E36: PAM JAYA | F36: Penyampaian Hasil Inspeksi K3L Terjadwal di IPA Pulogadung Tahun 2025 | G36: ABJ untuk menyampaikan rencana perbaikan selambatnya 14 hari kalender | H36: Produksi | I36: Pulogadung | J36: HSE | K36: Ya | L36: Closed | M36: Closed | O36: ABJ/DIR/EKS/02.26/0106 | P36: ABJ/DIR/EKS/02.26/0106 | R36: HSE | S36: Irsan | T36: =DATEDIF(C36,$Z$1,"Y")&" tahun, "&DATEDIF(C36,$Z$1,"YM")&" bulan, "&DATEDIF(C36,$Z$1,"MD")&" hari" -> 0 tahun, 8 bulan, 7 hari | U36: =DATEDIF(C36,Summary!$A$1,"d") -> 249 | W36: {=_xlfn.IFS(U36<=X36,X36,U36<=X36*2,X36*2,U36<=X36*3,X36*3,U36>X36*3,">"&X36*3)} -> Closed | X36: {=_xlfn.IFS(M36="Level 1",7,M36="Level 2",14,M36="Level 3","30",M36="Info","Info",M36="Closed","Closed")} -> Closed
A37: 36 | B37: e-72147/PP.03.05 | C37: 46055 | D37: 46041 | E37: PAM JAYA | F37: Penyampaian Hasil Inspeksi Aset dan Peralatan di IPA Pulogadung Tanggal 26 Februari 2025, 04 Juli 2025, dan 26 Agustus 2025 | G37: ABJ untuk menyampaikan rencana perbaikan selambat-lambatnya jangka waktu 14 hari kalender | H37: Produksi | I37: Pulogadung | J37: Operation & Maintenance | K37: Ya | L37: Closed | M37: Closed | O37: ABJ/DIR/EKS/02.26/0127 | P37: ABJ/DIR/EKS/02.26/0127 | R37: Produksi | S37: Wahyudian | T37: =DATEDIF(C37,$Z$1,"Y")&" tahun, "&DATEDIF(C37,$Z$1,"YM")&" bulan, "&DATEDIF(C37,$Z$1,"MD")&" hari" -> 0 tahun, 8 bulan, 7 hari | U37: =DATEDIF(C37,Summary!$A$1,"d") -> 249 | W37: {=_xlfn.IFS(U37<=X37,X37,U37<=X37*2,X37*2,U37<=X37*3,X37*3,U37>X37*3,">"&X37*3)} -> Closed | X37: {=_xlfn.IFS(M37="Level 1",7,M37="Level 2",14,M37="Level 3","30",M37="Info","Info",M37="Closed","Closed")} -> Closed
A38: 37 | B38: e-71848.PM.02.03 | C38: 46055 | D38: 46030 | E38: PAM JAYA | F38: Tindak Lanjut Strategi Target Realisasi Pemasangan Sambungan Langsung 2026 | G38: PAM JAYA meminta ABJ untuk melaksanakan pemasangan SL pada lokasi RW yang telah mencapai 50% dari total potensi bangunan non pelanggan dan telah disampaikan data oleh PAM melalui FA online | H38: Project | I38: Greenfield | J38: Sambungan Langsung | K38: Tidak | L38: Closed | M38: Closed | O38: ABJ/DIR/EKS/02.26/0107, ABJ/DIR/EKS/02.26/0149 | P38: ABJ/DIR/EKS/02.26/0107, ABJ/DIR/EKS/02.26/0149 | R38: PMO NC | S38: A. Levi | T38: =DATEDIF(C38,$Z$1,"Y")&" tahun, "&DATEDIF(C38,$Z$1,"YM")&" bulan, "&DATEDIF(C38,$Z$1,"MD")&" hari" -> 0 tahun, 8 bulan, 7 hari | U38: =DATEDIF(C38,Summary!$A$1,"d") -> 249 | V38: Lewat 7d | W38: {=_xlfn.IFS(U38<=X38,X38,U38<=X38*2,X38*2,U38<=X38*3,X38*3,U38>X38*3,">"&X38*3)} -> Closed | X38: {=_xlfn.IFS(M38="Level 1",7,M38="Level 2",14,M38="Level 3","30",M38="Info","Info",M38="Closed","Closed")} -> Closed
A39: 38 | B39: 164/SCI-KPI/I/2026 | C39: 46055 | D39: 46045 | E39: KPI - Sucofindo | F39: Tanggapan atas Surat PT Air Bersih Jakarta No. ABJ/DIR/EKS/11.25/1025 Tentang DED dan RAB Perluasan Jaringan Untuk 3 Lokasi Infill Ad Hoc Sambungan Baru Proyek SPAM Jatiluhur Hilir dan SPAM Buaran 3 Hilir | G39: Penyampaian hasil pemeriksaan DED RAB Perluasan Jaringan Untuk 3 Lokasi Infill Ad Hoc Sambungan Baru Proyek SPAM Jatiluhur Hilir dan SPAM Buaran 3 Hilir | H39: Project | I39: Greenfield | J39: Perencanaan Program Greenfield | K39: Tidak | L39: Info | M39: Info | P39: ABJ/DIR/EKS/11.25/1025 | R39: Planning | S39: Aji S | T39: =DATEDIF(C39,$Z$1,"Y")&" tahun, "&DATEDIF(C39,$Z$1,"YM")&" bulan, "&DATEDIF(C39,$Z$1,"MD")&" hari" -> 0 tahun, 8 bulan, 7 hari | U39: =DATEDIF(C39,Summary!$A$1,"d") -> 249 | W39: {=_xlfn.IFS(U39<=X39,X39,U39<=X39*2,X39*2,U39<=X39*3,X39*3,U39>X39*3,">"&X39*3)} -> Info | X39: {=_xlfn.IFS(M39="Level 1",7,M39="Level 2",14,M39="Level 3","30",M39="Info","Info",M39="Closed","Closed")} -> Info
A40: 39 | B40: 175/SCI-KPI/I/2026 | C40: 46056 | D40: 46052 | E40: KPI - Sucofindo | F40: Laporan Hasil Verifikasi KPI Terkait Pencairan Dana Cadangan Proyek Greenfield | G40: KPI menyampaikan bahwa tahun 2025 pekerjaan rehabilitasi untuk FPB belum dipersyaratkan untuk dilaksanakan oleh ABJ | H40: Project | I40: Buaran 3 Hulu | J40: Administrasi & Dokumentasi | K40: Tidak | L40: Info | M40: Info | R40: Compliance | S40: Indradi | T40: =DATEDIF(C40,$Z$1,"Y")&" tahun, "&DATEDIF(C40,$Z$1,"YM")&" bulan, "&DATEDIF(C40,$Z$1,"MD")&" hari" -> 0 tahun, 8 bulan, 6 hari | U40: =DATEDIF(C40,Summary!$A$1,"d") -> 248 | W40: {=_xlfn.IFS(U40<=X40,X40,U40<=X40*2,X40*2,U40<=X40*3,X40*3,U40>X40*3,">"&X40*3)} -> Info | X40: {=_xlfn.IFS(M40="Level 1",7,M40="Level 2",14,M40="Level 3","30",M40="Info","Info",M40="Closed","Closed")} -> Info
A41: 40 | B41: e-72469/PS.04.03 | C41: 46056 | D41: 46052 | E41: PAM JAYA | F41: Klarifikasi dan Permintaan Bukti Asuransi terhadap Kewajiban A&PK Bundling | G41: Undangan PAM JAYA kepada ABJ terkait pembahasan klarifikasi dan pemetaan polis asuransi | H41: Project | I41: Project | J41: Kontrak & Legal | K41: Ya | L41: Open | M41: Level 2 | R41: PMO Infill | S41: Aan H | T41: =DATEDIF(C41,$Z$1,"Y")&" tahun, "&DATEDIF(C41,$Z$1,"YM")&" bulan, "&DATEDIF(C41,$Z$1,"MD")&" hari" -> 0 tahun, 8 bulan, 6 hari | U41: =DATEDIF(C41,Summary!$A$1,"d") -> 248 | V41: lewat 30d | W41: {=_xlfn.IFS(U41<=X41,X41,U41<=X41*2,X41*2,U41<=X41*3,X41*3,U41>X41*3,">"&X41*3)} -> >42 | X41: {=_xlfn.IFS(M41="Level 1",7,M41="Level 2",14,M41="Level 3","30",M41="Info","Info",M41="Closed","Closed")} -> 14
A42: 41 | B42: 167/SCI-KPI/I/2026 | C42: 46056 | D42: 46045 | E42: KPI - Sucofindo | F42: Tanggapan atas Surat PT Air Bersih Jakarta No. ABJ/DIR/EKS/11.25/0996 Tentang Pembaharuan DED dan RAB Desain Akhir Untuk Mater Meter Binton Silaen Proyek SPAM Jatiluhur Hilir | G42: Penyampaian KPI terhadap Pembaharuan DED dan RAB Desain Akhir Untuk Mater Meter Binton Silaen Proyek SPAM Jatiluhur Hilir | H42: Project | I42: Greenfield | J42: Perencanaan Program Greenfield | K42: Tidak | L42: Info | M42: Info | P42: ABJ/DIR/EKS/11.25/0996 | R42: Planning | S42: Aji S | T42: =DATEDIF(C42,$Z$1,"Y")&" tahun, "&DATEDIF(C42,$Z$1,"YM")&" bulan, "&DATEDIF(C42,$Z$1,"MD")&" hari" -> 0 tahun, 8 bulan, 6 hari | U42: =DATEDIF(C42,Summary!$A$1,"d") -> 248 | W42: {=_xlfn.IFS(U42<=X42,X42,U42<=X42*2,X42*2,U42<=X42*3,X42*3,U42>X42*3,">"&X42*3)} -> Info | X42: {=_xlfn.IFS(M42="Level 1",7,M42="Level 2",14,M42="Level 3","30",M42="Info","Info",M42="Closed","Closed")} -> Info
A43: 42 | B43: 147/SCI-KPI/I/2026 | C43: 46056 | D43: 46043 | E43: KPI - Sucofindo | F43: Tanggapan atas Surat PT Air Bersih Jakarta No. ABJ/DIR/EKS/11.25/1004 Tentang DED dan RAB Perluasan Jaringan Untuk 2 Lokasi Infill Ad Hoc Sambungan Baru Proyek SPAM Jatiluhur Hilir dan SPAM Karian Serpong Hilir | G43: Penyampaian KPI terhadap hasil DED dan RAB Perluasan Jaringan Untuk 2 Lokasi Infill Ad Hoc Sambungan Baru Proyek SPAM Jatiluhur Hilir dan SPAM Karian Serpong Hilir | H43: Project | I43: Greenfield | J43: Perencanaan Program Greenfield | K43: Tidak | L43: Info | M43: Info | P43: ABJ/DIR/EKS/11.25/1004 | R43: Planning | S43: Aji S | T43: =DATEDIF(C43,$Z$1,"Y")&" tahun, "&DATEDIF(C43,$Z$1,"YM")&" bulan, "&DATEDIF(C43,$Z$1,"MD")&" hari" -> 0 tahun, 8 bulan, 6 hari | U43: =DATEDIF(C43,Summary!$A$1,"d") -> 248 | W43: {=_xlfn.IFS(U43<=X43,X43,U43<=X43*2,X43*2,U43<=X43*3,X43*3,U43>X43*3,">"&X43*3)} -> Info | X43: {=_xlfn.IFS(M43="Level 1",7,M43="Level 2",14,M43="Level 3","30",M43="Info","Info",M43="Closed","Closed")} -> Info
A44: 43 | B44: 165/SCI-KPI/I/2026 | C44: 46057 | D44: 46045 | E44: KPI - Sucofindo | F44: Tanggapan atas Surat PT Air Bersih Jakarta No. ABJ/DIR/EKS/11.25/0994 Tentang DED dan RAB Perluasan Jaringan Untuk Proyek Tambah Infill Ad Hoc Perumahan Tanjung Mas Raya SPAM Jatiluhur Hilir | G44: Hasil pemeriksaan KPI terhadap DED dan RAB Perluasan Jaringan Untuk Proyek Tambah Infill Ad Hoc Perumahan Tanjung Mas Raya SPAM Jatiluhur Hilir | H44: Project | I44: Greenfield | J44: Perencanaan Program Greenfield | K44: Tidak | L44: Info | M44: Info | P44: ABJ/DIR/EKS/11.25/0994 | R44: Planning | S44: Aji S | T44: =DATEDIF(C44,$Z$1,"Y")&" tahun, "&DATEDIF(C44,$Z$1,"YM")&" bulan, "&DATEDIF(C44,$Z$1,"MD")&" hari" -> 0 tahun, 8 bulan, 5 hari | U44: =DATEDIF(C44,Summary!$A$1,"d") -> 247 | W44: {=_xlfn.IFS(U44<=X44,X44,U44<=X44*2,X44*2,U44<=X44*3,X44*3,U44>X44*3,">"&X44*3)} -> Info | X44: {=_xlfn.IFS(M44="Level 1",7,M44="Level 2",14,M44="Level 3","30",M44="Info","Info",M44="Closed","Closed")} -> Info
A45: 44 | B45: 166/SCI-KPI/I/2026 | C45: 46057 | D45: 46045 | E45: KPI - Sucofindo | F45: Tanggapan atas Surat PT Air Bersih Jakarta No. ABJ/DIR/EKS/11.25/0969 Tentang Pembaharuan DED dan RAB Proyek SPAM Pesanggrahan Hilir – Tahap Kedua | G45: Penyampaian KPI terhadap hasil pembaharuan DED dan RAB Proyek SPAM Pesanggrahan Hilir – Tahap Kedua | H45: Project | I45: Greenfield | J45: Perencanaan Program Greenfield | K45: Tidak | L45: Info | M45: Info | P45: ABJ/DIR/EKS/11.25/0969 | R45: Planning | S45: Aji S | T45: =DATEDIF(C45,$Z$1,"Y")&" tahun, "&DATEDIF(C45,$Z$1,"YM")&" bulan, "&DATEDIF(C45,$Z$1,"MD")&" hari" -> 0 tahun, 8 bulan, 5 hari | U45: =DATEDIF(C45,Summary!$A$1,"d") -> 247 | W45: {=_xlfn.IFS(U45<=X45,X45,U45<=X45*2,X45*2,U45<=X45*3,X45*3,U45>X45*3,">"&X45*3)} -> Info | X45: {=_xlfn.IFS(M45="Level 1",7,M45="Level 2",14,M45="Level 3","30",M45="Info","Info",M45="Closed","Closed")} -> Info
A46: 45 | B46: 171/SCI-KPI/I/2026 | C46: 46057 | D46: 46045 | E46: KPI - Sucofindo | F46: Tanggapan atas Surat PT Air Bersih Jakarta No. ABJ/DIR/EKS/11.25/1024 Tentang DED dan RAB Perluasan Jaringan Untuk Proyek Tambah Infill Ad Hoc Jl. Perjuangan SPAM Jatiluhur Hilir | G46: Penyampaian KPI terhadap DED dan RAB Perluasan Jaringan Untuk Proyek Tambah Infill Ad Hoc Jl. Perjuangan SPAM Jatiluhur Hilir | H46: Project | I46: Greenfield | J46: Perencanaan Program Greenfield | K46: Tidak | L46: Info | M46: Info | P46: ABJ/DIR/EKS/11.25/1024 | R46: Planning | S46: Aji S | T46: =DATEDIF(C46,$Z$1,"Y")&" tahun, "&DATEDIF(C46,$Z$1,"YM")&" bulan, "&DATEDIF(C46,$Z$1,"MD")&" hari" -> 0 tahun, 8 bulan, 5 hari | U46: =DATEDIF(C46,Summary!$A$1,"d") -> 247 | W46: {=_xlfn.IFS(U46<=X46,X46,U46<=X46*2,X46*2,U46<=X46*3,X46*3,U46>X46*3,">"&X46*3)} -> Info | X46: {=_xlfn.IFS(M46="Level 1",7,M46="Level 2",14,M46="Level 3","30",M46="Info","Info",M46="Closed","Closed")} -> Info
A47: 46 | B47: 176/SCI-KPI/II/2026 | C47: 46057 | D47: 46055 | E47: KPI - Sucofindo | F47: Tanggapan atas Surat PT Air Bersih Jakarta No. ABJ/DIR/EKS/01.26/0074 perihal Penyampaian Laporan Penyelesaian Uji Komisioning Project Greenfield – SPAM Jatiluhur Hilir PC 054 Rawa Badung RW 07 | G47: Dapat dilanjutkan ke MC100 | H47: Project | I47: Jatiluhur Hilir | J47: Konstruksi Program Greenfield | K47: Tidak | L47: Info | M47: Info | P47: ABJ/DIR/EKS/01.26/0074 | R47: PMO Infill | S47: Muhrojin | T47: =DATEDIF(C47,$Z$1,"Y")&" tahun, "&DATEDIF(C47,$Z$1,"YM")&" bulan, "&DATEDIF(C47,$Z$1,"MD")&" hari" -> 0 tahun, 8 bulan, 5 hari | U47: =DATEDIF(C47,Summary!$A$1,"d") -> 247 | W47: {=_xlfn.IFS(U47<=X47,X47,U47<=X47*2,X47*2,U47<=X47*3,X47*3,U47>X47*3,">"&X47*3)} -> Info | X47: {=_xlfn.IFS(M47="Level 1",7,M47="Level 2",14,M47="Level 3","30",M47="Info","Info",M47="Closed","Closed")} -> Info
A48: 47 | B48: 120/S/DIR/BPM/II/2026 | C48: 46063 | D48: 46056 | E48: BPM | F48: Permohonan Persetujuan Perubahan Spesifikasi Material Tee DCI menjadi Tee Steel | G48: BPM mengajukan permohonan persetujuan perubahan spesifikasi material dari tee DCI menjadi tee steel dalam keterbatasan kapasitas produksi tee DCI | H48: Project | I48: Greenfield | J48: Konstruksi Program Greenfield | K48: Ya | L48: Closed | M48: Closed | O48: ABJ/DIR/EKS/DIR/03.26/0325 | R48: PMO Infill/PMO TM | S48: Danny L / Suci | T48: =DATEDIF(C48,$Z$1,"Y")&" tahun, "&DATEDIF(C48,$Z$1,"YM")&" bulan, "&DATEDIF(C48,$Z$1,"MD")&" hari" -> 0 tahun, 7 bulan, 29 hari | U48: =DATEDIF(C48,Summary!$A$1,"d") -> 241 | V48: lewat 30d | W48: {=_xlfn.IFS(U48<=X48,X48,U48<=X48*2,X48*2,U48<=X48*3,X48*3,U48>X48*3,">"&X48*3)} -> Closed | X48: {=_xlfn.IFS(M48="Level 1",7,M48="Level 2",14,M48="Level 3","30",M48="Info","Info",M48="Closed","Closed")} -> Closed
A49: 48 | B49: e-72803/PP.01.05 | C49: 46063 | D49: 46057 | E49: PAM JAYA | F49: Permintaan Pemenuhan Kewajiban Penyerahan Laporan Fasilitas Distribusi Baru | G49: PAM JAYA mengingatkaan ABJ untuk memenuhi kewajiban PKS Bundling maksimal 5 Februari untuk pengiriman laporan fasilitas distribusi baru | H49: Project | I49: Greenfield | J49: Monitoring & Pelaporan | K49: Ya | L49: Closed | M49: Closed | O49: ABJ/DIR/EKS/02.26/0109 ABJ/DIR/EKS/02.26/0110 | P49: ABJ/DIR/EKS/02.26/0109 ABJ/DIR/EKS/02.26/0110 | R49: PMO Infill/PMO TM | S49: Danny L / Suci | T49: =DATEDIF(C49,$Z$1,"Y")&" tahun, "&DATEDIF(C49,$Z$1,"YM")&" bulan, "&DATEDIF(C49,$Z$1,"MD")&" hari" -> 0 tahun, 7 bulan, 29 hari | U49: =DATEDIF(C49,Summary!$A$1,"d") -> 241 | V49: < 7 | W49: {=_xlfn.IFS(U49<=X49,X49,U49<=X49*2,X49*2,U49<=X49*3,X49*3,U49>X49*3,">"&X49*3)} -> Closed | X49: {=_xlfn.IFS(M49="Level 1",7,M49="Level 2",14,M49="Level 3","30",M49="Info","Info",M49="Closed","Closed")} -> Closed
A50: 49 | B50: e-72454/PS.04.06 | C50: 46063 | D50: 46051 | E50: PAM JAYA | F50: Tanggapan atas Surat ABJ No. ABJ/ DIR/EKS/11.25/1023 perihal Proyek Reservoir Pejompongan 2 | G50: PAM JAYA meminta ABJ untuk menetapkan pembangunan reservoir baru IPA Pejompongan 2 dan relokasi gedung CM PAM yang merupakan bagian rehabilitasi | H50: Project | I50: Cyclical | J50: Perencanaan Program Greenfield | K50: Ya | L50: Closed | M50: Closed | O50: ABJ/DIR/EKS/03.26/0323 | P50: ABJ/DIR/EKS/03.26/0323 | R50: Planning | S50: Andriani | T50: =DATEDIF(C50,$Z$1,"Y")&" tahun, "&DATEDIF(C50,$Z$1,"YM")&" bulan, "&DATEDIF(C50,$Z$1,"MD")&" hari" -> 0 tahun, 7 bulan, 29 hari | U50: =DATEDIF(C50,Summary!$A$1,"d") -> 241 | V50: lewat 30d | W50: {=_xlfn.IFS(U50<=X50,X50,U50<=X50*2,X50*2,U50<=X50*3,X50*3,U50>X50*3,">"&X50*3)} -> Closed | X50: {=_xlfn.IFS(M50="Level 1",7,M50="Level 2",14,M50="Level 3","30",M50="Info","Info",M50="Closed","Closed")} -> Closed
A51: 50 | B51: e-72123/PP.00.02 | C51: 46063 | D51: 46043 | E51: PAM JAYA | F51: Pembaharuan Informasi Proyek Greenfield JDU JDB JDL dan SL Regional Utara | G51: PAM JAYA meminta ABJ untuk menindaklanjuti lokasi rencana pekerjaan sesuai surat terlampir | H51: Project | I51: Greenfield | J51: Perencanaan Program Greenfield | K51: Ya | L51: Info | M51: Info | R51: Planning | S51: Aji S | T51: =DATEDIF(C51,$Z$1,"Y")&" tahun, "&DATEDIF(C51,$Z$1,"YM")&" bulan, "&DATEDIF(C51,$Z$1,"MD")&" hari" -> 0 tahun, 7 bulan, 29 hari | U51: =DATEDIF(C51,Summary!$A$1,"d") -> 241 | V51: lewat 30d | W51: {=_xlfn.IFS(U51<=X51,X51,U51<=X51*2,X51*2,U51<=X51*3,X51*3,U51>X51*3,">"&X51*3)} -> Info | X51: {=_xlfn.IFS(M51="Level 1",7,M51="Level 2",14,M51="Level 3","30",M51="Info","Info",M51="Closed","Closed")} -> Info
A52: 51 | B52: e-72455/PS.04.00 | C52: 46063 | D52: 46050 | E52: PAM JAYA | F52: Permintaan Pemenuhan Realisasi Investasi Amandemen dan Pernyataan Kembali Perjanjian Brownfield Periode Tahun 2026 | G52: PAM JAYA mengingatkan ABJ untuk memenuhi kewajiban investasi sebagaimana PKS A&R Brownfield | H52: Project | I52: Cyclical | J52: Keuangan, Pembayaran, Investasi | K52: Ya | L52: Closed | M52: Closed | O52: ABJ/DIR/EKS/06.26/0656 | P52: ABJ/DIR/EKS/06.26/0656 | R52: Planning / PGO | S52: Andriani / Angelika | T52: =DATEDIF(C52,$Z$1,"Y")&" tahun, "&DATEDIF(C52,$Z$1,"YM")&" bulan, "&DATEDIF(C52,$Z$1,"MD")&" hari" -> 0 tahun, 7 bulan, 29 hari | U52: =DATEDIF(C52,Summary!$A$1,"d") -> 241 | V52: lewat 30d | W52: {=_xlfn.IFS(U52<=X52,X52,U52<=X52*2,X52*2,U52<=X52*3,X52*3,U52>X52*3,">"&X52*3)} -> Closed | X52: {=_xlfn.IFS(M52="Level 1",7,M52="Level 2",14,M52="Level 3","30",M52="Info","Info",M52="Closed","Closed")} -> Closed
A53: 52 | B53: e-72456/PS.04.00 | C53: 46063 | D53: 46050 | E53: PAM JAYA | F53: Permintaan Pemenuhan Realisasi Investasi Amandemen dan Pernyataan Kembali Perjanjian Greenfield Periode Tahun 2026 | G53: PAM JAYA mengingatkan ABJ untuk memenuhi kewajiban investasi sebagaimana PKS A&R Greenfield | H53: Project | I53: Greenfield | J53: Keuangan, Pembayaran, Investasi | K53: Ya | L53: Open | M53: Level 1 | R53: PGO | S53: Lusian F | T53: =DATEDIF(C53,$Z$1,"Y")&" tahun, "&DATEDIF(C53,$Z$1,"YM")&" bulan, "&DATEDIF(C53,$Z$1,"MD")&" hari" -> 0 tahun, 7 bulan, 29 hari | U53: =DATEDIF(C53,Summary!$A$1,"d") -> 241 | V53: lewat 30d | W53: {=_xlfn.IFS(U53<=X53,X53,U53<=X53*2,X53*2,U53<=X53*3,X53*3,U53>X53*3,">"&X53*3)} -> >21 | X53: {=_xlfn.IFS(M53="Level 1",7,M53="Level 2",14,M53="Level 3","30",M53="Info","Info",M53="Closed","Closed")} -> 7
A54: 53 | B54: e-72732/PP.01.02 | C54: 46063 | D54: 46056 | E54: PAM JAYA | F54: Teguran Pemenuhan Kewajiban Penyelesaian Paket Pekerjaaan Kedua Proyek Greenfield Pada Saat Tanggal Operasi Komersial atau 5 Oktober 2025 | G54: Teguran PAM JAYA kepada ABJ terhadap 25 program TOK Oktober 2025 yang belum selesai dan PAM JAYA meminta ABJ untuk memenuhi seluruh ketentuan PKS A&R | H54: Project | I54: Greenfield | J54: Konstruksi Program Greenfield | K54: Ya | L54: Closed | M54: Closed | O54: ABJ/DIR/EKS/03.26/0218 | P54: ABJ/DIR/EKS/03.26/0218 | R54: PMO Infill/PMO TM | S54: Suci; Jusman | T54: =DATEDIF(C54,$Z$1,"Y")&" tahun, "&DATEDIF(C54,$Z$1,"YM")&" bulan, "&DATEDIF(C54,$Z$1,"MD")&" hari" -> 0 tahun, 7 bulan, 29 hari | U54: =DATEDIF(C54,Summary!$A$1,"d") -> 241 | V54: lewat 30d | W54: {=_xlfn.IFS(U54<=X54,X54,U54<=X54*2,X54*2,U54<=X54*3,X54*3,U54>X54*3,">"&X54*3)} -> Closed | X54: {=_xlfn.IFS(M54="Level 1",7,M54="Level 2",14,M54="Level 3","30",M54="Info","Info",M54="Closed","Closed")} -> Closed
A55: 54 | B55: e-72733/PS.04.06 | C55: 46063 | D55: 46055 | E55: PAM JAYA | F55: Tanggapan Atas Surat ABJ No. ABJ/ DIR/EKS/12.25/1113 perihal Pemasangan Ramset Program Master Meter Binton | G55: PAM JAYA meminta ABJ untuk menyampaikan secara tertulis kronologis permohonan izin dan kendala selama proses perizinan | H55: Project | I55: Jatiluhur Hilir | J55: Konstruksi Program Greenfield | K55: Ya | L55: Open | M55: Level 1 | O55: ABJ/DIR/EKS/12.25/1113 | P55: ABJ/DIR/EKS/12.25/1113 | R55: PMO Infill | S55: Muhrojin | T55: =DATEDIF(C55,$Z$1,"Y")&" tahun, "&DATEDIF(C55,$Z$1,"YM")&" bulan, "&DATEDIF(C55,$Z$1,"MD")&" hari" -> 0 tahun, 7 bulan, 29 hari | U55: =DATEDIF(C55,Summary!$A$1,"d") -> 241 | V55: lewat 30d | W55: {=_xlfn.IFS(U55<=X55,X55,U55<=X55*2,X55*2,U55<=X55*3,X55*3,U55>X55*3,">"&X55*3)} -> >21 | X55: {=_xlfn.IFS(M55="Level 1",7,M55="Level 2",14,M55="Level 3","30",M55="Info","Info",M55="Closed","Closed")} -> 7
A56: 55 | B56: e-72734/PS.04.00 | C56: 46063 | D56: 46050 | E56: PAM JAYA | F56: Tanggapan atas Surat ABJ No.: ABJ/ DIR/EKS/01.26/0035 Tertangal 12 Januari 2026 Perihal Usulan Penyederhanaan Workflow Desain Akhir, Proposal Modifikasi, dan Closing melalui BIM | G56: PAM JAYA meminta untuk komitmen terhadap penyampaian dokumen dalam CDE BIM dan hanya dilakukan oleh pihak ABJ (non MK), ABJ untuk memastikan konsistensi antar dokumen | H56: Project | I56: Project | J56: Administrasi & Dokumentasi | K56: Tidak | L56: Closed | M56: Closed | O56: ABJ/DIR/EKS/01.26/0035 | P56: ABJ/DIR/EKS/01.26/0035 | R56: PGO | S56: Angelika | T56: =DATEDIF(C56,$Z$1,"Y")&" tahun, "&DATEDIF(C56,$Z$1,"YM")&" bulan, "&DATEDIF(C56,$Z$1,"MD")&" hari" -> 0 tahun, 7 bulan, 29 hari | U56: =DATEDIF(C56,Summary!$A$1,"d") -> 241 | V56: < 8 | W56: {=_xlfn.IFS(U56<=X56,X56,U56<=X56*2,X56*2,U56<=X56*3,X56*3,U56>X56*3,">"&X56*3)} -> Closed | X56: {=_xlfn.IFS(M56="Level 1",7,M56="Level 2",14,M56="Level 3","30",M56="Info","Info",M56="Closed","Closed")} -> Closed
A57: 56 | B57: 168/SCI-KPI/I/2026 | C57: 46064 | D57: 46045 | E57: KPI - Sucofindo | F57: Tanggapan atas Surat PT Air Bersih Jakarta No. ABJ/DIR/EKS/12.25/1082 Tentang DED dan RAB Perluasan Jaringan Untuk Proyek Tambahan Infill Ad Hoc Pesanggrahan Tahap 1 SPAM Karian Serpong Hilir | G57: Tanggapan atas DED RAB Perluasan Jaringan Untuk Proyek Tambahan Infill Ad Hoc Pesanggrahan Tahap 1 SPAM Karian Serpong Hilir | H57: Project | I57: Karian Serpong Hilir | J57: Perencanaan Program Greenfield | K57: Tidak | L57: Info | M57: Info | P57: ABJ/DIR/EKS/12.25/1082 | R57: Planning | S57: Aji S | T57: =DATEDIF(C57,$Z$1,"Y")&" tahun, "&DATEDIF(C57,$Z$1,"YM")&" bulan, "&DATEDIF(C57,$Z$1,"MD")&" hari" -> 0 tahun, 7 bulan, 28 hari | U57: =DATEDIF(C57,Summary!$A$1,"d") -> 240 | V57: < 9 | W57: {=_xlfn.IFS(U57<=X57,X57,U57<=X57*2,X57*2,U57<=X57*3,X57*3,U57>X57*3,">"&X57*3)} -> Info | X57: {=_xlfn.IFS(M57="Level 1",7,M57="Level 2",14,M57="Level 3","30",M57="Info","Info",M57="Closed","Closed")} -> Info
A58: 57 | B58: e-73256/PP.01.05 | C58: 46065 | D58: 46058 | E58: PAM JAYA | F58: Teguran Pemenuhan Kewajiban Penyerahan Laporan Fasilitas Distribusi Baru | G58: Teguran PAM JAYA terhadap tidak dipenuhinya dokumen penyerahan Fasilitas Distribusi Baru Paket Pekerjaan Ketiga | H58: Project | I58: Greenfield | J58: Konstruksi Program Greenfield | K58: Ya | L58: Closed | M58: Closed | O58: ABJ/DIR/EKS/02.26/0109 ABJ/DIR/EKS/02.26/0110 | P58: ABJ/DIR/EKS/02.26/0109 ABJ/DIR/EKS/02.26/0110 | R58: PMO Infill/PMO TM | S58: Danny L / Suci | T58: =DATEDIF(C58,$Z$1,"Y")&" tahun, "&DATEDIF(C58,$Z$1,"YM")&" bulan, "&DATEDIF(C58,$Z$1,"MD")&" hari" -> 0 tahun, 7 bulan, 27 hari | U58: =DATEDIF(C58,Summary!$A$1,"d") -> 239 | V58: < 7 | W58: {=_xlfn.IFS(U58<=X58,X58,U58<=X58*2,X58*2,U58<=X58*3,X58*3,U58>X58*3,">"&X58*3)} -> Closed | X58: {=_xlfn.IFS(M58="Level 1",7,M58="Level 2",14,M58="Level 3","30",M58="Info","Info",M58="Closed","Closed")} -> Closed
A59: 58 | B59: e-73094/PP.00.02 | C59: 46065 | D59: 46058 | E59: PAM JAYA | F59: Pemutakhiran Program Konstruksi dan Desain Akhir DC Pegadungan dan JDU JDB JDL Citra Extension | G59: PAM JAYA meminta ABJ untuk menyampaikan usulan modifikasi Reservoir DC Pegadungan dan melakukan pemutakhiran Desain Akhir | H59: Project | I59: Greenfield | J59: Perencanaan Program Greenfield | K59: Ya | L59: Open | M59: Level 2 | R59: Planning | S59: Aji S | T59: =DATEDIF(C59,$Z$1,"Y")&" tahun, "&DATEDIF(C59,$Z$1,"YM")&" bulan, "&DATEDIF(C59,$Z$1,"MD")&" hari" -> 0 tahun, 7 bulan, 27 hari | U59: =DATEDIF(C59,Summary!$A$1,"d") -> 239 | V59: lewat 7d | W59: {=_xlfn.IFS(U59<=X59,X59,U59<=X59*2,X59*2,U59<=X59*3,X59*3,U59>X59*3,">"&X59*3)} -> >42 | X59: {=_xlfn.IFS(M59="Level 1",7,M59="Level 2",14,M59="Level 3","30",M59="Info","Info",M59="Closed","Closed")} -> 14
A60: 59 | B60: e-73095/PP.00.02 | C60: 46065 | D60: 46059 | E60: PAM JAYA | F60: Pemutakhiran Desain Akhir JDU JDB JDL dan SL Proyek Greenfield Master Meter Khoirul Rokhim | G60: PAM JAYA meminta ABJ untuk menindaklanjuti lokasi rencana dan pemutakhiran DED dan pemodelan hidrolis | H60: Project | I60: Greenfield | J60: Perencanaan Program Greenfield | K60: Ya | L60: Closed | M60: Closed | O60: ABJ/DIR/EKS/08.26/0981 | P60: ABJ/DIR/EKS/08.26/0981 | R60: Planning | S60: Aji S | T60: =DATEDIF(C60,$Z$1,"Y")&" tahun, "&DATEDIF(C60,$Z$1,"YM")&" bulan, "&DATEDIF(C60,$Z$1,"MD")&" hari" -> 0 tahun, 7 bulan, 27 hari | U60: =DATEDIF(C60,Summary!$A$1,"d") -> 239 | V60: lewat 7d | W60: {=_xlfn.IFS(U60<=X60,X60,U60<=X60*2,X60*2,U60<=X60*3,X60*3,U60>X60*3,">"&X60*3)} -> Closed | X60: {=_xlfn.IFS(M60="Level 1",7,M60="Level 2",14,M60="Level 3","30",M60="Info","Info",M60="Closed","Closed")} -> Closed
A61: 60 | B61: e-73146/PS.04.03 | C61: 46065 | D61: 46056 | E61: PAM JAYA | F61: Permintaan Pemenuhan Dokumen Pendukung Program Konstruksi untuk pekerjaan Fasilitas Distribusi Baru TOK Oktober 2025 | G61: PAM JAYA menyampaikan belum adanya dokumen DPPK untuk program TOK Oktober 2025 | H61: Project | I61: Greenfield | J61: Konstruksi Program Greenfield | K61: Ya | L61: Closed | M61: Closed | O61: ABJ/DIR/EKS/03.26/0227 | P61: ABJ/DIR/EKS/03.26/0227 | R61: PMO Infill/PMO TM | S61: Danny L / Suci | T61: =DATEDIF(C61,$Z$1,"Y")&" tahun, "&DATEDIF(C61,$Z$1,"YM")&" bulan, "&DATEDIF(C61,$Z$1,"MD")&" hari" -> 0 tahun, 7 bulan, 27 hari | U61: =DATEDIF(C61,Summary!$A$1,"d") -> 239 | V61: lewat 7d | W61: {=_xlfn.IFS(U61<=X61,X61,U61<=X61*2,X61*2,U61<=X61*3,X61*3,U61>X61*3,">"&X61*3)} -> Closed | X61: {=_xlfn.IFS(M61="Level 1",7,M61="Level 2",14,M61="Level 3","30",M61="Info","Info",M61="Closed","Closed")} -> Closed
A62: 61 | B62: e-73147/PP.00.02 | C62: 46065 | D62: 46057 | E62: PAM JAYA | F62: Pemutakhiran Desain Akhir JDU JDB JDL dan SL Proyek Greenfield Regional Utara dan Selatan | G62: PAM JAYA meminta ABJ untuk menindaklanjuti lokasi rencana dan pemutakhiran DED dan pemodelan hidrolis | H62: Project | I62: Greenfield | J62: Perencanaan Program Greenfield | K62: Ya | L62: Open | M62: Level 2 | R62: Planning | S62: Aji S | T62: =DATEDIF(C62,$Z$1,"Y")&" tahun, "&DATEDIF(C62,$Z$1,"YM")&" bulan, "&DATEDIF(C62,$Z$1,"MD")&" hari" -> 0 tahun, 7 bulan, 27 hari | U62: =DATEDIF(C62,Summary!$A$1,"d") -> 239 | V62: lewat 7d | W62: {=_xlfn.IFS(U62<=X62,X62,U62<=X62*2,X62*2,U62<=X62*3,X62*3,U62>X62*3,">"&X62*3)} -> >42 | X62: {=_xlfn.IFS(M62="Level 1",7,M62="Level 2",14,M62="Level 3","30",M62="Info","Info",M62="Closed","Closed")} -> 14
A63: 62 | B63: 009/BLLS/SI/II/2026 | C63: 46065 | D63: 46062 | E63: PT. Bina Lestari Lingkungan Sejahtera (BLLS) | F63: Penyampaian Informasi Keterlambatan Progres Aktual Pelaksanaan Project | G63: Penyampaian informasi project TOK April 2025 dan TOK Oktober 2025 serta progres TOK April 2026 | H63: Project | I63: Greenfield | J63: Konstruksi Program Greenfield | K63: Tidak | L63: Info | M63: Info | R63: PGO | S63: Angelika | T63: =DATEDIF(C63,$Z$1,"Y")&" tahun, "&DATEDIF(C63,$Z$1,"YM")&" bulan, "&DATEDIF(C63,$Z$1,"MD")&" hari" -> 0 tahun, 7 bulan, 27 hari | U63: =DATEDIF(C63,Summary!$A$1,"d") -> 239 | V63: < 15 | W63: {=_xlfn.IFS(U63<=X63,X63,U63<=X63*2,X63*2,U63<=X63*3,X63*3,U63>X63*3,">"&X63*3)} -> Info | X63: {=_xlfn.IFS(M63="Level 1",7,M63="Level 2",14,M63="Level 3","30",M63="Info","Info",M63="Closed","Closed")} -> Info
A64: 63 | B64: 185/SCI-KPI/II/2026 | C64: 46066 | D64: 46063 | E64: KPI - Sucofindo | F64: Tanggapan atas Surat PT Air Bersih Jakarta No. ABJ/DIR/EKS/02.26/0117 perihal Penyampaian Laporan Penyelesaian Uji Komisioning Project Greenfield – SPAM Buaran 3 Hilir Program PC 162 Centex | G64: Program PC 162 Centex belum dapat dilanjutkan MC100 karena masih ada kekurangan dokumen | H64: Project | I64: Buaran 3 Hilir | J64: Konstruksi Program Greenfield | K64: Tidak | L64: Info | M64: Info | P64: ABJ/DIR/EKS/02.26/0117 | R64: PMO Infill | S64: Topan | T64: =DATEDIF(C64,$Z$1,"Y")&" tahun, "&DATEDIF(C64,$Z$1,"YM")&" bulan, "&DATEDIF(C64,$Z$1,"MD")&" hari" -> 0 tahun, 7 bulan, 26 hari | U64: =DATEDIF(C64,Summary!$A$1,"d") -> 238 | V64: < 16 | W64: {=_xlfn.IFS(U64<=X64,X64,U64<=X64*2,X64*2,U64<=X64*3,X64*3,U64>X64*3,">"&X64*3)} -> Info | X64: {=_xlfn.IFS(M64="Level 1",7,M64="Level 2",14,M64="Level 3","30",M64="Info","Info",M64="Closed","Closed")} -> Info
A65: 64 | B65: 188/SCI-KPI/II/2026 | C65: 46066 | D65: 46066 | E65: KPI - Sucofindo | F65: Pemberitahuan Libur Nasional dan Cuti Bersama Tahun Baru Imlek | G65: Pemberitahuan Libur Nasional dan Cuti Bersama Tahun Baru Imlek | H65: Project | I65: Project | J65: Monitoring & Pelaporan | K65: Tidak | L65: Info | M65: Info | R65: Compliance | S65: Indradi | T65: =DATEDIF(C65,$Z$1,"Y")&" tahun, "&DATEDIF(C65,$Z$1,"YM")&" bulan, "&DATEDIF(C65,$Z$1,"MD")&" hari" -> 0 tahun, 7 bulan, 26 hari | U65: =DATEDIF(C65,Summary!$A$1,"d") -> 238 | V65: < 17 | W65: {=_xlfn.IFS(U65<=X65,X65,U65<=X65*2,X65*2,U65<=X65*3,X65*3,U65>X65*3,">"&X65*3)} -> Info | X65: {=_xlfn.IFS(M65="Level 1",7,M65="Level 2",14,M65="Level 3","30",M65="Info","Info",M65="Closed","Closed")} -> Info
A66: 65 | B66: 192/SCI-KPI/II/2026 | C66: 46076 | D66: 46073 | E66: KPI - Sucofindo | F66: Penyampaian Laporan Penyelesaian Uji Komisioning Project Greenfield – SPAM Jatiluhur Hilir 3 Program Tertanggal 12 Februari 2026 | G66: Program dapat dilanjutkan ke MC100 | H66: Project | I66: Jatiluhur Hilir | J66: Konstruksi Program Greenfield | K66: Tidak | L66: Info | M66: Info | P66: ABJ/DIR/EKS/02.26/0147 | R66: PMO Infill | S66: Muhrojin | T66: =DATEDIF(C66,$Z$1,"Y")&" tahun, "&DATEDIF(C66,$Z$1,"YM")&" bulan, "&DATEDIF(C66,$Z$1,"MD")&" hari" -> 0 tahun, 7 bulan, 16 hari | U66: =DATEDIF(C66,Summary!$A$1,"d") -> 228 | V66: < 18 | W66: {=_xlfn.IFS(U66<=X66,X66,U66<=X66*2,X66*2,U66<=X66*3,X66*3,U66>X66*3,">"&X66*3)} -> Info | X66: {=_xlfn.IFS(M66="Level 1",7,M66="Level 2",14,M66="Level 3","30",M66="Info","Info",M66="Closed","Closed")} -> Info
A67: 66 | B67: e-73685/PS.04.03 | C67: 46077 | D67: 46065 | E67: PAM JAYA | F67: Pemenuhan Kewajiban Penyampaian Pembaharuan Daftar Asset Periode Kedua 2025 | G67: PAM JAYA meminta ABJ untuk menyerahkan pembaruan daftar aset dengan data yang sudah diverifikasi bersama PAM JAYA | H67: Project | I67: Cyclical | J67: Aset Management | K67: Ya | L67: Closed | M67: Closed | R67: Compliance | S67: Indradi | T67: =DATEDIF(C67,$Z$1,"Y")&" tahun, "&DATEDIF(C67,$Z$1,"YM")&" bulan, "&DATEDIF(C67,$Z$1,"MD")&" hari" -> 0 tahun, 7 bulan, 15 hari | U67: =DATEDIF(C67,Summary!$A$1,"d") -> 227 | V67: < 19 | W67: {=_xlfn.IFS(U67<=X67,X67,U67<=X67*2,X67*2,U67<=X67*3,X67*3,U67>X67*3,">"&X67*3)} -> Closed | X67: {=_xlfn.IFS(M67="Level 1",7,M67="Level 2",14,M67="Level 3","30",M67="Info","Info",M67="Closed","Closed")} -> Closed
A68: 67 | B68: e-73689/PP.00.02 | C68: 46077 | D68: 46065 | E68: PAM JAYA | F68: Pemutakhiran Desain Akhir JDU JDB JDL dan SL Proyek Greenfield Sekolah Citra Kasih Don Bosco dan RW 003 Cilandak Barat | G68: PAM JAYA meminta ABJ untuk pemutakhiran desain akhir pada lokasi terlampir | H68: Project | I68: Greenfield | J68: Perencanaan Program Greenfield | K68: Ya | L68: Closed | M68: Closed | O68: ABJ/DIR/EKS/08.26/0981 | P68: ABJ/DIR/EKS/08.26/0981 | R68: Planning | S68: Aji S | T68: =DATEDIF(C68,$Z$1,"Y")&" tahun, "&DATEDIF(C68,$Z$1,"YM")&" bulan, "&DATEDIF(C68,$Z$1,"MD")&" hari" -> 0 tahun, 7 bulan, 15 hari | U68: =DATEDIF(C68,Summary!$A$1,"d") -> 227 | V68: < 20 | W68: {=_xlfn.IFS(U68<=X68,X68,U68<=X68*2,X68*2,U68<=X68*3,X68*3,U68>X68*3,">"&X68*3)} -> Closed | X68: {=_xlfn.IFS(M68="Level 1",7,M68="Level 2",14,M68="Level 3","30",M68="Info","Info",M68="Closed","Closed")} -> Closed
A69: 68 | B69: e-73687/KH.01.00 | C69: 46077 | D69: 46065 | E69: PAM JAYA | F69: Pengiriman Jadwal Calender of Event Program Rehabilitasi Tahun 2026 | G69: PAM JAYA meminta ABJ untuk menyampaikan sifat gangguan dan jangka waktu gangguan pada saat CoE; mengidentifikasi jadwal pelaksanaan CoE selama periode libur panjang 2026 | H69: Project | I69: Cyclical | J69: Perencanaan Program Rehabilitasi | K69: Tidak | L69: Closed | M69: Closed | O69: ABJ/DIR/EKS/03.26/0269 | P69: ABJ/DIR/EKS/03.26/0269 | R69: PMO Cyclical | S69: Agus H | T69: =DATEDIF(C69,$Z$1,"Y")&" tahun, "&DATEDIF(C69,$Z$1,"YM")&" bulan, "&DATEDIF(C69,$Z$1,"MD")&" hari" -> 0 tahun, 7 bulan, 15 hari | U69: =DATEDIF(C69,Summary!$A$1,"d") -> 227 | V69: < 21 | W69: {=_xlfn.IFS(U69<=X69,X69,U69<=X69*2,X69*2,U69<=X69*3,X69*3,U69>X69*3,">"&X69*3)} -> Closed | X69: {=_xlfn.IFS(M69="Level 1",7,M69="Level 2",14,M69="Level 3","30",M69="Info","Info",M69="Closed","Closed")} -> Closed
A70: 69 | B70: e-73798/PP.01.02 | C70: 46077 | D70: 46065 | E70: PAM JAYA | F70: Teguran atas Keterlambatan Pelaksanaan Program Rehabilitasi Proyek Brownfield Tahun 2026 | G70: PAM JAYA meminta ABJ untuk menyampaikan pembaharuan jadwal pelaksanaan cyclical 2026 program 46204 dan 46325 | H70: Project | I70: Cyclical | J70: Perencanaan Program Rehabilitasi | K70: Ya | L70: Closed | M70: Closed | O70: ABJ/DIR/EKS/05.26/0567, ABJ/DIR/EKS/02.26/0205 | P70: ABJ/DIR/EKS/02.26/0205 ABJ/DIR/EKS/04.26/0461 PJ 1324/PP.01.02-EKST-IV-2026 ABJ/DIR/EKS/05.26/0567 | R70: PMO Cyclical | S70: Agus H | T70: =DATEDIF(C70,$Z$1,"Y")&" tahun, "&DATEDIF(C70,$Z$1,"YM")&" bulan, "&DATEDIF(C70,$Z$1,"MD")&" hari" -> 0 tahun, 7 bulan, 15 hari | U70: =DATEDIF(C70,Summary!$A$1,"d") -> 227 | V70: < 22 | W70: {=_xlfn.IFS(U70<=X70,X70,U70<=X70*2,X70*2,U70<=X70*3,X70*3,U70>X70*3,">"&X70*3)} -> Closed | X70: {=_xlfn.IFS(M70="Level 1",7,M70="Level 2",14,M70="Level 3","30",M70="Info","Info",M70="Closed","Closed")} -> Closed
A71: 70 | B71: e-73829/PP.01.05 | C71: 46077 | D71: 46066 | E71: PAM JAYA | F71: Permintaan Pemenuhan Kewajiban Penyelesaian Paket Pekerjaan Ketiga atau Tanggal Operasi Komersial 5 April 2026 | G71: PAM JAYA meminta ABJ untuk menyelesaikan seluruh pekerjaan TOK April 2026; Tidak adanya keterlambatan; Melakukan pembaharuan informasi dan memastikan pemenuhan perizinan | H71: Project | I71: Greenfield | J71: Konstruksi Program Greenfield | K71: Tidak | L71: Info | M71: Info | R71: PMO Infill/PMO TM | S71: Danny L; Suci | T71: =DATEDIF(C71,$Z$1,"Y")&" tahun, "&DATEDIF(C71,$Z$1,"YM")&" bulan, "&DATEDIF(C71,$Z$1,"MD")&" hari" -> 0 tahun, 7 bulan, 15 hari | U71: =DATEDIF(C71,Summary!$A$1,"d") -> 227 | V71: < 23 | W71: {=_xlfn.IFS(U71<=X71,X71,U71<=X71*2,X71*2,U71<=X71*3,X71*3,U71>X71*3,">"&X71*3)} -> Info | X71: {=_xlfn.IFS(M71="Level 1",7,M71="Level 2",14,M71="Level 3","30",M71="Info","Info",M71="Closed","Closed")} -> Info
A72: 71 | B72: e-73656/PP.01.05 | C72: 46079 | D72: 46059 | E72: PAM JAYA | F72: Tanggapan atas Surat Dinas Bina Marga Prov DKI Jakarta No. 266/KR.02.00 tanggal 23 Jan 2026 | G72: Surat PAM JAYA kepada Kementerian PU terkait permohanan arahan atas tindak lanjut serah terima pembangunan sarana prasarana di komplek pengairan Kota Bekasi | H72: Project | I72: Greenfield | J72: Perizinan | K72: Tidak | L72: Info | M72: Info | R72: Permit | S72: Rais A | T72: =DATEDIF(C72,$Z$1,"Y")&" tahun, "&DATEDIF(C72,$Z$1,"YM")&" bulan, "&DATEDIF(C72,$Z$1,"MD")&" hari" -> 0 tahun, 7 bulan, 13 hari | U72: =DATEDIF(C72,Summary!$A$1,"d") -> 225 | V72: < 24 | W72: {=_xlfn.IFS(U72<=X72,X72,U72<=X72*2,X72*2,U72<=X72*3,X72*3,U72>X72*3,">"&X72*3)} -> Info | X72: {=_xlfn.IFS(M72="Level 1",7,M72="Level 2",14,M72="Level 3","30",M72="Info","Info",M72="Closed","Closed")} -> Info
A73: 72 | B73: 889/PS.04.04/EKST/II/2026 | C73: 46080 | D73: 46079 | E73: PAM JAYA | F73: Peringatan | G73: PAM JAYA meminta ABJ untuk menyelesaikan seluruh perbaikan paling lambat 7 hari kalender sejak surat diterima | H73: Project | I73: Greenfield | J73: Konstruksi Program Greenfield | K73: Ya | L73: Closed | M73: Closed | O73: ABJ/DIR/EKS/03.26/0225 | P73: ABJ/DIR/EKS/03.26/0225 | R73: PMO Infill | S73: Danny L | T73: =DATEDIF(C73,$Z$1,"Y")&" tahun, "&DATEDIF(C73,$Z$1,"YM")&" bulan, "&DATEDIF(C73,$Z$1,"MD")&" hari" -> 0 tahun, 7 bulan, 12 hari | U73: =DATEDIF(C73,Summary!$A$1,"d") -> 224 | V73: < 25 | W73: {=_xlfn.IFS(U73<=X73,X73,U73<=X73*2,X73*2,U73<=X73*3,X73*3,U73>X73*3,">"&X73*3)} -> Closed | X73: {=_xlfn.IFS(M73="Level 1",7,M73="Level 2",14,M73="Level 3","30",M73="Info","Info",M73="Closed","Closed")} -> Closed
A74: 73 | B74: 894/PP.01.02/EKST/II/2026 | C74: 46080 | D74: 46079 | E74: PAM JAYA | F74: Teguran Penerapan Aspek Keselamatan dan Kesehatan Kerja (K3) pada Proyek Greenfield | G74: PAM JAYA meminta ABJ untuk memastikan ABJ menindaklanjuti temuan inspeksi PAM | H74: Project | I74: Greenfield | J74: HSE | K74: Ya | L74: Closed | M74: Closed | O74: ABJ/DIR/EKS/03.26/0297 | P74: ABJ/DIR/EKS/03.26/0297 | R74: HSE | S74: Irsan | T74: =DATEDIF(C74,$Z$1,"Y")&" tahun, "&DATEDIF(C74,$Z$1,"YM")&" bulan, "&DATEDIF(C74,$Z$1,"MD")&" hari" -> 0 tahun, 7 bulan, 12 hari | U74: =DATEDIF(C74,Summary!$A$1,"d") -> 224 | V74: < 26 | W74: {=_xlfn.IFS(U74<=X74,X74,U74<=X74*2,X74*2,U74<=X74*3,X74*3,U74>X74*3,">"&X74*3)} -> Closed | X74: {=_xlfn.IFS(M74="Level 1",7,M74="Level 2",14,M74="Level 3","30",M74="Info","Info",M74="Closed","Closed")} -> Closed
A75: 74 | B75: 197/SCI-KPI/II/2026 | C75: 46082 | D75: 46080 | E75: KPI - Sucofindo | F75: Surat Pengantar Laporan Bulanan Proyek Bundling SPAM DKI Jakarta - Konsultan Pengawas Independen Periode Januari 2026 | G75: Laporan Bulanan Proyek Bundling SPAM DKI Jakarta - Konsultan Pengawas Independen Periode Januari 2026 | H75: Project | I75: Greenfield | J75: Monitoring & Pelaporan | K75: Tidak | L75: Info | M75: Info | R75: Compliance | S75: A. Levi | T75: =DATEDIF(C75,$Z$1,"Y")&" tahun, "&DATEDIF(C75,$Z$1,"YM")&" bulan, "&DATEDIF(C75,$Z$1,"MD")&" hari" -> 0 tahun, 7 bulan, 8 hari | U75: =DATEDIF(C75,Summary!$A$1,"d") -> 222 | V75: < 27 | W75: {=_xlfn.IFS(U75<=X75,X75,U75<=X75*2,X75*2,U75<=X75*3,X75*3,U75>X75*3,">"&X75*3)} -> Info | X75: {=_xlfn.IFS(M75="Level 1",7,M75="Level 2",14,M75="Level 3","30",M75="Info","Info",M75="Closed","Closed")} -> Info
A76: 75 | B76: 199/SCI-KPI/III/2026 | C76: 46084 | D76: 46083 | E76: KPI - Sucofindo | F76: Rekomendasi Metode Sampling Cyble dan Sambungan Langsung (SL) | G76: Rekomendasi metode Sampling Cyble dan Sambungan Langsung (SL) dari KPI | H76: Project | I76: Greenfield | J76: Sambungan Langsung | K76: Tidak | L76: Info | M76: Info | R76: PMO NC | S76: Angelika | T76: =DATEDIF(C76,$Z$1,"Y")&" tahun, "&DATEDIF(C76,$Z$1,"YM")&" bulan, "&DATEDIF(C76,$Z$1,"MD")&" hari" -> 0 tahun, 7 bulan, 6 hari | U76: =DATEDIF(C76,Summary!$A$1,"d") -> 220 | V76: < 28 | W76: {=_xlfn.IFS(U76<=X76,X76,U76<=X76*2,X76*2,U76<=X76*3,X76*3,U76>X76*3,">"&X76*3)} -> Info | X76: {=_xlfn.IFS(M76="Level 1",7,M76="Level 2",14,M76="Level 3","30",M76="Info","Info",M76="Closed","Closed")} -> Info
A77: 76 | B77: 200/SCI-KPI/III/2026 | C77: 46084 | D77: 46083 | E77: KPI - Sucofindo | F77: Rekomendasi Konsultan Pengawas Independen (“KPI”) Terkait Metode Verifikasi Data Sambungan Langsung (SL) | G77: Rekomendasi KPI terhadap metode verifikasi data SL : 1. Verifikasi dilakukan berdasarkan kesesuaian data titik koordinat; 2. Verifikasi data pembayaran pelanggan mengacu pada kode pelanggan | H77: Project | I77: Greenfield | J77: Sambungan Langsung | K77: Tidak | L77: Info | M77: Info | R77: PMO NC | S77: Angelika | T77: =DATEDIF(C77,$Z$1,"Y")&" tahun, "&DATEDIF(C77,$Z$1,"YM")&" bulan, "&DATEDIF(C77,$Z$1,"MD")&" hari" -> 0 tahun, 7 bulan, 6 hari | U77: =DATEDIF(C77,Summary!$A$1,"d") -> 220 | V77: < 29 | W77: {=_xlfn.IFS(U77<=X77,X77,U77<=X77*2,X77*2,U77<=X77*3,X77*3,U77>X77*3,">"&X77*3)} -> Info | X77: {=_xlfn.IFS(M77="Level 1",7,M77="Level 2",14,M77="Level 3","30",M77="Info","Info",M77="Closed","Closed")} -> Info
A78: 77 | B78: 184/SCI-KPI/II/2026 | C78: 46085 | D78: 46063 | E78: KPI - Sucofindo | F78: Rekomendasi Perpanjangan Masa Konstruksi Selama 90 (Sembilan Puluh) Hari Untuk Program-Program Yang Belum Selesai Tahap Konstruksi Serta Terkait Perizinan | G78: Rekomendasi KPI yaitu ABJ dapat menyampaikan jadwal pelaksanaan perpanjangan konstruksi 90 hari dan justek terhadap keterlambatan proyek | H78: Project | I78: Greenfield | J78: Konstruksi Program Greenfield | K78: Tidak | L78: Info | M78: Info | R78: PMO Infill/PMO TM | S78: Danny L; Suci | T78: =DATEDIF(C78,$Z$1,"Y")&" tahun, "&DATEDIF(C78,$Z$1,"YM")&" bulan, "&DATEDIF(C78,$Z$1,"MD")&" hari" -> 0 tahun, 7 bulan, 5 hari | U78: =DATEDIF(C78,Summary!$A$1,"d") -> 219 | V78: < 30 | W78: {=_xlfn.IFS(U78<=X78,X78,U78<=X78*2,X78*2,U78<=X78*3,X78*3,U78>X78*3,">"&X78*3)} -> Info | X78: {=_xlfn.IFS(M78="Level 1",7,M78="Level 2",14,M78="Level 3","30",M78="Info","Info",M78="Closed","Closed")} -> Info
A79: 78 | B79: e-74540/PP.01.02 | C79: 46086 | D79: 46078 | E79: PAM JAYA | F79: Permintaan Pemenuhan Dokumen untuk Paket Pekerjaan Ketiga (TOK 5 April 2026) | G79: PAM JAYA meminta ABJ untuk menyampaikan kekurangan DPPP sebanyak 17 sub program paling lambat 5 hari setelah MC100 | H79: Project | I79: Greenfield | J79: Administrasi & Dokumentasi Program Greenfield | K79: Ya | L79: Closed | M79: Closed | R79: PGO | S79: Lusian F | T79: =DATEDIF(C79,$Z$1,"Y")&" tahun, "&DATEDIF(C79,$Z$1,"YM")&" bulan, "&DATEDIF(C79,$Z$1,"MD")&" hari" -> 0 tahun, 7 bulan, 4 hari | U79: =DATEDIF(C79,Summary!$A$1,"d") -> 218 | V79: < 31 | W79: {=_xlfn.IFS(U79<=X79,X79,U79<=X79*2,X79*2,U79<=X79*3,X79*3,U79>X79*3,">"&X79*3)} -> Closed | X79: {=_xlfn.IFS(M79="Level 1",7,M79="Level 2",14,M79="Level 3","30",M79="Info","Info",M79="Closed","Closed")} -> Closed
A80: 79 | B80: e-74543/PP.01.02 | C80: 46086 | D80: 46078 | E80: PAM JAYA | F80: Teguran Permintaan Pemenuhan Kewajiban Penyelesaian Paket Pekerjaan Ketiga atau Tanggal Operasi Komersial 5 April 2026 | G80: 3 program belum terdapat DPPK | H80: Project | I80: Greenfield | J80: Perencanaan Program Greenfield | K80: Ya | L80: Open | M80: Level 2 | R80: PMO Infill/PMO TM | S80: Suci; Jusman | T80: =DATEDIF(C80,$Z$1,"Y")&" tahun, "&DATEDIF(C80,$Z$1,"YM")&" bulan, "&DATEDIF(C80,$Z$1,"MD")&" hari" -> 0 tahun, 7 bulan, 4 hari | U80: =DATEDIF(C80,Summary!$A$1,"d") -> 218 | V80: < 32 | W80: {=_xlfn.IFS(U80<=X80,X80,U80<=X80*2,X80*2,U80<=X80*3,X80*3,U80>X80*3,">"&X80*3)} -> >42 | X80: {=_xlfn.IFS(M80="Level 1",7,M80="Level 2",14,M80="Level 3","30",M80="Info","Info",M80="Closed","Closed")} -> 14
A81: 80 | B81: 947/PP.00.06/EKST/III/2026 | C81: 46087 | D81: 46084 | E81: PAM JAYA | F81: Permohonan Ijin Dispensasi Angkutan selama Libur Hari Raya Idul Fitri 1447 H | G81: Surat PAM JAYA kepada DisHub DKI Jakarta perihal Permohonan Ijin Dispensasi Angkutan selama Libur Hari Raya Idul Fitri 1447 H | H81: Produksi | I81: ALL WTP | J81: Operation & Maintenance | K81: Tidak | L81: Info | M81: Info | R81: Produksi | S81: Irawan | T81: =DATEDIF(C81,$Z$1,"Y")&" tahun, "&DATEDIF(C81,$Z$1,"YM")&" bulan, "&DATEDIF(C81,$Z$1,"MD")&" hari" -> 0 tahun, 7 bulan, 3 hari | U81: =DATEDIF(C81,Summary!$A$1,"d") -> 217 | V81: < 33 | W81: {=_xlfn.IFS(U81<=X81,X81,U81<=X81*2,X81*2,U81<=X81*3,X81*3,U81>X81*3,">"&X81*3)} -> Info | X81: {=_xlfn.IFS(M81="Level 1",7,M81="Level 2",14,M81="Level 3","30",M81="Info","Info",M81="Closed","Closed")} -> Info
A82: 81 | B82: 207/SCI-KPI/III/2026 | C82: 46090 | D82: 46087 | E82: KPI - Sucofindo | F82: Tanggapan atas Surat PT Air Bersih Jakarta No. ABJ/DIR/EKS/03.26/0228 perihal Penyampaian Laporan Penyelesaian Uji Komisioning Project Greenfield – SPAM Jatiluhur Hilir Program PC 070 Jl. Inspeksi Kirana dan S010 Pancoran Barat VI B | G82: Dapat dilanjutkan MC100 | H82: Project | I82: Jatiluhur Hilir | J82: Konstruksi Program Greenfield | K82: Tidak | L82: Info | M82: Info | P82: ABJ/DIR/EKS/03.26/0228 | R82: PMO Infill | S82: Muhrojin | T82: =DATEDIF(C82,$Z$1,"Y")&" tahun, "&DATEDIF(C82,$Z$1,"YM")&" bulan, "&DATEDIF(C82,$Z$1,"MD")&" hari" -> 0 tahun, 7 bulan, 0 hari | U82: =DATEDIF(C82,Summary!$A$1,"d") -> 214 | V82: < 34 | W82: {=_xlfn.IFS(U82<=X82,X82,U82<=X82*2,X82*2,U82<=X82*3,X82*3,U82>X82*3,">"&X82*3)} -> Info | X82: {=_xlfn.IFS(M82="Level 1",7,M82="Level 2",14,M82="Level 3","30",M82="Info","Info",M82="Closed","Closed")} -> Info
A83: 82 | B83: 208/SCI-KPI/III/2026 | C83: 46091 | D83: 46087 | E83: KPI - Sucofindo | F83: Tanggapan atas Surat PT Air Bersih Jakarta No. ABJ/DIR/EKS/03.26/0230 perihal Penyampaian Laporan Penyelesaian Uji Komisioning Project Greenfield – SPAM Karian Serpong Hilir Program SN02 Rumah Wagub | G83: Dapat dilanjutkan MC100 | H83: Project | I83: Karian Serpong Hilir | J83: Konstruksi Program Greenfield | K83: Tidak | L83: Info | M83: Info | P83: ABJ/DIR/EKS/03.26/0230 | R83: PMO Infill | S83: Ervin Y | T83: =DATEDIF(C83,$Z$1,"Y")&" tahun, "&DATEDIF(C83,$Z$1,"YM")&" bulan, "&DATEDIF(C83,$Z$1,"MD")&" hari" -> 0 tahun, 6 bulan, 29 hari | U83: =DATEDIF(C83,Summary!$A$1,"d") -> 213 | V83: < 35 | W83: {=_xlfn.IFS(U83<=X83,X83,U83<=X83*2,X83*2,U83<=X83*3,X83*3,U83>X83*3,">"&X83*3)} -> Info | X83: {=_xlfn.IFS(M83="Level 1",7,M83="Level 2",14,M83="Level 3","30",M83="Info","Info",M83="Closed","Closed")} -> Info
A84: 83 | B84: 1109/PS.04.03/EKST/III/2026 | C84: 46092 | D84: 46091 | E84: PAM JAYA | F84: Penyampaian Hasil Inspeksi K3L di IPA Buaran 1,2 dan 3 tanggal 23 Jan 26 | G84: PAM JAYA meminta ABJ untuk menyampaikan rencana perbaikan maksimal 14 hari kalender | H84: Produksi | I84: Buaran 1 &2 | J84: HSE | K84: Ya | L84: Closed | M84: Closed | O84: ABJ/DIR/EKS/03.26/0299 | P84: ABJ/DIR/EKS/03.26/0299 | R84: HSE | S84: Irsan | T84: =DATEDIF(C84,$Z$1,"Y")&" tahun, "&DATEDIF(C84,$Z$1,"YM")&" bulan, "&DATEDIF(C84,$Z$1,"MD")&" hari" -> 0 tahun, 6 bulan, 28 hari | U84: =DATEDIF(C84,Summary!$A$1,"d") -> 212 | V84: < 38 | W84: {=_xlfn.IFS(U84<=X84,X84,U84<=X84*2,X84*2,U84<=X84*3,X84*3,U84>X84*3,">"&X84*3)} -> Closed | X84: {=_xlfn.IFS(M84="Level 1",7,M84="Level 2",14,M84="Level 3","30",M84="Info","Info",M84="Closed","Closed")} -> Closed
A85: 84 | B85: 1111/PS.04.03/EKST/III/2026 | C85: 46092 | D85: 46091 | E85: PAM JAYA | F85: Pemutakhiran Desain Akhir JDU JDB JDL dan SL Proyek Greenfield PT. Altrak 1978 dan Kawasan Kebayoran Icon | G85: PAM JAYA meminta ABJ untuk pemutakhiran desain akhir pada lokasi terlampir | H85: Project | I85: Greenfield | J85: Perencanaan Program Greenfield | K85: Ya | L85: Closed | M85: Closed | O85: ABJ/DIR/EKS/03.26/0291 | P85: ABJ/DIR/EKS/03.26/0291 | R85: Planning | S85: Aji S | T85: =DATEDIF(C85,$Z$1,"Y")&" tahun, "&DATEDIF(C85,$Z$1,"YM")&" bulan, "&DATEDIF(C85,$Z$1,"MD")&" hari" -> 0 tahun, 6 bulan, 28 hari | U85: =DATEDIF(C85,Summary!$A$1,"d") -> 212 | V85: < 39 | W85: {=_xlfn.IFS(U85<=X85,X85,U85<=X85*2,X85*2,U85<=X85*3,X85*3,U85>X85*3,">"&X85*3)} -> Closed | X85: {=_xlfn.IFS(M85="Level 1",7,M85="Level 2",14,M85="Level 3","30",M85="Info","Info",M85="Closed","Closed")} -> Closed
A86: 85 | B86: 1106/PS.04.06/EKST/III/2026 | C86: 46092 | D86: 46091 | E86: PAM JAYA | F86: Pemutakhiran Desain Akhir JDU JDB JDL dan SL Proyek Greenfield AB Pulomas dan Muara Karang | G86: PAM JAYA meminta ABJ untuk pemutakhiran desain akhir pada lokasi terlampir | H86: Project | I86: Greenfield | J86: Perencanaan Program Greenfield | K86: Ya | L86: Open | M86: Level 2 | R86: Planning | S86: Aji S | T86: =DATEDIF(C86,$Z$1,"Y")&" tahun, "&DATEDIF(C86,$Z$1,"YM")&" bulan, "&DATEDIF(C86,$Z$1,"MD")&" hari" -> 0 tahun, 6 bulan, 28 hari | U86: =DATEDIF(C86,Summary!$A$1,"d") -> 212 | V86: < 40 | W86: {=_xlfn.IFS(U86<=X86,X86,U86<=X86*2,X86*2,U86<=X86*3,X86*3,U86>X86*3,">"&X86*3)} -> >42 | X86: {=_xlfn.IFS(M86="Level 1",7,M86="Level 2",14,M86="Level 3","30",M86="Info","Info",M86="Closed","Closed")} -> 14
A87: 86 | B87: 1107/PS.04.03/EKST/III/2026 | C87: 46092 | D87: 46091 | E87: PAM JAYA | F87: Permintaan Tindak Lanjut Hasil Rapat Klarifikasi dan Permintaan Bukti Asuransi | G87: PAM JAYA meminta ABJ untuk mengiriimkan bentuk klarifikasi pemenuhan kewajiban asuransi yang dipersyaratkan | H87: Project | I87: Project | J87: Asuransi | K87: Ya | L87: Open | M87: Level 1 | R87: PMO Infill/PMO TM | S87: Suci; Jusman | T87: =DATEDIF(C87,$Z$1,"Y")&" tahun, "&DATEDIF(C87,$Z$1,"YM")&" bulan, "&DATEDIF(C87,$Z$1,"MD")&" hari" -> 0 tahun, 6 bulan, 28 hari | U87: =DATEDIF(C87,Summary!$A$1,"d") -> 212 | V87: < 41 | W87: {=_xlfn.IFS(U87<=X87,X87,U87<=X87*2,X87*2,U87<=X87*3,X87*3,U87>X87*3,">"&X87*3)} -> >21 | X87: {=_xlfn.IFS(M87="Level 1",7,M87="Level 2",14,M87="Level 3","30",M87="Info","Info",M87="Closed","Closed")} -> 7
A88: 87 | B88: e-74887/PS.04.06 | C88: 46092 | D88: 46080 | E88: PAM JAYA | F88: Permintaan Pemenuhan Pengelolaan dan Pengendalian Limbah dari Fasilitas Baru dan Fasilitas Produksi Eksisting oleh PT ABJ Periode Tahun 2026 | G88: PAM JAYA meminta ABJ untuk melakukan pemantauan terhadap penumpukan limbah/lumpur. PAM JAYA meminta ABJ untuk menindaklanjuti temuan hasil inspeksi pemantauan lingkungan | H88: Produksi | I88: ALL WTP | J88: Operation & Maintenance | K88: Ya | L88: Closed | M88: Closed | O88: ABJ/DIR/EKS/03.26/0298 | P88: ABJ/DIR/EKS/03.26/0298 | R88: HSE | S88: Irsan | T88: =DATEDIF(C88,$Z$1,"Y")&" tahun, "&DATEDIF(C88,$Z$1,"YM")&" bulan, "&DATEDIF(C88,$Z$1,"MD")&" hari" -> 0 tahun, 6 bulan, 28 hari | U88: =DATEDIF(C88,Summary!$A$1,"d") -> 212 | V88: < 42 | W88: {=_xlfn.IFS(U88<=X88,X88,U88<=X88*2,X88*2,U88<=X88*3,X88*3,U88>X88*3,">"&X88*3)} -> Closed | X88: {=_xlfn.IFS(M88="Level 1",7,M88="Level 2",14,M88="Level 3","30",M88="Info","Info",M88="Closed","Closed")} -> Closed
A89: 88 | B89: 1033/TU.00.00/EKST/III/2026 | C89: 46091 | D89: 46087 | E89: PAM JAYA | F89: Undangan Rapat Evaluasi Dampak Padam Listrik PLN di Fasilitas IPA Bundling | G89: Undangan PAM JAYA kepada ABJ terkait Rapat Evaluasi Dampak Padam Listrik PLN di Fasilitas IPA Bundling pada Kamis, 12 Maret 2026 | H89: Produksi | I89: ALL WTP | J89: Operation & Maintenance | K89: Tidak | L89: Info | M89: Info | R89: Produksi | S89: Destriaji | T89: =DATEDIF(C89,$Z$1,"Y")&" tahun, "&DATEDIF(C89,$Z$1,"YM")&" bulan, "&DATEDIF(C89,$Z$1,"MD")&" hari" -> 0 tahun, 6 bulan, 29 hari | U89: =DATEDIF(C89,Summary!$A$1,"d") -> 213 | V89: < 44 | W89: {=_xlfn.IFS(U89<=X89,X89,U89<=X89*2,X89*2,U89<=X89*3,X89*3,U89>X89*3,">"&X89*3)} -> Info | X89: {=_xlfn.IFS(M89="Level 1",7,M89="Level 2",14,M89="Level 3","30",M89="Info","Info",M89="Closed","Closed")} -> Info
A90: 89 | B90: E-73652/PP.01.05 | C90: 46091 | D90: 46057 | E90: PAM JAYA | F90: Teguran atas Bina Marga Nomor 266/KR.02.00 perihal Pelaksanaan Pekerjaan Galian Utilitas Pipa Air Bersih | G90: Teguran atas Bina Marga Nomor 266/KR.02.00 perihal Pelaksanaan Pekerjaan Galian Utilitas Pipa Air Bersih | H90: Project | I90: Greenfield | J90: Konstruksi Program Greenfield | K90: Ya | L90: Open | M90: Level 2 | R90: PMO Infill/PMO TM | S90: Suci; Jusman | T90: =DATEDIF(C90,$Z$1,"Y")&" tahun, "&DATEDIF(C90,$Z$1,"YM")&" bulan, "&DATEDIF(C90,$Z$1,"MD")&" hari" -> 0 tahun, 6 bulan, 29 hari | U90: =DATEDIF(C90,Summary!$A$1,"d") -> 213 | V90: < 45 | W90: {=_xlfn.IFS(U90<=X90,X90,U90<=X90*2,X90*2,U90<=X90*3,X90*3,U90>X90*3,">"&X90*3)} -> >42 | X90: {=_xlfn.IFS(M90="Level 1",7,M90="Level 2",14,M90="Level 3","30",M90="Info","Info",M90="Closed","Closed")} -> 14
A91: 90 | B91: 208/SCI-KPI/III/2026 | C91: 46091 | D91: 46087 | E91: KPI - Sucofindo | F91: Tanggapan atas Surat PT Air Bersih Jakarta No. ABJ/DIR/EKS/03.26/0230 perihal Penyampaian Laporan Penyelesaian Uji Komisioning Project Greenfield – SPAM Karian Serpong Hilir Program SN02 Rumah Wagub. | G91: Dapat dilanjutkan MC100 | H91: Project | I91: Karian Serpong Hilir | J91: Konstruksi Program Greenfield | K91: Tidak | L91: Info | M91: Info | P91: ABJ/DIR/EKS/03.26/0230 | R91: PMO Infill | S91: Ervin Y | T91: =DATEDIF(C91,$Z$1,"Y")&" tahun, "&DATEDIF(C91,$Z$1,"YM")&" bulan, "&DATEDIF(C91,$Z$1,"MD")&" hari" -> 0 tahun, 6 bulan, 29 hari | U91: =DATEDIF(C91,Summary!$A$1,"d") -> 213 | V91: < 46 | W91: {=_xlfn.IFS(U91<=X91,X91,U91<=X91*2,X91*2,U91<=X91*3,X91*3,U91>X91*3,">"&X91*3)} -> Info | X91: {=_xlfn.IFS(M91="Level 1",7,M91="Level 2",14,M91="Level 3","30",M91="Info","Info",M91="Closed","Closed")} -> Info
A92: 91 | B92: 209/SCI-KPI/III/2026 | C92: 46091 | D92: 46087 | E92: KPI - Sucofindo | F92: Tanggapan atas Surat PT Air Bersih Jakarta No. ABJ/DIR/EKS/03.26/0212 perihal Penyampaian Laporan Penyelesaian Uji Komisioning Project Greenfield – SPAM Karian Serpong Hilir Program B020 Citra 5 Tambahan dan S017 Copylast Blok K Cluster Lavender. | G92: Dapat dilanjutkan MC100 | H92: Project | I92: Karian Serpong Hilir | J92: Konstruksi Program Greenfield | K92: Tidak | L92: Info | M92: Info | P92: ABJ/DIR/EKS/03.26/0212 | R92: PMO Infill | S92: Ervin Y | T92: =DATEDIF(C92,$Z$1,"Y")&" tahun, "&DATEDIF(C92,$Z$1,"YM")&" bulan, "&DATEDIF(C92,$Z$1,"MD")&" hari" -> 0 tahun, 6 bulan, 29 hari | U92: =DATEDIF(C92,Summary!$A$1,"d") -> 213 | V92: < 47 | W92: {=_xlfn.IFS(U92<=X92,X92,U92<=X92*2,X92*2,U92<=X92*3,X92*3,U92>X92*3,">"&X92*3)} -> Info | X92: {=_xlfn.IFS(M92="Level 1",7,M92="Level 2",14,M92="Level 3","30",M92="Info","Info",M92="Closed","Closed")} -> Info
A93: 92 | B93: 1105/PS.04.03/EKST/III/2026 | C93: 46092 | D93: 46091 | E93: PAM JAYA | F93: Permintaan Struktur Organisasi Termutakhir Perode Tahun 2026 | G93: PAM JAYA meminta PT ABJ menyampaikan struktur organisasi terbaru, data personel beserta sertifikasinya, serta memastikan komitmen pelaksanaan ketentuan kerja sama bundling berjalan optimal. | H93: Corporate | I93: Corporate | J93: Kontrak & Legal | K93: Ya | L93: Closed | M93: Closed | O93: ABJ/DIR/EKS/05.26/0518 | P93: ABJ/DIR/EKS/05.26/0518 | R93: Compliance/HC | S93: A. Levi/Cucum | T93: =DATEDIF(C93,$Z$1,"Y")&" tahun, "&DATEDIF(C93,$Z$1,"YM")&" bulan, "&DATEDIF(C93,$Z$1,"MD")&" hari" -> 0 tahun, 6 bulan, 28 hari | U93: =DATEDIF(C93,Summary!$A$1,"d") -> 212 | V93: < 48 | W93: {=_xlfn.IFS(U93<=X93,X93,U93<=X93*2,X93*2,U93<=X93*3,X93*3,U93>X93*3,">"&X93*3)} -> Closed | X93: {=_xlfn.IFS(M93="Level 1",7,M93="Level 2",14,M93="Level 3","30",M93="Info","Info",M93="Closed","Closed")} -> Closed
A94: 93 | B94: 1107/PS.04.03/III/2026 | C94: 46092 | D94: 46091 | E94: PAM JAYA | F94: Permintaan Tindak Lanjut Hasil Rapat Klarifikasi dan Permintaan Bukti Asuransi | G94: Pamjaya meminta untuk dikirimkan klarifikasi pemenuhan kewajiban asuransi dan dikirimkan bukti pembayaran premi tahunan atas polis asuransi (persyaratan didetail surat, etc) | H94: Project | I94: Project | J94: Asuransi | K94: Ya | L94: Closed | M94: Closed | R94: Compliance/Finance | S94: A. Levi/Nurul S | T94: =DATEDIF(C94,$Z$1,"Y")&" tahun, "&DATEDIF(C94,$Z$1,"YM")&" bulan, "&DATEDIF(C94,$Z$1,"MD")&" hari" -> 0 tahun, 6 bulan, 28 hari | U94: =DATEDIF(C94,Summary!$A$1,"d") -> 212 | V94: < 49 | W94: {=_xlfn.IFS(U94<=X94,X94,U94<=X94*2,X94*2,U94<=X94*3,X94*3,U94>X94*3,">"&X94*3)} -> Closed | X94: {=_xlfn.IFS(M94="Level 1",7,M94="Level 2",14,M94="Level 3","30",M94="Info","Info",M94="Closed","Closed")} -> Closed
A95: 94 | B95: 1109/PS.04.03/EKST/III/2026 | C95: 46092 | D95: 46091 | E95: PAM JAYA | F95: Penyampaian Hasil Inspeksi K3L di IPA Buaran 1,2 dan 3 Tanggal 23 Januari 2026. | G95: Temuan dari hasil inspeksi peralatan serta housekeeping di IPA Buaran (77 temuan) | H95: Produksi | I95: Buaran 1, 2, 3 | J95: HSE | K95: Ya | L95: Closed | M95: Closed | O95: ABJ/DIR/EKS/03.26/0299 | P95: ABJ/DIR/EKS/03.26/0299 | R95: HSE | S95: Irsan | T95: =DATEDIF(C95,$Z$1,"Y")&" tahun, "&DATEDIF(C95,$Z$1,"YM")&" bulan, "&DATEDIF(C95,$Z$1,"MD")&" hari" -> 0 tahun, 6 bulan, 28 hari | U95: =DATEDIF(C95,Summary!$A$1,"d") -> 212 | V95: < 50 | W95: {=_xlfn.IFS(U95<=X95,X95,U95<=X95*2,X95*2,U95<=X95*3,X95*3,U95>X95*3,">"&X95*3)} -> Closed | X95: {=_xlfn.IFS(M95="Level 1",7,M95="Level 2",14,M95="Level 3","30",M95="Info","Info",M95="Closed","Closed")} -> Closed
A96: 95 | B96: 1111/PS.04.03/EKST/III/2026 | C96: 46092 | D96: 46091 | E96: PAM JAYA | F96: Pemutakhiran Desain Akhir JDU JDB JDL dan SL Proyek Greenfield PT. Altrak 1978 dan Kawasan Kebayoran Icon | G96: ABJ diminta membuat DED dan pemodelan hidrolis fasilitas distribusi baru sesuai standar yang berlaku, serta melakukan pembahasan dan survey teknis bersama PAM JAYA dan KPI terkait desain, tekanan air, dan kebutuhan jaringan pipa agar memenuhi ketentuan teknis distribusi air. | H96: Project | I96: Greenfield | J96: Perencanaan Program Greenfield | K96: Ya | L96: Open | M96: Level 3 | R96: Planning | S96: Aji S | T96: =DATEDIF(C96,$Z$1,"Y")&" tahun, "&DATEDIF(C96,$Z$1,"YM")&" bulan, "&DATEDIF(C96,$Z$1,"MD")&" hari" -> 0 tahun, 6 bulan, 28 hari | U96: =DATEDIF(C96,Summary!$A$1,"d") -> 212 | V96: < 51 | W96: {=_xlfn.IFS(U96<=X96,X96,U96<=X96*2,X96*2,U96<=X96*3,X96*3,U96>X96*3,">"&X96*3)} -> 30 | X96: {=_xlfn.IFS(M96="Level 1",7,M96="Level 2",14,M96="Level 3","30",M96="Info","Info",M96="Closed","Closed")} -> 30
A97: 97 | B97: E-75190/PP.01.04 | C97: 46092 | D97: 46077 | E97: PAM JAYA | F97: Tanggapan atas Surat ABJ No. ABJ/DIR/EKS/12.25/1111 Perihal Gangguan Listrik PLN di IPA Buaran 1 dan IPA Buaran 2 pada tanggal 21 Desember 2026 | G97: Gangguan pasokan listrik PLN di IPA Buaran 1 dan 2 menyebabkan pompa berhenti beroperasi dan target tekanan serta aliran air tidak tercapai. Berdasarkan bukti under voltage dari PLN, PAM JAYA menyetujui pengecualian denda kinerja yang diajukan PT ABJ. | H97: Produksi | I97: Buaran 1 &2 | J97: Operation & Maintenance | K97: Tidak | L97: Closed | M97: Closed | O97: ABJ/DIR/EKS/03.26/0251 | P97: ABJ/DIR/EKS/03.26/0251, ABJ/DIR/EKS/12.25/1111 | R97: Produksi | S97: Wahyudian | T97: =DATEDIF(C97,$Z$1,"Y")&" tahun, "&DATEDIF(C97,$Z$1,"YM")&" bulan, "&DATEDIF(C97,$Z$1,"MD")&" hari" -> 0 tahun, 6 bulan, 28 hari | U97: =DATEDIF(C97,Summary!$A$1,"d") -> 212 | V97: < 54 | W97: {=_xlfn.IFS(U97<=X97,X97,U97<=X97*2,X97*2,U97<=X97*3,X97*3,U97>X97*3,">"&X97*3)} -> Closed | X97: {=_xlfn.IFS(M97="Level 1",7,M97="Level 2",14,M97="Level 3","30",M97="Info","Info",M97="Closed","Closed")} -> Closed
A98: 98 | B98: 215/SCI-KPI/III/2026 | C98: 46092 | D98: 46092 | E98: KPI - Sucofindo | F98: Tanggapan dan Rekomendasi Persiapan Pelaksanaan TOK 5 April 2026. | G98: KPI menyampaikan rekomendasi program yang akan di-TOK-kan dan review Dokumen DPPP di BIM untuk program Greenfield Hilir, serta hasil analisis tren pelaksanaan TOK dari tahun ke tahun. | H98: Project | I98: Greenfield | J98: Konstruksi Program Greenfield | K98: Tidak | L98: Info | M98: Info | R98: PMO/PGO | S98: Suci/Lusian F | T98: =DATEDIF(C98,$Z$1,"Y")&" tahun, "&DATEDIF(C98,$Z$1,"YM")&" bulan, "&DATEDIF(C98,$Z$1,"MD")&" hari" -> 0 tahun, 6 bulan, 28 hari | U98: =DATEDIF(C98,Summary!$A$1,"d") -> 212 | V98: < 55 | W98: {=_xlfn.IFS(U98<=X98,X98,U98<=X98*2,X98*2,U98<=X98*3,X98*3,U98>X98*3,">"&X98*3)} -> Info | X98: {=_xlfn.IFS(M98="Level 1",7,M98="Level 2",14,M98="Level 3","30",M98="Info","Info",M98="Closed","Closed")} -> Info
A99: 99 | B99: 214/SCI-KPI/III/2026 | C99: 46092 | D99: 46091 | E99: KPI - Sucofindo | F99: Tanggapan atas Surat PT Air Bersih Jakarta No. ABJ/DIR/EKS/03.26/0259 perihal Penyampaian Laporan Penyelesaian Uji Komisioning Project Greenfield – SPAM Karian Serpong Hilir Program B20 Cendrawasih 7 dan S006 Jiban. | G99: Dapat dilanjutkan MC100 | H99: Project | I99: Karian Serpong Hilir | J99: Konstruksi Program Greenfield | K99: Tidak | L99: Info | M99: Info | P99: ABJ/DIR/EKS/03.26/0259 | R99: PMO Infill | S99: Ervin Y | T99: =DATEDIF(C99,$Z$1,"Y")&" tahun, "&DATEDIF(C99,$Z$1,"YM")&" bulan, "&DATEDIF(C99,$Z$1,"MD")&" hari" -> 0 tahun, 6 bulan, 28 hari | U99: =DATEDIF(C99,Summary!$A$1,"d") -> 212 | V99: < 56 | W99: {=_xlfn.IFS(U99<=X99,X99,U99<=X99*2,X99*2,U99<=X99*3,X99*3,U99>X99*3,">"&X99*3)} -> Info | X99: {=_xlfn.IFS(M99="Level 1",7,M99="Level 2",14,M99="Level 3","30",M99="Info","Info",M99="Closed","Closed")} -> Info
A100: 100 | B100: Revisi Surat KPI No. 199/SCI-KPI/III/2026 | C100: 46093 | D100: 46083 | E100: KPI - Sucofindo | F100: Rekomendasi Metode Sampling Cyble dan Sambungan Langsung (SL). | G100: Penyampaian revisi surat yang Merujuk pada MoM Diskusi Pengakuan Investasi SL dan Cyble tertanggal 20 Februari 2026 | H100: Project | I100: Greenfield | J100: Sambungan Langsung | K100: Tidak | L100: Info | M100: Info | R100: PMO NC | S100: Angelika | T100: =DATEDIF(C100,$Z$1,"Y")&" tahun, "&DATEDIF(C100,$Z$1,"YM")&" bulan, "&DATEDIF(C100,$Z$1,"MD")&" hari" -> 0 tahun, 6 bulan, 27 hari | U100: =DATEDIF(C100,Summary!$A$1,"d") -> 211 | V100: < 57 | W100: {=_xlfn.IFS(U100<=X100,X100,U100<=X100*2,X100*2,U100<=X100*3,X100*3,U100>X100*3,">"&X100*3)} -> Info | X100: {=_xlfn.IFS(M100="Level 1",7,M100="Level 2",14,M100="Level 3","30",M100="Info","Info",M100="Closed","Closed")} -> Info
...

Sheet Outgoing 2025
A1: No | B1: Nomor Surat | C1: Tanggal Surat | D1: Penerima | E1: Perihal | F1: Deskripsi | G1: Produksi/Project | H1: Lokasi | I1: Kategori | J1: Due Date | K1: Status | L1: DIC | M1: PIC | N1: Durasi | O1: Durasi (Hari) | P1: Attachment | Q1: Keterangan
A2: 1 | B2: ABJ/DIR/EKS/01.25/0003 | C2: 45663 | D2: PAM JAYA | E2: Tagihan Air Curah Periode Desember 2024 | G2: Corporate | H2: Corporate | I2: Tagihan | K2: Info | L2: Compliance | M2: Indradi | N2: =DATEDIF(C2,'Outgoing 2023'!$L$2,"Y")&" tahun, "&DATEDIF(C2,'Outgoing 2023'!$L$2,"YM")&" bulan, "&DATEDIF(C2,'Outgoing 2023'!$L$2,"MD")&" hari" -> 1 tahun, 9 bulan, 3 hari | O2: =TODAY()-C2 -> 641 | S2: {=_xlfn.UNIQUE(I2:I1159)} -> Tagihan | T2: =COUNTIF($I$2:$I$1159,S2) -> 26
A3: 2 | B3: ABJ/DIR/EKS/01.25/0004 | C3: 45663 | D3: PAM JAYA | E3: Pengiriman Ke-3 Tanggapan Atas Hasil Review PAM dan KPI Terhadap Dokumen Desain Akhir Program Rehabilitasi Tahun 2025 | G3: Project | H3: Cyclical | I3: DED/RAB | K3: Info | L3: PMO | M3: Aan Hendra | N3: =DATEDIF(C3,'Outgoing 2023'!$L$2,"Y")&" tahun, "&DATEDIF(C3,'Outgoing 2023'!$L$2,"YM")&" bulan, "&DATEDIF(C3,'Outgoing 2023'!$L$2,"MD")&" hari" -> 1 tahun, 9 bulan, 3 hari | O3: =TODAY()-C3 -> 641 | S3: DED/RAB | T3: =COUNTIF($I$2:$I$1159,S3) -> 146
A4: 3 | B4: ABJ/DIR/EKS/01.25/0005 | C4: 45663 | D4: PAM JAYA | E4: Laporan Bulanan Kualitas Air Baku dan Air Curah Periode Desember 2024 | G4: Produksi | H4: ALL WTP | I4: Laporan Periodik | K4: Info | L4: WQA | M4: Novi | N4: =DATEDIF(C4,'Outgoing 2023'!$L$2,"Y")&" tahun, "&DATEDIF(C4,'Outgoing 2023'!$L$2,"YM")&" bulan, "&DATEDIF(C4,'Outgoing 2023'!$L$2,"MD")&" hari" -> 1 tahun, 9 bulan, 3 hari | O4: =TODAY()-C4 -> 641 | S4: Laporan Periodik | T4: =COUNTIF($I$2:$I$1159,S4) -> 48
A5: 4 | B5: ABJ/DIR/EKS/01.25/0006 | C5: 45663 | D5: PAM JAYA | E5: Pengiriman Risalah Rapat Pre Construction Meeting SPAM Buaran 3 Hilir, PC162 EZ 02 Jl. Manunggal 1A, PC163 EZ05 Jl. IntisariRaya dan PC159 EZ 01 Jl. Dato Tonggara | G5: Project | H5: Buaran 3 Hilir | I5: MoM | K5: Info | L5: PMO | M5: Puji R | N5: =DATEDIF(C5,'Outgoing 2023'!$L$2,"Y")&" tahun, "&DATEDIF(C5,'Outgoing 2023'!$L$2,"YM")&" bulan, "&DATEDIF(C5,'Outgoing 2023'!$L$2,"MD")&" hari" -> 1 tahun, 9 bulan, 3 hari | O5: =TODAY()-C5 -> 641 | S5: MoM | T5: =COUNTIF($I$2:$I$1159,S5) -> 16
A6: 5 | B6: ABJ/DIR/EKS/01.25/0007 | C6: 45663 | D6: Bank BTPN | E6: Pencairan Deposito | G6: Corporate | H6: Corporate | I6: Finance | K6: Info | L6: Finance | M6: Wahyu Tjahyadi | N6: =DATEDIF(C6,'Outgoing 2023'!$L$2,"Y")&" tahun, "&DATEDIF(C6,'Outgoing 2023'!$L$2,"YM")&" bulan, "&DATEDIF(C6,'Outgoing 2023'!$L$2,"MD")&" hari" -> 1 tahun, 9 bulan, 3 hari | O6: =TODAY()-C6 -> 641 | S6: Finance | T6: =COUNTIF($I$2:$I$1159,S6) -> 39
A7: 6 | B7: ABJ/DIR/EKS/01.25/0008 | C7: 45663 | D7: Kepala Dinas Perhubungan Kota Bekasi | E7: Permohonan Rekayasa Lalu Lintas terkait Proyek SPAM Buaran 3 Hulu | G7: Project | H7: Buaran 3 Hulu | I7: Jadwal Pekerjaan | K7: Info | L7: Permit | M7: Rais A | N7: =DATEDIF(C7,'Outgoing 2023'!$L$2,"Y")&" tahun, "&DATEDIF(C7,'Outgoing 2023'!$L$2,"YM")&" bulan, "&DATEDIF(C7,'Outgoing 2023'!$L$2,"MD")&" hari" -> 1 tahun, 9 bulan, 3 hari | O7: =TODAY()-C7 -> 641 | S7: Jadwal Pekerjaan | T7: =COUNTIF($I$2:$I$1159,S7) -> 45
A8: 7 | B8: ABJ/DIR/EKS/01.25/0009 | C8: 45664 | D8: Perum Jasa Tirta II - General Manajer Unit Wilayah I | E8: Permohonan Rekayasa Lalu Lintas terkait Proyek SPAM Buaran 3 Hulu | G8: Produksi | H8: Corporate | I8: Permohonan | K8: Info | L8: Permit | M8: Rais A | N8: =DATEDIF(C8,'Outgoing 2023'!$L$2,"Y")&" tahun, "&DATEDIF(C8,'Outgoing 2023'!$L$2,"YM")&" bulan, "&DATEDIF(C8,'Outgoing 2023'!$L$2,"MD")&" hari" -> 1 tahun, 9 bulan, 2 hari | O8: =TODAY()-C8 -> 640 | S8: Permohonan | T8: =COUNTIF($I$2:$I$1159,S8) -> 11
A9: 8 | B9: ABJ/DIR/EKS/01.25/0010 | C9: 45665 | D9: PAM JAYA | E9: Pengiriman Ke-4 Tanggapan Atas Hasil Review PAM dan KPI Terhadap Dokumen Desain Akhir Program Rehabilitasi Tahun 2025 | G9: Project | H9: Cyclical | I9: DED/RAB | K9: Info | L9: PMO | M9: Aan Hendra | N9: =DATEDIF(C9,'Outgoing 2023'!$L$2,"Y")&" tahun, "&DATEDIF(C9,'Outgoing 2023'!$L$2,"YM")&" bulan, "&DATEDIF(C9,'Outgoing 2023'!$L$2,"MD")&" hari" -> 1 tahun, 9 bulan, 1 hari | O9: =TODAY()-C9 -> 639 | S9: Asuransi | T9: =COUNTIF($I$2:$I$1159,S9) -> 2
A10: 9 | B10: ABJ/DIR/EKS/01.25/0011 | C10: 45665 | D10: PAM JAYA | E10: Permohonan Pembelian Sparepart Standby Untuk Operasional IPA Pejompongan 2 | G10: Project | H10: Cyclical | I10: Permohonan | K10: Info | L10: PMO | M10: Johnson | N10: =DATEDIF(C10,'Outgoing 2023'!$L$2,"Y")&" tahun, "&DATEDIF(C10,'Outgoing 2023'!$L$2,"YM")&" bulan, "&DATEDIF(C10,'Outgoing 2023'!$L$2,"MD")&" hari" -> 1 tahun, 9 bulan, 1 hari | O10: =TODAY()-C10 -> 639 | S10: Komisioning/Pengoperasian | T10: =COUNTIF($I$2:$I$1159,S10) -> 229
A11: 10 | B11: ABJ/DIR/EKS/01.25/0012 | C11: 45665 | D11: Bank OCBC NISP | E11: Penyampaian Salinan Asli Polis Asuransi | G11: Corporate | H11: Corporate | I11: Asuransi | K11: Info | L11: Finance | M11: Wahyu Tjahyadi | N11: =DATEDIF(C11,'Outgoing 2023'!$L$2,"Y")&" tahun, "&DATEDIF(C11,'Outgoing 2023'!$L$2,"YM")&" bulan, "&DATEDIF(C11,'Outgoing 2023'!$L$2,"MD")&" hari" -> 1 tahun, 9 bulan, 1 hari | O11: =TODAY()-C11 -> 639 | S11: HSE | T11: =COUNTIF($I$2:$I$1159,S11) -> 27
A12: 11 | B12: ABJ/DIR/EKS/01.25/0013 | C12: 45666 | D12: PAM JAYA | E12: Pemberitahuan Uji Komisioning SPAM Jatiluhur Hilir – Infill C03 Kebon Kosong | G12: Project | H12: Jatiluhur Hilir | I12: Komisioning/Pengoperasian | K12: Info | L12: PMO | M12: Juny Jety | N12: =DATEDIF(C12,'Outgoing 2023'!$L$2,"Y")&" tahun, "&DATEDIF(C12,'Outgoing 2023'!$L$2,"YM")&" bulan, "&DATEDIF(C12,'Outgoing 2023'!$L$2,"MD")&" hari" -> 1 tahun, 9 bulan, 0 hari | O12: =TODAY()-C12 -> 638 | S12: Manajemen Risiko | T12: =COUNTIF($I$2:$I$1159,S12) -> 9
A13: 12 | B13: ABJ/DIR/EKS/01.25/0014 | C13: 45666 | D13: PAM JAYA | E13: Laporan Bulanan Kuantitas Air Baku dan Air Curah Periode Desember 2024 | G13: Produksi | H13: ALL WTP | I13: Laporan Periodik | K13: Info | L13: Compliance | M13: Indradi | N13: =DATEDIF(C13,'Outgoing 2023'!$L$2,"Y")&" tahun, "&DATEDIF(C13,'Outgoing 2023'!$L$2,"YM")&" bulan, "&DATEDIF(C13,'Outgoing 2023'!$L$2,"MD")&" hari" -> 1 tahun, 9 bulan, 0 hari | O13: =TODAY()-C13 -> 638 | S13: Sambungan Rumah/Sambungan Baru | T13: =COUNTIF($I$2:$I$1159,S13) -> 22
A14: 13 | B14: ABJ/DIR/EKS/01.25/0015 | C14: 45666 | D14: PAM JAYA | E14: Tanggapan atas Surat PAM JAYA No. e-31298/KM.02.25 tentang Penyampaian Hasil Inspeksi Aset dan Peralatan di IPA Buaran Bulan Oktober 2024 | G14: Project | H14: Buaran 1 & 2 | I14: HSE | K14: Info | L14: HSE | M14: Irsan | N14: =DATEDIF(C14,'Outgoing 2023'!$L$2,"Y")&" tahun, "&DATEDIF(C14,'Outgoing 2023'!$L$2,"YM")&" bulan, "&DATEDIF(C14,'Outgoing 2023'!$L$2,"MD")&" hari" -> 1 tahun, 9 bulan, 0 hari | O14: =TODAY()-C14 -> 638 | S14: Pemberitahuan | T14: =COUNTIF($I$2:$I$1159,S14) -> 147
... A33: 32 | B33: ABJ/DIR/EKS/01.25/0034 | C33: 45677 | D33: PAM JAYA | E33: Tanggapan Permohonan Penyusunan Desain Akhir Infill Sambungan Baru Jl. Timor | G33: Project | H33: Greenfield | I33: DED/RAB | K33: Info | L33: Planning | M33: Aji S | N33: =DATEDIF(C33,'Outgoing 2023'!$L$2,"Y")&" tahun, "&DATEDIF(C33,'Outgoing 2023'!$L$2,"YM")&" bulan, "&DATEDIF(C33,'Outgoing 2023'!$L$2,"MD")&" hari" -> 1 tahun, 8 bulan, 19 hari | O33: =TODAY()-C33 -> 627 | S33: DPPP | T33: =COUNTIF($I$2:$I$1159,S33) -> 2
A34: 33 | B34: ABJ/DIR/EKS/01.25/0035 | C34: 45677 | D34: PAM JAYA | E34: Pengiriman Risalah Rapat Pre Construction Meeting Program Rehabilitasi Periode 6 – 12 Januari 2025 | G34: Project | H34: Cyclical | I34: MoM | K34: Info | L34: PMO | M34: Project Manager | N34: =DATEDIF(C34,'Outgoing 2023'!$L$2,"Y")&" tahun, "&DATEDIF(C34,'Outgoing 2023'!$L$2,"YM")&" bulan, "&DATEDIF(C34,'Outgoing 2023'!$L$2,"MD")&" hari" -> 1 tahun, 8 bulan, 19 hari | O34: =TODAY()-C34 -> 627 | S34: 0 | T34: =COUNTIF($I$2:$I$1159,S34) -> 0
A35: 34 | B35: ABJ/DIR/EKS/01.25/0036 | C35: 45678 | D35: PAM JAYA | E35: Penyampaian DED dan RAB Perluasan Jaringan Untuk Sambungan Baru Proyek SPAM Jatiluhur Hilir dan Buaran 3 Hilir | G35: Project | H35: Greenfield | I35: DED/RAB | K35: Info | L35: Planning | M35: Aji S | N35: =DATEDIF(C35,'Outgoing 2023'!$L$2,"Y")&" tahun, "&DATEDIF(C35,'Outgoing 2023'!$L$2,"YM")&" bulan, "&DATEDIF(C35,'Outgoing 2023'!$L$2,"MD")&" hari" -> 1 tahun, 8 bulan, 18 hari | O35: =TODAY()-C35 -> 626 | S35: Kendala Proyek | T35: =COUNTIF($I$2:$I$1159,S35) -> 32
A36: 35 | B36: ABJ/DIR/EKS/01.25/0037 | C36: 45678 | D36: Bapak Rasikin - Lurah Kelurahan Pondok Kelapa | E36: Permohonan Bantuan Fasilitasi untuk Kegiatan Sosialisasi Pekerjaan Pemasangan Pipa di Area Kompleks Kavling Marinir, Kelurahan Pondok Kelapa, Kecamatan Duren Sawit, Jakarta Timur | G36: Corporate | H36: Corporate | I36: Permohonan | K36: Info | L36: Corcom | M36: Valent | N36: =DATEDIF(C36,'Outgoing 2023'!$L$2,"Y")&" tahun, "&DATEDIF(C36,'Outgoing 2023'!$L$2,"YM")&" bulan, "&DATEDIF(C36,'Outgoing 2023'!$L$2,"MD")&" hari" -> 1 tahun, 8 bulan, 18 hari | O36: =TODAY()-C36 -> 626 | S36: Produksi | T36: =COUNTIF($I$2:$I$1159,S36) -> 2
A37: 36 | B37: ABJ/DIR/EKS/01.25/0038 | C37: 45678 | D37: PAM JAYA | E37: Usulan Kepada PAM JAYA Terkait Pencapaian Target Sambungan Baru | G37: Project | H37: Greenfield | I37: Sambungan Rumah/Sambungan Baru | K37: Info | L37: PMO NC | M37: A. Levi | N37: =DATEDIF(C37,'Outgoing 2023'!$L$2,"Y")&" tahun, "&DATEDIF(C37,'Outgoing 2023'!$L$2,"YM")&" bulan, "&DATEDIF(C37,'Outgoing 2023'!$L$2,"MD")&" hari" -> 1 tahun, 8 bulan, 18 hari | O37: =TODAY()-C37 -> 626 | S37: DPPK | T37: =COUNTIF($I$2:$I$1159,S37) -> 23
A38: 37 | B38: ABJ/DIR/EKS/01.25/0039 | C38: 45679 | D38: PAM JAYA | E38: Shop Drawing Proyek SPAM Jatiluhur Hilir Panel PLC MC CDC | G38: Project | H38: Jatiluhur Hilir | I38: Shop Drawing | K38: Info | L38: PMO | M38: Juny Jety | N38: =DATEDIF(C38,'Outgoing 2023'!$L$2,"Y")&" tahun, "&DATEDIF(C38,'Outgoing 2023'!$L$2,"YM")&" bulan, "&DATEDIF(C38,'Outgoing 2023'!$L$2,"MD")&" hari" -> 1 tahun, 8 bulan, 17 hari | O38: =TODAY()-C38 -> 625 | S38: Inspeksi | T38: =COUNTIF($I$2:$I$1159,S38) -> 10
A39: 38 | B39: ABJ/DIR/SCM/01.25/0040 | C39: 45680 | D39: PT. Karsa Buana Lestari | E39: Kontrak Uji Air Limbah periode 23 Januari 2025- 31 Desember 2026 (2 tahun) | G39: Corporate | H39: Corporate | I39: SCM | K39: Info | L39: SCM | M39: Wahyu S | N39: =DATEDIF(C39,'Outgoing 2023'!$L$2,"Y")&" tahun, "&DATEDIF(C39,'Outgoing 2023'!$L$2,"YM")&" bulan, "&DATEDIF(C39,'Outgoing 2023'!$L$2,"MD")&" hari" -> 1 tahun, 8 bulan, 16 hari | O39: =TODAY()-C39 -> 624 | S39: PKS | T39: =COUNTIF($I$2:$I$1159,S39) -> 7
A40: 39 | B40: ABJ/DIR/EKS/01.25/0041 | C40: 45681 | D40: PAM JAYA | E40: Tanggapan atas Surat PAM JAYA No. e-37092/PP.03.02 Tanggal 16 Desember 2024 | G40: Project | H40: Project | I40: HSE | K40: Info | L40: HSE | M40: Irsan | N40: =DATEDIF(C40,'Outgoing 2023'!$L$2,"Y")&" tahun, "&DATEDIF(C40,'Outgoing 2023'!$L$2,"YM")&" bulan, "&DATEDIF(C40,'Outgoing 2023'!$L$2,"MD")&" hari" -> 1 tahun, 8 bulan, 15 hari | O40: =TODAY()-C40 -> 623 | S40: Berita Acara | T40: =COUNTIF($I$2:$I$1159,S40) -> 2
A41: 40 | B41: ABJ/DIR/EKS/01.25/0042 | C41: 45681 | D41: PAM JAYA | E41: Tanggapan Permohonan Penyusunan Desain Akhir Infill Sambungan Baru Jl. Kalisari (Pak Endriartono) | G41: Project | H41: Greenfield | I41: DED/RAB | K41: Info | L41: Planning | M41: Aji S | N41: =DATEDIF(C41,'Outgoing 2023'!$L$2,"Y")&" tahun, "&DATEDIF(C41,'Outgoing 2023'!$L$2,"YM")&" bulan, "&DATEDIF(C41,'Outgoing 2023'!$L$2,"MD")&" hari" -> 1 tahun, 8 bulan, 15 hari | O41: =TODAY()-C41 -> 623 | S41: Polis Asuransi | T41: =COUNTIF($I$2:$I$1159,S41) -> 2
A42: 41 | B42: ABJ/DIR/EKS/01.25/0043 | C42: 45681 | D42: PAM JAYA | E42: Shop Drawing Proyek SPAM Jatiluhur Hilir Bulk Water Delivering 4000 Lps – A2.2 Pondok Kopi – By Pass | G42: Project | H42: Jatiluhur Hilir | I42: Shop Drawing | K42: Info | L42: PMO | M42: Juny Jety | N42: =DATEDIF(C42,'Outgoing 2023'!$L$2,"Y")&" tahun, "&DATEDIF(C42,'Outgoing 2023'!$L$2,"YM")&" bulan, "&DATEDIF(C42,'Outgoing 2023'!$L$2,"MD")&" hari" -> 1 tahun, 8 bulan, 15 hari | O42: =TODAY()-C42 -> 623 | S42: Perawatan | T42: =COUNTIF($I$2:$I$1159,S42) -> 15
A43: 42 | B43: ABJ/DIR/EKS/01.25/0044 | C43: 45681 | D43: PAM JAYA | E43: Shop Drawing & Justifikasi Proyek SPAM Jatiluhur Hilir Jalur A2 Phase 1b (Hot Tapping) | G43: Project | H43: Jatiluhur Hilir | I43: Shop Drawing | K43: Open | L43: PMO | M43: Juny Jety | N43: =DATEDIF(C43,'Outgoing 2023'!$L$2,"Y")&" tahun, "&DATEDIF(C43,'Outgoing 2023'!$L$2,"YM")&" bulan, "&DATEDIF(C43,'Outgoing 2023'!$L$2,"MD")&" hari" -> 1 tahun, 8 bulan, 15 hari | O43: =TODAY()-C43 -> 623 | S43: Proposal Modifikasi | T43: =COUNTIF($I$2:$I$1159,S43) -> 2
A44: 43 | B44: ABJ/DIR/EKS/01.25/0045 | C44: 45681 | D44: PAM JAYA | E44: Penyampaian Dokumen Polis Asuransi | G44: Corporate | H44: Corporate | I44: Finance | K44: Info | L44: Finance | M44: Wahyu Tjahyadi | N44: =DATEDIF(C44,'Outgoing 2023'!$L$2,"Y")&" tahun, "&DATEDIF(C44,'Outgoing 2023'!$L$2,"YM")&" bulan, "&DATEDIF(C44,'Outgoing 2023'!$L$2,"MD")&" hari" -> 1 tahun, 8 bulan, 15 hari | O44: =TODAY()-C44 -> 623 | S44: Sosialisasi | T44: =COUNTIF($I$2:$I$1159,S44) -> 15
A45: 44 | B45: ABJ/DIR/EKS/01.25/0046 | C45: 45681 | D45: PAM JAYA | E45: Tanggapan Surat PAM Jaya No 10447/KM.01.11/EKST/XII/2024 terkait Tanggapan surat ABJ No ABJ/DIR/EKS/10.24/0858 | G45: Produksi | H45: PJP 2 | I45: Denda | K45: Open | L45: Produksi | M45: Ahmad Fandhi | N45: =DATEDIF(C45,'Outgoing 2023'!$L$2,"Y")&" tahun, "&DATEDIF(C45,'Outgoing 2023'!$L$2,"YM")&" bulan, "&DATEDIF(C45,'Outgoing 2023'!$L$2,"MD")&" hari" -> 1 tahun, 8 bulan, 15 hari | O45: =TODAY()-C45 -> 623 | S45: Proposal Substitusi | T45: =COUNTIF($I$2:$I$1159,S45) -> 1
A46: 45 | B46: ABJ/DIR/EKS/01.25/0047 | C46: 45684 | D46: PAM JAYA | E46: Pemberitahuan Uji Komisioning SPAM Jatiluhur Hilir – Infill Adhoc PC 86 EZ 01, Infill Adhoc PC 80 EZ 03, Infill Adhoc PC 70 EZ 09, Infill Adhoc PC 055 EZ 13 | G46: Project | H46: Jatiluhur Hilir | I46: Komisioning/Pengoperasian | K46: Info | L46: PMO | M46: Muhrojin | N46: =DATEDIF(C46,'Outgoing 2023'!$L$2,"Y")&" tahun, "&DATEDIF(C46,'Outgoing 2023'!$L$2,"YM")&" bulan, "&DATEDIF(C46,'Outgoing 2023'!$L$2,"MD")&" hari" -> 1 tahun, 8 bulan, 12 hari | O46: =TODAY()-C46 -> 620 | S46: COE | T46: =COUNTIF($I$2:$I$1159,S46) -> 8
... A51: 50 | B51: ABJ/DIR/EKS/01.25/0052 | C51: 45687 | D51: PAM JAYA | E51: Tanggapan Atas Surat PAM JAYA No.e-39800/PM.01.02 Tanggal 23 Januari 2025 | G51: Corporate | H51: Corporate | I51: Pemberitahuan | K51: Info | L51: Planning | M51: Aji S | N51: =DATEDIF(C51,'Outgoing 2023'!$L$2,"Y")&" tahun, "&DATEDIF(C51,'Outgoing 2023'!$L$2,"YM")&" bulan, "&DATEDIF(C51,'Outgoing 2023'!$L$2,"MD")&" hari" -> 1 tahun, 8 bulan, 9 hari | O51: =TODAY()-C51 -> 617 | S51: Transfer Knowledge | T51: =COUNTIF($I$2:$I$1159,S51) -> 2
A52: 51 | B52: ABJ/DIR/EKS/01.25/0053 | C52: 45687 | D52: PAM JAYA | E52: Tanggapan atas surat PAM Jaya No e.39066/PM.01.00 | F52: perubahan schedule line B dan line F | G52: Project | H52: Buaran 3 Hulu | I52: Jadwal Pekerjaan | K52: Info | L52: PMO | M52: Danny L | N52: =DATEDIF(C52,'Outgoing 2023'!$L$2,"Y")&" tahun, "&DATEDIF(C52,'Outgoing 2023'!$L$2,"YM")&" bulan, "&DATEDIF(C52,'Outgoing 2023'!$L$2,"MD")&" hari" -> 1 tahun, 8 bulan, 9 hari | O52: =TODAY()-C52 -> 617 | S52: Ekuitas | T52: =COUNTIF($I$2:$I$1159,S52) -> 1
A53: 52 | B53: ABJ/DIR/EKS/01.25/0054 | C53: 45688 | D53: PAM JAYA | E53: RAB Untuk Konsultan DED Reservoir IPA Pejompongan 2 dan Fasilitas terkait | G53: Project | H53: Brownfield | I53: DED/RAB | K53: Open | L53: Planning | M53: Aji S | N53: =DATEDIF(C53,'Outgoing 2023'!$L$2,"Y")&" tahun, "&DATEDIF(C53,'Outgoing 2023'!$L$2,"YM")&" bulan, "&DATEDIF(C53,'Outgoing 2023'!$L$2,"MD")&" hari" -> 1 tahun, 8 bulan, 8 hari | O53: =TODAY()-C53 -> 616 | S53: KBA | T53: =COUNTIF($I$2:$I$1159,S53) -> 2
A54: 53 | B54: ABJ/DIR/EKS/01.25/0055 | C54: 45688 | D54: PAM JAYA | E54: Penyampaian Dokumen SOP IPA Buaran 3 dan Revisi SOP IPA Buaran 1&2, IPA Pejompongan 1&2 dan IPA Pulogadung | G54: Produksi | H54: Produksi | I54: SOP | K54: Info | L54: Produksi | M54: Rika I | N54: =DATEDIF(C54,'Outgoing 2023'!$L$2,"Y")&" tahun, "&DATEDIF(C54,'Outgoing 2023'!$L$2,"YM")&" bulan, "&DATEDIF(C54,'Outgoing 2023'!$L$2,"MD")&" hari" -> 1 tahun, 8 bulan, 8 hari | O54: =TODAY()-C54 -> 616 | T54: =COUNTIF($I$2:$I$1159,S54) -> 0
A55: 54 | B55: ABJ/DIR/EKS/01.25/0056 | C55: 45688 | D55: PAM JAYA | E55: DED dan RAB Perluasan Jaringan Untuk Sambungan Baru Master Meter Syamsudin | G55: Project | H55: Greenfield | I55: DED/RAB | K55: Info | L55: Planning | M55: Aji S | N55: =DATEDIF(C55,'Outgoing 2023'!$L$2,"Y")&" tahun, "&DATEDIF(C55,'Outgoing 2023'!$L$2,"YM")&" bulan, "&DATEDIF(C55,'Outgoing 2023'!$L$2,"MD")&" hari" -> 1 tahun, 8 bulan, 8 hari | O55: =TODAY()-C55 -> 616
A56: 55 | B56: ABJ/DIR/EKS/01.25/0057 | C56: 45688 | D56: PAM JAYA | E56: Permohonan Bantuan Terkait Pengajuan Surat Permohonan Relokasi Utilitas Kepada DBM | G56: Project | H56: Jatiluhur Hilir | I56: Permohonan | K56: Open | L56: PMO | M56: Muhrojin | N56: =DATEDIF(C56,'Outgoing 2023'!$L$2,"Y")&" tahun, "&DATEDIF(C56,'Outgoing 2023'!$L$2,"YM")&" bulan, "&DATEDIF(C56,'Outgoing 2023'!$L$2,"MD")&" hari" -> 1 tahun, 8 bulan, 8 hari | O56: =TODAY()-C56 -> 616
A57: 56 | B57: ABJ/DIR/EKS/01.25/0058 | C57: 45688 | D57: PAM JAYA | E57: Pengiriman Ke-6 Tanggapan Atas Hasil Review PAM dan KPI Terhadap Dokumen Desain Akhir Program Rehabilitasi Proyek Brownfield Tahun 2025 | G57: Project | H57: Cyclical | I57: DED/RAB | K57: Info | L57: PMO | M57: Aan Hendra | N57: =DATEDIF(C57,'Outgoing 2023'!$L$2,"Y")&" tahun, "&DATEDIF(C57,'Outgoing 2023'!$L$2,"YM")&" bulan, "&DATEDIF(C57,'Outgoing 2023'!$L$2,"MD")&" hari" -> 1 tahun, 8 bulan, 8 hari | O57: =TODAY()-C57 -> 616
A58: 57 | B58: ABJ/DIR/EKS/01.25/0059 | C58: 45688 | D58: PT. Jakarta Setiabudi, Tbk | E58: Permohonan Pengembalian Security Deposit HO ABJ Setiabudi | G58: Corporate | H58: Corporate | I58: Permohonan | K58: Info | L58: HC | M58: Cucum | N58: =DATEDIF(C58,'Outgoing 2023'!$L$2,"Y")&" tahun, "&DATEDIF(C58,'Outgoing 2023'!$L$2,"YM")&" bulan, "&DATEDIF(C58,'Outgoing 2023'!$L$2,"MD")&" hari" -> 1 tahun, 8 bulan, 8 hari | O58: =TODAY()-C58 -> 616
A59: 58 | B59: ABJ/DIR/EKS/01.25/0060 | C59: 45688 | D59: PAM JAYA | E59: Undangan Pengecekan Hasil Uji Kebocoran (Leak Test) Bangunan Reservoir B | G59: Project | H59: Buaran 3 Hulu | I59: Undangan | K59: Info | L59: PMO | M59: Danny L | N59: =DATEDIF(C59,'Outgoing 2023'!$L$2,"Y")&" tahun, "&DATEDIF(C59,'Outgoing 2023'!$L$2,"YM")&" bulan, "&DATEDIF(C59,'Outgoing 2023'!$L$2,"MD")&" hari" -> 1 tahun, 8 bulan, 8 hari | O59: =TODAY()-C59 -> 616
A60: 59 | B60: ABJ/DIR/EKS/01.25/0061 | C60: 45688 | D60: SIINas | E60: Laporan Triwulan 3 Tahun 2024 | G60: Project | H60: Project | I60: Laporan Periodik | K60: Info | L60: PMO | M60: Johnson | N60: =DATEDIF(C60,'Outgoing 2023'!$L$2,"Y")&" tahun, "&DATEDIF(C60,'Outgoing 2023'!$L$2,"YM")&" bulan, "&DATEDIF(C60,'Outgoing 2023'!$L$2,"MD")&" hari" -> 1 tahun, 8 bulan, 8 hari | O60: =TODAY()-C60 -> 616
A61: 60 | B61: ABJ/DIR/EKS/01.25/0062 | C61: 45688 | D61: SIINas | E61: Laporan Triwulan 4 tahun 2024 | G61: Project | H61: Project | I61: Laporan Periodik | K61: Info | L61: PMO | M61: Johnson | N61: =DATEDIF(C61,'Outgoing 2023'!$L$2,"Y")&" tahun, "&DATEDIF(C61,'Outgoing 2023'!$L$2,"YM")&" bulan, "&DATEDIF(C61,'Outgoing 2023'!$L$2,"MD")&" hari" -> 1 tahun, 8 bulan, 8 hari | O61: =TODAY()-C61 -> 616
A62: 61 | B62: ABJ/DIR/EKS/01.25/0063 | C62: 45691 | D62: PAM JAYA | E62: Penyampaian Bukti Sertifikasi ISO/IEC 17025:2017 | G62: Corporate | H62: Corporate | I62: Sertifikasi | K62: Info | L62: WQA | M62: Novi | N62: =DATEDIF(C62,'Outgoing 2023'!$L$2,"Y")&" tahun, "&DATEDIF(C62,'Outgoing 2023'!$L$2,"YM")&" bulan, "&DATEDIF(C62,'Outgoing 2023'!$L$2,"MD")&" hari" -> 1 tahun, 8 bulan, 6 hari | O62: =TODAY()-C62 -> 613
